Workbook
Name 在此区间: 建设单位管理费!$L$5
Name 在此区间内: 建设单位管理费!$L$5

Sheet 项目技术经济指标
A1: 序号 | B1: 内容名称 | C1: 单位 | D1: 数量 | E1: 备注
A2: 一 | B2: 方案技术指标
A3: =总投资估算!A4 -> （一） | B3: =总投资估算!B4 -> 农村产业融合示范园
A4: =总投资估算!A5 -> 1 | B4: =总投资估算!B5 -> 分拣仓库 | C4: =总投资估算!I6 -> 平方米 | D4: =总投资估算!J5 -> 1000
A5: =总投资估算!A6 -> 1.1 | B5: =总投资估算!B6 -> 土建工程 | C5: =总投资估算!I7 -> 平方米 | D5: =总投资估算!J6 -> 1000
A6: =总投资估算!A7 -> 1.2 | B6: =总投资估算!B7 -> 给排水工程 | C6: =总投资估算!I8 -> 平方米 | D6: =总投资估算!J7 -> 1000
A7: =总投资估算!A8 -> 1.3 | B7: =总投资估算!B8 -> 电气工程 | C7: =总投资估算!I9 -> 平方米 | D7: =总投资估算!J8 -> 1000
A8: =总投资估算!A9 -> 1.4 | B8: =总投资估算!B9 -> 消防工程 | C8: =总投资估算!I10 -> 平方米 | D8: =总投资估算!J9 -> 1000 | G8: 成本 | H8: 工资 | I8: 管理人员 | K8: 职工 | M8: 每五年增长率
A9: =总投资估算!A10 -> 1.5 | B9: =总投资估算!B10 -> 暖通工程 | C9: =总投资估算!I11 -> 平方米 | D9: =总投资估算!J10 -> 1000 | I9: 人数 | J9: 月工资 | K9: 人数 | L9: 月工资
A10: =总投资估算!A11 -> 2 | B10: =总投资估算!B11 -> 农产品加工厂房 | C10: =总投资估算!I12 -> 平方米 | D10: =总投资估算!J11 -> 1000 | I10: 5 | J10: 4500 | K10: 15 | L10: 4000 | M10: 0.1
A11: =总投资估算!A12 -> 2.1 | B11: =总投资估算!B12 -> 土建工程 | C11: =总投资估算!I13 -> 平方米 | D11: =总投资估算!J12 -> 1000
A12: =总投资估算!A13 -> 2.2 | B12: =总投资估算!B13 -> 给排水工程 | C12: =总投资估算!I14 -> 平方米 | D12: =总投资估算!J13 -> 1000 | H12: =SUM(D5:D8) -> 4000 | I12: =SUM(H12:H13) -> 6000
A13: =总投资估算!A14 -> 2.3 | B13: =总投资估算!B14 -> 电气工程 | C13: =总投资估算!I15 -> 平方米 | D13: =总投资估算!J14 -> 1000 | H13: =SUM(D10:D11) -> 2000
A14: =总投资估算!A15 -> 2.4 | B14: =总投资估算!B15 -> 消防工程 | C14: =总投资估算!I16 -> 平方米 | D14: =总投资估算!J15 -> 1000
A15: =总投资估算!A16 -> 2.5 | B15: =总投资估算!B16 -> 暖通工程 | C15: =总投资估算!I17 -> 平方米 | D15: =总投资估算!J16 -> 1000
A16: =总投资估算!A17 -> 3 | B16: =总投资估算!B17 -> 保鲜仓储中心 | C16: =总投资估算!I18 -> 平方米 | D16: =总投资估算!J17 -> 500
A17: =总投资估算!A18 -> 3.1 | B17: =总投资估算!B18 -> 土建工程 | C17: =总投资估算!I19 -> 平方米 | D17: =总投资估算!J18 -> 500
A18: =总投资估算!A19 -> 3.2 | B18: =总投资估算!B19 -> 给排水工程 | C18: =总投资估算!I20 -> 平方米 | D18: =总投资估算!J19 -> 500
A19: =总投资估算!A20 -> 3.3 | B19: =总投资估算!B20 -> 电气工程 | C19: =总投资估算!I21 -> 平方米 | D19: =总投资估算!J20 -> 500
A20: =总投资估算!A21 -> 3.4 | B20: =总投资估算!B21 -> 消防工程 | C20: =总投资估算!I22 -> 平方米 | D20: =总投资估算!J21 -> 500
A21: =总投资估算!A22 -> 3.5 | B21: =总投资估算!B22 -> 暖通工程 | C21: =总投资估算!I23 -> 平方米 | D21: =总投资估算!J22 -> 500
A22: =总投资估算!A23 -> 4 | B22: =总投资估算!B23 -> 实践教育综合基地 | C22: =总投资估算!I24 -> 平方米 | D22: =总投资估算!J23 -> 5300
A23: =总投资估算!A24 -> 4.1 | B23: =总投资估算!B24 -> 土建工程 | C23: =总投资估算!I25 -> 平方米 | D23: =总投资估算!J24 -> 5300
A24: =总投资估算!A25 -> 4.2 | B24: =总投资估算!B25 -> 给排水工程 | C24: =总投资估算!I26 -> 平方米 | D24: =总投资估算!J25 -> 5300
A25: =总投资估算!A26 -> 4.3 | B25: =总投资估算!B26 -> 电气工程 | C25: =总投资估算!I27 -> 平方米 | D25: =总投资估算!J26 -> 5300
... A39: =总投资估算!A40 -> 6.5 | B39: =总投资估算!B40 -> 暖通工程 | C39: =总投资估算!I41 -> 平方米 | D39: =总投资估算!J40 -> 20089
A40: =总投资估算!A41 -> 7 | B40: =总投资估算!B41 -> 创新创业孵化平台地下停车场 | C40: =总投资估算!I42 -> 平方米 | D40: =总投资估算!J41 -> 6000 | E40: 停车位225个
A41: =总投资估算!A42 -> 7.1 | B41: =总投资估算!B42 -> 支护工程 | C41: =总投资估算!I43 -> 平方米 | D41: =总投资估算!J42 -> 6000
A42: =总投资估算!A43 -> 7.2 | B42: =总投资估算!B43 -> 主体工程 | C42: =总投资估算!I45 -> 平方米 | D42: =总投资估算!J43 -> 6000
A43: =总投资估算!A45 -> 9.2 | B43: =总投资估算!B45 -> 电气工程 | C43: =总投资估算!I46 -> 平方米 | D43: =总投资估算!J45 -> 6000
A44: =总投资估算!A46 -> 7.4 | B44: =总投资估算!B46 -> 消防工程 | C44: =总投资估算!I47 -> 平方米 | D44: =总投资估算!J46 -> 6000
A45: =总投资估算!A47 -> 7.5 | B45: =总投资估算!B47 -> 通风工程 | C45: =总投资估算!I48 -> 平方米 | D45: =总投资估算!J47 -> 6000
A46: =总投资估算!A48 -> 8 | B46: =总投资估算!B48 -> 停车场 | C46: =总投资估算!I49 -> 平方米 | D46: =总投资估算!J48 -> 1050 | E46: 停车位30个
A47: =总投资估算!A49 -> 8.1 | B47: =总投资估算!B49 -> 场地铺装 | C47: =总投资估算!I50 -> 平方米 | D47: =总投资估算!J49 -> 1050
A48: =总投资估算!A50 -> 8.2 | B48: =总投资估算!B50 -> 标线工程 | C48: =总投资估算!I51 -> 项 | D48: =总投资估算!J50 -> 1050
A49: =总投资估算!A51 -> 8.3 | B49: =总投资估算!B51 -> 闸机及停车管理系统 | C49: =总投资估算!I52 -> 亩 | D49: =总投资估算!J51 -> 1
A50: =总投资估算!A52 -> 9 | B50: =总投资估算!B52 -> 标准化农田 | C50: =总投资估算!I53 -> 亩 | D50: =总投资估算!J52 -> 73.86
A51: =总投资估算!A53 -> 9.1 | B51: =总投资估算!B53 -> 土地平整 | C51: =总投资估算!I54 -> 亩 | D51: =总投资估算!J53 -> 73.86
A52: =总投资估算!A54 -> 9.2 | B52: =总投资估算!B54 -> 挖壕打穴 | C52: =总投资估算!I55 -> 亩 | D52: =总投资估算!J54 -> 73.86
A53: =总投资估算!A55 -> 9.3 | B53: =总投资估算!B55 -> 水肥一体 | C53: =总投资估算!I56 -> 亩 | D53: =总投资估算!J55 -> 73.86
A54: =总投资估算!A56 -> 10 | B54: =总投资估算!B56 -> 标准化高效栽培试验示范田 | C54: =总投资估算!I57 -> 亩 | D54: =总投资估算!J56 -> 20.45
A55: =总投资估算!A57 -> 10.1 | B55: =总投资估算!B57 -> 土地平整 | C55: =总投资估算!I58 -> 亩 | D55: =总投资估算!J57 -> 20.45
A56: =总投资估算!A58 -> 10.2 | B56: =总投资估算!B58 -> 挖壕打穴 | C56: =总投资估算!I59 -> 亩 | D56: =总投资估算!J58 -> 20.45
A57: =总投资估算!A59 -> 10.3 | B57: =总投资估算!B59 -> 水肥一体 | C57: =总投资估算!I60 -> 亩 | D57: =总投资估算!J59 -> 20.45
A58: =总投资估算!A60 -> 11 | B58: =总投资估算!B60 -> 育苗基地 | C58: =总投资估算!I61 -> 亩 | D58: =总投资估算!J60 -> 19.46
... A61: =总投资估算!A63 -> 11.3 | B61: =总投资估算!B63 -> 水肥一体 | C61: =总投资估算!I64 -> 项 | D61: =总投资估算!J63 -> 19.46
A62: =总投资估算!A64 -> （二） | B62: =总投资估算!B64 -> 附属配套工程
A63: =总投资估算!A65 -> 1 | B63: =总投资估算!B65 -> 供配电系统 | C63: =总投资估算!I66 -> 项 | D63: =总投资估算!J65 -> 1
A64: =总投资估算!A66 -> 2 | B64: =总投资估算!B66 -> 室外给排水工程 | C64: =总投资估算!I67 -> 项 | D64: =总投资估算!J66 -> 1
A65: =总投资估算!A67 -> 3 | B65: =总投资估算!B67 -> 室外消防工程 | C65: =总投资估算!I68 -> 项 | D65: =总投资估算!J67 -> 1
A66: =总投资估算!A68 -> 4 | B66: =总投资估算!B68 -> 通信工程 | C66: =总投资估算!I69 -> 项 | D66: =总投资估算!J68 -> 1
A67: =总投资估算!A69 -> 5 | B67: =总投资估算!B69 -> 其他配套工程 | C67: 项 | D67: =总投资估算!J69 -> 1
A68: 二 | B68: 经济技术指标
A69: 1 | B69: 总投资 | C69: 万元 | D69: =总投资估算!G95 -> 22000 | H69: 项目总建筑面积为16260平方米，其中新建污水处理厂15468㎡，污水处理规模为1.5万m³/天，含粗格栅池2400㎡、提升池2400㎡、沉砂池2400㎡、兼氧 FMBR 池2000㎡、消毒回用池1600㎡、污泥池1200㎡、贮泥池1200㎡、污泥脱水机房1500㎡、管理用房768㎡；新建污水管网提升泵站792㎡，污水提升规模为0.2m³/秒；新建污水管网50㎞、检查井1250座。
A70: 1.1 | B70: 工程费用 | C70: 万元 | D70: =D71+D72 -> 17385.78
A71: 1.1.1 | B71: 建筑安装工程费用 | C71: 万元 | D71: =总投资估算!C3+总投资估算!D3 -> 17385.78
A72: 1.1.2 | B72: 设备及工器具购置费 | C72: 万元 | D72: =总投资估算!E3 -> 0
A73: 1.2 | B73: 工程建设其他费用 | C73: 万元 | D73: =总投资估算!G70 -> 2754.06
A74: 1.3 | B74: 基本预备费 | C74: 万元 | D74: =总投资估算!G90 -> 1590.16
A75: 1.4 | B75: 建设期利息 | C75: 万元 | D75: =总投资估算!G94 -> 270
A76: 2 | B76: 资金筹措 | C76: 万元 | D76: =SUM(D77:D78) -> 22000
A77: 2.1 | B77: 自筹资本金 | C77: 万元 | D77: =分年计划及建设期利息!G2 -> 13000 | E77: =D77/$D$76 -> 0.59090909
A78: 2.2 | B78: 融资及政府债券 | C78: 万元 | D78: =资金平衡表!C36 -> 9000 | E78: =D78/$D$76 -> 0.40909091
A79: 3 | B79: 年均营业收入 | C79: 万元 | D79: =AVERAGE(收入成本!Z6:Z35) -> 1123.466
A80: 4 | B80: 年均税收 | C80: 万元 | D80: =AVERAGE(收入成本!AJ6:AJ35) -> 172.96393
A81: 5 | B81: 运营期总收入 | C81: 万元 | D81: =资金平衡表!F36 -> 34395.05
A82: 6 | B82: 运营期总成本 | C82: 万元 | D82: =资金平衡表!H36 -> 12303.77
A83: 7 | B83: 项目总收益 | C83: 万元 | D83: =资金平衡表!J36 -> 22091.28
A84: 8 | B84: 债券覆盖倍数 | C84: - | D84: =资金平衡表!J37 -> 1.29 | E84: 正常情况下
D85: =资金平衡表!K37 -> 1.09 | E85: =资金平衡表!K2 -> 收入下降10%
D86: =资金平衡表!L37 -> 1.25 | E86: =资金平衡表!L2 -> 成本上升10%
D87: =资金平衡表!M37 -> 1.05 | E87: =资金平衡表!M2 -> 收入下降10%且成本上升10%
B93: 本项目总投资约为9000.00万元，其中：工程费用约为6317.35万元，工程建设其他费用约为1887.32万元，预备费约为645.33万元，建设期利息150.00万元。 | C93: 本项目建设总投资估算9000.00万元。项目资金来源为：建设单位自筹资本金为4000.00万元，占总投资比例为44.44%，剩余5000万元拟申请地方政府专项债券，占总投资比例为55.56%。 | D93: 本项目为八里湖新区九龙村农村产业融合示范园建设项目,总用地面积约1302695㎡（约1954.03亩），总建筑面积为33600㎡。主要建设内容包括建设标准化农田69.7亩，建设标准化高效栽培试验示范26.7亩、育苗基地87.6亩；分拣仓库7500㎡，农产品加工厂房8000㎡，冷库仓储中心6500㎡，科研基地实验室3000㎡，实践教育综合基地3000㎡，农业技术推广中心4000㎡，种子繁育基地600㎡，配套用房1000㎡，停车场800㎡，及其他供配电、消防、给排水、通信等配套基础设施建设。 | E93: 本项目建设期为12个月，运营期为29年，计算期内总收入20510.96万元，总成本8075.90万元，累计收益余额10384.01万元，项目债券期内，本息合计金额为9500.00万元，正常运营状态下，项目本息覆盖率为1.31。 | O93: 本项目为八里湖新区九龙村农村产业融合示范园建设项目,总用地面积约1302695㎡（约1954.03亩），总建筑面积为33600㎡。主要建设内容包括建设标准化农田69.7亩，建设标准化高效栽培试验示范26.7亩、育苗基地87.6亩；分拣仓库7500㎡，农产品加工厂房8000㎡，冷库仓储中心6500㎡，科研基地实验室3000㎡，实践教育综合基地3000㎡，农业技术推广中心4000㎡，种子繁育基地600㎡，配套用房1000㎡，停车场800㎡，及其他供配电、消防、给排水、通信等配套基础设施建设。
O98: =1302695/666.67 -> 1954.0327

Sheet 标准化指标设定
C1: 本表所有此颜色单元格为基础数据，需自行嵌入。其余单元格均为联动，勿调整。
B3: 农村污水处理及中水再利用建设项目
A4: 江西省指标要求和假设参数设计 | J4: 江西省生活用水定额 | S4: 吉水县2021年末人口统计
A5: 序号 | B5: 指标项 | C5: 江西省用地指标（2018） | D5: 参数设定 | E5: 单位 | F5: 项目数据 | G5: 备注
A6: 1 | B6: 二级污水处理站用地 | C6: 参考城市污水处理厂建设用地指标 | D6: =1.5+(F11/10000-1)*((6-1.5)/(5-1)) -> 5.325 | E6: 公顷 | G6: 1、为应对突发情况污水处理厂、污水管网泵站设计规模应比计算规模适当增大 2、污水处理厂规模按项目数据中的污水处理量来测算，收入计算时按参数设定中的处理量来计算
A7: 1.1 | B7: 区域人口 | C7: 根据地区情况确定 | D7: =G60/10000 -> 28.4983 | E7: 万人
A8: 1.2 | B8: 用水定额 | C8: 参考江西省生活用水定额 | D8: 200 | E8: L/（人*天）
A9: 1.3 | B9: 产污系数 | C9: 0.80-0.9 | D9: 0.85
A10: 1.4 | B10: 污水收集系数 | C10: 0.7-0.95 | D10: 0.9
A11: 1.5 | B11: 污水处理量 | D11: =D7*D8*D9*D10*10000/1000 -> 43602.399 | E11: m³/天 | F11: 44000
A12: 1.6 | B12: 容积率 | C12: ≥0.7 | D12: 0.75
A13: 2 | B13: 污水管网泵站用地 | C13: 参考污水管网泵站建设用地指标 | D13: =800+(F15-0.1)*(2500-800)/(1-0.1) -> 2122.2222 | E13: ㎡
A14: 2.1 | B14: 容积率 | C14: ≥0.7 | D14: =F28/D13 -> 0.84816754 | I14: 污水处理厂规模按项目数据中的污水处理量来测定，收入计算时按参数设定中的处理量来计算
A15: 2.2 | B15: 建设规模 | C15: 参考污水管网泵站建设用地指标 | D15: =F11/(24*60*60) -> 0.50925926 | F15: 0.8
A16: 一 | B16: 总建筑面积 | F16: =F17+F28 -> 41737
A17: 1 | B17: 污水处理厂 | E17: ㎡ | F17: =INT(D6*10000*D12) -> 39937 | K17: 江西省用地指标（2018）
A18: 1.1 | B18: 粗格栅池 | C18: 根据实际需要确定 | E18: ㎡ | F18: 6300
A19: 1.2 | B19: 提升池 | C19: 根据实际需要确定 | E19: ㎡ | F19: 6300
A20: 1.3 | B20: 沉砂池 | C20: 根据实际需要确定 | E20: ㎡ | F20: 6300
A21: 1.4 | B21: 兼氧 FMBR 池 | C21: 根据实际需要确定 | E21: ㎡ | F21: 3800
A22: 1.5 | B22: 消毒回用池 | C22: 根据实际需要确定 | E22: ㎡ | F22: 3800
A23: 1.6 | B23: 污泥池 | C23: 根据实际需要确定 | E23: ㎡ | F23: 3100
A24: 1.7 | B24: 贮泥池 | C24: 根据实际需要确定 | E24: ㎡ | F24: 3100
A25: 1.8 | B25: 污泥脱水机房 | C25: 根据实际需要确定 | E25: ㎡ | F25: 3600
A26: 1.9 | B26: 管理用房 | C26: 建筑面积比例不超过总建筑面积的15% | E26: ㎡ | F26: =F17-SUM(F18:F25) -> 3637 | G26: =F16*0.15 -> 6260.55
A27: 2 | B27: 厂区室外工程 | C27: 不得低于用地面积的30% | D27: 0.3 | E27: ㎡ | F27: =INT(D6*10000*D27) -> 15975
A28: 3 | B28: 污水管网泵站 | E28: ㎡ | F28: 1800 | K28: 容积率
A29: 4 | B29: 污水管网 | E29: ㎞ | F29: =F30 -> 125
A30: 4.1 | B30: 新建污水管道 | C30: 根据实际需要确定 | E30: ㎞ | F30: =F31+F32+F33 -> 125
A31: 4.1.1 | B31: HDPE缠绕结构壁管-DN300 | C31: 根据实际需要确定 | E31: ㎞ | F31: 78
A32: 4.1.2 | B32: HDPE缠绕结构壁管-DN400 | C32: 根据实际需要确定 | E32: ㎞ | F32: 32
A33: 4.1.3 | B33: HDPE缠绕结构壁管-DN500 | C33: 根据实际需要确定 | E33: ㎞ | F33: 15
A34: 4.2 | B34: 检查井 | C34: 检查井之间的距离不宜大于50m | D34: 40 | E34: 个 | F34: =F30*1000/D34 -> 3125
I42: 吉水县农村生活污水治理专项规划
E50: 36573 | F50: 24368 | G50: 42477
E51: 31338 | F51: 19132 | G51: 29008
E52: 27783 | F52: 18504 | G52: 34226
E53: 31264 | F53: 27490 | G53: 38580
E54: 16007 | F54: 6259 | G54: 14591
E55: 10649 | F55: 8510 | G55: 14010
E56: 17935 | F56: 16414 | G56: 24144
E57: 18586 | F57: 16323 | G57: 40074
E58: 12149 | F58: 9862 | G58: 15002
E59: 25757 | F59: 19966 | G59: 32871
E60: =SUM(E50:E59) -> 228041 | F60: =SUM(F50:F59) -> 166828 | G60: =SUM(G50:G59) -> 284983

Sheet 总投资估算
A1: 序号 | B1: 工程或费用名称 | C1: 估算金额（万元） | I1: 技术经济指标 | L1: 备注
C2: 建筑工程费 | D2: 安装工程费 | E2: 设备购置费 | F2: 其他费用 | G2: 小计 | H2: 比例 | I2: 单位 | J2: 数量 | K2: 单价（元）
A3: 一 | B3: 工程费用 | C3: =SUM(C4+C64) -> 17385.78 | D3: =SUM(D4+D64) -> 0 | E3: =SUM(E4+E64) -> 0 | F3: =SUM(F4+F64) -> 0 | G3: =SUM(G4+G64) -> 17385.78 | H3: =SUM(H4+H64) -> 0.79026273
A4: （一） | B4: 农村产业融合示范园 | C4: =SUM(C5+C11+C17+C23+C29+C35+C41+C48+C52+C56+C60) -> 14755.78 | D4: =SUM(D5+D11+D17+D23+D29+D35+D41+D48+D52+D56+D60) -> 0 | E4: =SUM(E5+E11+E17+E23+E29+E35+E41+E48+E52+E56+E60) -> 0 | F4: =SUM(F5+F11+F17+F23+F29+F35+F41+F48+F52+F56+F60) -> 0 | G4: =SUM(G5+G11+G17+G23+G29+G35+G41+G48+G52+G56+G60) -> 14755.78 | H4: =G4/$G$95 -> 0.67071727
A5: 1 | B5: 分拣仓库 | C5: =SUM(C6:C10) -> 366 | D5: =SUM(D6:D10) -> 0 | E5: =SUM(E6:E10) -> 0 | F5: =SUM(F6:F10) -> 0 | G5: =SUM(G6:G10) -> 366 | H5: =G5/$G$95 -> 0.016636364 | I5: 平方米 | J5: 1000
A6: 1.1 | B6: 土建工程 | C6: =ROUND(J6*K6/10000,2) -> 330 | G6: =C6+E6+D6+F6 -> 330 | H6: =G6/$G$95 -> 0.015 | I6: 平方米 | J6: =J5 -> 1000 | K6: 3300
A7: 1.2 | B7: 给排水工程 | C7: =ROUND(J7*K7/10000,2) -> 9 | G7: =C7+E7+D7+F7 -> 9 | H7: =G7/$G$95 -> 0.00040909091 | I7: 平方米 | J7: =J6 -> 1000 | K7: 90
A8: 1.3 | B8: 电气工程 | C8: =ROUND(J8*K8/10000,2) -> 11 | G8: =C8+E8+D8+F8 -> 11 | H8: =G8/$G$95 -> 0.0005 | I8: 平方米 | J8: =J7 -> 1000 | K8: 110
A9: 1.4 | B9: 消防工程 | C9: =ROUND(J9*K9/10000,2) -> 9 | G9: =C9+E9+D9+F9 -> 9 | H9: =G9/$G$95 -> 0.00040909091 | I9: 平方米 | J9: =J8 -> 1000 | K9: 90
A10: 1.5 | B10: 暖通工程 | C10: =ROUND(J10*K10/10000,2) -> 7 | G10: =C10+E10+D10+F10 -> 7 | H10: =G10/$G$95 -> 0.00031818182 | I10: 平方米 | J10: =J9 -> 1000 | K10: 70
A11: 2 | B11: 农产品加工厂房 | C11: =SUM(C12:C16) -> 366 | D11: =SUM(D12:D16) -> 0 | E11: =SUM(E12:E16) -> 0 | F11: =SUM(F12:F16) -> 0 | G11: =C11+E11+D11+F11 -> 366 | H11: =G11/$G$95 -> 0.016636364 | I11: 平方米 | J11: 1000
A12: 2.1 | B12: 土建工程 | C12: =ROUND(J12*K12/10000,2) -> 330 | G12: =C12+E12+D12+F12 -> 330 | H12: =G12/$G$95 -> 0.015 | I12: 平方米 | J12: =J11 -> 1000 | K12: =K6 -> 3300
A13: 2.2 | B13: 给排水工程 | C13: =ROUND(J13*K13/10000,2) -> 9 | G13: =C13+E13+D13+F13 -> 9 | H13: =G13/$G$95 -> 0.00040909091 | I13: 平方米 | J13: =J12 -> 1000 | K13: =K7 -> 90
A14: 2.3 | B14: 电气工程 | C14: =ROUND(J14*K14/10000,2) -> 11 | G14: =C14+E14+D14+F14 -> 11 | H14: =G14/$G$95 -> 0.0005 | I14: 平方米 | J14: =J13 -> 1000 | K14: =K8 -> 110
A15: 2.4 | B15: 消防工程 | C15: =ROUND(J15*K15/10000,2) -> 9 | G15: =C15+E15+D15+F15 -> 9 | H15: =G15/$G$95 -> 0.00040909091 | I15: 平方米 | J15: =J14 -> 1000 | K15: =K9 -> 90
A16: 2.5 | B16: 暖通工程 | C16: =ROUND(J16*K16/10000,2) -> 7 | G16: =C16+E16+D16+F16 -> 7 | H16: =G16/$G$95 -> 0.00031818182 | I16: 平方米 | J16: =J15 -> 1000 | K16: =K10 -> 70
A17: 3 | B17: 保鲜仓储中心 | C17: =SUM(C18:C22) -> 194.5 | D17: =SUM(D18:D22) -> 0 | E17: =SUM(E18:E22) -> 0 | F17: =SUM(F18:F22) -> 0 | G17: =C17+E17+D17+F17 -> 194.5 | H17: =G17/$G$95 -> 0.0088409091 | I17: 平方米 | J17: 500
A18: 3.1 | B18: 土建工程 | C18: =ROUND(J18*K18/10000,2) -> 165 | G18: =C18+E18+D18+F18 -> 165 | H18: =G18/$G$95 -> 0.0075 | I18: 平方米 | J18: =J17 -> 500 | K18: =K12 -> 3300
A19: 3.2 | B19: 给排水工程 | C19: =ROUND(J19*K19/10000,2) -> 4.5 | G19: =C19+E19+D19+F19 -> 4.5 | H19: =G19/$G$95 -> 0.00020454545 | I19: 平方米 | J19: =J18 -> 500 | K19: =K13 -> 90
A20: 3.3 | B20: 电气工程 | C20: =ROUND(J20*K20/10000,2) -> 5.5 | G20: =C20+E20+D20+F20 -> 5.5 | H20: =G20/$G$95 -> 0.00025 | I20: 平方米 | J20: =J19 -> 500 | K20: =K14 -> 110
A21: 3.4 | B21: 消防工程 | C21: =ROUND(J21*K21/10000,2) -> 4.5 | G21: =C21+E21+D21+F21 -> 4.5 | H21: =G21/$G$95 -> 0.00020454545 | I21: 平方米 | J21: =J20 -> 500 | K21: =K15 -> 90
A22: 3.5 | B22: 暖通工程 | C22: =ROUND(J22*K22/10000,2) -> 15 | G22: =C22+E22+D22+F22 -> 15 | H22: =G22/$G$95 -> 0.00068181818 | I22: 平方米 | J22: =J21 -> 500 | K22: 300
A23: 4 | B23: 实践教育综合基地 | C23: =SUM(C24:C28) -> 1939.8 | D23: =SUM(D24:D28) -> 0 | E23: =SUM(E24:E28) -> 0 | F23: =SUM(F24:F28) -> 0 | G23: =C23+E23+D23+F23 -> 1939.8 | H23: =G23/$G$95 -> 0.088172727 | I23: 平方米 | J23: 5300
A24: 4.1 | B24: 土建工程 | C24: =ROUND(J24*K24/10000,2) -> 1749 | G24: =C24+E24+D24+F24 -> 1749 | H24: =G24/$G$95 -> 0.0795 | I24: 平方米 | J24: =J23 -> 5300 | K24: =K18 -> 3300
A25: 4.2 | B25: 给排水工程 | C25: =ROUND(J25*K25/10000,2) -> 47.7 | G25: =C25+E25+D25+F25 -> 47.7 | H25: =G25/$G$95 -> 0.0021681818 | I25: 平方米 | J25: =J24 -> 5300 | K25: =K19 -> 90
A26: 4.3 | B26: 电气工程 | C26: =ROUND(J26*K26/10000,2) -> 58.3 | G26: =C26+E26+D26+F26 -> 58.3 | H26: =G26/$G$95 -> 0.00265 | I26: 平方米 | J26: =J25 -> 5300 | K26: =K20 -> 110
A27: 4.4 | B27: 消防工程 | C27: =ROUND(J27*K27/10000,2) -> 47.7 | G27: =C27+E27+D27+F27 -> 47.7 | H27: =G27/$G$95 -> 0.0021681818 | I27: 平方米 | J27: =J26 -> 5300 | K27: =K21 -> 90
A28: 4.5 | B28: 暖通工程 | C28: =ROUND(J28*K28/10000,2) -> 37.1 | G28: =C28+E28+D28+F28 -> 37.1 | H28: =G28/$G$95 -> 0.0016863636 | I28: 平方米 | J28: =J27 -> 5300 | K28: =K16 -> 70
A29: 5 | B29: 农业技术推广中心 | C29: =SUM(C30:C34) -> 219.6 | D29: =SUM(D30:D34) -> 0 | E29: =SUM(E30:E34) -> 0 | F29: =SUM(F30:F34) -> 0 | G29: =C29+E29+D29+F29 -> 219.6 | H29: =G29/$G$95 -> 0.0099818182 | I29: 平方米 | J29: 600
A30: 5.1 | B30: 土建工程 | C30: =ROUND(J30*K30/10000,2) -> 198 | G30: =C30+E30+D30+F30 -> 198 | H30: =G30/$G$95 -> 0.009 | I30: 平方米 | J30: =J29 -> 600 | K30: =K24 -> 3300 | O30: =5000/0.8 -> 6250
A31: 5.2 | B31: 给排水工程 | C31: =ROUND(J31*K31/10000,2) -> 5.4 | G31: =C31+E31+D31+F31 -> 5.4 | H31: =G31/$G$95 -> 0.00024545455 | I31: 平方米 | J31: =J30 -> 600 | K31: =K25 -> 90
A32: 5.3 | B32: 电气工程 | C32: =ROUND(J32*K32/10000,2) -> 6.6 | G32: =C32+E32+D32+F32 -> 6.6 | H32: =G32/$G$95 -> 0.0003 | I32: 平方米 | J32: =J31 -> 600 | K32: =K26 -> 110
A33: 5.4 | B33: 消防工程 | C33: =ROUND(J33*K33/10000,2) -> 5.4 | G33: =C33+E33+D33+F33 -> 5.4 | H33: =G33/$G$95 -> 0.00024545455 | I33: 平方米 | J33: =J32 -> 600 | K33: =K27 -> 90
A34: 5.5 | B34: 暖通工程 | C34: =ROUND(J34*K34/10000,2) -> 4.2 | G34: =C34+E34+D34+F34 -> 4.2 | H34: =G34/$G$95 -> 0.00019090909 | I34: 平方米 | J34: =J33 -> 600 | K34: =K28 -> 70
A35: 6 | B35: 创新创业孵化平台 | C35: =SUM(C36:C40) -> 7352.57 | D35: =SUM(D36:D40) -> 0 | E35: =SUM(E36:E40) -> 0 | F35: =SUM(F36:F40) -> 0 | G35: =C35+E35+D35+F35 -> 7352.57 | H35: =G35/$G$95 -> 0.33420773 | I35: 平方米 | J35: 20089
A36: 6.1 | B36: 土建工程 | C36: =ROUND(J36*K36/10000,2) -> 6629.37 | G36: =C36+E36+D36+F36 -> 6629.37 | H36: =G36/$G$95 -> 0.301335 | I36: 平方米 | J36: =J35 -> 20089 | K36: =K30 -> 3300
A37: 6.2 | B37: 给排水工程 | C37: =ROUND(J37*K37/10000,2) -> 180.8 | G37: =C37+E37+D37+F37 -> 180.8 | H37: =G37/$G$95 -> 0.0082181818 | I37: 平方米 | J37: =J36 -> 20089 | K37: =K31 -> 90
A38: 6.3 | B38: 电气工程 | C38: =ROUND(J38*K38/10000,2) -> 220.98 | G38: =C38+E38+D38+F38 -> 220.98 | H38: =G38/$G$95 -> 0.010044545 | I38: 平方米 | J38: =J37 -> 20089 | K38: =K32 -> 110
A39: 6.4 | B39: 消防工程 | C39: =ROUND(J39*K39/10000,2) -> 180.8 | G39: =C39+E39+D39+F39 -> 180.8 | H39: =G39/$G$95 -> 0.0082181818 | I39: 平方米 | J39: =J38 -> 20089 | K39: =K33 -> 90
A40: 6.5 | B40: 暖通工程 | C40: =ROUND(J40*K40/10000,2) -> 140.62 | G40: =C40+E40+D40+F40 -> 140.62 | H40: =G40/$G$95 -> 0.0063918182 | I40: 平方米 | J40: =J39 -> 20089 | K40: =K34 -> 70
A41: 7 | B41: 创新创业孵化平台地下停车场 | C41: =SUM(C42:C47) -> 3612 | D41: =SUM(D42:D47) -> 0 | E41: =SUM(E42:E47) -> 0 | F41: =SUM(F42:F47) -> 0 | G41: =C41+E41+D41+F41 -> 3612 | H41: =G41/$G$95 -> 0.16418182 | I41: 平方米 | J41: 6000 | L41: 停车位225个
A42: 7.1 | B42: 支护工程 | C42: =ROUND(J42*K42/10000,2) -> 540 | G42: =C42+E42+D42+F42 -> 540 | H42: =G42/$G$95 -> 0.024545455 | I42: 平方米 | J42: =J41 -> 6000 | K42: 900
A43: 7.2 | B43: 主体工程 | C43: =ROUND(J43*K43/10000,2) -> 2880 | G43: =C43+E43+D43+F43 -> 2880 | H43: =G43/$G$95 -> 0.13090909 | I43: 平方米 | J43: =J42 -> 6000 | K43: 4800
A44: 8.2 | B44: 给排水工程 | C44: =ROUND(J44*K44/10000,2) -> 54 | G44: =C44+E44+D44+F44 -> 54 | H44: =G44/$G$95 -> 0.0024545455 | I44: 平方米 | J44: =J43 -> 6000 | K44: 90
A45: 9.2 | B45: 电气工程 | C45: =ROUND(J45*K45/10000,2) -> 66 | G45: =C45+E45+D45+F45 -> 66 | H45: =G45/$G$95 -> 0.003 | I45: 平方米 | J45: =J44 -> 6000 | K45: 110
A46: 7.4 | B46: 消防工程 | C46: =ROUND(J46*K46/10000,2) -> 42 | G46: =C46+E46+D46+F46 -> 42 | H46: =G46/$G$95 -> 0.0019090909 | I46: 平方米 | J46: =J45 -> 6000 | K46: 70
A47: 7.5 | B47: 通风工程 | C47: =ROUND(J47*K47/10000,2) -> 30 | G47: =C47+E47+D47+F47 -> 30 | H47: =G47/$G$95 -> 0.0013636364 | I47: 平方米 | J47: =J46 -> 6000 | K47: 50
A48: 8 | B48: 停车场 | C48: =SUM(C49:C51) -> 34.05 | D48: =SUM(D49:D51) -> 0 | E48: =SUM(E49:E51) -> 0 | F48: =SUM(F49:F51) -> 0 | G48: =SUM(G49:G51) -> 34.05 | H48: =G48/$G$95 -> 0.0015477273 | I48: 平方米 | J48: 1050
A49: 8.1 | B49: 场地铺装 | C49: =ROUND(J49*K49/10000,2) -> 31.5 | G49: =C49+E49+D49+F49 -> 31.5 | H49: =G49/$G$95 -> 0.0014318182 | I49: 平方米 | J49: =J48 -> 1050 | K49: 300 | L49: 停车位40个
A50: 8.2 | B50: 标线工程 | C50: =ROUND(J50*K50/10000,2) -> 1.05 | G50: =C50+E50+D50+F50 -> 1.05 | H50: =G50/$G$95 -> 4.7727273e-05 | I50: 平方米 | J50: =J49 -> 1050 | K50: 10
A51: 8.3 | B51: 闸机及停车管理系统 | C51: =ROUND(J51*K51/10000,2) -> 1.5 | G51: =C51+E51+D51+F51 -> 1.5 | H51: =G51/$G$95 -> 6.8181818e-05 | I51: 项 | J51: 1 | K51: 15000
A52: 9 | B52: 标准化农田 | C52: =SUM(C53:C55) -> 435.78 | D52: =SUM(D53:D55) -> 0 | E52: =SUM(E53:E55) -> 0 | F52: =SUM(F53:F55) -> 0 | G52: =SUM(G53:G55) -> 435.78 | H52: =G52/$G$95 -> 0.019808182 | I52: 亩 | J52: =ROUND(49237/666.67,2) -> 73.86 | L52: 49237平方米
A53: 9.1 | B53: 土地平整 | C53: =ROUND(J53*K53/10000,2) -> 44.32 | G53: =C53+E53+D53+F53 -> 44.32 | H53: =G53/$G$95 -> 0.0020145455 | I53: 亩 | J53: =J52 -> 73.86 | K53: 6000
A54: 9.2 | B54: 挖壕打穴 | C54: =ROUND(J54*K54/10000,2) -> 59.09 | G54: =C54+E54+D54+F54 -> 59.09 | H54: =G54/$G$95 -> 0.0026859091 | I54: 亩 | J54: =J53 -> 73.86 | K54: 8000
A55: 9.3 | B55: 水肥一体 | C55: =ROUND(J55*K55/10000,2) -> 332.37 | G55: =C55+E55+D55+F55 -> 332.37 | H55: =G55/$G$95 -> 0.015107727 | I55: 亩 | J55: =J54 -> 73.86 | K55: 45000
A56: 10 | B56: 标准化高效栽培试验示范田 | C56: =SUM(C57:C59) -> 120.66 | D56: =SUM(D57:D59) -> 0 | E56: =SUM(E57:E59) -> 0 | F56: =SUM(F57:F59) -> 0 | G56: =SUM(G57:G59) -> 120.66 | H56: =G56/$G$95 -> 0.0054845455 | I56: 亩 | J56: =ROUND(13631/666.67,2) -> 20.45 | L56: 13631平方米
A57: 10.1 | B57: 土地平整 | C57: =ROUND(J57*K57/10000,2) -> 12.27 | G57: =C57+E57+D57+F57 -> 12.27 | H57: =G57/$G$95 -> 0.00055772727 | I57: 亩 | J57: =J56 -> 20.45 | K57: =K53 -> 6000
A58: 10.2 | B58: 挖壕打穴 | C58: =ROUND(J58*K58/10000,2) -> 16.36 | G58: =C58+E58+D58+F58 -> 16.36 | H58: =G58/$G$95 -> 0.00074363636 | I58: 亩 | J58: =J57 -> 20.45 | K58: =K54 -> 8000
A59: 10.3 | B59: 水肥一体 | C59: =ROUND(J59*K59/10000,2) -> 92.03 | G59: =C59+E59+D59+F59 -> 92.03 | H59: =G59/$G$95 -> 0.0041831818 | I59: 亩 | J59: =J58 -> 20.45 | K59: =K55 -> 45000 | O59: 数量 | P59: 单价
A60: 11 | B60: 育苗基地 | C60: =SUM(C61:C63) -> 114.82 | D60: =SUM(D61:D63) -> 0 | E60: =SUM(E61:E63) -> 0 | F60: =SUM(F61:F63) -> 0 | G60: =SUM(G61:G63) -> 114.82 | H60: =G60/$G$95 -> 0.0052190909 | I60: 亩 | J60: =ROUND(12972/666.67,2) -> 19.46 | L60: 12972平方米 | O60: 114 | P60: 100
A61: 11.1 | B61: 土地平整 | C61: =ROUND(J61*K61/10000,2) -> 11.68 | G61: =C61+E61+D61+F61 -> 11.68 | H61: =G61/$G$95 -> 0.00053090909 | I61: 亩 | J61: =J60 -> 19.46 | K61: =K57 -> 6000 | M61: =J59+J54+J62 -> 113.77 | O61: 1233 | P61: 150
A62: 11.2 | B62: 挖壕打穴 | C62: =ROUND(J62*K62/10000,2) -> 15.57 | G62: =C62+E62+D62+F62 -> 15.57 | H62: =G62/$G$95 -> 0.00070772727 | I62: 亩 | J62: =J61 -> 19.46 | K62: =K58 -> 8000 | O62: 177 | P62: 120
A63: 11.3 | B63: 水肥一体 | C63: =ROUND(J63*K63/10000,2) -> 87.57 | G63: =C63+E63+D63+F63 -> 87.57 | H63: =G63/$G$95 -> 0.0039804545 | I63: 亩 | J63: =J62 -> 19.46 | K63: =K59 -> 45000 | O63: 431 | P63: 160
A64: （二） | B64: 附属配套工程 | C64: =SUM(C65:C69) -> 2630 | D64: =SUM(D65:D69) -> 0 | E64: =SUM(E65:E69) -> 0 | F64: =SUM(F65:F69) -> 0 | G64: =C64+E64+D64+F64 -> 2630 | H64: =G64/$G$95 -> 0.11954545 | I64: 项 | J64: 1
A65: 1 | B65: 供配电系统 | C65: =ROUND(J65*K65/10000,2) -> 650 | G65: =C65+E65+D65+F65 -> 650 | H65: =G65/$G$95 -> 0.029545455 | I65: 项 | J65: 1 | K65: 6500000
A66: 2 | B66: 室外给排水工程 | C66: =ROUND(J66*K66/10000,2) -> 360 | G66: =C66+E66+D66+F66 -> 360 | H66: =G66/$G$95 -> 0.016363636 | I66: 项 | J66: 1 | K66: 3600000
A67: 3 | B67: 室外消防工程 | C67: =ROUND(J67*K67/10000,2) -> 420 | G67: =C67+E67+D67+F67 -> 420 | H67: =G67/$G$95 -> 0.019090909 | I67: 项 | J67: 1 | K67: 4200000
A68: 4 | B68: 通信工程 | C68: =ROUND(J68*K68/10000,2) -> 320 | G68: =C68+E68+D68+F68 -> 320 | H68: =G68/$G$95 -> 0.014545455 | I68: 项 | J68: 1 | K68: 3200000
A69: 5 | B69: 其他配套工程 | C69: =ROUND(J69*K69/10000,2) -> 880 | G69: =C69+E69+D69+F69 -> 880 | H69: =G69/$G$95 -> 0.04 | I69: 项 | J69: 1 | K69: 8800000
A70: 二 | B70: 工程建设其他费用 | F70: =SUM(F71:F89) -> 2754.06 | G70: =F70 -> 2754.06 | H70: =G70/$G$95 -> 0.12518455
A71: 1 | B71: =其他费自动计算!B12 -> 建设单位管理费 | F71: =ROUND(其他费自动计算!C12,2) -> 213.86 | G71: =F71 -> 213.86 | H71: =G71/$G$95 -> 0.0097209091 | I71: =工程建设其他费细则说明!E4 -> 财建[2016]504号
A72: 2 | B72: =其他费自动计算!B13 -> 场地准备及临时设施费 | F72: =ROUND(其他费自动计算!C13,2) -> 173.86 | G72: =F72 -> 173.86 | H72: =G72/$G$95 -> 0.0079027273 | I72: =工程建设其他费细则说明!E18 -> 建标〔2011〕1号
A73: 3 | B73: =其他费自动计算!B14 -> 前期工作咨询费 | F73: =ROUND(其他费自动计算!C14,2) -> 21.14 | G73: =F73 -> 21.14 | H73: =G73/$G$95 -> 0.00096090909 | I73: =工程建设其他费细则说明!E21 -> 计价格［1999］1283号
A74: 4 | B74: =其他费自动计算!B15 -> 勘察费 | F74: =ROUND(其他费自动计算!C15,2) -> 173.86 | G74: =F74 -> 173.86 | H74: =G74/$G$95 -> 0.0079027273 | I74: =工程建设其他费细则说明!E36 -> 建标〔2011〕1号
A75: 5 | B75: =其他费自动计算!B16 -> 设计费 | F75: =ROUND(其他费自动计算!C16,2) -> 498.31 | G75: =F75 -> 498.31 | H75: =G75/$G$95 -> 0.022650455 | I75: =工程建设其他费细则说明!E37 -> 计价格[2002]10号
A76: 6 | B76: =其他费自动计算!B17 -> 工程监理费 | F76: =ROUND(其他费自动计算!C17,2) -> 347.7 | G76: =F76 -> 347.7 | H76: =G76/$G$95 -> 0.015804545 | I76: =工程建设其他费细则说明!E38 -> 发改价格[2007]670号
A77: 7 | B77: =其他费自动计算!B18 -> 招标代理费 | F77: =ROUND(其他费自动计算!C18,2) -> 44.5 | G77: =F77 -> 44.5 | H77: =G77/$G$95 -> 0.0020227273 | I77: =工程建设其他费细则说明!E42 -> 发改价格[2011]534号
A78: 8 | B78: =其他费自动计算!B19 -> 施工图审查费 | F78: =ROUND(其他费自动计算!C19,2) -> 18.99 | G78: =F78 -> 18.99 | H78: =G78/$G$95 -> 0.00086318182 | I78: =工程建设其他费细则说明!E43 -> 赣价房字[2000]6号
A79: 9 | B79: =其他费自动计算!B20 -> 工程造价咨询费 | F79: =ROUND(其他费自动计算!C20,2) -> 127.17 | G79: =F79 -> 127.17 | H79: =G79/$G$95 -> 0.0057804545 | I79: =工程建设其他费细则说明!E45 -> 赣价协[2021]23号
A80: 10 | B80: =其他费自动计算!B21 -> 工程保险费 | F80: =ROUND(其他费自动计算!C21,2) -> 86.93 | G80: =F80 -> 86.93 | H80: =G80/$G$95 -> 0.0039513636 | I80: =工程建设其他费细则说明!E46 -> 建标〔2011〕1号
A81: 11 | B81: =其他费自动计算!B22 -> 环境影响评价费 | F81: =ROUND(其他费自动计算!C22,2) -> 5.24 | G81: =F81 -> 5.24 | H81: =G81/$G$95 -> 0.00023818182 | I81: =工程建设其他费细则说明!E23 -> 计价格[2002]125 号
A82: 12 | B82: =其他费自动计算!B23 -> 节能评估费 | F82: =ROUND(其他费自动计算!C23,2) -> 7.29 | G82: =F82 -> 7.29 | H82: =G82/$G$95 -> 0.00033136364 | I82: =工程建设其他费细则说明!E29 -> 沪发改环资（2012）043号
A83: 13 | B83: =其他费自动计算!B24 -> 水土保持评价费 | F83: =ROUND(其他费自动计算!C24,2) -> 66.77 | G83: =F83 -> 66.77 | H83: =G83/$G$95 -> 0.003035 | I83: =工程建设其他费细则说明!E27 -> 保监[2005]22 号 2005 年 6 月 17 日
A84: 14 | B84: =其他费自动计算!B25 -> 劳动安全卫生评审费 | F84: =ROUND(其他费自动计算!C25,2) -> 86.93 | G84: =F84 -> 86.93 | H84: =G84/$G$95 -> 0.0039513636 | I84: =工程建设其他费细则说明!E32 -> 建标〔2011〕1号
A85: 15 | B85: =其他费自动计算!B26 -> 社会稳定风险评估费 | F85: =ROUND(其他费自动计算!C26,2) -> 5.66 | G85: =F85 -> 5.66 | H85: =G85/$G$95 -> 0.00025727273 | I85: =工程建设其他费细则说明!E31 -> 赣评审字[2015]70 号
A86: 16 | B86: =其他费自动计算!B27 -> 安全预评价费 | F86: =ROUND(其他费自动计算!C27,2) -> 7.2 | G86: =F86 -> 7.2 | H86: =G86/$G$95 -> 0.00032727273 | I86: =工程建设其他费细则说明!E24 -> 江西省安全评价收费指导价格（试行）
A87: 17 | B87: =其他费自动计算!B28 -> 交通影响评估费 | F87: =ROUND(其他费自动计算!C28,2) -> 0 | G87: =F87 -> 0 | H87: =G87/$G$95 -> 0 | I87: =工程建设其他费细则说明!E33 -> 5万平米（含）以下，2元/平米，5-20万平米，2元/平米，20-100万平米，1.5元/平米，100-200万平米，1.0元/平米；大于200万平米的，0.8元/平米
A88: 17 | B88: 土地流转费 | F88: =ROUND((O60*P60+O61*P61+O62*P62+O63*P63)*30/10000,2) -> 859.65 | G88: =F88 -> 859.65 | H88: =G88/$G$95 -> 0.039075 | I88: 按土地流转协议执行
A89: 18 | B89: 债券发行费 | F89: =ROUND(还本付息!E38*I89,2) -> 9 | G89: =F89 -> 9 | H89: =G89/$G$95 -> 0.00040909091 | I89: 0.001
A90: 三 | B90: 预备费 | F90: =F91+F92 -> 1590.16 | G90: =F90 -> 1590.16 | H90: =G90/$G$95 -> 0.07228
A91: 1 | B91: 基本预备费 | F91: =ROUND((G3+G70)*8%,2)-21.03 -> 1590.16 | G91: =F91 -> 1590.16 | H91: =G91/$G$95 -> 0.07228 | I91: 不超过（一+二）*8%
A92: 2 | B92: 涨价预备费 | F92: 0 | G92: =F92 -> 0 | H92: =G92/$G$95 -> 0
B93: 一+二+三部分合计 | C93: =C3+C70+C90 -> 17385.78 | D93: =D3+D70+D90 -> 0 | E93: =E3+E70+E90 -> 0 | F93: =F3+F70+F90 -> 4344.22 | G93: =C93+E93+D93+F93 -> 21730 | H93: =G93/$G$95 -> 0.98772727
A94: 四 | B94: 建设期利息 | F94: =G94 -> 270 | G94: =分年计划及建设期利息!D20 -> 270 | H94: =G94/$G$95 -> 0.012272727
A95: 五 | B95: 总投资 | C95: =C3+C70+C90+C94 -> 17385.78 | D95: =D3+D70+D90+D94 -> 0 | E95: =E3+E70+E90+E94 -> 0 | F95: =F3+F70+F90+F94 -> 4614.22 | G95: =G93+G94 -> 22000 | H95: =G95/$G$95 -> 1
M97: 2600±400
M98: 2000±300
M117: ←可直接调整数字，前面文字为单元格格式，不影响计算

Sheet 其他费自动计算
A1: 序号 | B1: 费用输入（万元） | C1: 输入👇
A2: 1 | B2: 工程费用 | C2: =总投资估算!G3 -> 17385.78 | E2: 总投资 | G2: 总建筑面积
A3: 2 | B3: 总投资 | E3: 7000 | F3: ☜手动输入 | G3: =项目技术经济指标!D3/10000 -> 0 | H3: ☜手动输入
A4: 3 | B4: 设备购置费 | C4: =总投资估算!E3 -> 0
A7: 地区筛选 | B7: 红谷滩区
E9: 单位：万元 | G9: 地区折扣目录
A10: 序号 | B10: 费用名称 | C10: 估算金额 | D10: 地区折扣 | E10: 折后金额 | F10: 计费基础 | G10: 南昌市 | I10: 红谷滩区 | K10: 南昌县
G11: 参考文件 | H11: 折扣率 | I11: 参考文件 | J11: 折扣率 | K11: 参考文件 | L11: 折扣率
A12: 1 | B12: =工程建设其他费细则说明!B4 -> 建设单位管理费 | C12: =H112 -> 213.8578 | D12: =SUMIF(G$10:L$10,B$7,H12) -> 0.8 | E12: =C12*D12 -> 171.08624 | F12: 工程费用 | H12: 0.3 | J12: 0.8 | L12: 0.7
A13: 2 | B13: =工程建设其他费细则说明!B18 -> 场地准备及临时设施费 | C13: =C2*1% -> 173.8578 | D13: =SUMIF(G$10:L$10,B$7,H13) -> 0.6 | E13: =C13*D13 -> 104.31468 | F13: 工程费用 | H13: 0.6 | J13: 0.6 | L13: 0.6
A14: 3 | B14: =工程建设其他费细则说明!B21 -> 前期工作咨询费 | C14: =G34 -> 21.141877 | D14: =SUMIF(G$10:L$10,B$7,H14) -> 0.5 | E14: =C14*D14 -> 10.570939 | F14: 总投资 | H14: 0.5 | J14: 0.5 | L14: 0.6
A15: 4 | B15: =工程建设其他费细则说明!B36 -> 勘察费 | C15: =C2*1% -> 173.8578 | D15: =SUMIF(G$10:L$10,B$7,H15) -> 0.4 | E15: =C15*D15 -> 69.54312 | F15: 工程费用 | H15: 0.8 | J15: 0.4 | L15: 0.85
A16: 5 | B16: =工程建设其他费细则说明!B37 -> 设计费 | C16: =E123 -> 498.30744 | D16: =SUMIF(G$10:L$10,B$7,H16) -> 0.4 | E16: =C16*D16 -> 199.32297 | F16: 工程费用 | H16: 0.9 | J16: 0.4 | L16: 0.85
A17: 6 | B17: =工程建设其他费细则说明!B38 -> 工程监理费 | C17: =E147 -> 347.70343 | D17: =SUMIF(G$10:L$10,B$7,H17) -> 0.7 | E17: =C17*D17 -> 243.3924 | F17: 工程费用 | H17: 0.5 | J17: 0.7 | L17: 0.7
A18: 7 | B18: =工程建设其他费细则说明!B42 -> 招标代理费 | C18: =S57 -> 44.501839 | D18: =SUMIF(G$10:L$10,B$7,H18) -> 0.49 | E18: =C18*D18 -> 21.805901 | F18: 分包 | H18: 0.3 | J18: 0.49 | L18: 0.8
A19: 8 | B19: =工程建设其他费细则说明!B43 -> 施工图审查费 | C19: =H181 -> 18.98578 | D19: =SUMIF(G$10:L$10,B$7,H19) -> 0.7 | E19: =C19*D19 -> 13.290046 | F19: 工程费用 | H19: 0.4 | J19: 0.7 | L19: 0.6
A20: 9 | B20: =工程建设其他费细则说明!B45 -> 工程造价咨询费 | C20: =H169 -> 127.16615 | D20: =SUMIF(G$10:L$10,B$7,H20) -> 0.5 | E20: =C20*D20 -> 63.583074 | F20: 工程费用 | H20: 0.7 | J20: 0.5 | L20: 0.7
A21: 10 | B21: =工程建设其他费细则说明!B46 -> 工程保险费 | C21: =C2*0.5% -> 86.9289 | D21: =SUMIF(G$10:L$10,B$7,H21) -> 0.7 | E21: =C21*D21 -> 60.85023 | F21: 工程费用 | H21: 0.6 | J21: 0.7 | L21: 0.7
A22: 11 | B22: =工程建设其他费细则说明!B23 -> 环境影响评价费 | C22: =G64 -> 5.2352941 | D22: =SUMIF(G$10:L$10,B$7,H22) -> 0.7 | E22: =C22*D22 -> 3.6647059 | F22: 总投资 | H22: 0.7 | J22: 0.7 | L22: 0.7
A23: 12 | B23: =工程建设其他费细则说明!B29 -> 节能评估费 | C23: =H218 -> 7.2925115 | D23: =SUMIF(G$10:L$10,B$7,H23) -> 0.7 | E23: =C23*D23 -> 5.1047581 | F23: 工程费用 | H23: 0.7 | J23: 0.7 | L23: 0.7
A24: 13 | B24: =工程建设其他费细则说明!B27 -> 水土保持评价费 | C24: =G190 -> 66.77156 | D24: =SUMIF(G$10:L$10,B$7,H24) -> 0.7 | E24: =C24*D24 -> 46.740092 | F24: 工程费用 | H24: 0.7 | J24: 0.7 | L24: 0.7
A25: 14 | B25: =工程建设其他费细则说明!B32 -> 劳动安全卫生评审费 | C25: =C2*0.5% -> 86.9289 | D25: =SUMIF(G$10:L$10,B$7,H25) -> 0.7 | E25: =C25*D25 -> 60.85023 | F25: 工程费用 | H25: 0.7 | J25: 0.7 | L25: 0.7
A26: 15 | B26: =工程建设其他费细则说明!B31 -> 社会稳定风险评估费 | C26: =I75 -> 5.6571429 | D26: =SUMIF(G$10:L$10,B$7,H26) -> 0.7 | E26: =C26*D26 -> 3.96 | F26: 总投资 | H26: 0.7 | J26: 0.7 | L26: 0.7
A27: 16 | B27: =工程建设其他费细则说明!B24 -> 安全预评价费 | C27: =G87 -> 7.2 | D27: =SUMIF(G$10:L$10,B$7,H27) -> 0.7 | E27: =C27*D27 -> 5.04 | F27: 总投资 | H27: 0.7 | J27: 0.7 | L27: 0.7
A28: 17 | B28: =工程建设其他费细则说明!B33 -> 交通影响评估费 | C28: 0 | D28: =SUMIF(G$10:L$10,B$7,H28) -> 0.7 | E28: =C28*D28 -> 0 | F28: 总建筑面积 | H28: 0.7 | J28: 0.7 | L28: 0.7
A29: 合计 | C29: =SUM(C12:C28) -> 1885.3942
A32: 前期工作咨询费（可行性研究报告）
A33: 序号 | B33: 计费额 | E33: 基价 | F33: 输入费用👇 | G33: 直线内插法计取
F34: =E3 -> 7000 | G34: =SUM(G35:G41) -> 21.141877
A35: 1 | C35: > | D35: 1000 | E35: 3 | F35: =IF(F34<=D35,1,0) -> 0 | G35: =IF($F35=1,(E35/D35*$F34),0) -> 0
A36: 2 | B36: 1001 | C36: ~ | D36: 3000 | E36: 6 | F36: =IF(AND($F$34<=D36,$F$34>B36),1,0) -> 0 | G36: =IF($F36=1,(E36+((E37-E36)/(D36-B36)*($F$34-B36))),0) -> 0
A37: 3 | B37: 3001 | C37: ~ | D37: 10000 | E37: 12 | F37: =IF(AND($F$34<=D37,$F$34>B37),1,0) -> 1 | G37: =IF($F37=1,(E37+((E38-E37)/(D37-B37)*($F$34-B37))),0) -> 21.141877
A38: 4 | B38: 10001 | C38: ~ | D38: 50000 | E38: 28 | F38: =IF(AND($F$34<=D38,$F$34>B38),1,0) -> 0 | G38: =IF($F38=1,(E38+((E39-E38)/(D38-B38)*($F$34-B38))),0) -> 0
A39: 5 | B39: 50001 | C39: ~ | D39: 100000 | E39: 75 | F39: =IF(AND($F$34<=D39,$F$34>B39),1,0) -> 0 | G39: =IF($F39=1,(E39+((E40-E39)/(D39-B39)*($F$34-B39))),0) -> 0
A40: 6 | B40: 100000 | C40: ~ | D40: 500000 | E40: 110 | F40: =IF(AND($F$34<=D40,$F$34>B40),1,0) -> 0 | G40: =IF($F40=1,(E40+((E41-E40)/(D40-B40)*($F$34-B40))),0) -> 0
A41: 7 | B41: 500000 | E41: 200 | F41: =IF(AND($F$34>B41),1,0) -> 0 | G41: =IF($F41=1,MIN(250,F34*E41/B41),0) -> 0
A44: 招标代理服务费
A45: 计费额 | D45: 货物采购 | G45: 服务招标（勘察） | J45: 服务招标（设计） | M45: 服务招标（监理） | P45: 工程招标
D46: =C4 -> 0 | G46: =C15 -> 173.8578 | J46: =C16 -> 498.30744 | M46: =C17 -> 347.70343 | P46: =C2-C4 -> 17385.78
B47: < | C47: 100 | D47: =C47*E47 -> 1.5 | E47: 0.015 | F47: =IF(D46<=C47,D46*E47,0) -> 0 | G47: =C47*H47 -> 1.5 | H47: 0.015 | I47: =IF(H46<=C47,H46*H47,0) -> 0 | J47: =C47*K47 -> 1.5 | K47: 0.015 | L47: =IF(J46<=C47,J46*K47,0) -> 0 | M47: =C47*N47 -> 1.5 | N47: 0.015 | O47: =IF(M46<=C47,M46*N47,0) -> 0 | P47: =C47*Q47 -> 1 | Q47: 0.01 | R47: =IF(P46<=C47,P46*Q47,0) -> 0
A48: 100 | B48: ~ | C48: 500 | D48: =D47+(C48-A48)*E48 -> 5.9 | E48: 0.011 | F48: =IF(AND($D$46>A48,$D$458<C48),(D47+($D$46-C47)*E48),0) -> 0 | G48: =G47+(C48-C47)*H48 -> 4.7 | H48: 0.008 | I48: =IF(AND($G$46>A48,$G$46<C48),(G47+($G$46-C47)*H48),0) -> 2.0908624 | J48: =J47+(C48-A48)*K48 -> 4.7 | K48: 0.008 | L48: =IF(AND($J$46>A48,$J$46<C48),(J47+($J$46-C47)*K48),0) -> 4.6864595 | M48: =M47+(C48-C47)*N48 -> 4.7 | N48: 0.008 | O48: =IF(AND($M$46>A48,$M$46<C48),(M47+($M$46-C47)*N48),0) -> 3.4816275 | P48: =P47+(C48-C47)*Q48 -> 3.8 | Q48: 0.007 | R48: =IF(AND($P$46>A48,$P$46<C48),(P47+($P$46-C47)*Q48),0) -> 0
A49: 500 | B49: ~ | C49: 1000 | D49: =D48+(C49-A49)*E49 -> 9.9 | E49: 0.008 | F49: =IF(AND($D$46>A49,$D$458<C49),(D48+($D$46-C48)*E49),0) -> 0 | G49: =G48+(C49-C48)*H49 -> 6.95 | H49: 0.0045 | I49: =IF(AND($G$46>A49,$G$46<C49),(G48+($G$46-C48)*H49),0) -> 0 | J49: =J48+(C49-A49)*K49 -> 6.95 | K49: 0.0045 | L49: =IF(AND($J$46>A49,$J$46<C49),(J48+($J$46-C48)*K49),0) -> 0 | M49: =M48+(C49-C48)*N49 -> 6.95 | N49: 0.0045 | O49: =IF(AND($M$46>A49,$M$46<C49),(M48+($M$46-C48)*N49),0) -> 0 | P49: =P48+(C49-C48)*Q49 -> 6.55 | Q49: 0.0055 | R49: =IF(AND($P$46>A49,$P$46<C49),(P48+($P$46-C48)*Q49),0) -> 0
A50: 1000 | B50: ~ | C50: 5000 | D50: =D49+(C50-A50)*E50 -> 29.9 | E50: 0.005 | F50: =IF(AND($D$46>A50,$D$458<C50),(D49+($D$46-C49)*E50),0) -> 0 | G50: =G49+(C50-C49)*H50 -> 16.95 | H50: 0.0025 | I50: =IF(AND($G$46>A50,$G$46<C50),(G49+($G$46-C49)*H50),0) -> 0 | J50: =J49+(C50-A50)*K50 -> 16.95 | K50: 0.0025 | L50: =IF(AND($J$46>A50,$J$46<C50),(J49+($J$46-C49)*K50),0) -> 0 | M50: =M49+(C50-C49)*N50 -> 16.95 | N50: 0.0025 | O50: =IF(AND($M$46>A50,$M$46<C50),(M49+($M$46-C49)*N50),0) -> 0 | P50: =P49+(C50-C49)*Q50 -> 20.55 | Q50: 0.0035 | R50: =IF(AND($P$46>A50,$P$46<C50),(P49+($P$46-C49)*Q50),0) -> 0
A51: 5000 | B51: ~ | C51: 10000 | D51: =D50+(C51-A51)*E51 -> 42.4 | E51: 0.0025 | F51: =IF(AND($D$46>A51,$D$458<C51),(D50+($D$46-C50)*E51),0) -> 0 | G51: =G50+(C51-C50)*H51 -> 21.95 | H51: 0.001 | I51: =IF(AND($G$46>A51,$G$46<C51),(G50+($G$46-C50)*H51),0) -> 0 | J51: =J50+(C51-A51)*K51 -> 21.95 | K51: 0.001 | L51: =IF(AND($J$46>A51,$J$46<C51),(J50+($J$46-C50)*K51),0) -> 0 | M51: =M50+(C51-C50)*N51 -> 21.95 | N51: 0.001 | O51: =IF(AND($M$46>A51,$M$46<C51),(M50+($M$46-C50)*N51),0) -> 0 | P51: =P50+(C51-C50)*Q51 -> 30.55 | Q51: 0.002 | R51: =IF(AND($P$46>A51,$P$46<C51),(P50+($P$46-C50)*Q51),0) -> 0
A52: 10000 | B52: ~ | C52: 50000 | D52: =D51+(C52-A52)*E52 -> 62.4 | E52: 0.0005 | F52: =IF(AND($D$46>A52,$D$458<C52),(D51+($D$46-C51)*E52),0) -> 0 | G52: =G51+(C52-C51)*H52 -> 41.95 | H52: 0.0005 | I52: =IF(AND($G$46>A52,$G$46<C52),(G51+($G$46-C51)*H52),0) -> 0 | J52: =J51+(C52-A52)*K52 -> 41.95 | K52: 0.0005 | L52: =IF(AND($J$46>A52,$J$46<C52),(J51+($J$46-C51)*K52),0) -> 0 | M52: =M51+(C52-C51)*N52 -> 41.95 | N52: 0.0005 | O52: =IF(AND($M$46>A52,$M$46<C52),(M51+($M$46-C51)*N52),0) -> 0 | P52: =P51+(C52-C51)*Q52 -> 50.55 | Q52: 0.0005 | R52: =IF(AND($P$46>A52,$P$46<C52),(P51+($P$46-C51)*Q52),0) -> 34.24289
A53: 50000 | B53: ~ | C53: 100000 | D53: =D52+(C53-A53)*E53 -> 79.9 | E53: 0.00035 | F53: =IF(AND($D$46>A53,$D$458<C53),(D52+($D$46-C52)*E53),0) -> 0 | G53: =G52+(C53-C52)*H53 -> 59.45 | H53: 0.00035 | I53: =IF(AND($G$46>A53,$G$46<C53),(G52+($G$46-C52)*H53),0) -> 0 | J53: =J52+(C53-A53)*K53 -> 59.45 | K53: 0.00035 | L53: =IF(AND($J$46>A53,$J$46<C53),(J52+($J$46-C52)*K53),0) -> 0 | M53: =M52+(C53-C52)*N53 -> 59.45 | N53: 0.00035 | O53: =IF(AND($M$46>A53,$M$46<C53),(M52+($M$46-C52)*N53),0) -> 0 | P53: =P52+(C53-C52)*Q53 -> 68.05 | Q53: 0.00035 | R53: =IF(AND($P$46>A53,$P$46<C53),(P52+($P$46-C52)*Q53),0) -> 0
A54: 100000 | B54: ~ | C54: 500000 | D54: =D53+(C54-A54)*E54 -> 111.9 | E54: 8e-05 | F54: =IF(AND($D$46>A54,$D$458<C54),(D53+($D$46-C53)*E54),0) -> 0 | G54: =G53+(C54-C53)*H54 -> 91.45 | H54: 8e-05 | I54: =IF(AND($G$46>A54,$G$46<C54),(G53+($G$46-C53)*H54),0) -> 0 | J54: =J53+(C54-A54)*K54 -> 91.45 | K54: 8e-05 | L54: =IF(AND($J$46>A54,$J$46<C54),(J53+($J$46-C53)*K54),0) -> 0 | M54: =M53+(C54-C53)*N54 -> 91.45 | N54: 8e-05 | O54: =IF(AND($M$46>A54,$M$46<C54),(M53+($M$46-C53)*N54),0) -> 0 | P54: =P53+(C54-C53)*Q54 -> 100.05 | Q54: 8e-05 | R54: =IF(AND($P$46>A54,$P$46<C54),(P53+($P$46-C53)*Q54),0) -> 0
A55: 500000 | B55: ~ | C55: 1000000 | D55: =D54+(C55-A55)*E55 -> 141.9 | E55: 6e-05 | F55: =IF(AND($D$46>A55,$D$458<C55),(D54+($D$46-C54)*E55),0) -> 0 | G55: =G54+(C55-C54)*H55 -> 121.45 | H55: 6e-05 | I55: =IF(AND($G$46>A55,$G$46<C55),(G54+($G$46-C54)*H55),0) -> 0 | J55: =J54+(C55-A55)*K55 -> 121.45 | K55: 6e-05 | L55: =IF(AND($J$46>A55,$J$46<C55),(J54+($J$46-C54)*K55),0) -> 0 | M55: =M54+(C55-C54)*N55 -> 121.45 | N55: 6e-05 | O55: =IF(AND($M$46>A55,$M$46<C55),(M54+($M$46-C54)*N55),0) -> 0 | P55: =P54+(C55-C54)*Q55 -> 130.05 | Q55: 6e-05 | R55: =IF(AND($P$46>A55,$P$46<C55),(P54+($P$46-C54)*Q55),0) -> 0
A56: 1000000 | B56: < | E56: 4e-05 | F56: =IF(AND($D$46>A56),(D55+($D$46-A56)*E56),0) -> 0 | H56: 4e-05 | I56: =IF(AND(G46>A56),(G55+(G46-A56)*H56),0) -> 0 | K56: 4e-05 | L56: =IF(AND(J46>A56),(J55+(J46-A56)*K56),0) -> 0 | N56: 4e-05 | O56: =IF(AND(M46>A56),(M55+(M46-A56)*N56),0) -> 0 | Q56: 4e-05 | R56: =IF(AND(P46>A56),(P55+(P46-A56)*Q56),0) -> 0 | S56: 总费用
A57: 费用合计 | D57: =SUM(F47:F56) -> 0 | G57: =SUM(I47:I56) -> 2.0908624 | J57: =SUM(L47:L56) -> 4.6864595 | M57: =SUM(O47:O56) -> 3.4816275 | P57: =SUM(R47:R56) -> 34.24289 | S57: =SUM(D57:Q57) -> 44.501839
A61: 环境影响评估费
A62: 序号 | B62: 计费额 | E62: 基价 | F62: 输入费用👇 | G62: 直线内插法
E63: 编制报告书 （含大纲） | G63: 编制报告表
F64: =E3 -> 7000 | G64: =SUM(G65:G70) -> 5.2352941
A65: 1 | C65: > | D65: 3000 | E65: 5 | F65: =IF(F64<=D65,1,0) -> 0 | G65: =IF(F65=1,(E65/D65*F64),0) -> 0
A66: 2 | B66: 3000 | C66: ~ | D66: 20000 | E66: 6 | F66: =IF(AND($F$64<=D66,$F$64>B66),1,0) -> 1 | G66: =IF(F66=1,(E65+((E66-E65)/(D66-B66)*($F$64-B66))),0) -> 5.2352941
A67: 3 | B67: 20000 | C67: ~ | D67: 100000 | E67: 15 | F67: =IF(AND($F$64<=D67,$F$64>B67),1,0) -> 0 | G67: =IF(F67=1,(E66+((E67-E66)/(D67-B67)*($F$64-B67))),0) -> 0
A68: 4 | B68: 100000 | C68: ~ | D68: 500000 | E68: 35 | F68: =IF(AND($F$64<=D68,$F$64>B68),1,0) -> 0 | G68: =IF(F68=1,(E67+((E68-E67)/(D68-B68)*($F$64-B68))),0) -> 0
A69: 5 | B69: 500000 | C69: ~ | D69: 1000000 | E69: 75 | F69: =IF(AND($F$64<=D69,$F$64>B69),1,0) -> 0 | G69: =IF(F69=1,(E68+((E69-E68)/(D69-B69)*($F$64-B69))),0) -> 0
A70: 6 | B70: 1000000 | C70: ~ | D70: 500000 | E70: 110 | F70: =IF(AND($F$64<=D70,$F$64>B70),1,0) -> 0 | G70: =IF(F70=1,(E69+((E70-E69)/(D70-B70)*($F$64-B70))),0) -> 0
A73: =工程建设其他费细则说明!B31 -> 社会稳定风险评估费
A74: 序号 | B74: 投资额 | E74: 基费 | F74: 输入费用👇 | G74: 直线内插法计算 | H74: 风险敏感系数 | I74: 合计
F75: =E3 -> 7000 | G75: =SUM(G76:G81) -> 4.7142857 | H75: 1.2 | I75: =SUM(I76:I81) -> 5.6571429
A76: 1 | C76: < | D76: 3000 | E76: 3 | F76: =IF(AND(F75<=D76,F75>0),1,0) -> 0 | G76: =IF(F76=1,E76/D76*F75,0) -> 0 | H76: 1.2 | I76: =IF(F76=1,MAX(G76*H76,E76),0) -> 0
A77: 2 | B77: 3000 | C77: ~ | D77: 10000 | E77: 6 | F77: =IF(AND($F$75>B77,$F$75<=D77),1,0) -> 1 | G77: =IF(F77=1,(E76+(E77-E76)/(D77-B77)*($F$75-B77)),0) -> 4.7142857 | H77: 1.2 | I77: =G77*H77 -> 5.6571429
A78: 3 | B78: 10000 | C78: ~ | D78: 50000 | E78: 9 | F78: =IF(AND($F$75>B78,$F$75<=D78),1,0) -> 0 | G78: =IF(F78=1,(E77+(E78-E77)/(D78-B78)*($F$75-B78)),0) -> 0 | H78: 1.2 | I78: =G78*H78 -> 0
A79: 4 | B79: 50000 | C79: ~ | D79: 100000 | E79: 12 | F79: =IF(AND($F$75>B79,$F$75<=D79),1,0) -> 0 | G79: =IF(F79=1,(E78+(E79-E78)/(D79-B79)*($F$75-B79)),0) -> 0 | H79: 1.2 | I79: =G79*H79 -> 0
A80: 5 | B80: 100000 | C80: ~ | D80: 500000 | E80: 15 | F80: =IF(AND($F$75>B80,$F$75<=D80),1,0) -> 0 | G80: =IF(F80=1,(E79+(E80-E79)/(D80-B80)*($F$75-B80)),0) -> 0 | H80: 1.2 | I80: =G80*H80 -> 0
A81: 6 | B81: 500000 | C81: < | E81: 20 | F81: =IF(F75>B81,1,0) -> 0 | G81: =IF(F81=1,E81/B81*F75,0) -> 0 | H81: 1.2 | I81: =IF(F81=1,MIN(G81*H81,E81),0) -> 0
A82: 注：不考虑行业调整系数，敏感性系数按规划方案、环评、拆迁征地补偿方案等尚未公示，项目社会稳定风险尚不确定的项目考虑，系数为1.2，收费低于3万元的，按3万元收取；高于20万元的，按20万元收取。
A85: 安全预评价
A86: 序号 | B86: 总投资额 （万元） | E86: 基础报价 （万元） | F86: 输入费用👇 | G86: 直线内插法计取
F87: =E3 -> 7000 | G87: =SUM(G88:G96) -> 7.2
A88: 1 | C88: < | D88: =10000*0.05 -> 500 | E88: 2 | F88: =IF(F87<=D88,1,0) -> 0 | G88: =IF(F88=1,E88/D88*F87,0) -> 0
A89: 2 | B89: =10000*0.05 -> 500 | C89: ~ | D89: =10000*0.1 -> 1000 | E89: 3.5 | F89: =IF(AND($F$87>B89,$F$87<=D89),1,0) -> 0 | G89: =IF(F89=1,(E88+(E89-E88)/(D89-B89)*($F$87-B89)),0) -> 0
A90: 3 | B90: =10000*0.1 -> 1000 | C90: ~ | D90: =10000*0.2 -> 2000 | E90: 5 | F90: =IF(AND($F$87>B90,$F$87<=D90),1,0) -> 0 | G90: =IF(F90=1,(E89+(E90-E89)/(D90-B90)*($F$87-B90)),0) -> 0
A91: 4 | B91: =10000*0.2 -> 2000 | C91: ~ | D91: =10000*0.5 -> 5000 | E91: 7 | F91: =IF(AND($F$87>B91,$F$87<=D91),1,0) -> 0 | G91: =IF(F91=1,(E90+(E91-E90)/(D91-B91)*($F$87-B91)),0) -> 0
A92: 5 | B92: =10000*0.5 -> 5000 | C92: ~ | D92: 10000 | E92: =0.5*1.5*10000/1000 -> 7.5 | F92: =IF(AND($F$87>B92,$F$87<=D92),1,0) -> 1 | G92: =IF(F92=1,(E91+(E92-E91)/(D92-B92)*($F$87-B92)),0) -> 7.2
A93: 6 | B93: 10000 | C93: ~ | D93: 20000 | E93: =1*10000*1/1000 -> 10 | F93: =IF(AND($F$87>B93,$F$87<=D93),1,0) -> 0 | G93: =IF(F93=1,(E92+(E93-E92)/(D93-B93)*($F$87-B93)),0) -> 0
A94: 7 | B94: 20000 | C94: ~ | D94: 50000 | E94: =2*0.7*10000/1000 -> 14 | F94: =IF(AND($F$87>B94,$F$87<=D94),1,0) -> 0 | G94: =IF(F94=1,(E93+(E94-E93)/(D94-B94)*($F$87-B94)),0) -> 0
A95: 8 | B95: 50000 | C95: ~ | D95: 100000 | E95: =5*0.4*10000/1000 -> 20 | F95: =IF(AND($F$87>B95,$F$87<=D95),1,0) -> 0 | G95: =IF(F95=1,(E94+(E95-E94)/(D95-B95)*($F$87-B95)),0) -> 0
A96: 9 | B96: 100000 | E96: =10*0.3*10000/1000 -> 30 | F96: =IF(F87>B96,1,0) -> 0 | G96: =IF(F96=1,E96/B96*F87,0) -> 0
A99: 交通影响评估费
A100: 序号 | B100: 规模 （建筑总面积：万平方米） | E100: 单价 （元/平方米） | F100: 收费基数 （万元） | G100: 输入建筑面积👇 | H100: 差额累进法计算 | I100: 系数 | J100: 总计
G101: =G3 -> 0 | H101: =SUM(H102:H106) -> 0 | I101: 1 | J101: =SUM(J102:J106) -> 0
A102: 1 | C102: < | D102: 5 | E102: 2 | F102: 10 | G102: =IF(AND(G101<=D102,G101>0),1,0) -> 0 | H102: =IF(G102=1,F102,0) -> 0 | I102: =I$101 -> 1 | J102: =H102*I102 -> 0
A103: 2 | B103: 5 | C103: ~ | D103: 20 | E103: 2 | F103: 10 | G103: =IF(AND($G$2<=D103,$G$2>B103),1,0) -> 0 | H103: =IF(G103=1,(F103+(G$2-B103)*E103),0) -> 0 | I103: =I$101 -> 1 | J103: =H103*I103 -> 0
A104: 3 | B104: 20 | C104: ~ | D104: 100 | E104: 1.5 | F104: 40 | G104: =IF(AND($G$2<=D104,$G$2>B104),1,0) -> 0 | H104: =IF(G104=1,(F104+(G$2-B104)*E104),0) -> 0 | I104: =I$101 -> 1 | J104: =H104*I104 -> 0
A105: 4 | B105: 100 | C105: ~ | D105: 200 | E105: 1 | F105: 160 | G105: =IF(AND($G$2<=D105,$G$2>B105),1,0) -> 0 | H105: =IF(G105=1,(F105+(G$2-B105)*E105),0) -> 0 | I105: =I$101 -> 1 | J105: =H105*I105 -> 0
A106: 5 | B106: 200 | C106: < | E106: 0.8 | F106: 260 | G106: =IF(G101>B106,1,0) -> 0 | H106: =IF(G106=1,MAX(F106,E106*$G$2),0) -> 0 | I106: =I$101 -> 1 | J106: =H106*I106 -> 0
A107: 注：大型会议中心、体育运动中心、居住区、商业中心、学校、大型停车场（库）、区域路网等收费应取 1.5-1.8 系数。
A110: 建设单位管理费
A111: 收费基价表 | G111: 工程费用👇 | H111: 差额定率累进法
A112: 序号 | B112: 计费额 | E112: 费率 | F112: 全额 | G112: =C2 -> 17385.78 | H112: =SUM(H113:H118) -> 213.8578
A113: 1 | C113: > | D113: 1000 | E113: 0.02 | F113: =E113*D113 -> 20 | G113: =IF(G112<=D113,1,0) -> 0 | H113: =IF(G113=1,(G112*E113),0) -> 0
A114: 2 | B114: 1001 | C114: ~ | D114: 5000 | E114: 0.015 | F114: =F113+(D114-D113)*E114 -> 80 | G114: =IF(AND($G$112<=D114,$G$112>B114),1,0) -> 0 | H114: =IF(G114=1,(F113+($G$112-D113)*E114),0) -> 0
A115: 3 | B115: 5001 | C115: ~ | D115: 10000 | E115: 0.012 | F115: =F114+(D115-D114)*E115 -> 140 | G115: =IF(AND($G$112<=D115,$G$112>B115),1,0) -> 0 | H115: =IF(G115=1,(F114+($G$112-D114)*E115),0) -> 0
A116: 4 | B116: 10001 | C116: ~ | D116: 50000 | E116: 0.01 | F116: =F115+(D116-D115)*E116 -> 540 | G116: =IF(AND($G$112<=D116,$G$112>B116),1,0) -> 1 | H116: =IF(G116=1,(F115+($G$112-D115)*E116),0) -> 213.8578
A117: 5 | B117: 50001 | C117: ~ | D117: 100000 | E117: 0.008 | F117: =F116+(D117-D116)*E117 -> 940 | G117: =IF(AND($G$112<=D117,$G$112>B117),1,0) -> 0 | H117: =IF(G117=1,(F116+($G$112-D116)*E117),0) -> 0
A118: 6 | B118: 100000 | C118: < | E118: 0.004 | G118: =IF(AND($G$112>B118),1,0) -> 0 | H118: =IF(G118=1,(F117+($G$112-D117)*E118),0) -> 0
...

Sheet 分年计划及建设期利息
B1: 工期起始 | C1: 45108.9 | D1: 月数汇总 | F1: 资金来源 | G1: 金额（万元） | H1: 占比 | K1: ☜该色块为需手动输入
B2: 工期结束 | C2: 45535 | D2: =(YEAR(C2)-YEAR(C1))*12 -> 12 | F2: 资本金 | G2: =G4-G3 -> 13000 | H2: =G2/$G$4 -> 0.59090909 | K2: ☜出现该色块的单元格为报错格
B3: 建设年度 | C3: 建设年度起 | D3: 建设年度止 | F3: 发债金额 | G3: 9000 | H3: =G3/$G$4 -> 0.40909091
B4: 第一年度 | C4: =C1 -> 45108.9 | D4: =EOMONTH(C4,11) -> 45473 | F4: 总投资 | G4: =总投资估算!G95 -> 22000 | H4: =G4/$G$4 -> 1
B5: 第二年度 | C5: =EOMONTH(D4,1) -> 45504 | D5: =EOMONTH(C5,11) -> 45838
B6: 第三年度 | C6: =EOMONTH(D5,1) -> 45869 | D6: =C2 -> 45535
B8: 表1-分年资金使用
B9: 序号 | C9: 项目 | D9: 合计 | E9: 建设期 | I9: 检查列
E10: 2025 | F10: 2026 | G10: =F10+1 -> 2027 | H10: =G10+1 -> 2028
B11: 一 | C11: 进度安排
B12: 1 | C12: 建设进度 | D12: =SUM(E12:H12) -> 1 | E12: 0.6 | F12: 0.4 | G12: =1-F12-E12 -> 0 | H12: 0 | I12: =SUM(E12:H12) -> 1
B13: 2 | C13: 其他费投入进度 | D13: =SUM(E13:H13) -> 1 | E13: 0.6 | F13: 0.4 | G13: =1-F13-E13 -> 0 | H13: 0 | I13: =SUM(E13:H13) -> 1
B14: 3 | C14: 专项债投入进度 | D14: =SUM(E14:H14) -> 1 | E14: 1 | F14: 0 | G14: =1-F14-E14 -> 0 | H14: 0 | I14: =SUM(E14:H14) -> 1
B15: 二 | C15: 总投资 | D15: =D16+D20 -> 22000 | E15: =E16+E20 -> 13173.01 | F15: =F16+F20 -> 8826.99 | H15: =H16+H20 -> 0 | I15: =SUM(E15:H15) -> 22000 | J15: =I15-D15 -> 0
B16: 1 | C16: 建设投资 | D16: =SUM(E16:H16) -> 21730 | E16: =E17+E18+E19 -> 13038.01 | F16: =F17+F18+F19 -> 8691.99 | G16: =G17+G18+G19 -> 0 | H16: =H17+H18+H19 -> 0 | I16: =SUM(E16:H16) -> 21730 | J16: =I16-D16 -> 0
B17: 1.1 | C17: 工程费用 | D17: =总投资估算!G3 -> 17385.78 | E17: =ROUND($D$17*E12,2) -> 10431.47 | F17: =ROUND($D$17*F12,2) -> 6954.31 | G17: =ROUND($D$17*G12,2) -> 0 | H17: =ROUND($D$17*H12,2) -> 0 | I17: =SUM(E17:H17) -> 17385.78 | J17: =I17-D17 -> 0
B18: 1.2 | C18: 工程建设其他费 | D18: =总投资估算!G70 -> 2754.06 | E18: =ROUND($D$18*E13,2) -> 1652.44 | F18: =ROUND($D$18*F13,2) -> 1101.62 | G18: =ROUND($D$18*G13,2) -> 0 | H18: =ROUND($D$18*H13,2) -> 0 | I18: =SUM(E18:H18) -> 2754.06 | J18: =I18-D18 -> 0
B19: 1.3 | C19: 基本预备费 | D19: =总投资估算!G90 -> 1590.16 | E19: =ROUND($D$19*E12,2) -> 954.1 | F19: =ROUND($D$19*F12,2) -> 636.06 | G19: =ROUND($D$19*G12,2) -> 0 | H19: =ROUND($D$19*H12,2) -> 0 | I19: =SUM(E19:H19) -> 1590.16 | J19: =I19-D19 -> 0
B20: 2 | C20: 建设期利息 | D20: =SUM(E20:H20) -> 270 | E20: =E23*0.03*0.5 -> 135 | F20: =E23*0.03*0.5+F23*0.03 -> 135 | G20: 0 | H20: 0 | I20: =SUM(E20:H20) -> 270 | J20: =I20-D20 -> 0
B21: 三 | C21: 资金筹措 | D21: =D22+D23 -> 22000 | E21: =E15 -> 13173.01 | F21: =F15 -> 8826.99 | G21: =G15 -> 0 | H21: =H15 -> 0 | I21: =SUM(E21:H21) -> 22000 | J21: =I21-D21 -> 0
B22: 1 | C22: 项目资本金 | D22: =G2 -> 13000 | E22: =E21-E23 -> 4173.01 | F22: =F21-F23 -> 8826.99 | G22: =G21-G23 -> 0 | H22: =H21-H23 -> 0 | I22: =SUM(E22:H22) -> 13000 | J22: =I22-D22 -> 0
B23: 2 | C23: 专项债券 | D23: =G3 -> 9000 | E23: =D23*E14 -> 9000 | F23: 0 | G23: =$D$23*G14 -> 0 | H23: =$D$23*H14 -> 0 | I23: =SUM(E23:H23) -> 9000 | J23: =I23-D23 -> 0

Sheet 信息采集表
A1: 填表注释：公式请勿修改 | B1: 黄色单元格需要填写 | C1: 此为测算结果
A2: 1、项目建设期运营期相关
A3: 项目实际情况：
A4: ①截止到填表日，本项目是否开工 | B4: 否
A5: ②本项目建设期 | B5: =DATEDIF(B6,B7+1,"M") -> 14 | C5: 个月。
A6: ③本项目建设期开工日期 | B6: =分年计划及建设期利息!C1 -> 45108.9 | C6: 如：202X年X月1日
A7: ④本项目建设期完工日期 | B7: =分年计划及建设期利息!C2 -> 45535 | C7: 如：202X年X月1日 | D7: =(B7-B6)/30-B5 -> 0.20333333 | E7: （④-③）/30-② | F7: 注意与B5单元格的勾稽关系
A9: 项目可研报告中数据情况：
A10: ⑤本项目建设期 | B10: =B5 -> 14 | C10: 个月。 | D10: =B10-B5 -> 0 | E10: ⑤-②
A11: ⑥本项目建设期开工日期 | B11: =B6 -> 45108.9 | C11: 如：202X年X月1日 | D11: =B11-B6 -> 0 | E11: ⑥-③ | F11: 如与项目实际情况存在较大差异。1、笔误等情况酌情修改可研；2、编制错误或是以前年度编制可研造成，考虑是否影响可研数据的准确性（以前年度编制的可研，依据的参考数据都是以前年度的，是否与现在情况存在偏差，是否合理）；
A12: ⑦本项目建设期完工日期 | B12: =B7 -> 45535 | C12: 如：202X年X月1日 | D12: =B12-B7 -> 0 | E12: ⑦-④
A13: ⑧建设工程费用 | B13: =分年计划及建设期利息!D17 -> 17385.78 | C13: =B13-B24 -> 0 | D13: ⑧-⑭ | E13: 此处进行测算，存在差异，则需找具体原因
A14: ⑨工程建设其他费用 | B14: =分年计划及建设期利息!D18 -> 2754.06 | C14: =B14-B25 -> 0 | D14: ⑨-⑮ | E14: 此处进行测算，存在差异，则需找具体原因
A15: ⑩预备费 | B15: =分年计划及建设期利息!D19 -> 1590.16 | C15: =B15-B26 -> 0 | D15: ⑩-⑯ | E15: 此处进行测算，存在差异，则需找具体原因
A16: ⑪建设期利息 | B16: =分年计划及建设期利息!D20 -> 270 | C16: =B16-B27 -> 0 | D16: ⑪-⑰ | E16: 此处进行测算，存在差异，则需找具体原因
A17: 合计 | B17: =SUM(B13:B16) -> 22000 | C17: =B17-B28 -> 0 | D17: 合计差异 | E17: 此处进行测算，存在差异，则需找具体原因
A19: 2、投资构成及分年度计划（万元）
A20: 可研批复文号
A21: ⑫可研批复金额 | B21: =B22 -> 22000 | C21: =B21-B22 -> 0 | D21: ⑫-⑬ | E21: 此处进行测算，存在差异，则需找具体原因
A22: ⑬可研总投资金额 | B22: =总投资估算!G95 -> 22000 | C22: =B28-B22 -> 0 | D22: ⑬-（⑭+⑮+⑯+⑰） | E22: 此处进行测算，存在差异，则需找具体原因
A23: 具体每年项目投资情况 | B23: 合计 | C23: 以前年度 | D23: 2022年 | E23: 2023年 | F23: 2024年 | G23: 2025年 | H23: 2026年 | I23: 2027年
A24: ⑭建设工程费用 | B24: =SUM(C24:I24) -> 17385.78 | D24: =分年计划及建设期利息!E17 -> 10431.47 | E24: =分年计划及建设期利息!F17 -> 6954.31 | F24: =分年计划及建设期利息!G17 -> 0 | G24: =分年计划及建设期利息!H17 -> 0
A25: ⑮工程建设其他费用 | B25: =SUM(C25:I25) -> 2754.06 | D25: =分年计划及建设期利息!E18 -> 1652.44 | E25: =分年计划及建设期利息!F18 -> 1101.62 | F25: =分年计划及建设期利息!G18 -> 0 | G25: =分年计划及建设期利息!H18 -> 0
A26: ⑯预备费 | B26: =SUM(C26:I26) -> 1590.16 | D26: =分年计划及建设期利息!E19 -> 954.1 | E26: =分年计划及建设期利息!F19 -> 636.06 | F26: =分年计划及建设期利息!G19 -> 0 | G26: =分年计划及建设期利息!H19 -> 0
A27: ⑰建设期利息 | B27: =SUM(C27:I27) -> 270 | D27: =分年计划及建设期利息!E20 -> 135 | E27: =分年计划及建设期利息!F20 -> 135 | F27: =分年计划及建设期利息!G20 -> 0 | G27: =分年计划及建设期利息!H20 -> 0
A28: 合计 | B28: =SUM(B24:B27) -> 22000 | C28: =SUM(C24:C27) -> 0 | D28: =SUM(D24:D27) -> 13173.01 | E28: =SUM(E24:E27) -> 8826.99 | F28: =SUM(F24:F27) -> 0 | G28: =SUM(G24:G27) -> 0 | H28: =SUM(H24:H27) -> 0 | I28: =SUM(I24:I27) -> 0 | J28: 此处数据请与建设期所填数据核对，是否勾稽，不要存在无建设期，但存在项目投资的情况
A29: 注：若项目已开工，以前年度的支出按实际支出金额填写；若项目截止目前还未开工，按未来计划支出金额分年度填写
A31: 3、项目建设期运营期相关（万元） | B31: =B28-B36 -> 0 | C31: （⑭+⑮+⑯+⑰）-（⑱+⑲+⑳） | E31: 此处进行测算，存在差异，则需找具体原因 | G31: =B33/B36 -> 0.59090909 | H31: ⑱/（⑱+⑲+⑳） | I31: 此处不能小于20%，资本金必须大于等于占比20%
A32: 项目筹资情况 | B32: 合计 | C32: 以前年度 | D32: 2022年 | E32: 2023年 | F32: 2024年 | G32: 2025年 | H32: 2026年 | I32: 2027年
A33: ⑱资本金 | B33: =SUM(C33:I33) -> 13000 | D33: =分年计划及建设期利息!E22 -> 4173.01 | E33: =分年计划及建设期利息!F22 -> 8826.99 | F33: =分年计划及建设期利息!G22 -> 0 | G33: =分年计划及建设期利息!H22 -> 0
A34: ⑲其他融资 | B34: =SUM(C34:I34) -> 0 | J34: 如果该列填数，则前面的资料，一定要囊括这部分的资料
A35: ⑳债券发行 | B35: =SUM(C35:I35) -> 9000 | D35: =分年计划及建设期利息!E23 -> 9000 | E35: =分年计划及建设期利息!F23 -> 0 | F35: =分年计划及建设期利息!G23 -> 0 | G35: =分年计划及建设期利息!H23 -> 0
A36: 合计 | B36: =SUM(C36:I36) -> 22000 | C36: =SUM(C33:C35) -> 0 | D36: =SUM(D33:D35) -> 13173.01 | E36: =SUM(E33:E35) -> 8826.99 | F36: =SUM(F33:F35) -> 0 | G36: =SUM(G33:G35) -> 0 | H36: =SUM(H33:H35) -> 0 | I36: =SUM(I33:I35) -> 0
A37: 注：此列允许存在差异：如果是负数，则填列无误；如果是正数，则需修改发行债券分年计划，因此当年发债金额不允许大于当年投资金额 | D37: =D35-D28 -> -4173.01 | E37: =E35-E28 -> -8826.99 | F37: =F35-F28 -> 0 | G37: =G35-G28 -> 0 | H37: =H35-H28 -> 0 | I37: =I35-I28 -> 0

Sheet 还本付息
H2: 金额单位：人民币万元
B3: 年度 | C3: 期初本金余额 | D3: 本年发放 | E3: 本期偿还本金 | F3: 期末本金余额 | G3: 融资利率 | H3: 应付利息 | I3: 本息合计
B5: 1 | C5: 0 | D5: 9000 | F5: =C5+D5-E5 -> 9000 | G5: 0.03 | H5: =F5*G5 -> 270 | I5: =E5+H5 -> 270
B6: 2 | C6: =F5 -> 9000 | D6: 0 | F6: =C6+D6-E6 -> 9000 | G6: =G5 -> 0.03 | H6: =(C6+D6)*G6 -> 270 | I6: =E6+H6 -> 270
B7: 3 | C7: =F6 -> 9000 | D7: =分年计划及建设期利息!G23 -> 0 | F7: =C7+D7-E7 -> 9000 | G7: =G6 -> 0.03 | H7: =(C7+D7)*G7 -> 270 | I7: =E7+H7 -> 270
B8: 4 | C8: =F7 -> 9000 | D8: =分年计划及建设期利息!H23 -> 0 | F8: =C8+D8-E8 -> 9000 | G8: =G7 -> 0.03 | H8: =(C8+D8)*G8 -> 270 | I8: =E8+H8 -> 270
B9: 5 | C9: =F8 -> 9000 | F9: =C9+D9-E9 -> 9000 | G9: =G8 -> 0.03 | H9: =(C9+D9)*G9 -> 270 | I9: =E9+H9 -> 270
B10: 6 | C10: =F9 -> 9000 | F10: =C10+D10-E10 -> 9000 | G10: =G9 -> 0.03 | H10: =(C10+D10)*G10 -> 270 | I10: =E10+H10 -> 270
B11: 7 | C11: =F10 -> 9000 | F11: =C11+D11-E11 -> 9000 | G11: =G10 -> 0.03 | H11: =(C11+D11)*G11 -> 270 | I11: =E11+H11 -> 270
B12: 8 | C12: =F11 -> 9000 | F12: =C12+D12-E12 -> 9000 | G12: =G11 -> 0.03 | H12: =(C12+D12)*G12 -> 270 | I12: =E12+H12 -> 270
B13: 9 | C13: =F12 -> 9000 | F13: =C13+D13-E13 -> 9000 | G13: =G12 -> 0.03 | H13: =(C13+D13)*G13 -> 270 | I13: =E13+H13 -> 270
B14: 10 | C14: =F13 -> 9000 | F14: =C14+D14-E14 -> 9000 | G14: =G13 -> 0.03 | H14: =(C14+D14)*G14 -> 270 | I14: =E14+H14 -> 270
B15: 11 | C15: =F14 -> 9000 | F15: =C15+D15-E15 -> 9000 | G15: =G14 -> 0.03 | H15: =(C15+D15)*G15 -> 270 | I15: =E15+H15 -> 270
B16: 12 | C16: =F15 -> 9000 | F16: =C16+D16-E16 -> 9000 | G16: =G15 -> 0.03 | H16: =(C16+D16)*G16 -> 270 | I16: =E16+H16 -> 270
B17: 13 | C17: =F16 -> 9000 | F17: =C17+D17-E17 -> 9000 | G17: =G16 -> 0.03 | H17: =(C17+D17)*G17 -> 270 | I17: =E17+H17 -> 270
B18: 14 | C18: =F17 -> 9000 | F18: =C18+D18-E18 -> 9000 | G18: =G17 -> 0.03 | H18: =(C18+D18)*G18 -> 270 | I18: =E18+H18 -> 270
B19: 15 | C19: =F18 -> 9000 | F19: =C19+D19-E19 -> 9000 | G19: =G18 -> 0.03 | H19: =(C19+D19)*G19 -> 270 | I19: =E19+H19 -> 270
B20: 16 | C20: =F19 -> 9000 | F20: =C20+D20-E20 -> 9000 | G20: =G19 -> 0.03 | H20: =(C20+D20)*G20 -> 270 | I20: =E20+H20 -> 270
... B33: 29 | C33: =F32 -> 9000 | F33: =C33+D33-E33 -> 9000 | G33: =G32 -> 0.03 | H33: =(C33+D33)*G33 -> 270 | I33: =E33+H33 -> 270
B34: 30 | C34: =F33 -> 9000 | E34: =D5 -> 9000 | F34: =C34+D34-E34 -> 0 | G34: =G33 -> 0.03 | H34: =(C34+D34)*G34 -> 270 | I34: =E34+H34 -> 9270
B35: 31 | C35: =F34 -> 0 | E35: =D6 -> 0 | F35: =C35+D35-E35 -> 0 | G35: =G34 -> 0.03 | H35: =(C35+D35)*G35 -> 0 | I35: =E35+H35 -> 0
B36: 32 | C36: =F35 -> 0 | E36: =D7 -> 0 | F36: =C36+D36-E36 -> 0 | G36: =G35 -> 0.03 | H36: =(C36+D36)*G36 -> 0 | I36: =E36+H36 -> 0
B37: 33 | C37: =F36 -> 0 | E37: =D8 -> 0 | F37: =C37+D37-E37 -> 0 | G37: =G36 -> 0.03 | H37: =(C37+D37)*G37 -> 0 | I37: =E37+H37 -> 0
B38: 合计 | E38: =SUM(E5:E37) -> 9000 | H38: =SUM(H5:H37) -> 8100 | I38: =SUM(I5:I37) -> 17100
H41: =E38*4.5%*30 -> 12150

Sheet 收入成本
A1: 周期 | B1: 年度 | C1: 种植基地出租收入 | H1: 停车位收入 | L1: 充电桩收入 | R1: 物业收入 | V1: 厂房出租收入 | Z1: 经营收 入合计 | AB1: 修理费占比折旧（自行键入） | AG1: 0.05 | AI1: 金额单位：人民币万元
C2: 负荷率 | D2: 出租价格（元/年·亩） | E2: 出租价格（元/年·亩） | F2: 数量（亩） | G2: 年运营收入（万元） | H2: 负荷率 | I2: 单价 | J2: 数量 | K2: 年运营收入（万元） | L2: 负荷率 | M2: 单价（元/kwh) | N2: 收费数量（个） | O2: 充电桩功率（kw） | P2: 日充电时长 | Q2: 年运营收入（万元） | R2: 负荷率 | S2: 单价 （元/月） | T2: 出租面积 | U2: 年运营收入（万元） | V2: 负荷率 | W2: 单价 （元/月） | X2: 出租面积 | Y2: 年运营收入（万元） | AC2: 年度 | AD2: 外购原材料费 | AE2: 外购燃料动力 | AF2: 工资福利费用 | AG2: 年维修成本 | AH2: 污泥处理费 | AI2: 其他费用 | AJ2: 税费 | AK2: 经营成本合计 | AL2: =资金流入流出平衡表!A20 -> 业务成本流出
AD3: 0.03 | AE3: 0.05 | AG3: 0.05 | AI3: 0.02
A4: 建设期 | B4: 1 | AA4: 地下停车场收入 | AC4: 1 | AE4: =ROUND(Z4*3%,2) -> 0
A5: 运营期 | B5: 2 | C5: 0.5 | D5: 850 | E5: 0 | F5: 113.76 | G5: =ROUND(D5*F5*C5/10000,2) -> 4.83 | H5: 0.4 | I5: 8 | J5: 265 | K5: =ROUND(J5*I5*H5*365/10000,2) -> 30.95 | L5: 0.3 | M5: 0.6 | N5: 40 | O5: 120 | P5: 2 | Q5: =ROUND(L5*M5*N5*330*P5*O5/10000,2) -> 57.02 | R5: =V5 -> 0.5 | S5: 0 | T5: =X5 -> 28489 | U5: =T5*S5*R5*12/10000 -> 0 | V5: =C5 -> 0.5 | W5: 35 | X5: =8400+20089 -> 28489 | Y5: =ROUND(X5*W5*V5*12/10000,2) -> 598.27 | Z5: =ROUND(G5+K5+Y5+Q5,2) -> 691.07 | AA5: 122.36 | AB5: 运营期 | AC5: 2 | AE5: =Z5*5% -> 34.5535 | AF5: =ROUND((项目技术经济指标!I10*项目技术经济指标!J10+项目技术经济指标!K10*项目技术经济指标!L10)*12/10000,2) -> 99 | AG5: =ROUND(固定资产折旧!$E$17*$AG$1,2) -> 35.09 | AI5: =ROUND(Z5*$AI$3,2) -> 13.82 | AJ5: =税费计算!O6 -> 71.79 | AK5: =ROUND(SUM(AD5:AJ5),2) -> 254.25 | AL5: =SUM(AE5:AI5) -> 182.4635
B6: 3 | C6: =C5+5% -> 0.55 | D6: =D5 -> 850 | E6: =E5 -> 0 | F6: =F5 -> 113.76 | G6: =ROUND(D6*F6*C6/10000,2) -> 5.32 | H6: =H5+5% -> 0.45 | I6: =I5 -> 8 | J6: =J5 -> 265 | K6: =ROUND(J6*I6*H6*365/10000,2) -> 34.82 | L6: =L5+10% -> 0.4 | M6: =M5 -> 0.6 | N6: =N5 -> 40 | O6: =O5 -> 120 | P6: =P5 -> 2 | Q6: =ROUND(L6*M6*N6*330*P6*O6/10000,2) -> 76.03 | R6: =V6 -> 0.55 | S6: =S5 -> 0 | T6: =X6 -> 28489 | U6: =T6*S6*R6*12/10000 -> 0 | V6: =C6 -> 0.55 | W6: =W5 -> 35 | X6: =X5 -> 28489 | Y6: =ROUND(X6*W6*V6*12/10000,2) -> 658.1 | Z6: =ROUND(G6+K6+Y6+Q6,2) -> 774.27 | AA6: 132.56 | AC6: 3 | AE6: =Z6*5% -> 38.7135 | AF6: =AF5 -> 99 | AG6: =ROUND(固定资产折旧!$E$17*$AG$1,2) -> 35.09 | AH6: 0 | AI6: =ROUND(Z6*$AI$3,2) -> 15.49 | AJ6: =税费计算!O7 -> 78.97 | AK6: =ROUND(SUM(AD6:AJ6),2) -> 267.26 | AL6: =SUM(AE6:AI6) -> 188.2935
B7: 4 | C7: =C6+5% -> 0.6 | D7: =D6 -> 850 | E7: =E6 -> 0 | F7: =F6 -> 113.76 | G7: =ROUND(D7*F7*C7/10000,2) -> 5.8 | H7: =H6+5% -> 0.5 | I7: =I6 -> 8 | J7: =J6 -> 265 | K7: =ROUND(J7*I7*H7*365/10000,2) -> 38.69 | L7: =L6+10% -> 0.5 | M7: =M6 -> 0.6 | N7: =N6 -> 40 | O7: =O6 -> 120 | P7: =P6 -> 2 | Q7: =ROUND(L7*M7*N7*330*P7*O7/10000,2) -> 95.04 | R7: =V7 -> 0.6 | S7: =S6 -> 0 | T7: =X7 -> 28489 | U7: =T7*S7*R7*12/10000 -> 0 | V7: =C7 -> 0.6 | W7: =W6 -> 35 | X7: =X6 -> 28489 | Y7: =ROUND(X7*W7*V7*12/10000,2) -> 717.92 | Z7: =ROUND(G7+K7+Y7+Q7,2) -> 857.45 | AA7: 142.76 | AC7: 4 | AE7: =Z7*5% -> 42.8725 | AF7: =AF6 -> 99 | AG7: =ROUND(固定资产折旧!$E$17*$AG$1,2) -> 35.09 | AH7: =AH6 -> 0 | AI7: =ROUND(Z7*$AI$3,2) -> 17.15 | AJ7: =税费计算!O8 -> 86.15 | AK7: =ROUND(SUM(AD7:AJ7),2) -> 280.26 | AL7: =SUM(AE7:AI7) -> 194.1125
B8: 5 | C8: =C7+5% -> 0.65 | D8: =D7 -> 850 | E8: =E7 -> 0 | F8: =F7 -> 113.76 | G8: =ROUND(D8*F8*C8/10000,2) -> 6.29 | H8: =L8+5% -> 0.6 | I8: =I7 -> 8 | J8: =J7 -> 265 | K8: =ROUND(J8*I8*H8*365/10000,2) -> 46.43 | L8: =L7+5% -> 0.55 | M8: =M7 -> 0.6 | N8: =N7 -> 40 | O8: =O7 -> 120 | P8: =P7 -> 2 | Q8: =ROUND(L8*M8*N8*330*P8*O8/10000,2) -> 104.54 | R8: =V8 -> 0.65 | S8: =S7 -> 0 | T8: =X8 -> 28489 | U8: =T8*S8*R8*12/10000 -> 0 | V8: =C8 -> 0.65 | W8: =W7 -> 35 | X8: =X7 -> 28489 | Y8: =ROUND(X8*W8*V8*12/10000,2) -> 777.75 | Z8: =ROUND(G8+K8+Y8+Q8,2) -> 935.01 | AA8: 152.96 | AC8: 5 | AE8: =Z8*5% -> 46.7505 | AF8: =AF7 -> 99 | AG8: =ROUND(固定资产折旧!$E$17*$AG$1,2) -> 35.09 | AH8: =AH7 -> 0 | AI8: =ROUND(Z8*$AI$3,2) -> 18.7 | AJ8: =税费计算!O9 -> 93.33 | AK8: =ROUND(SUM(AD8:AJ8),2) -> 292.87 | AL8: =SUM(AE8:AI8) -> 199.5405
B9: 6 | C9: =C8+5% -> 0.7 | D9: =D8 -> 850 | E9: =E8 -> 0 | F9: =F8 -> 113.76 | G9: =ROUND(D9*F9*C9/10000,2) -> 6.77 | H9: 0.6 | I9: =I8 -> 8 | J9: =J8 -> 265 | K9: =ROUND(J9*I9*H9*365/10000,2) -> 46.43 | L9: =L8+5% -> 0.6 | M9: =M8 -> 0.6 | N9: =N8 -> 40 | O9: =O8 -> 120 | P9: =P8 -> 2 | Q9: =ROUND(L9*M9*N9*330*P9*O9/10000,2) -> 114.05 | R9: =V9 -> 0.7 | S9: =S8 -> 0 | T9: =X9 -> 28489 | U9: =T9*S9*R9*12/10000 -> 0 | V9: =C9 -> 0.7 | W9: =W8 -> 35 | X9: =X8 -> 28489 | Y9: =ROUND(X9*W9*V9*12/10000,2) -> 837.58 | Z9: =ROUND(G9+K9+Y9+Q9,2) -> 1004.83 | AA9: 163.15 | AC9: 6 | AE9: =Z9*5% -> 50.2415 | AF9: =AF8 -> 99 | AG9: =ROUND(固定资产折旧!$E$17*$AG$1,2) -> 35.09 | AH9: =AH8 -> 0 | AI9: =ROUND(Z9*$AI$3,2) -> 20.1 | AJ9: =税费计算!O10 -> 100.51 | AK9: =ROUND(SUM(AD9:AJ9),2) -> 304.94 | AL9: =SUM(AE9:AI9) -> 204.4315
B10: 7 | C10: =C9+5% -> 0.75 | D10: =ROUND(D5*1.05,2) -> 892.5 | E10: =E9 -> 0 | F10: =F9 -> 113.76 | G10: =ROUND(D10*F10*C10/10000,2) -> 7.61 | H10: =H9+5% -> 0.65 | I10: =ROUND(I9*1.05,2) -> 8.4 | J10: =J9 -> 265 | K10: =ROUND(J10*I10*H10*365/10000,2) -> 52.81 | L10: =L9 -> 0.6 | M10: =M5*1.1 -> 0.66 | N10: =N9 -> 40 | O10: =O9 -> 120 | P10: =P9 -> 2 | Q10: =ROUND(L10*M10*N10*330*P10*O10/10000,2) -> 125.45 | R10: =V10 -> 0.75 | S10: =S9*1.05 -> 0 | T10: =X10 -> 28489 | U10: =T10*S10*R10*12/10000 -> 0 | V10: =C10 -> 0.75 | W10: =ROUND(W9*1.05,2) -> 36.75 | X10: =X9 -> 28489 | Y10: =ROUND(X10*W10*V10*12/10000,2) -> 942.27 | Z10: =ROUND(G10+K10+Y10+Q10,2) -> 1128.14 | AA10: 190.68 | AC10: 7 | AE10: =Z10*5% -> 56.407 | AF10: =AF5*(1+项目技术经济指标!$M$10) -> 108.9 | AG10: =AG5*(1+$AG$3) -> 36.8445 | AH10: =AH9 -> 0 | AI10: =ROUND(Z10*$AI$3,2) -> 22.56 | AJ10: =税费计算!O11 -> 113.07 | AK10: =ROUND(SUM(AD10:AJ10),2) -> 337.78 | AL10: =SUM(AE10:AI10) -> 224.7115 | AN10: 69.7
B11: 8 | C11: =C10 -> 0.75 | D11: =ROUND(D6*1.05,2) -> 892.5 | E11: =E10 -> 0 | F11: =F10 -> 113.76 | G11: =ROUND(D11*F11*C11/10000,2) -> 7.61 | H11: =H10 -> 0.65 | I11: =I10 -> 8.4 | J11: =J10 -> 265 | K11: =ROUND(J11*I11*H11*365/10000,2) -> 52.81 | L11: =L10 -> 0.6 | M11: =M6*1.1 -> 0.66 | N11: =N10 -> 40 | O11: =O10 -> 120 | P11: =P10 -> 2 | Q11: =ROUND(L11*M11*N11*330*P11*O11/10000,2) -> 125.45 | R11: =V11 -> 0.75 | S11: =S10 -> 0 | T11: =X11 -> 28489 | U11: =T11*S11*R11*12/10000 -> 0 | V11: =C11 -> 0.75 | W11: =W10 -> 36.75 | X11: =X10 -> 28489 | Y11: =ROUND(X11*W11*V11*12/10000,2) -> 942.27 | Z11: =ROUND(G11+K11+Y11+Q11,2) -> 1128.14 | AA11: 190.68 | AC11: 8 | AE11: =Z11*5% -> 56.407 | AF11: =AF6*(1+项目技术经济指标!$M$10) -> 108.9 | AG11: =AG6*(1+$AG$3) -> 36.8445 | AH11: =AH10 -> 0 | AI11: =ROUND(Z11*$AI$3,2) -> 22.56 | AJ11: =税费计算!O12 -> 113.07 | AK11: =ROUND(SUM(AD11:AJ11),2) -> 337.78 | AL11: =SUM(AE11:AI11) -> 224.7115 | AN11: 200
B12: 9 | C12: =C11 -> 0.75 | D12: =ROUND(D7*1.05,2) -> 892.5 | E12: =E11 -> 0 | F12: =F11 -> 113.76 | G12: =ROUND(D12*F12*C12/10000,2) -> 7.61 | H12: =H11 -> 0.65 | I12: =I11 -> 8.4 | J12: =J11 -> 265 | K12: =ROUND(J12*I12*H12*365/10000,2) -> 52.81 | L12: =L11 -> 0.6 | M12: =M7*1.1 -> 0.66 | N12: =N11 -> 40 | O12: =O11 -> 120 | P12: =P11 -> 2 | Q12: =ROUND(L12*M12*N12*330*P12*O12/10000,2) -> 125.45 | R12: =V12 -> 0.75 | S12: =S11 -> 0 | T12: =X12 -> 28489 | U12: =T12*S12*R12*12/10000 -> 0 | V12: =C12 -> 0.75 | W12: =W11 -> 36.75 | X12: =X11 -> 28489 | Y12: =ROUND(X12*W12*V12*12/10000,2) -> 942.27 | Z12: =ROUND(G12+K12+Y12+Q12,2) -> 1128.14 | AA12: 190.68 | AC12: 9 | AE12: =Z12*5% -> 56.407 | AF12: =AF7*(1+项目技术经济指标!$M$10) -> 108.9 | AG12: =AG7*(1+$AG$3) -> 36.8445 | AH12: =AH11 -> 0 | AI12: =ROUND(Z12*$AI$3,2) -> 22.56 | AJ12: =税费计算!O13 -> 113.07 | AK12: =ROUND(SUM(AD12:AJ12),2) -> 337.78 | AL12: =SUM(AE12:AI12) -> 224.7115 | AN12: 50
B13: 10 | C13: =C12 -> 0.75 | D13: =ROUND(D8*1.05,2) -> 892.5 | E13: =E12 -> 0 | F13: =F12 -> 113.76 | G13: =ROUND(D13*F13*C13/10000,2) -> 7.61 | H13: =H12 -> 0.65 | I13: =I12 -> 8.4 | J13: =J12 -> 265 | K13: =ROUND(J13*I13*H13*365/10000,2) -> 52.81 | L13: =L12 -> 0.6 | M13: =M8*1.1 -> 0.66 | N13: =N12 -> 40 | O13: =O12 -> 120 | P13: =P12 -> 2 | Q13: =ROUND(L13*M13*N13*330*P13*O13/10000,2) -> 125.45 | R13: =V13 -> 0.75 | S13: =S12 -> 0 | T13: =X13 -> 28489 | U13: =T13*S13*R13*12/10000 -> 0 | V13: =C13 -> 0.75 | W13: =W12 -> 36.75 | X13: =X12 -> 28489 | Y13: =ROUND(X13*W13*V13*12/10000,2) -> 942.27 | Z13: =ROUND(G13+K13+Y13+Q13,2) -> 1128.14 | AA13: 190.68 | AC13: 10 | AE13: =Z13*5% -> 56.407 | AF13: =AF8*(1+项目技术经济指标!$M$10) -> 108.9 | AG13: =AG8*(1+$AG$3) -> 36.8445 | AH13: =AH12 -> 0 | AI13: =ROUND(Z13*$AI$3,2) -> 22.56 | AJ13: =税费计算!O14 -> 113.07 | AK13: =ROUND(SUM(AD13:AJ13),2) -> 337.78 | AL13: =SUM(AE13:AI13) -> 224.7115 | AN13: 100
B14: 11 | C14: =C13 -> 0.75 | D14: =ROUND(D9*1.05,2) -> 892.5 | E14: =E13 -> 0 | F14: =F13 -> 113.76 | G14: =ROUND(D14*F14*C14/10000,2) -> 7.61 | H14: =H13 -> 0.65 | I14: =I13 -> 8.4 | J14: =J13 -> 265 | K14: =ROUND(J14*I14*H14*365/10000,2) -> 52.81 | L14: =L13 -> 0.6 | M14: =M9*1.1 -> 0.66 | N14: =N13 -> 40 | O14: =O13 -> 120 | P14: =P13 -> 2 | Q14: =ROUND(L14*M14*N14*330*P14*O14/10000,2) -> 125.45 | R14: =V14 -> 0.75 | S14: =S13 -> 0 | T14: =X14 -> 28489 | U14: =T14*S14*R14*12/10000 -> 0 | V14: =C14 -> 0.75 | W14: =W13 -> 36.75 | X14: =X13 -> 28489 | Y14: =ROUND(X14*W14*V14*12/10000,2) -> 942.27 | Z14: =ROUND(G14+K14+Y14+Q14,2) -> 1128.14 | AA14: 190.68 | AC14: 11 | AE14: =Z14*5% -> 56.407 | AF14: =AF9*(1+项目技术经济指标!$M$10) -> 108.9 | AG14: =AG9*(1+$AG$3) -> 36.8445 | AH14: =AH13 -> 0 | AI14: =ROUND(Z14*$AI$3,2) -> 22.56 | AJ14: =税费计算!O15 -> 113.07 | AK14: =ROUND(SUM(AD14:AJ14),2) -> 337.78 | AL14: =SUM(AE14:AI14) -> 224.7115 | AN14: 26.7
B15: 12 | C15: =C14 -> 0.75 | D15: =ROUND(D10*1.05,2) -> 937.13 | E15: =E14 -> 0 | F15: =F14 -> 113.76 | G15: =ROUND(D15*F15*C15/10000,2) -> 8 | H15: =H14 -> 0.65 | I15: =ROUND(I14*1.05,2) -> 8.82 | J15: =J14 -> 265 | K15: =ROUND(J15*I15*H15*365/10000,2) -> 55.45 | L15: =L14 -> 0.6 | M15: =M10*1.1 -> 0.726 | N15: =N14 -> 40 | O15: =O14 -> 120 | P15: =P14 -> 2 | Q15: =ROUND(L15*M15*N15*330*P15*O15/10000,2) -> 138 | R15: =V15 -> 0.75 | S15: =S14*1.05 -> 0 | T15: =X15 -> 28489 | U15: =T15*S15*R15*12/10000 -> 0 | V15: =C15 -> 0.75 | W15: =ROUND(W14*1.05,2) -> 38.59 | X15: =X14 -> 28489 | Y15: =ROUND(X15*W15*V15*12/10000,2) -> 989.45 | Z15: =ROUND(G15+K15+Y15+Q15,2) -> 1190.9 | AA15: 209.75 | AC15: 12 | AE15: =Z15*5% -> 59.545 | AF15: =AF10*(1+项目技术经济指标!$M$10) -> 119.79 | AG15: =AG10*(1+$AG$3) -> 38.686725 | AH15: =AH14 -> 0 | AI15: =ROUND(Z15*$AI$3,2) -> 23.82 | AJ15: =税费计算!O16 -> 118.73 | AK15: =ROUND(SUM(AD15:AJ15),2) -> 360.57 | AL15: =SUM(AE15:AI15) -> 241.84172 | AN15: 87.6
B16: 13 | C16: =C15 -> 0.75 | D16: =ROUND(D11*1.05,2) -> 937.13 | E16: =E15 -> 0 | F16: =F15 -> 113.76 | G16: =ROUND(D16*F16*C16/10000,2) -> 8 | H16: =H15 -> 0.65 | I16: =I15 -> 8.82 | J16: =J15 -> 265 | K16: =ROUND(J16*I16*H16*365/10000,2) -> 55.45 | L16: =L15 -> 0.6 | M16: =M11*1.1 -> 0.726 | N16: =N15 -> 40 | O16: =O15 -> 120 | P16: =P15 -> 2 | Q16: =ROUND(L16*M16*N16*330*P16*O16/10000,2) -> 138 | R16: =V16 -> 0.75 | S16: =S15 -> 0 | T16: =X16 -> 28489 | U16: =T16*S16*R16*12/10000 -> 0 | V16: =C16 -> 0.75 | W16: =W15 -> 38.59 | X16: =X15 -> 28489 | Y16: =ROUND(X16*W16*V16*12/10000,2) -> 989.45 | Z16: =ROUND(G16+K16+Y16+Q16,2) -> 1190.9 | AA16: 209.75 | AC16: 13 | AE16: =Z16*5% -> 59.545 | AF16: =AF11*(1+项目技术经济指标!$M$10) -> 119.79 | AG16: =AG11*(1+$AG$3) -> 38.686725 | AH16: =AH15 -> 0 | AI16: =ROUND(Z16*$AI$3,2) -> 23.82 | AJ16: =税费计算!O17 -> 118.73 | AK16: =ROUND(SUM(AD16:AJ16),2) -> 360.57 | AL16: =SUM(AE16:AI16) -> 241.84172
B17: 14 | C17: =C16 -> 0.75 | D17: =ROUND(D12*1.05,2) -> 937.13 | E17: =E16 -> 0 | F17: =F16 -> 113.76 | G17: =ROUND(D17*F17*C17/10000,2) -> 8 | H17: =H16 -> 0.65 | I17: =I16 -> 8.82 | J17: =J16 -> 265 | K17: =ROUND(J17*I17*H17*365/10000,2) -> 55.45 | L17: =L16 -> 0.6 | M17: =M12*1.1 -> 0.726 | N17: =N16 -> 40 | O17: =O16 -> 120 | P17: =P16 -> 2 | Q17: =ROUND(L17*M17*N17*330*P17*O17/10000,2) -> 138 | R17: =V17 -> 0.75 | S17: =S16 -> 0 | T17: =X17 -> 28489 | U17: =T17*S17*R17*12/10000 -> 0 | V17: =C17 -> 0.75 | W17: =W16 -> 38.59 | X17: =X16 -> 28489 | Y17: =ROUND(X17*W17*V17*12/10000,2) -> 989.45 | Z17: =ROUND(G17+K17+Y17+Q17,2) -> 1190.9 | AA17: 209.75 | AC17: 14 | AE17: =Z17*5% -> 59.545 | AF17: =AF12*(1+项目技术经济指标!$M$10) -> 119.79 | AG17: =AG12*(1+$AG$3) -> 38.686725 | AH17: =AH16 -> 0 | AI17: =ROUND(Z17*$AI$3,2) -> 23.82 | AJ17: =税费计算!O18 -> 118.73 | AK17: =ROUND(SUM(AD17:AJ17),2) -> 360.57 | AL17: =SUM(AE17:AI17) -> 241.84172 | AM17: =SUM(AN10:AN15)+AM22 -> 558.22488
B18: 15 | C18: =C17 -> 0.75 | D18: =ROUND(D13*1.05,2) -> 937.13 | E18: =E17 -> 0 | F18: =F17 -> 113.76 | G18: =ROUND(D18*F18*C18/10000,2) -> 8 | H18: =H17 -> 0.65 | I18: =I17 -> 8.82 | J18: =J17 -> 265 | K18: =ROUND(J18*I18*H18*365/10000,2) -> 55.45 | L18: =L17 -> 0.6 | M18: =M13*1.1 -> 0.726 | N18: =N17 -> 40 | O18: =O17 -> 120 | P18: =P17 -> 2 | Q18: =ROUND(L18*M18*N18*330*P18*O18/10000,2) -> 138 | R18: =V18 -> 0.75 | S18: =S17 -> 0 | T18: =X18 -> 28489 | U18: =T18*S18*R18*12/10000 -> 0 | V18: =C18 -> 0.75 | W18: =W17 -> 38.59 | X18: =X17 -> 28489 | Y18: =ROUND(X18*W18*V18*12/10000,2) -> 989.45 | Z18: =ROUND(G18+K18+Y18+Q18,2) -> 1190.9 | AA18: 209.75 | AC18: 15 | AE18: =Z18*5% -> 59.545 | AF18: =AF13*(1+项目技术经济指标!$M$10) -> 119.79 | AG18: =AG13*(1+$AG$3) -> 38.686725 | AH18: =AH17 -> 0 | AI18: =ROUND(Z18*$AI$3,2) -> 23.82 | AJ18: =税费计算!O19 -> 118.73 | AK18: =ROUND(SUM(AD18:AJ18),2) -> 360.57 | AL18: =SUM(AE18:AI18) -> 241.84172
B19: 16 | C19: =C18 -> 0.75 | D19: =ROUND(D14*1.05,2) -> 937.13 | E19: =E18 -> 0 | F19: =F18 -> 113.76 | G19: =ROUND(D19*F19*C19/10000,2) -> 8 | H19: =H18 -> 0.65 | I19: =I18 -> 8.82 | J19: =J18 -> 265 | K19: =ROUND(J19*I19*H19*365/10000,2) -> 55.45 | L19: =L18 -> 0.6 | M19: =M14*1.1 -> 0.726 | N19: =N18 -> 40 | O19: =O18 -> 120 | P19: =P18 -> 2 | Q19: =ROUND(L19*M19*N19*330*P19*O19/10000,2) -> 138 | R19: =V19 -> 0.75 | S19: =S18 -> 0 | T19: =X19 -> 28489 | U19: =T19*S19*R19*12/10000 -> 0 | V19: =C19 -> 0.75 | W19: =W18 -> 38.59 | X19: =X18 -> 28489 | Y19: =ROUND(X19*W19*V19*12/10000,2) -> 989.45 | Z19: =ROUND(G19+K19+Y19+Q19,2) -> 1190.9 | AA19: 209.75 | AC19: 16 | AE19: =Z19*5% -> 59.545 | AF19: =AF14*(1+项目技术经济指标!$M$10) -> 119.79 | AG19: =AG14*(1+$AG$3) -> 38.686725 | AH19: =AH18 -> 0 | AI19: =ROUND(Z19*$AI$3,2) -> 23.82 | AJ19: =税费计算!O20 -> 118.73 | AK19: =ROUND(SUM(AD19:AJ19),2) -> 360.57 | AL19: =SUM(AE19:AI19) -> 241.84172
B20: 17 | C20: =C19 -> 0.75 | D20: =ROUND(D15*1.05,2) -> 983.99 | E20: =E19 -> 0 | F20: =F19 -> 113.76 | G20: =ROUND(D20*F20*C20/10000,2) -> 8.4 | H20: =H19 -> 0.65 | I20: =ROUND(I19*1.05,2) -> 9.26 | J20: =J19 -> 265 | K20: =ROUND(J20*I20*H20*365/10000,2) -> 58.22 | L20: =L19 -> 0.6 | M20: =M15*1.1 -> 0.7986 | N20: =N19 -> 40 | O20: =O19 -> 120 | P20: =P19 -> 2 | Q20: =ROUND(L20*M20*N20*330*P20*O20/10000,2) -> 151.8 | R20: =V20 -> 0.75 | S20: =S19*1.05 -> 0 | T20: =X20 -> 28489 | U20: =T20*S20*R20*12/10000 -> 0 | V20: =C20 -> 0.75 | W20: =ROUND(W19*1.05,2) -> 40.52 | X20: =X19 -> 28489 | Y20: =ROUND(X20*W20*V20*12/10000,2) -> 1038.94 | Z20: =ROUND(G20+K20+Y20+Q20,2) -> 1257.36 | AA20: 230.9 | AC20: 17 | AE20: =Z20*5% -> 62.868 | AF20: =AF15*(1+项目技术经济指标!$M$10) -> 131.769 | AG20: =AG15*(1+$AG$3) -> 40.621061 | AH20: =AH19 -> 0 | AI20: =ROUND(Z20*$AI$3,2) -> 25.15 | AJ20: =税费计算!O21 -> 158.05789 | AK20: =ROUND(SUM(AD20:AJ20),2) -> 418.47 | AL20: =SUM(AE20:AI20) -> 260.40806 | AN20: 4700
B21: 18 | C21: =C20 -> 0.75 | D21: =ROUND(D16*1.05,2) -> 983.99 | E21: =E20 -> 0 | F21: =F20 -> 113.76 | G21: =ROUND(D21*F21*C21/10000,2) -> 8.4 | H21: =H20 -> 0.65 | I21: =I20 -> 9.26 | J21: =J20 -> 265 | K21: =ROUND(J21*I21*H21*365/10000,2) -> 58.22 | L21: =L20 -> 0.6 | M21: =M16*1.1 -> 0.7986 | N21: =N20 -> 40 | O21: =O20 -> 120 | P21: =P20 -> 2 | Q21: =ROUND(L21*M21*N21*330*P21*O21/10000,2) -> 151.8 | R21: =V21 -> 0.75 | S21: =S20 -> 0 | T21: =X21 -> 28489 | U21: =T21*S21*R21*12/10000 -> 0 | V21: =C21 -> 0.75 | W21: =W20 -> 40.52 | X21: =X20 -> 28489 | Y21: =ROUND(X21*W21*V21*12/10000,2) -> 1038.94 | Z21: =ROUND(G21+K21+Y21+Q21,2) -> 1257.36 | AA21: 230.9 | AC21: 18 | AE21: =Z21*5% -> 62.868 | AF21: =AF16*(1+项目技术经济指标!$M$10) -> 131.769 | AG21: =AG16*(1+$AG$3) -> 40.621061 | AH21: =AH20 -> 0 | AI21: =ROUND(Z21*$AI$3,2) -> 25.15 | AJ21: =税费计算!O22 -> 243.52119 | AK21: =ROUND(SUM(AD21:AJ21),2) -> 503.93 | AL21: =SUM(AE21:AI21) -> 260.40806
B22: 19 | C22: =C21 -> 0.75 | D22: =ROUND(D17*1.05,2) -> 983.99 | E22: =E21 -> 0 | F22: =F21 -> 113.76 | G22: =ROUND(D22*F22*C22/10000,2) -> 8.4 | H22: =H21 -> 0.65 | I22: =I21 -> 9.26 | J22: =J21 -> 265 | K22: =ROUND(J22*I22*H22*365/10000,2) -> 58.22 | L22: =L21 -> 0.6 | M22: =M17*1.1 -> 0.7986 | N22: =N21 -> 40 | O22: =O21 -> 120 | P22: =P21 -> 2 | Q22: =ROUND(L22*M22*N22*330*P22*O22/10000,2) -> 151.8 | R22: =V22 -> 0.75 | S22: =S21 -> 0 | T22: =X22 -> 28489 | U22: =T22*S22*R22*12/10000 -> 0 | V22: =C22 -> 0.75 | W22: =W21 -> 40.52 | X22: =X21 -> 28489 | Y22: =ROUND(X22*W22*V22*12/10000,2) -> 1038.94 | Z22: =ROUND(G22+K22+Y22+Q22,2) -> 1257.36 | AA22: 230.9 | AC22: 19 | AE22: =Z22*5% -> 62.868 | AF22: =AF17*(1+项目技术经济指标!$M$10) -> 131.769 | AG22: =AG17*(1+$AG$3) -> 40.621061 | AH22: =AH21 -> 0 | AI22: =ROUND(Z22*$AI$3,2) -> 25.15 | AJ22: =税费计算!O23 -> 243.52119 | AK22: =ROUND(SUM(AD22:AJ22),2) -> 503.93 | AL22: =SUM(AE22:AI22) -> 260.40806 | AM22: =16150/666.67 -> 24.224879
B23: 20 | C23: =C22 -> 0.75 | D23: =ROUND(D18*1.05,2) -> 983.99 | E23: =E22 -> 0 | F23: =F22 -> 113.76 | G23: =ROUND(D23*F23*C23/10000,2) -> 8.4 | H23: =H22 -> 0.65 | I23: =I22 -> 9.26 | J23: =J22 -> 265 | K23: =ROUND(J23*I23*H23*365/10000,2) -> 58.22 | L23: =L22 -> 0.6 | M23: =M18*1.1 -> 0.7986 | N23: =N22 -> 40 | O23: =O22 -> 120 | P23: =P22 -> 2 | Q23: =ROUND(L23*M23*N23*330*P23*O23/10000,2) -> 151.8 | R23: =V23 -> 0.75 | S23: =S22 -> 0 | T23: =X23 -> 28489 | U23: =T23*S23*R23*12/10000 -> 0 | V23: =C23 -> 0.75 | W23: =W22 -> 40.52 | X23: =X22 -> 28489 | Y23: =ROUND(X23*W23*V23*12/10000,2) -> 1038.94 | Z23: =ROUND(G23+K23+Y23+Q23,2) -> 1257.36 | AA23: 230.9 | AC23: 20 | AE23: =Z23*5% -> 62.868 | AF23: =AF18*(1+项目技术经济指标!$M$10) -> 131.769 | AG23: =AG18*(1+$AG$3) -> 40.621061 | AH23: =AH22 -> 0 | AI23: =ROUND(Z23*$AI$3,2) -> 25.15 | AJ23: =税费计算!O24 -> 243.52119 | AK23: =ROUND(SUM(AD23:AJ23),2) -> 503.93 | AL23: =SUM(AE23:AI23) -> 260.40806
B24: 21 | C24: =C23 -> 0.75 | D24: =ROUND(D19*1.05,2) -> 983.99 | E24: =E23 -> 0 | F24: =F23 -> 113.76 | G24: =ROUND(D24*F24*C24/10000,2) -> 8.4 | H24: =H23 -> 0.65 | I24: =I23 -> 9.26 | J24: =J23 -> 265 | K24: =ROUND(J24*I24*H24*365/10000,2) -> 58.22 | L24: =L23 -> 0.6 | M24: =M19*1.1 -> 0.7986 | N24: =N23 -> 40 | O24: =O23 -> 120 | P24: =P23 -> 2 | Q24: =ROUND(L24*M24*N24*330*P24*O24/10000,2) -> 151.8 | R24: =V24 -> 0.75 | S24: =S23 -> 0 | T24: =X24 -> 28489 | U24: =T24*S24*R24*12/10000 -> 0 | V24: =C24 -> 0.75 | W24: =W23 -> 40.52 | X24: =X23 -> 28489 | Y24: =ROUND(X24*W24*V24*12/10000,2) -> 1038.94 | Z24: =ROUND(G24+K24+Y24+Q24,2) -> 1257.36 | AA24: 230.9 | AC24: 21 | AE24: =Z24*5% -> 62.868 | AF24: =AF19*(1+项目技术经济指标!$M$10) -> 131.769 | AG24: =AG19*(1+$AG$3) -> 40.621061 | AH24: =AH23 -> 0 | AI24: =ROUND(Z24*$AI$3,2) -> 25.15 | AJ24: =税费计算!O25 -> 243.52119 | AK24: =ROUND(SUM(AD24:AJ24),2) -> 503.93 | AL24: =SUM(AE24:AI24) -> 260.40806 | AN24: 1500
B25: 22 | C25: =C24 -> 0.75 | D25: =ROUND(D20*1.05,2) -> 1033.19 | E25: =E24 -> 0 | F25: =F24 -> 113.76 | G25: =ROUND(D25*F25*C25/10000,2) -> 8.82 | H25: =H24 -> 0.65 | I25: =ROUND(I24*1.05,2) -> 9.72 | J25: =J24 -> 265 | K25: =ROUND(J25*I25*H25*365/10000,2) -> 61.11 | L25: =L24 -> 0.6 | M25: =M20*1.1 -> 0.87846 | N25: =N24 -> 40 | O25: =O24 -> 120 | P25: =P24 -> 2 | Q25: =ROUND(L25*M25*N25*330*P25*O25/10000,2) -> 166.98 | R25: =V25 -> 0.75 | S25: =S24*1.05 -> 0 | T25: =X25 -> 28489 | U25: =T25*S25*R25*12/10000 -> 0 | V25: =C25 -> 0.75 | W25: =ROUND(W24*1.05,2) -> 42.55 | X25: =X24 -> 28489 | Y25: =ROUND(X25*W25*V25*12/10000,2) -> 1090.99 | Z25: =ROUND(G25+K25+Y25+Q25,2) -> 1327.9 | AA25: 254.13 | AC25: 22 | AE25: =Z25*5% -> 66.395 | AF25: =AF20*(1+项目技术经济指标!$M$10) -> 144.9459 | AG25: =AG20*(1+$AG$3) -> 42.652114 | AH25: =AH24 -> 0 | AI25: =ROUND(Z25*$AI$3,2) -> 26.56 | AJ25: =税费计算!O26 -> 256.69752 | AK25: =ROUND(SUM(AD25:AJ25),2) -> 537.25 | AL25: =SUM(AE25:AI25) -> 280.55301 | AN25: 2000
B26: 23 | C26: =C25 -> 0.75 | D26: =ROUND(D21*1.05,2) -> 1033.19 | E26: =E25 -> 0 | F26: =F25 -> 113.76 | G26: =ROUND(D26*F26*C26/10000,2) -> 8.82 | H26: =H25 -> 0.65 | I26: =I25 -> 9.72 | J26: =J25 -> 265 | K26: =ROUND(J26*I26*H26*365/10000,2) -> 61.11 | L26: =L25 -> 0.6 | M26: =M21*1.1 -> 0.87846 | N26: =N25 -> 40 | O26: =O25 -> 120 | P26: =P25 -> 2 | Q26: =ROUND(L26*M26*N26*330*P26*O26/10000,2) -> 166.98 | R26: =V26 -> 0.75 | S26: =S25 -> 0 | T26: =X26 -> 28489 | U26: =T26*S26*R26*12/10000 -> 0 | V26: =C26 -> 0.75 | W26: =W25 -> 42.55 | X26: =X25 -> 28489 | Y26: =ROUND(X26*W26*V26*12/10000,2) -> 1090.99 | Z26: =ROUND(G26+K26+Y26+Q26,2) -> 1327.9 | AA26: 254.13 | AC26: 23 | AE26: =Z26*5% -> 66.395 | AF26: =AF21*(1+项目技术经济指标!$M$10) -> 144.9459 | AG26: =AG21*(1+$AG$3) -> 42.652114 | AH26: =AH25 -> 0 | AI26: =ROUND(Z26*$AI$3,2) -> 26.56 | AJ26: =税费计算!O27 -> 256.69752 | AK26: =ROUND(SUM(AD26:AJ26),2) -> 537.25 | AL26: =SUM(AE26:AI26) -> 280.55301 | AN26: 600
B27: 24 | C27: =C26 -> 0.75 | D27: =ROUND(D22*1.05,2) -> 1033.19 | E27: =E26 -> 0 | F27: =F26 -> 113.76 | G27: =ROUND(D27*F27*C27/10000,2) -> 8.82 | H27: =H26 -> 0.65 | I27: =I26 -> 9.72 | J27: =J26 -> 265 | K27: =ROUND(J27*I27*H27*365/10000,2) -> 61.11 | L27: =L26 -> 0.6 | M27: =M22*1.1 -> 0.87846 | N27: =N26 -> 40 | O27: =O26 -> 120 | P27: =P26 -> 2 | Q27: =ROUND(L27*M27*N27*330*P27*O27/10000,2) -> 166.98 | R27: =V27 -> 0.75 | S27: =S26 -> 0 | T27: =X27 -> 28489 | U27: =T27*S27*R27*12/10000 -> 0 | V27: =C27 -> 0.75 | W27: =W26 -> 42.55 | X27: =X26 -> 28489 | Y27: =ROUND(X27*W27*V27*12/10000,2) -> 1090.99 | Z27: =ROUND(G27+K27+Y27+Q27,2) -> 1327.9 | AA27: 254.13 | AC27: 24 | AE27: =Z27*5% -> 66.395 | AF27: =AF22*(1+项目技术经济指标!$M$10) -> 144.9459 | AG27: =AG22*(1+$AG$3) -> 42.652114 | AH27: =AH26 -> 0 | AI27: =ROUND(Z27*$AI$3,2) -> 26.56 | AJ27: =税费计算!O28 -> 256.69752 | AK27: =ROUND(SUM(AD27:AJ27),2) -> 537.25 | AL27: =SUM(AE27:AI27) -> 280.55301 | AN27: 600
B28: 25 | C28: =C27 -> 0.75 | D28: =ROUND(D23*1.05,2) -> 1033.19 | E28: =E27 -> 0 | F28: =F27 -> 113.76 | G28: =ROUND(D28*F28*C28/10000,2) -> 8.82 | H28: =H27 -> 0.65 | I28: =I27 -> 9.72 | J28: =J27 -> 265 | K28: =ROUND(J28*I28*H28*365/10000,2) -> 61.11 | L28: =L27 -> 0.6 | M28: =M23*1.1 -> 0.87846 | N28: =N27 -> 40 | O28: =O27 -> 120 | P28: =P27 -> 2 | Q28: =ROUND(L28*M28*N28*330*P28*O28/10000,2) -> 166.98 | R28: =V28 -> 0.75 | S28: =S27 -> 0 | T28: =X28 -> 28489 | U28: =T28*S28*R28*12/10000 -> 0 | V28: =C28 -> 0.75 | W28: =W27 -> 42.55 | X28: =X27 -> 28489 | Y28: =ROUND(X28*W28*V28*12/10000,2) -> 1090.99 | Z28: =ROUND(G28+K28+Y28+Q28,2) -> 1327.9 | AA28: 254.13 | AC28: 25 | AE28: =Z28*5% -> 66.395 | AF28: =AF23*(1+项目技术经济指标!$M$10) -> 144.9459 | AG28: =AG23*(1+$AG$3) -> 42.652114 | AH28: =AH27 -> 0 | AI28: =ROUND(Z28*$AI$3,2) -> 26.56 | AJ28: =税费计算!O29 -> 256.69752 | AK28: =ROUND(SUM(AD28:AJ28),2) -> 537.25 | AL28: =SUM(AE28:AI28) -> 280.55301 | AN28: 1000
B29: 26 | C29: =C28 -> 0.75 | D29: =ROUND(D24*1.05,2) -> 1033.19 | E29: =E28 -> 0 | F29: =F28 -> 113.76 | G29: =ROUND(D29*F29*C29/10000,2) -> 8.82 | H29: =H28 -> 0.65 | I29: =I28 -> 9.72 | J29: =J28 -> 265 | K29: =ROUND(J29*I29*H29*365/10000,2) -> 61.11 | L29: =L28 -> 0.6 | M29: =M24*1.1 -> 0.87846 | N29: =N28 -> 40 | O29: =O28 -> 120 | P29: =P28 -> 2 | Q29: =ROUND(L29*M29*N29*330*P29*O29/10000,2) -> 166.98 | R29: =V29 -> 0.75 | S29: =S28 -> 0 | T29: =X29 -> 28489 | U29: =T29*S29*R29*12/10000 -> 0 | V29: =C29 -> 0.75 | W29: =W28 -> 42.55 | X29: =X28 -> 28489 | Y29: =ROUND(X29*W29*V29*12/10000,2) -> 1090.99 | Z29: =ROUND(G29+K29+Y29+Q29,2) -> 1327.9 | AA29: 254.13 | AC29: 26 | AE29: =Z29*5% -> 66.395 | AF29: =AF24*(1+项目技术经济指标!$M$10) -> 144.9459 | AG29: =AG24*(1+$AG$3) -> 42.652114 | AH29: =AH28 -> 0 | AI29: =ROUND(Z29*$AI$3,2) -> 26.56 | AJ29: =税费计算!O30 -> 256.69752 | AK29: =ROUND(SUM(AD29:AJ29),2) -> 537.25 | AL29: =SUM(AE29:AI29) -> 280.55301 | AN29: 1300
B30: 27 | C30: =C29 -> 0.75 | D30: =ROUND(D25*1.05,2) -> 1084.85 | E30: =E29 -> 0 | F30: =F29 -> 113.76 | G30: =ROUND(D30*F30*C30/10000,2) -> 9.26 | H30: =H29 -> 0.65 | I30: =ROUND(I29*1.05,2) -> 10.21 | J30: =J29 -> 265 | K30: =ROUND(J30*I30*H30*365/10000,2) -> 64.19 | L30: =L29 -> 0.6 | M30: =M25*1.1 -> 0.966306 | N30: =N29 -> 40 | O30: =O29 -> 120 | P30: =P29 -> 2 | Q30: =ROUND(L30*M30*N30*330*P30*O30/10000,2) -> 183.68 | R30: =V30 -> 0.75 | S30: =S29*1.05 -> 0 | T30: =X30 -> 28489 | U30: =T30*S30*R30*12/10000 -> 0 | V30: =C30 -> 0.75 | W30: =ROUND(W29*1.05,2) -> 44.68 | X30: =X29 -> 28489 | Y30: =ROUND(X30*W30*V30*12/10000,2) -> 1145.6 | Z30: =ROUND(G30+K30+Y30+Q30,2) -> 1402.73 | AA30: 279.44 | AC30: 27 | AE30: =Z30*5% -> 70.1365 | AF30: =AF25*(1+项目技术经济指标!$M$10) -> 159.44049 | AG30: =AG25*(1+$AG$3) -> 44.78472 | AH30: =AH29 -> 0 | AI30: =ROUND(Z30*$AI$3,2) -> 28.05 | AJ30: =税费计算!O31 -> 270.59092 | AK30: =ROUND(SUM(AD30:AJ30),2) -> 573 | AL30: =SUM(AE30:AI30) -> 302.41171 | AN30: 2000
B31: 28 | C31: =C30 -> 0.75 | D31: =ROUND(D26*1.05,2) -> 1084.85 | E31: =E30 -> 0 | F31: =F30 -> 113.76 | G31: =ROUND(D31*F31*C31/10000,2) -> 9.26 | H31: =H30 -> 0.65 | I31: =I30 -> 10.21 | J31: =J30 -> 265 | K31: =ROUND(J31*I31*H31*365/10000,2) -> 64.19 | L31: =L30 -> 0.6 | M31: =M26*1.1 -> 0.966306 | N31: =N30 -> 40 | O31: =O30 -> 120 | P31: =P30 -> 2 | Q31: =ROUND(L31*M31*N31*330*P31*O31/10000,2) -> 183.68 | R31: =V31 -> 0.75 | S31: =S30 -> 0 | T31: =X31 -> 28489 | U31: =T31*S31*R31*12/10000 -> 0 | V31: =C31 -> 0.75 | W31: =W30 -> 44.68 | X31: =X30 -> 28489 | Y31: =ROUND(X31*W31*V31*12/10000,2) -> 1145.6 | Z31: =ROUND(G31+K31+Y31+Q31,2) -> 1402.73 | AA31: 279.44 | AC31: 28 | AE31: =Z31*5% -> 70.1365 | AF31: =AF26*(1+项目技术经济指标!$M$10) -> 159.44049 | AG31: =AG26*(1+$AG$3) -> 44.78472 | AH31: =AH30 -> 0 | AI31: =ROUND(Z31*$AI$3,2) -> 28.05 | AJ31: =税费计算!O32 -> 270.59092 | AK31: =ROUND(SUM(AD31:AJ31),2) -> 573 | AL31: =SUM(AE31:AI31) -> 302.41171 | AN31: =490*5 -> 2450
B32: 29 | C32: =C31 -> 0.75 | D32: =ROUND(D27*1.05,2) -> 1084.85 | E32: =E31 -> 0 | F32: =F31 -> 113.76 | G32: =ROUND(D32*F32*C32/10000,2) -> 9.26 | H32: =H31 -> 0.65 | I32: =I31 -> 10.21 | J32: =J31 -> 265 | K32: =ROUND(J32*I32*H32*365/10000,2) -> 64.19 | L32: =L31 -> 0.6 | M32: =M27*1.1 -> 0.966306 | N32: =N31 -> 40 | O32: =O31 -> 120 | P32: =P31 -> 2 | Q32: =ROUND(L32*M32*N32*330*P32*O32/10000,2) -> 183.68 | R32: =V32 -> 0.75 | S32: =S31 -> 0 | T32: =X32 -> 28489 | U32: =T32*S32*R32*12/10000 -> 0 | V32: =C32 -> 0.75 | W32: =W31 -> 44.68 | X32: =X31 -> 28489 | Y32: =ROUND(X32*W32*V32*12/10000,2) -> 1145.6 | Z32: =ROUND(G32+K32+Y32+Q32,2) -> 1402.73 | AA32: 279.44 | AC32: 29 | AE32: =Z32*5% -> 70.1365 | AF32: =AF27*(1+项目技术经济指标!$M$10) -> 159.44049 | AG32: =AG27*(1+$AG$3) -> 44.78472 | AH32: =AH31 -> 0 | AI32: =ROUND(Z32*$AI$3,2) -> 28.05 | AJ32: =税费计算!O33 -> 270.59092 | AK32: =ROUND(SUM(AD32:AJ32),2) -> 573 | AL32: =SUM(AE32:AI32) -> 302.41171
B33: 30 | C33: =C32 -> 0.75 | D33: =ROUND(D28*1.05,2) -> 1084.85 | E33: =E32 -> 0 | F33: =F32 -> 113.76 | G33: =ROUND(D33*F33*C33/10000,2) -> 9.26 | H33: =H32 -> 0.65 | I33: =I32 -> 10.21 | J33: =J32 -> 265 | K33: =ROUND(J33*I33*H33*365/10000,2) -> 64.19 | L33: =L32 -> 0.6 | M33: =M28*1.1 -> 0.966306 | N33: =N32 -> 40 | O33: =O32 -> 120 | P33: =P32 -> 2 | Q33: =ROUND(L33*M33*N33*330*P33*O33/10000,2) -> 183.68 | R33: =V33 -> 0.75 | S33: =S32 -> 0 | T33: =X33 -> 28489 | U33: =T33*S33*R33*12/10000 -> 0 | V33: =C33 -> 0.75 | W33: =W32 -> 44.68 | X33: =X32 -> 28489 | Y33: =ROUND(X33*W33*V33*12/10000,2) -> 1145.6 | Z33: =ROUND(G33+K33+Y33+Q33,2) -> 1402.73 | AA33: 279.44 | AC33: 30 | AE33: =Z33*5% -> 70.1365 | AF33: =AF28*(1+项目技术经济指标!$M$10) -> 159.44049 | AG33: =AG28*(1+$AG$3) -> 44.78472 | AH33: =AH32 -> 0 | AI33: =ROUND(Z33*$AI$3,2) -> 28.05 | AJ33: =税费计算!O34 -> 270.59092 | AK33: =ROUND(SUM(AD33:AJ33),2) -> 573 | AL33: =SUM(AE33:AI33) -> 302.41171
B34: 31 | Y34: =ROUND(X34*W34*V34*12/10000,2) -> 0 | Z34: =ROUND(G34+K34+Y34,2) -> 0 | AC34: 31 | AE34: =ROUND(Z34*$AE$3,2) -> 0 | AH34: =AH33 -> 0 | AI34: =ROUND(Z34*$AI$3,2) -> 0 | AJ34: =ROUND(税费计算!O35,2) -> 0 | AK34: =ROUND(SUM(AD34:AJ34),2) -> 0 | AL34: =SUM(AE34:AI34) -> 0
Y35: =ROUND(X35*W35*V35*12/10000,2) -> 0 | Z35: =ROUND(G35+K35+Y35,2) -> 0
A36: 合计 | G36: =SUM(G4:G35) -> 230.2 | K36: =SUM(K5:K33) -> 1592.03 | Q36: =SUM(Q4:Q35) -> 4092.55 | U36: =SUM(U5:U33) -> 0 | Y36: =SUM(Y4:Y35) -> 28480.27 | Z36: =SUM(Z5:Z33) -> 34395.05 | AA36: 6258.85 | AB36: 合计 | AD36: =SUM(AD4:AD35) -> 0 | AE36: =SUM(AE4:AE35) -> 1719.7525 | AF36: =SUM(AF4:AF35) -> 3659.7865 | AG36: =SUM(AG4:AG35) -> 1148.6109 | AH36: =SUM(AH4:AH35) -> 0 | AI36: =SUM(AI4:AI35) -> 687.91 | AJ36: =SUM(AJ4:AJ35) -> 5087.7439 | AK36: =SUM(AK4:AK35) -> 12303.77 | AL36: =SUM(AL5:AL34) -> 7216.0598 | AM36: =SUM(AE36:AI36) -> 7216.0598
AF37: =AF36/20/29 -> 6.3099767
Y38: =V20*W20*X20*12 -> 10389369
AD39: =Z36-AK36 -> 22091.28 | AE39: =Z36-AK36 -> 22091.28
AE41: =AF36/29/14 -> 9.0142524
AD46: 参考同类型项目
AD47: 原材料 | AE47: 消耗量（吨） | AF47: 单价/吨 | AG47: 总价（万元） | AI47: 污水处理量（吨） | AJ47: 每万吨污水 淤泥产生量（吨） | AK47: 年淤泥量（吨） | AL47: 处理单价（元/吨） | AM47: 淤泥处理费
AD48: 药剂 PAC | AE48: =$F$6/20000*160 -> 0.91008 | AF48: 1800 | AG48: =AE48*AF48/10000 -> 0.1638144 | AI48: =F6 -> 113.76 | AJ48: 1 | AK48: =AI48/10000*AJ48*365 -> 4.15224 | AL48: 160 | AM48: =AK48*AL48/10000 -> 0.06643584
AD49: 药剂 PAM | AE49: =$F$6/20000*7.8 -> 0.0443664 | AF49: 28600 | AG49: =AE49*AF49/10000 -> 0.1268879
AD50: NaCl | AE50: =$F$6/20000*125 -> 0.711 | AF50: 2200 | AG50: =AE50*AF50/10000 -> 0.15642
AD51: 乙酸钠 | AE51: =$F$6/20000*115 -> 0.65412 | AF51: 3000 | AG51: =AE51*AF51/10000 -> 0.196236
AD52: 合计 | AG52: =SUM(AG48:AG51) -> 0.6433583
B54: 69.7
B55: 26.7 | AD55: 吉水县移民安置区排水防涝蓄水功能建设项目
B56: 87.6
B61: 7500
B62: 8000
B63: 6500
B65: 3000
B66: 3000
B67: 4000
B68: 1000
B74: =33600/666.67 -> 50.399748

Sheet 资金平衡表
B1: 年度 | C1: 借贷本息支付 | F1: 经营收入 | H1: 总费用成本 | J1: 收益余额
C2: 本金 | D2: 利息 | E2: 本息合计 | F2: 1 | G2: 下降10% | H2: 1 | I2: 上升10% | J2: 1 | K2: 收入下降10% | L2: 成本上升10% | M2: 收入下降10%且成本上升10%
B3: 1 | C3: =还本付息!E5 -> 0 | D3: =还本付息!H5 -> 270 | E3: =C3+D3 -> 270
B4: 2 | C4: =还本付息!E6 -> 0 | D4: =还本付息!H6 -> 270 | E4: =C4+D4 -> 270 | F4: =ROUND(收入成本!Z5,2) -> 691.07 | G4: =ROUND(收入成本!Z5*0.9,2) -> 621.96 | H4: =ROUND(收入成本!AK5,2) -> 254.25 | I4: =ROUND(收入成本!AL5*1.1+收入成本!AJ5,2) -> 272.5 | J4: =F4-H4 -> 436.82 | K4: =G4-H4 -> 367.71 | L4: =F4-I4 -> 418.57 | M4: =G4-I4 -> 349.46
B5: 3 | C5: =还本付息!E7 -> 0 | D5: =还本付息!H7 -> 270 | E5: =C5+D5 -> 270 | F5: =ROUND(收入成本!Z6,2) -> 774.27 | G5: =ROUND(收入成本!Z6*0.9,2) -> 696.84 | H5: =ROUND(收入成本!AK6,2) -> 267.26 | I5: =ROUND(收入成本!AL6*1.1+收入成本!AJ6,2) -> 286.09 | J5: =F5-H5 -> 507.01 | K5: =G5-H5 -> 429.58 | L5: =F5-I5 -> 488.18 | M5: =G5-I5 -> 410.75
B6: 4 | C6: =还本付息!E8 -> 0 | D6: =还本付息!H8 -> 270 | E6: =C6+D6 -> 270 | F6: =ROUND(收入成本!Z7,2) -> 857.45 | G6: =ROUND(收入成本!Z7*0.9,2) -> 771.71 | H6: =ROUND(收入成本!AK7,2) -> 280.26 | I6: =ROUND(收入成本!AL7*1.1+收入成本!AJ7,2) -> 299.67 | J6: =F6-H6 -> 577.19 | K6: =G6-H6 -> 491.45 | L6: =F6-I6 -> 557.78 | M6: =G6-I6 -> 472.04
B7: 5 | C7: =还本付息!E9 -> 0 | D7: =还本付息!H9 -> 270 | E7: =C7+D7 -> 270 | F7: =ROUND(收入成本!Z8,2) -> 935.01 | G7: =ROUND(收入成本!Z8*0.9,2) -> 841.51 | H7: =ROUND(收入成本!AK8,2) -> 292.87 | I7: =ROUND(收入成本!AL8*1.1+收入成本!AJ8,2) -> 312.82 | J7: =F7-H7 -> 642.14 | K7: =G7-H7 -> 548.64 | L7: =F7-I7 -> 622.19 | M7: =G7-I7 -> 528.69
B8: 6 | C8: =还本付息!E10 -> 0 | D8: =还本付息!H10 -> 270 | E8: =C8+D8 -> 270 | F8: =ROUND(收入成本!Z9,2) -> 1004.83 | G8: =ROUND(收入成本!Z9*0.9,2) -> 904.35 | H8: =ROUND(收入成本!AK9,2) -> 304.94 | I8: =ROUND(收入成本!AL9*1.1+收入成本!AJ9,2) -> 325.38 | J8: =F8-H8 -> 699.89 | K8: =G8-H8 -> 599.41 | L8: =F8-I8 -> 679.45 | M8: =G8-I8 -> 578.97
B9: 7 | C9: =还本付息!E11 -> 0 | D9: =还本付息!H11 -> 270 | E9: =C9+D9 -> 270 | F9: =ROUND(收入成本!Z10,2) -> 1128.14 | G9: =ROUND(收入成本!Z10*0.9,2) -> 1015.33 | H9: =ROUND(收入成本!AK10,2) -> 337.78 | I9: =ROUND(收入成本!AL10*1.1+收入成本!AJ10,2) -> 360.25 | J9: =F9-H9 -> 790.36 | K9: =G9-H9 -> 677.55 | L9: =F9-I9 -> 767.89 | M9: =G9-I9 -> 655.08
B10: 8 | C10: =还本付息!E12 -> 0 | D10: =还本付息!H12 -> 270 | E10: =C10+D10 -> 270 | F10: =ROUND(收入成本!Z11,2) -> 1128.14 | G10: =ROUND(收入成本!Z11*0.9,2) -> 1015.33 | H10: =ROUND(收入成本!AK11,2) -> 337.78 | I10: =ROUND(收入成本!AL11*1.1+收入成本!AJ11,2) -> 360.25 | J10: =F10-H10 -> 790.36 | K10: =G10-H10 -> 677.55 | L10: =F10-I10 -> 767.89 | M10: =G10-I10 -> 655.08
B11: 9 | C11: =还本付息!E13 -> 0 | D11: =还本付息!H13 -> 270 | E11: =C11+D11 -> 270 | F11: =ROUND(收入成本!Z12,2) -> 1128.14 | G11: =ROUND(收入成本!Z12*0.9,2) -> 1015.33 | H11: =ROUND(收入成本!AK12,2) -> 337.78 | I11: =ROUND(收入成本!AL12*1.1+收入成本!AJ12,2) -> 360.25 | J11: =F11-H11 -> 790.36 | K11: =G11-H11 -> 677.55 | L11: =F11-I11 -> 767.89 | M11: =G11-I11 -> 655.08
B12: 10 | C12: =还本付息!E14 -> 0 | D12: =还本付息!H14 -> 270 | E12: =C12+D12 -> 270 | F12: =ROUND(收入成本!Z13,2) -> 1128.14 | G12: =ROUND(收入成本!Z13*0.9,2) -> 1015.33 | H12: =ROUND(收入成本!AK13,2) -> 337.78 | I12: =ROUND(收入成本!AL13*1.1+收入成本!AJ13,2) -> 360.25 | J12: =F12-H12 -> 790.36 | K12: =G12-H12 -> 677.55 | L12: =F12-I12 -> 767.89 | M12: =G12-I12 -> 655.08
B13: 11 | C13: =还本付息!E15 -> 0 | D13: =还本付息!H15 -> 270 | E13: =C13+D13 -> 270 | F13: =ROUND(收入成本!Z14,2) -> 1128.14 | G13: =ROUND(收入成本!Z14*0.9,2) -> 1015.33 | H13: =ROUND(收入成本!AK14,2) -> 337.78 | I13: =ROUND(收入成本!AL14*1.1+收入成本!AJ14,2) -> 360.25 | J13: =F13-H13 -> 790.36 | K13: =G13-H13 -> 677.55 | L13: =F13-I13 -> 767.89 | M13: =G13-I13 -> 655.08
B14: 12 | C14: =还本付息!E16 -> 0 | D14: =还本付息!H16 -> 270 | E14: =C14+D14 -> 270 | F14: =ROUND(收入成本!Z15,2) -> 1190.9 | G14: =ROUND(收入成本!Z15*0.9,2) -> 1071.81 | H14: =ROUND(收入成本!AK15,2) -> 360.57 | I14: =ROUND(收入成本!AL15*1.1+收入成本!AJ15,2) -> 384.76 | J14: =F14-H14 -> 830.33 | K14: =G14-H14 -> 711.24 | L14: =F14-I14 -> 806.14 | M14: =G14-I14 -> 687.05
B15: 13 | C15: =还本付息!E17 -> 0 | D15: =还本付息!H17 -> 270 | E15: =C15+D15 -> 270 | F15: =ROUND(收入成本!Z16,2) -> 1190.9 | G15: =ROUND(收入成本!Z16*0.9,2) -> 1071.81 | H15: =ROUND(收入成本!AK16,2) -> 360.57 | I15: =ROUND(收入成本!AL16*1.1+收入成本!AJ16,2) -> 384.76 | J15: =F15-H15 -> 830.33 | K15: =G15-H15 -> 711.24 | L15: =F15-I15 -> 806.14 | M15: =G15-I15 -> 687.05
... B32: 30 | C32: =还本付息!E34 -> 9000 | D32: =还本付息!H34 -> 270 | E32: =C32+D32 -> 9270 | F32: =ROUND(收入成本!Z33,2) -> 1402.73 | G32: =ROUND(收入成本!Z33*0.9,2) -> 1262.46 | H32: =ROUND(收入成本!AK33,2) -> 573 | I32: =ROUND(收入成本!AL33*1.1+收入成本!AJ33,2) -> 603.24 | J32: =F32-H32 -> 829.73 | K32: =G32-H32 -> 689.46 | L32: =F32-I32 -> 799.49 | M32: =G32-I32 -> 659.22
B33: 31 | C33: =还本付息!E35 -> 0 | D33: =还本付息!H35 -> 0 | E33: =C33+D33 -> 0 | F33: =ROUND(收入成本!Z34,2) -> 0 | G33: =ROUND(收入成本!Z34*0.9,2) -> 0 | H33: =ROUND(收入成本!AK34,2) -> 0 | I33: =ROUND(收入成本!AK34*1.1,2) -> 0 | J33: =F33-H33 -> 0 | K33: =G33-H33 -> 0 | L33: =F33-I33 -> 0 | M33: =G33-I33 -> 0
B34: 32 | C34: =还本付息!E36 -> 0 | D34: =还本付息!H36 -> 0 | E34: =C34+D34 -> 0
B35: 33 | C35: =还本付息!E37 -> 0 | D35: =还本付息!H37 -> 0 | E35: =C35+D35 -> 0 | F35: =ROUND(收入成本!Z35,2) -> 0 | G35: =ROUND(收入成本!Z35*0.9,2) -> 0 | H35: =ROUND(收入成本!AK35,2) -> 0 | I35: =ROUND(收入成本!AK35*1.1,2) -> 0 | J35: =F35-H35 -> 0 | K35: =G35-H35 -> 0 | L35: =F35-I35 -> 0 | M35: =G35-I35 -> 0
B36: 合计 | C36: 9000 | D36: =SUM(D3:D35) -> 8100 | E36: =SUM(E3:E35) -> 17100 | F36: =SUM(F3:F35) -> 34395.05 | G36: =SUM(G3:G35) -> 30955.56 | H36: =SUM(H3:H35) -> 12303.77 | I36: =SUM(I3:I35) -> 13025.41 | J36: =SUM(J3:J35) -> 22091.28 | K36: =SUM(K3:K35) -> 18651.79 | ... M36: =SUM(M3:M35) -> 17930.15
B37: 本息覆盖率 | J37: =ROUND(J36/$E$36,2) -> 1.29 | K37: =ROUND(K36/$E$36,2) -> 1.09 | L37: =ROUND(L36/$E$36,2) -> 1.25 | M37: =ROUND(M36/$E$36,2) -> 1.05
C38: ☝输入发债额试算

Sheet 税费计算
A1: 年份 | B1: 增值税 | L1: 城市建设 维护税 | M1: 教育费 附加 | N1: 房产税 | O1: 税费合计 | P1: 工程施工进项税计算表
B2: 销项税 | G2: 进项税 | K2: 进销项 抵扣后 合计 | P2: 序号 | Q2: 项目 | R2: 含税金额 | S2: 税率 | T2: 进项税 | U2: 不含税金额（用于折旧）
B3: =收入成本!H1 -> 停车位收入 | C3: 充电桩收入 | D3: =收入成本!L1 -> 充电桩收入 | E3: =收入成本!V1 -> 厂房出租收入 | F3: 销项税 合计 | G3: 外购燃料动力 | H3: 维修 | I3: 进项税 合计 | J3: 工程施工留抵进项余额 | P3: 1.1 | Q3: 工程费用 | R3: =项目技术经济指标!D70 -> 17385.78 | S3: - | T3: =T4+T5 -> 1435.52 | U3: =R3-T3 -> 15950.26
B4: 0.09 | D4: 0.13 | E4: 0.09 | G4: 0 | H4: 0 | L4: 0.05 | M4: 0.05 | N4: 0.12 | P4: 1.1.1 | Q4: 建筑安装工程费 | R4: =项目技术经济指标!D71 -> 17385.78 | S4: 0.09 | T4: =ROUND(R4/(1+S4)*S4,2) -> 1435.52 | U4: =R4-T4 -> 15950.26
A5: 1 | B5: =ROUND(收入成本!G4/(1+$B$4)*$B$4,2) -> 0 | D5: =ROUND(收入成本!Q4/(1+$D$4)*$D$4,2) -> 0 | E5: =ROUND(收入成本!Y4/(1+$E$4)*$E$4,2) -> 0 | F5: =SUM(B5:E5) -> 0 | G5: =ROUND(收入成本!AE4/(1+$G$4)*$G$4,2) -> 0 | H5: =ROUND(收入成本!AG4/(1+$H$4)*$H$4,2) -> 0 | I5: =G5+H5 -> 0 | J5: =T9 -> 1435.52 | O5: =SUM(K5:N5) -> 0 | P5: 1.1.2 | Q5: 设备购置费 | R5: =项目技术经济指标!D72 -> 0 | S5: 0.13 | T5: =ROUND(R5/(1+S5)*S5,2) -> 0 | U5: =R5-T5 -> 0
A6: 2 | B6: =收入成本!K5/(1+$B$4)*$B$4 -> 2.5555046 | D6: =ROUND(收入成本!Q5/(1+$D$4)*$D$4,2) -> 6.56 | E6: =收入成本!Y5/(1+$E$4)*$E$4 -> 49.39844 | F6: =SUM(B6:E6) -> 58.513945 | G6: =ROUND(收入成本!AE5/(1+$G$4)*$G$4,2) -> 0 | H6: =ROUND(收入成本!AG5/(1+$H$4)*$H$4,2) -> 0 | I6: =G6+H6 -> 0 | J6: =IF((J5+H6+G6)-SUM(B6:E6)<0,0,(J5+H6+G6)-SUM(B6:E6)) -> 1377.0061 | N6: =ROUND(收入成本!Y5*$N$4,2) -> 71.79 | O6: =SUM(K6:N6) -> 71.79 | P6: 1.2 | Q6: 工程建设其他费 | R6: =项目技术经济指标!D73 -> 2754.06 | S6: 0 | T6: =ROUND(R6/(1+S6)*S6,2) -> 0 | U6: =R6-T6 -> 2754.06
A7: 3 | B7: =收入成本!K6/(1+$B$4)*$B$4 -> 2.8750459 | D7: =ROUND(收入成本!Q6/(1+$D$4)*$D$4,2) -> 8.75 | E7: =收入成本!Y6/(1+$E$4)*$E$4 -> 54.338532 | F7: =SUM(B7:E7) -> 65.963578 | G7: =ROUND(收入成本!AE6/(1+$G$4)*$G$4,2) -> 0 | H7: =ROUND(收入成本!AG6/(1+$H$4)*$H$4,2) -> 0 | I7: =G7+H7 -> 0 | J7: =IF((J6+H7+G7)-SUM(B7:E7)<0,0,(J6+H7+G7)-SUM(B7:E7)) -> 1311.0425 | K7: =IF((J6+H7+G7)-SUM(B7:E7)>0,0,SUM(B7:E7)-(J6+H7+G7)) -> 0 | L7: =ROUND(K7*$L$4,2) -> 0 | M7: =ROUND(K7*$M$4,2) -> 0 | N7: =ROUND(收入成本!Y6*$N$4,2) -> 78.97 | O7: =SUM(K7:N7) -> 78.97 | P7: 1.3 | Q7: 基本预备费 | R7: =项目技术经济指标!D74 -> 1590.16 | S7: 0 | T7: =ROUND(R7/(1+S7)*S7,2) -> 0 | U7: =R7-T7 -> 1590.16
A8: 4 | B8: =收入成本!K7/(1+$B$4)*$B$4 -> 3.1945872 | D8: =ROUND(收入成本!Q7/(1+$D$4)*$D$4,2) -> 10.93 | E8: =收入成本!Y7/(1+$E$4)*$E$4 -> 59.277798 | F8: =SUM(B8:E8) -> 73.402385 | G8: =ROUND(收入成本!AE7/(1+$G$4)*$G$4,2) -> 0 | H8: =ROUND(收入成本!AG7/(1+$H$4)*$H$4,2) -> 0 | I8: =G8+H8 -> 0 | J8: =IF((J7+H8+G8)-SUM(B8:E8)<0,0,(J7+H8+G8)-SUM(B8:E8)) -> 1237.6401 | K8: =IF((J7+H8+G8)-SUM(B8:E8)>0,0,SUM(B8:E8)-(J7+H8+G8)) -> 0 | L8: =ROUND(K8*$L$4,2) -> 0 | M8: =ROUND(K8*$M$4,2) -> 0 | N8: =ROUND(收入成本!Y7*$N$4,2) -> 86.15 | O8: =SUM(K8:N8) -> 86.15 | P8: 1.4 | Q8: 建设期利息 | R8: =项目技术经济指标!D75 -> 270 | S8: 0 | T8: =ROUND(R8/(1+S8)*S8,2) -> 0 | U8: =R8-T8 -> 270
A9: 5 | B9: =收入成本!K8/(1+$B$4)*$B$4 -> 3.8336697 | D9: =ROUND(收入成本!Q8/(1+$D$4)*$D$4,2) -> 12.03 | E9: =收入成本!Y8/(1+$E$4)*$E$4 -> 64.21789 | F9: =SUM(B9:E9) -> 80.08156 | G9: =ROUND(收入成本!AE8/(1+$G$4)*$G$4,2) -> 0 | H9: =ROUND(收入成本!AG8/(1+$H$4)*$H$4,2) -> 0 | I9: =G9+H9 -> 0 | J9: =IF((J8+H9+G9)-SUM(B9:E9)<0,0,(J8+H9+G9)-SUM(B9:E9)) -> 1157.5585 | K9: =IF((J8+H9+G9)-SUM(B9:E9)>0,0,SUM(B9:E9)-(J8+H9+G9)) -> 0 | L9: =ROUND(K9*$L$4,2) -> 0 | M9: =ROUND(K9*$M$4,2) -> 0 | N9: =ROUND(收入成本!Y8*$N$4,2) -> 93.33 | O9: =SUM(K9:N9) -> 93.33 | P9: 1 | Q9: 总投资 | R9: =R3+R6+R7+R8 -> 22000 | T9: =SUM(T4:T8) -> 1435.52 | U9: =SUM(U4:U8) -> 20564.48
A10: 6 | B10: =收入成本!K9/(1+$B$4)*$B$4 -> 3.8336697 | D10: =ROUND(收入成本!Q9/(1+$D$4)*$D$4,2) -> 13.12 | E10: =收入成本!Y9/(1+$E$4)*$E$4 -> 69.157982 | F10: =SUM(B10:E10) -> 86.111651 | G10: =ROUND(收入成本!AE9/(1+$G$4)*$G$4,2) -> 0 | H10: =ROUND(收入成本!AG9/(1+$H$4)*$H$4,2) -> 0 | I10: =G10+H10 -> 0 | J10: =IF((J9+H10+G10)-SUM(B10:E10)<0,0,(J9+H10+G10)-SUM(B10:E10)) -> 1071.4469 | K10: =IF((J9+H10+G10)-SUM(B10:E10)>0,0,SUM(B10:E10)-(J9+H10+G10)) -> 0 | L10: =ROUND(K10*$L$4,2) -> 0 | M10: =ROUND(K10*$M$4,2) -> 0 | N10: =ROUND(收入成本!Y9*$N$4,2) -> 100.51 | O10: =SUM(K10:N10) -> 100.51
A11: 7 | B11: =收入成本!K10/(1+$B$4)*$B$4 -> 4.3604587 | D11: =ROUND(收入成本!Q10/(1+$D$4)*$D$4,2) -> 14.43 | E11: =收入成本!Y10/(1+$E$4)*$E$4 -> 77.80211 | F11: =SUM(B11:E11) -> 96.592569 | G11: =ROUND(收入成本!AE10/(1+$G$4)*$G$4,2) -> 0 | H11: =ROUND(收入成本!AG10/(1+$H$4)*$H$4,2) -> 0 | I11: =G11+H11 -> 0 | J11: =IF((J10+H11+G11)-SUM(B11:E11)<0,0,(J10+H11+G11)-SUM(B11:E11)) -> 974.85431 | K11: =IF((J10+H11+G11)-SUM(B11:E11)>0,0,SUM(B11:E11)-(J10+H11+G11)) -> 0 | L11: =ROUND(K11*$L$4,2) -> 0 | M11: =ROUND(K11*$M$4,2) -> 0 | N11: =ROUND(收入成本!Y10*$N$4,2) -> 113.07 | O11: =SUM(K11:N11) -> 113.07
A12: 8 | B12: =收入成本!K11/(1+$B$4)*$B$4 -> 4.3604587 | D12: =ROUND(收入成本!Q11/(1+$D$4)*$D$4,2) -> 14.43 | E12: =收入成本!Y11/(1+$E$4)*$E$4 -> 77.80211 | F12: =SUM(B12:E12) -> 96.592569 | G12: =ROUND(收入成本!AE11/(1+$G$4)*$G$4,2) -> 0 | H12: =ROUND(收入成本!AG11/(1+$H$4)*$H$4,2) -> 0 | I12: =G12+H12 -> 0 | J12: =IF((J11+H12+G12)-SUM(B12:E12)<0,0,(J11+H12+G12)-SUM(B12:E12)) -> 878.26174 | K12: =IF((J11+H12+G12)-SUM(B12:E12)>0,0,SUM(B12:E12)-(J11+H12+G12)) -> 0 | L12: =ROUND(K12*$L$4,2) -> 0 | M12: =ROUND(K12*$M$4,2) -> 0 | N12: =ROUND(收入成本!Y11*$N$4,2) -> 113.07 | O12: =SUM(K12:N12) -> 113.07
A13: 9 | B13: =收入成本!K12/(1+$B$4)*$B$4 -> 4.3604587 | D13: =ROUND(收入成本!Q12/(1+$D$4)*$D$4,2) -> 14.43 | E13: =收入成本!Y12/(1+$E$4)*$E$4 -> 77.80211 | F13: =SUM(B13:E13) -> 96.592569 | G13: =ROUND(收入成本!AE12/(1+$G$4)*$G$4,2) -> 0 | H13: =ROUND(收入成本!AG12/(1+$H$4)*$H$4,2) -> 0 | I13: =G13+H13 -> 0 | J13: =IF((J12+H13+G13)-SUM(B13:E13)<0,0,(J12+H13+G13)-SUM(B13:E13)) -> 781.66917 | K13: =IF((J12+H13+G13)-SUM(B13:E13)>0,0,SUM(B13:E13)-(J12+H13+G13)) -> 0 | L13: =ROUND(K13*$L$4,2) -> 0 | M13: =ROUND(K13*$M$4,2) -> 0 | N13: =ROUND(收入成本!Y12*$N$4,2) -> 113.07 | O13: =SUM(K13:N13) -> 113.07
A14: 10 | B14: =收入成本!K13/(1+$B$4)*$B$4 -> 4.3604587 | D14: =ROUND(收入成本!Q13/(1+$D$4)*$D$4,2) -> 14.43 | E14: =收入成本!Y13/(1+$E$4)*$E$4 -> 77.80211 | F14: =SUM(B14:E14) -> 96.592569 | G14: =ROUND(收入成本!AE13/(1+$G$4)*$G$4,2) -> 0 | H14: =ROUND(收入成本!AG13/(1+$H$4)*$H$4,2) -> 0 | I14: =G14+H14 -> 0 | J14: =IF((J13+H14+G14)-SUM(B14:E14)<0,0,(J13+H14+G14)-SUM(B14:E14)) -> 685.07661 | K14: =IF((J13+H14+G14)-SUM(B14:E14)>0,0,SUM(B14:E14)-(J13+H14+G14)) -> 0 | L14: =ROUND(K14*$L$4,2) -> 0 | M14: =ROUND(K14*$M$4,2) -> 0 | N14: =ROUND(收入成本!Y13*$N$4,2) -> 113.07 | O14: =SUM(K14:N14) -> 113.07
A15: 11 | B15: =收入成本!K14/(1+$B$4)*$B$4 -> 4.3604587 | D15: =ROUND(收入成本!Q14/(1+$D$4)*$D$4,2) -> 14.43 | E15: =收入成本!Y14/(1+$E$4)*$E$4 -> 77.80211 | F15: =SUM(B15:E15) -> 96.592569 | G15: =ROUND(收入成本!AE14/(1+$G$4)*$G$4,2) -> 0 | H15: =ROUND(收入成本!AG14/(1+$H$4)*$H$4,2) -> 0 | I15: =G15+H15 -> 0 | J15: =IF((J14+H15+G15)-SUM(B15:E15)<0,0,(J14+H15+G15)-SUM(B15:E15)) -> 588.48404 | K15: =IF((J14+H15+G15)-SUM(B15:E15)>0,0,SUM(B15:E15)-(J14+H15+G15)) -> 0 | L15: =ROUND(K15*$L$4,2) -> 0 | M15: =ROUND(K15*$M$4,2) -> 0 | N15: =ROUND(收入成本!Y14*$N$4,2) -> 113.07 | O15: =SUM(K15:N15) -> 113.07
A16: 12 | B16: =收入成本!K15/(1+$B$4)*$B$4 -> 4.5784404 | D16: =ROUND(收入成本!Q15/(1+$D$4)*$D$4,2) -> 15.88 | E16: =收入成本!Y15/(1+$E$4)*$E$4 -> 81.697706 | F16: =SUM(B16:E16) -> 102.15615 | G16: =ROUND(收入成本!AE15/(1+$G$4)*$G$4,2) -> 0 | H16: =ROUND(收入成本!AG15/(1+$H$4)*$H$4,2) -> 0 | I16: =G16+H16 -> 0 | J16: =IF((J15+H16+G16)-SUM(B16:E16)<0,0,(J15+H16+G16)-SUM(B16:E16)) -> 486.32789 | K16: =IF((J15+H16+G16)-SUM(B16:E16)>0,0,SUM(B16:E16)-(J15+H16+G16)) -> 0 | L16: =ROUND(K16*$L$4,2) -> 0 | M16: =ROUND(K16*$M$4,2) -> 0 | N16: =ROUND(收入成本!Y15*$N$4,2) -> 118.73 | O16: =SUM(K16:N16) -> 118.73
A17: 13 | B17: =收入成本!K16/(1+$B$4)*$B$4 -> 4.5784404 | D17: =ROUND(收入成本!Q16/(1+$D$4)*$D$4,2) -> 15.88 | E17: =收入成本!Y16/(1+$E$4)*$E$4 -> 81.697706 | F17: =SUM(B17:E17) -> 102.15615 | G17: =ROUND(收入成本!AE16/(1+$G$4)*$G$4,2) -> 0 | H17: =ROUND(收入成本!AG16/(1+$H$4)*$H$4,2) -> 0 | I17: =G17+H17 -> 0 | J17: =IF((J16+H17+G17)-SUM(B17:E17)<0,0,(J16+H17+G17)-SUM(B17:E17)) -> 384.17174 | K17: =IF((J16+H17+G17)-SUM(B17:E17)>0,0,SUM(B17:E17)-(J16+H17+G17)) -> 0 | L17: =ROUND(K17*$L$4,2) -> 0 | M17: =ROUND(K17*$M$4,2) -> 0 | N17: =ROUND(收入成本!Y16*$N$4,2) -> 118.73 | O17: =SUM(K17:N17) -> 118.73
A18: 14 | B18: =收入成本!K17/(1+$B$4)*$B$4 -> 4.5784404 | D18: =ROUND(收入成本!Q17/(1+$D$4)*$D$4,2) -> 15.88 | E18: =收入成本!Y17/(1+$E$4)*$E$4 -> 81.697706 | F18: =SUM(B18:E18) -> 102.15615 | G18: =ROUND(收入成本!AE17/(1+$G$4)*$G$4,2) -> 0 | H18: =ROUND(收入成本!AG17/(1+$H$4)*$H$4,2) -> 0 | I18: =G18+H18 -> 0 | J18: =IF((J17+H18+G18)-SUM(B18:E18)<0,0,(J17+H18+G18)-SUM(B18:E18)) -> 282.0156 | K18: =IF((J17+H18+G18)-SUM(B18:E18)>0,0,SUM(B18:E18)-(J17+H18+G18)) -> 0 | L18: =ROUND(K18*$L$4,2) -> 0 | M18: =ROUND(K18*$M$4,2) -> 0 | N18: =ROUND(收入成本!Y17*$N$4,2) -> 118.73 | O18: =SUM(K18:N18) -> 118.73
A19: 15 | B19: =收入成本!K18/(1+$B$4)*$B$4 -> 4.5784404 | D19: =ROUND(收入成本!Q18/(1+$D$4)*$D$4,2) -> 15.88 | E19: =收入成本!Y18/(1+$E$4)*$E$4 -> 81.697706 | F19: =SUM(B19:E19) -> 102.15615 | G19: =ROUND(收入成本!AE18/(1+$G$4)*$G$4,2) -> 0 | H19: =ROUND(收入成本!AG18/(1+$H$4)*$H$4,2) -> 0 | I19: =G19+H19 -> 0 | J19: =IF((J18+H19+G19)-SUM(B19:E19)<0,0,(J18+H19+G19)-SUM(B19:E19)) -> 179.85945 | K19: =IF((J18+H19+G19)-SUM(B19:E19)>0,0,SUM(B19:E19)-(J18+H19+G19)) -> 0 | L19: =ROUND(K19*$L$4,2) -> 0 | M19: =ROUND(K19*$M$4,2) -> 0 | N19: =ROUND(收入成本!Y18*$N$4,2) -> 118.73 | O19: =SUM(K19:N19) -> 118.73
A20: 16 | B20: =收入成本!K19/(1+$B$4)*$B$4 -> 4.5784404 | D20: =ROUND(收入成本!Q19/(1+$D$4)*$D$4,2) -> 15.88 | E20: =收入成本!Y19/(1+$E$4)*$E$4 -> 81.697706 | F20: =SUM(B20:E20) -> 102.15615 | G20: =ROUND(收入成本!AE19/(1+$G$4)*$G$4,2) -> 0 | H20: =ROUND(收入成本!AG19/(1+$H$4)*$H$4,2) -> 0 | I20: =G20+H20 -> 0 | J20: =IF((J19+H20+G20)-SUM(B20:E20)<0,0,(J19+H20+G20)-SUM(B20:E20)) -> 77.703303 | K20: =IF((J19+H20+G20)-SUM(B20:E20)>0,0,SUM(B20:E20)-(J19+H20+G20)) -> 0 | L20: =ROUND(K20*$L$4,2) -> 0 | M20: =ROUND(K20*$M$4,2) -> 0 | N20: =ROUND(收入成本!Y19*$N$4,2) -> 118.73 | O20: =SUM(K20:N20) -> 118.73
A21: 17 | B21: =收入成本!K20/(1+$B$4)*$B$4 -> 4.807156 | D21: =ROUND(收入成本!Q20/(1+$D$4)*$D$4,2) -> 17.46 | E21: =收入成本!Y20/(1+$E$4)*$E$4 -> 85.784037 | F21: =SUM(B21:E21) -> 108.05119 | G21: =ROUND(收入成本!AE20/(1+$G$4)*$G$4,2) -> 0 | H21: =ROUND(收入成本!AG20/(1+$H$4)*$H$4,2) -> 0 | I21: =G21+H21 -> 0 | J21: =IF((J20+H21+G21)-SUM(B21:E21)<0,0,(J20+H21+G21)-SUM(B21:E21)) -> 0 | K21: =IF((J20+H21+G21)-SUM(B21:E21)>0,0,SUM(B21:E21)-(J20+H21+G21)) -> 30.34789 | L21: =ROUND(K21*$L$4,2) -> 1.52 | M21: =ROUND(K21*$M$4,2) -> 1.52 | N21: =ROUND(收入成本!Y20*$N$4,2) -> 124.67 | O21: =SUM(K21:N21) -> 158.05789
... A34: 30 | B34: =收入成本!K33/(1+$B$4)*$B$4 -> 5.3000917 | D34: =ROUND(收入成本!Q33/(1+$D$4)*$D$4,2) -> 21.13 | E34: =收入成本!Y33/(1+$E$4)*$E$4 -> 94.590826 | F34: =SUM(B34:E34) -> 121.02092 | G34: =ROUND(收入成本!AE33/(1+$G$4)*$G$4,2) -> 0 | H34: =ROUND(收入成本!AG33/(1+$H$4)*$H$4,2) -> 0 | I34: =G34+H34 -> 0 | J34: =IF((J33+H34+G34)-SUM(B34:E34)<0,0,(J33+H34+G34)-SUM(B34:E34)) -> 0 | K34: =IF((J33+H34+G34)-SUM(B34:E34)>0,0,SUM(B34:E34)-(J33+H34+G34)) -> 121.02092 | L34: =ROUND(K34*$L$4,2) -> 6.05 | M34: =ROUND(K34*$M$4,2) -> 6.05 | N34: =ROUND(收入成本!Y33*$N$4,2) -> 137.47 | O34: =SUM(K34:N34) -> 270.59092
A35: 31 | B35: =ROUND(收入成本!G34*$B$4/(1+$B$4),2) -> 0 | D35: =ROUND(收入成本!Q34/(1+$D$4)*$D$4,2) -> 0 | E35: =ROUND(收入成本!Y34/(1+$E$4)*$E$4,2) -> 0 | F35: =SUM(B35:E35) -> 0 | G35: =ROUND(收入成本!AE34/(1+$G$4)*$G$4,2) -> 0 | H35: =ROUND(收入成本!AG34/(1+$H$4)*$H$4,2) -> 0 | I35: =G35+H35 -> 0 | J35: =IF((J34+H35+G35)-SUM(B35:E35)<0,0,(J34+H35+G35)-SUM(B35:E35)) -> 0 | K35: =IF((J34+H35+G35)-SUM(B35:E35)>0,0,SUM(B35:E35)-(J34+H35+G35)) -> 0 | L35: =ROUND(K35*$L$4,2) -> 0 | M35: =ROUND(K35*$M$4,2) -> 0 | N35: =ROUND(收入成本!Y34*$N$4,2) -> 0 | O35: =SUM(K35:N35) -> 0
A37: 合计 | B37: =SUM(B5:B36) -> 131.45202 | C37: =SUM(C5:C36) -> 0 | D37: =SUM(D5:D36) -> 470.81 | E37: =SUM(E5:E36) -> 2351.5819 | F37: =SUM(F5:F36) -> 2953.8439 | G37: =SUM(G5:G36) -> 0 | H37: =SUM(H5:H36) -> 0 | I37: =SUM(I5:I36) -> 0 | K37: =SUM(K7:K36) -> 1518.3239 | L37: =SUM(L7:L36) -> 75.92 | M37: =SUM(M7:M36) -> 75.92 | N37: =SUM(N6:N36) -> 3417.58 | O37: =SUM(O6:O36) -> 5087.7439

Sheet 资金流入流出平衡表
A1: 项目资金流入流出平衡
AI2: 单位：万元
A3: 项目 | B3: 第1年 | C3: 第2年 | D3: 第3年 | E3: 第4年 | F3: 第5年 | G3: 第6年 | H3: 第7年 | I3: 第8年 | J3: 第9年 | K3: 第10年 | L3: 第11年 | M3: 第12年 | N3: 第13年 | O3: 第14年 | P3: 第15年 | Q3: 第16年 | R3: 第17年 | S3: 第18年 | T3: 第19年 | U3: 第20年 | V3: 第21年 | W3: 第22年 | X3: 第23年 | Y3: 第24年 | Z3: 第25年 | AA3: 第26年 | AB3: 第27年 | AC3: 第28年 | AD3: 第29年 | AE3: 第30年 | AF3: 第31年 | AG3: 第32年 | AH3: 第33年 | AI3: 合计
A4: 一、项目现金流入 | B4: =B5+B13 -> 13173.01 | C4: =C5+C13 -> 9487.11 | D4: =D5+D13 -> 774.27 | E4: =E5+E13 -> 857.45 | F4: =F5+F13 -> 935.01 | G4: =G5+G13 -> 1004.83 | H4: =H5+H13 -> 1128.14 | I4: =I5+I13 -> 1128.14 | ... AH4: =AH5+AH13 -> #N/A | AI4: =SUM(B4:AE4) -> 56364.1
A5: 1.业务活动现金流入 | B5: =SUM(B6:B8) -> 0 | C5: =SUM(C6:C8) -> 660.12 | D5: =SUM(D6:D12) -> 774.27 | E5: =SUM(E6:E12) -> 857.45 | F5: =SUM(F6:F12) -> 935.01 | G5: =SUM(G6:G12) -> 1004.83 | H5: =SUM(H6:H12) -> 1128.14 | I5: =SUM(I6:I12) -> 1128.14 | J5: =SUM(J6:J12) -> 1128.14 | K5: =SUM(K6:K12) -> 1128.14 | ... AH5: =SUM(AH6:AH12) -> #N/A | AI5: =SUM(B5:AE5) -> 34364.1
A6: =CONCATENATE("其中：",收入成本!C1,"") -> 其中：种植基地出租收入 | B6: {=TRANSPOSE(收入成本!G4:G35)} -> 0 | C6: 4.83 | D6: 5.32 | E6: 5.8 | F6: 6.29 | G6: 6.77 | H6: 7.61 | I6: 7.61 | J6: 7.61 | K6: 7.61 | L6: 7.61 | M6: 8 | N6: 8 | O6: 8 | P6: 8 | Q6: 8 | R6: 8.4 | S6: 8.4 | T6: 8.4 | U6: 8.4 | V6: 8.4 | W6: 8.82 | X6: 8.82 | Y6: 8.82 | Z6: 8.82 | AA6: 8.82 | AB6: 9.26 | AC6: 9.26 | AD6: 9.26 | AE6: 9.26 | AF6: 0 | AG6: 0 | AH6: #N/A | AI6: =SUM(B6:AF6) -> 230.2
A7: =CONCATENATE(收入成本!L1,"") -> 充电桩收入 | B7: {=TRANSPOSE(收入成本!Q4:Q35)} -> 0 | C7: 57.02 | D7: 76.03 | E7: 95.04 | F7: 104.54 | G7: 114.05 | H7: 125.45 | I7: 125.45 | J7: 125.45 | K7: 125.45 | L7: 125.45 | M7: 138 | N7: 138 | O7: 138 | P7: 138 | Q7: 138 | R7: 151.8 | S7: 151.8 | T7: 151.8 | U7: 151.8 | V7: 151.8 | W7: 166.98 | X7: 166.98 | Y7: 166.98 | Z7: 166.98 | AA7: 166.98 | AB7: 183.68 | AC7: 183.68 | AD7: 183.68 | AE7: 183.68 | AF7: 0 | AG7: 0 | AH7: #N/A | AI7: =SUM(B7:AF7) -> 4092.55
A8: =CONCATENATE(收入成本!V1) -> 厂房出租收入 | B8: {=TRANSPOSE(收入成本!Y4:Y35)} -> 0 | C8: 598.27 | D8: 658.1 | E8: 717.92 | F8: 777.75 | G8: 837.58 | H8: 942.27 | I8: 942.27 | J8: 942.27 | K8: 942.27 | L8: 942.27 | M8: 989.45 | N8: 989.45 | O8: 989.45 | P8: 989.45 | Q8: 989.45 | R8: 1038.94 | S8: 1038.94 | T8: 1038.94 | U8: 1038.94 | V8: 1038.94 | W8: 1090.99 | X8: 1090.99 | Y8: 1090.99 | Z8: 1090.99 | AA8: 1090.99 | AB8: 1145.6 | AC8: 1145.6 | AD8: 1145.6 | AE8: 1145.6 | AF8: 0 | AG8: 0 | AH8: #N/A | AI8: =SUM(B8:AF8) -> 28480.27
A9: 停车位收入 | B9: {=TRANSPOSE(收入成本!K4:K33)} -> 0 | C9: 30.95 | D9: 34.82 | E9: 38.69 | F9: 46.43 | G9: 46.43 | H9: 52.81 | I9: 52.81 | J9: 52.81 | K9: 52.81 | L9: 52.81 | M9: 55.45 | N9: 55.45 | O9: 55.45 | P9: 55.45 | Q9: 55.45 | R9: 58.22 | S9: 58.22 | T9: 58.22 | U9: 58.22 | V9: 58.22 | W9: 61.11 | X9: 61.11 | Y9: 61.11 | Z9: 61.11 | AA9: 61.11 | AB9: 64.19 | AC9: 64.19 | AD9: 64.19 | AE9: 64.19 | AF9: #N/A | AG9: #N/A | AI9: =SUM(B9:AE9) -> 1592.03
AI10: =SUM(B10:AF10) -> 0
AI11: =SUM(B11:AF11) -> 0
AI12: =SUM(B12:AF12) -> 0
A13: 2.融资活动现金流入 | B13: =SUM(B14:B15) -> 13173.01 | C13: =SUM(C14:C15) -> 8826.99 | D13: =SUM(D14:D15) -> 0 | E13: =SUM(E14:E15) -> 0 | F13: =SUM(F14:F15) -> 0 | G13: =SUM(G14:G15) -> 0 | H13: =SUM(H14:H15) -> 0 | I13: =SUM(I14:I15) -> 0 | ... AH13: =SUM(AH14:AH15) -> 0 | AI13: =SUM(B13:AF13) -> 22000
A14: 其中：专项债券资金 | B14: =分年计划及建设期利息!E23 -> 9000 | C14: =分年计划及建设期利息!F23 -> 0 | D14: =分年计划及建设期利息!G23 -> 0 | E14: =分年计划及建设期利息!H23 -> 0 | AI14: =SUM(B14:AF14) -> 9000
A15: 资本金投入 | B15: =分年计划及建设期利息!E22 -> 4173.01 | C15: =分年计划及建设期利息!F22 -> 8826.99 | D15: =分年计划及建设期利息!G22 -> 0 | E15: =分年计划及建设期利息!H22 -> 0 | AI15: =SUM(B15:AF15) -> 13000
A16: 二、项目现金流出 | B16: =B17+B21 -> 13173.01 | C16: =C17+C21 -> 524.2535 | D16: =D17+D21 -> 537.2635 | E16: =E17+E21 -> 550.2625 | F16: =F17+F21 -> 562.8705 | G16: =G17+G21 -> 574.9415 | H16: =H17+H21 -> 607.7815 | I16: =I17+I21 -> 607.7815 | ... AH16: =AH17+AH21 -> #N/A | AI16: =SUM(B16:AF16) -> 42306.814
A17: 1.业务活动现金流出 | B17: =SUM(B18:B20) -> 12894.01 | C17: =SUM(C18:C20) -> 254.2535 | D17: =SUM(D18:D20) -> 267.2635 | E17: =SUM(E18:E20) -> 280.2625 | F17: =SUM(F18:F20) -> 292.8705 | G17: =SUM(G18:G20) -> 304.9415 | H17: =SUM(H18:H20) -> 337.7815 | I17: =SUM(I18:I20) -> 337.7815 | ... AH17: =SUM(AH18:AH20) -> #N/A | AI17: =SUM(B17:AF17) -> 25197.814
A18: 其中：项目建设流出 | B18: =分年计划及建设期利息!E15-B21 -> 12894.01 | AI18: =SUM(B18:AF18) -> 12894.01
A19: 相关税费流出 | B19: {=TRANSPOSE(税费计算!O5:O36)} -> 0 | C19: 71.79 | D19: 78.97 | E19: 86.15 | F19: 93.33 | G19: 100.51 | H19: 113.07 | I19: 113.07 | J19: 113.07 | K19: 113.07 | L19: 113.07 | M19: 118.73 | N19: 118.73 | O19: 118.73 | P19: 118.73 | Q19: 118.73 | R19: 158.05789 | S19: 243.52119 | T19: 243.52119 | U19: 243.52119 | V19: 243.52119 | W19: 256.69752 | X19: 256.69752 | Y19: 256.69752 | Z19: 256.69752 | AA19: 256.69752 | AB19: 270.59092 | AC19: 270.59092 | AD19: 270.59092 | AE19: 270.59092 | AF19: 0 | AG19: 0 | AH19: #N/A | AI19: =SUM(B19:AF19) -> 5087.7439
A20: 业务成本流出 | B20: {=TRANSPOSE(收入成本!AL4:AL35)} -> 0 | C20: 182.4635 | D20: 188.2935 | E20: 194.1125 | F20: 199.5405 | G20: 204.4315 | H20: 224.7115 | I20: 224.7115 | J20: 224.7115 | K20: 224.7115 | L20: 224.7115 | M20: 241.84172 | N20: 241.84172 | O20: 241.84172 | P20: 241.84172 | Q20: 241.84172 | R20: 260.40806 | S20: 260.40806 | T20: 260.40806 | U20: 260.40806 | V20: 260.40806 | W20: 280.55301 | X20: 280.55301 | Y20: 280.55301 | Z20: 280.55301 | AA20: 280.55301 | AB20: 302.41171 | AC20: 302.41171 | AD20: 302.41171 | AE20: 302.41171 | AF20: 0 | AG20: 0 | AH20: #N/A | AI20: =SUM(B20:AF20) -> 7216.0598
A21: 2.融资活动现金流出 | B21: =SUM(B22:B24) -> 279 | C21: =SUM(C22:C24) -> 270 | D21: =SUM(D22:D24) -> 270 | E21: =SUM(E22:E24) -> 270 | F21: =SUM(F22:F24) -> 270 | G21: =SUM(G22:G24) -> 270 | H21: =SUM(H22:H24) -> 270 | I21: =SUM(I22:I24) -> 270 | ... AF21: =SUM(AF22:AF24) -> 0 | AI21: =SUM(B21:AF21) -> 17109
A22: 其中：债券发行费用 | B22: =B14*0.1% -> 9 | C22: =C14*0.1% -> 0 | D22: =D14*0.1% -> 0 | E22: =E14*0.1% -> 0 | F22: =F14*0.1% -> 0 | G22: =G14*0.1% -> 0 | H22: =H14*0.1% -> 0 | I22: =I14*0.1% -> 0 | ... AH22: =AH14*0.1% -> 0 | AI22: =SUM(B22:AF22) -> 9
A23: 偿还债券本金 | B23: {=TRANSPOSE(还本付息!E5:E37)} -> 0 | C23: 0 | D23: 0 | E23: 0 | F23: 0 | G23: 0 | H23: 0 | I23: 0 | J23: 0 | K23: 0 | L23: 0 | M23: 0 | N23: 0 | O23: 0 | P23: 0 | Q23: 0 | R23: 0 | S23: 0 | T23: 0 | U23: 0 | V23: 0 | W23: 0 | X23: 0 | Y23: 0 | Z23: 0 | AA23: 0 | AB23: 0 | AC23: 0 | AD23: 0 | AE23: 9000 | AF23: 0 | AG23: 0 | AH23: 0 | AI23: =SUM(B23:AF23) -> 9000
A24: 支付债券利息 | B24: {=TRANSPOSE(还本付息!H5:H37)} -> 270 | C24: 270 | D24: 270 | E24: 270 | F24: 270 | G24: 270 | H24: 270 | I24: 270 | J24: 270 | K24: 270 | L24: 270 | M24: 270 | N24: 270 | O24: 270 | P24: 270 | Q24: 270 | R24: 270 | S24: 270 | T24: 270 | U24: 270 | V24: 270 | W24: 270 | X24: 270 | Y24: 270 | Z24: 270 | AA24: 270 | AB24: 270 | AC24: 270 | AD24: 270 | AE24: 270 | AF24: 0 | AG24: 0 | AH24: 0 | AI24: =SUM(B24:AF24) -> 8100
A25: 项目期初现金余额 | C25: =B27 -> 0 | D25: =C27 -> 8962.8565 | E25: =D27 -> 9199.863 | F25: =E27 -> 9507.0505 | G25: =F27 -> 9879.19 | H25: =G27 -> 10309.078 | I25: =H27 -> 10829.437 | J25: =I27 -> 11349.796 | ... AH25: =AG27 -> #N/A
A26: 项目期内现金变动 | B26: =B4-B16 -> 0 | C26: =C4-C16 -> 8962.8565 | D26: =D4-D16 -> 237.0065 | E26: =E4-E16 -> 307.1875 | F26: =F4-F16 -> 372.1395 | G26: =G4-G16 -> 429.8885 | H26: =H4-H16 -> 520.3585 | I26: =I4-I16 -> 520.3585 | ... AH26: =AH4-AH16 -> #N/A | AI26: =SUM(B26:AE26) -> 14057.286
A27: 项目期末现金余额 | B27: =B25+B26 -> 0 | C27: =C25+C26 -> 8962.8565 | D27: =D25+D26 -> 9199.863 | E27: =E25+E26 -> 9507.0505 | F27: =F25+F26 -> 9879.19 | G27: =G25+G26 -> 10309.078 | H27: =H25+H26 -> 10829.437 | I27: =I25+I26 -> 11349.796 | ... AH27: =AH25+AH26 -> #N/A | AI27: =AE27 -> 14057.286

Sheet 固定资产折旧
A1: 序号 | B1: 项 目 | C1: 折旧年限 | D1: 合 计 | E1: 计 算 期
C2: (年) | E2: 4 | F2: =E2+1 -> 5 | G2: =F2+1 -> 6 | H2: =G2+1 -> 7 | I2: =H2+1 -> 8 | J2: =I2+1 -> 9 | K2: =J2+1 -> 10 | L2: =K2+1 -> 11 | M2: =L2+1 -> 12 | ... Q2: =P2+1 -> 16
A3: 1 | B3: 房屋、建筑物（新增） | C3: 30
A4: 1.1 | B4: 原值 | E4: =ROUND((税费计算!U4+税费计算!U7+税费计算!U8)*0.95,2) -> 16919.9
A5: 1.2 | B5: 当期折旧费 | E5: =ROUND($E$4/$C$3,2) -> 564 | F5: =E5 -> 564 | G5: =F5 -> 564 | H5: =G5 -> 564 | I5: =H5 -> 564 | J5: =I5 -> 564 | K5: =J5 -> 564 | L5: =K5 -> 564 | M5: =L5 -> 564 | ... Q5: =P5 -> 564
A6: 1.3 | B6: 净值 | E6: =E4-E5 -> 16355.9 | F6: =E6-F5 -> 15791.9 | G6: =F6-G5 -> 15227.9 | H6: =G6-H5 -> 14663.9 | I6: =H6-I5 -> 14099.9 | J6: =I6-J5 -> 13535.9 | K6: =J6-K5 -> 12971.9 | L6: =K6-L5 -> 12407.9 | M6: =L6-M5 -> 11843.9 | ... Q6: =P6-Q5 -> 9587.9
A7: 2 | B7: 机器设备 | C7: 15
A8: 2.1 | B8: 原值 | E8: =ROUND(税费计算!U5,2) -> 0
A9: 2.2 | B9: 当期折旧费 | E9: =ROUND($E$8/$C$7,2) -> 0 | F9: =E9 -> 0 | G9: =F9 -> 0 | H9: =G9 -> 0 | I9: =H9 -> 0 | J9: =I9 -> 0 | K9: =J9 -> 0 | L9: =K9 -> 0 | M9: =L9 -> 0 | ... Q9: =P9 -> 0
A10: 2.3 | B10: 净值 | E10: =E8-E9 -> 0 | F10: =E10-F9 -> 0 | G10: =F10-G9 -> 0 | H10: =G10-H9 -> 0 | I10: =H10-I9 -> 0 | J10: =I10-J9 -> 0 | K10: =J10-K9 -> 0 | L10: =K10-L9 -> 0 | M10: =L10-M9 -> 0 | ... Q10: =P10-Q9 -> 0
A11: 3 | B11: 属于固定资产的其他费用 | C11: 20
A12: 3.1 | B12: 原值 | E12: =ROUND(税费计算!U6,2) -> 2754.06
A13: 3.2 | B13: 当期折旧费 | E13: =ROUND(E12/$C$11,2) -> 137.7 | F13: =E13 -> 137.7 | G13: =F13 -> 137.7 | H13: =G13 -> 137.7 | I13: =H13 -> 137.7 | J13: =I13 -> 137.7 | K13: =J13 -> 137.7 | L13: =K13 -> 137.7 | M13: =L13 -> 137.7 | ... Q13: =P13 -> 137.7
A14: 3.3 | B14: 净值 | E14: =E12-E13 -> 2616.36 | F14: =E14-F13 -> 2478.66 | G14: =F14-G13 -> 2340.96 | H14: =G14-H13 -> 2203.26 | I14: =H14-I13 -> 2065.56 | J14: =I14-J13 -> 1927.86 | K14: =J14-K13 -> 1790.16 | L14: =K14-L13 -> 1652.46 | M14: =L14-M13 -> 1514.76 | ... Q14: =P14-Q13 -> 963.96
A15: 4 | B15: 固定资产合计
A16: 4.1 | B16: 原值 | E16: =E4+E8+E12 -> 19673.96
A17: 4.2 | B17: 当期折旧费 | E17: =E5+E9+E13 -> 701.7 | F17: =F5+F9+F13 -> 701.7 | G17: =G5+G9+G13 -> 701.7 | H17: =H5+H9+H13 -> 701.7 | I17: =I5+I9+I13 -> 701.7 | J17: =J5+J9+J13 -> 701.7 | K17: =K5+K9+K13 -> 701.7 | L17: =L5+L9+L13 -> 701.7 | ... Q17: =Q5+Q9+Q13 -> 701.7
A18: 4.3 | B18: 净值 | E18: =E6+E10+E14 -> 18972.26 | F18: =F6+F10+F14 -> 18270.56 | G18: =G6+G10+G14 -> 17568.86 | H18: =H6+H10+H14 -> 16867.16 | I18: =I6+I10+I14 -> 16165.46 | J18: =J6+J10+J14 -> 15463.76 | K18: =K6+K10+K14 -> 14762.06 | L18: =L6+L10+L14 -> 14060.36 | ... Q18: =Q6+Q10+Q14 -> 10551.86

Sheet 工程建设其他费细则说明
A1: 工程建设其他费
A2: 序号 | B2: 项目 | C2: 内容 | D2: 计算方式 | E2: 参考取费标准 | F2: 地区折扣 | G2: 备注
F3: 南昌市
A4: 一 | B4: 建设单位管理费 | C4: 从筹建之日起至办理竣工财务决算之日止发生的管理性质的支出，包括工作人员薪酬及相关费用、办公费、办公场地租用费、差旅交通费、劳动保护费、工具用具使用费、固定资产使用费、招募生产工人费、技术图书资料费（含软件）、业务招待费、竣工验收费和其他管理性质开支 | D4: 工程费用×建设单位管理费费率 | E4: 财建[2016]504号 | F4: 按80%计取
A5: 二 | B5: 用地与工程准备费
A6: （一） | B6: 土地使用费和补偿费 | C6: 此部分不考虑
A7: 1 | B7: 征地补偿费
A8: 1.1 | B8: 土地补偿费
A9: 1.2 | B9: 青苗补偿费和地上附着物补偿费
A10: 1.3 | B10: 安置补助费
A11: 1.4 | B11: 耕地开垦费和森林植被恢复费
A12: 1.5 | B12: 生态补偿与压覆矿产资源补偿费
A13: 1.6 | B13: 其他补偿费
A14: 2 | B14: 拆迁补偿费用
A15: 2.1 | B15: 拆迁补偿金
A16: 2.2 | B16: 迁移补偿费
A17: 3 | B17: 土地出让金
A18: （二） | B18: 场地准备及临时设施费 | C18: 场地准备费是使工程项目的建设场地达到开工条件，由建设单位组织进行的场地平整等准备工作而发生的费用。 临时设施费是指建设单位为满足施工建设需要而提供的未列入工程费用的临时水、电、路、信、气、热等工程和临时仓库等建（构）筑物的建设、维修、拆除、摊销费用或租赁费用，以及货物、码头租赁等费用 | D18: 工程费用×费率+拆除清理费 | E18: 建标〔2011〕1号 | F18: 按照“洪府发[2004]3号”的60%计取
A19: 三 | B19: 市政公用配套设施费 | C19: 使用市政公用设施的建设项目，按照项目所在地省级人民政府有关规定建设或缴纳的市政公用设施建设配套费用，可能发生的公用供水、供气、供热设施建设的贴补费用、供电多回路高可靠性供电费用以及绿化工程补偿费用。 | E19: 《南昌市市政公用设施配套费征收管理办法实施细则》计取，计取金额不包含“可能发生的公用供水、供气、供热设施建设的贴补费用、供电多回路高可靠性供电费用以及绿化工程补偿费用”
A20: 四 | B20: 技术服务费
A21: （一） | B21: 前期工作咨询费 | C21: 建设项目前期工作的咨询收费。包括：建设项目专题研究、编制目建议书、可行性研究报告,以及其他与建设项目前期工作有关的咨询服务收费。 | E21: 计价格［1999］1283号 | F21: 按照“洪府发[2004]3号”的60%计取
A22: （二） | B22: 专项评价费
A23: 1 | B23: 环境影响评价费 | E23: 计价格[2002]125 号 | F23: 洪府发[2004]3号”的70%计取
A24: 2 | B24: 安全预评价费 | E24: 江西省安全评价收费指导价格（试行） | F24: 洪府发[2004]3号”的70%计取
A25: 3 | B25: 职业病危害预评价费
A26: 4 | B26: 地质灾害危险性评价费
A27: 5 | B27: 水土保持评价费 | E27: 保监[2005]22 号 2005 年 6 月 17 日 | F27: “洪府发[2004]3号”的70%计取
A28: 6 | B28: 压覆矿产资源评价费
A29: 7 | B29: 节能评估费 | E29: 沪发改环资（2012）043号 | F29: “洪府发[2004]3号”的70%计取
A30: 8 | B30: 危险与可操作性分析及安全完整性评价费
A31: 9 | B31: 社会稳定风险评估费 | E31: 赣评审字[2015]70 号
A32: 10 | B32: 劳动安全卫生评审费 | C32: 按照原劳动部《建设项目（工程）劳动安全卫生监察规定》和《建设项目（工程）劳动安全卫生评价管理办法》的规定，为分析建设项目存在的职业危害、危害因素的种类和危害成都，并提出先进、科学、合理可行的劳动安全卫生技术和管理对策的所需费用。 | D32: 工程费用X(0.1%-0.5%) | E32: 建标〔2011〕1号 | F32: 洪府发[2004]3号”的70%计取
A33: 11 | B33: 交通影响评估费 | E33: 5万平米（含）以下，2元/平米，5-20万平米，2元/平米，20-100万平米，1.5元/平米，100-200万平米，1.0元/平米；大于200万平米的，0.8元/平米
A34: 12 | B34: 其他专项评价费
A35: （三） | B35: 勘察设计费
A36: 1 | B36: 勘察费 | D36: 工程费用的0.8%-1.1% | E36: 建标〔2011〕1号
A37: 2 | B37: 设计费 | E37: 计价格[2002]10号 | F37: 工程设计费参照执行“计价格[2002]10号”标准，并按照投资5000万元以下按85%、投资5000万元以上（含）按80%计取。
A38: （四） | B38: 工程监理费 | C38: 指委托工程监理单位对工程实施监理工作所需费用。包括：施工监理和勘察、设计、保修等阶段监理。 | E38: 发改价格[2007]670号 | F38: 洪府发[2004]3号”的70%计取
A39: （五） | B39: 研究试验费
A40: （六） | B40: 特殊设备安全监督检验费
A41: （七） | B41: 监造费
A42: （八） | B42: 招标代理费 | C42: 指招标代理机构接受招标人委托,从事招标业务所需的费用。包括：编制招标文件，审查投标人资格，组织投标人踏勘现场并答疑，组织开标、评标、定标、以及提供招标前期咨询、协调合同的签订等业务。 | E42: 发改价格[2011]534号 | F42: 下浮20%计取
A43: （九） | B43: 施工图审查费 | C43: 指施工图审查机构受建设单位委托，根据国家法律、法规、技术标准与规范，对施工图进行审查所需的费用。 | E43: 赣价房字[2000]6号 | F43: 按70%计取
A44: （十） | B44: 技术经济标准使用费
A45: （十一） | B45: 工程造价咨询费 | C45: 指委托工程造价咨询单位审核设计概算、编制工程量清单、工程结算和竣工决算等计价文件，以及从事建设各阶段工程造价管理的咨询服务，出具工程造价成果文件等费用。 | E45: 赣价协[2021]23号 | F45: 洪府发[2004]3号”的70%计取
A46: （十二） | B46: 工程保险费 | C46: 指建设项目在建设期间根据需要对建筑工程、安装工程及机器设备和人身安全进行投保而发生的保险费用。包括：建筑安装工程一切险、人身意外伤害险和引进设备财产保险等费用。 | D46: 工程费用 X(0.3%~.6%) | E46: 建标〔2011〕1号 | F46: 洪府发[2004]3号”的70%计取

Sheet 节能评估文件编制费
A1: 序号 | B1: 收费区间 | E1: 基价 | F1: 费率 | G1: 工程费用 | H1: 直线内插法计取
G2: =其他费自动计算!C2 -> 17385.78
A3: 1 | C3: < | D3: 10000 | E3: 6 | G3: =IF(G2<D3,1,0) -> 0 | H3: =IF(AND(G3=1,G2>0),E3,0) -> 0
A4: 2 | B4: 10000 | C4: ~ | D4: 50000 | E4: 13 | F4: 0.000175 | G4: =IF(AND(G$2<=D4,G$2>B4),1,0) -> 1 | H4: =IF(G4=1,(E3+($G$2-B4)*F4),0) -> 7.2925115
A5: 3 | B5: 50000 | C5: ~ | D5: 100000 | E5: 20 | F5: 0.00014 | G5: =IF(AND(G$2<=D5,G$2>B5),1,0) -> 0 | H5: =IF(G5=1,(E4+($G$2-B5)*F5),0) -> 0
A6: 4 | B6: 100000 | C6: < | G6: =IF(G2>B6,1,0) -> 0 | H6: =IF(G6=1,E5,0) -> 0

Sheet 社会稳定风险评估
A1: 序号 | B1: 投资额 | E1: 基费 | F1: 输入费用 | G1: 直线内插法计算 | H1: 风险敏感系数 | I1: 合计
G2: =SUM(G3:G8) -> 0 | H2: 1.2 | I2: =SUM(I3:I8) -> 0
A3: 1 | C3: < | D3: 3000 | E3: 3 | F3: =IF(AND(F2<=D3,F2>0),1,0) -> 0 | G3: =IF(F3=1,E3/D3*F2,0) -> 0 | H3: 1.2 | I3: =IF(F3=1,MAX(G3*H3,E3),0) -> 0
A4: 2 | B4: 3000 | C4: ~ | D4: 10000 | E4: 6 | F4: =IF(AND($F$2>B4,$F$2<=D4),1,0) -> 0 | G4: =IF(F4=1,(E3+(E4-E3)/(D4-B4)*($F$2-B4)),0) -> 0 | H4: 1.2 | I4: =G4*H4 -> 0
A5: 3 | B5: 10000 | C5: ~ | D5: 50000 | E5: 9 | F5: =IF(AND($F$2>B5,$F$2<=D5),1,0) -> 0 | G5: =IF(F5=1,(E4+(E5-E4)/(D5-B5)*($F$2-B5)),0) -> 0 | H5: 1.2 | I5: =G5*H5 -> 0
A6: 4 | B6: 50000 | C6: ~ | D6: 100000 | E6: 12 | F6: =IF(AND($F$2>B6,$F$2<=D6),1,0) -> 0 | G6: =IF(F6=1,(E5+(E6-E5)/(D6-B6)*($F$2-B6)),0) -> 0 | H6: 1.2 | I6: =G6*H6 -> 0
A7: 5 | B7: 100000 | C7: ~ | D7: 500000 | E7: 15 | F7: =IF(AND($F$2>B7,$F$2<=D7),1,0) -> 0 | G7: =IF(F7=1,(E6+(E7-E6)/(D7-B7)*($F$2-B7)),0) -> 0 | H7: 1.2 | I7: =G7*H7 -> 0
A8: 6 | B8: 500000 | C8: < | E8: 20 | F8: =IF(F2>B8,1,0) -> 0 | G8: =IF(F8=1,E8/B8*F2,0) -> 0 | H8: 1.2 | I8: =IF(F8=1,MIN(G8*H8,E8),0) -> 0

Sheet 水土保持费
A1: 序号 | B1: 计费区间 | E1: 基价 | F1: 工程费用 | G1: 直线内插法计取
F2: =其他费自动计算!C2 -> 17385.78 | G2: =SUM(G3:G24) -> 66.77156
A3: 1 | C3: < | D3: 5000 | E3: 30 | F3: =IF(F2<=D3,1,0) -> 0 | G3: =IF(F3=1,E3/D3*F2,0) -> 0
A4: 2 | B4: 5000 | C4: ~ | D4: 10000 | E4: 52 | F4: =IF(AND($F$2<=D4,$F$2>B4),1,) -> 0 | G4: =IF(F4=1,(E3+(E4-E3)/(D4-B4)*($F$2-B4)),0) -> 0
A5: 3 | B5: 10000 | C5: ~ | D5: 20000 | E5: 72 | F5: =IF(AND($F$2<=D5,$F$2>B5),1,) -> 1 | G5: =IF(F5=1,(E4+(E5-E4)/(D5-B5)*($F$2-B5)),0) -> 66.77156
A6: 4 | B6: 20000 | C6: ~ | D6: 30000 | E6: 82 | F6: =IF(AND($F$2<=D6,$F$2>B6),1,) -> 0 | G6: =IF(F6=1,(E5+(E6-E5)/(D6-B6)*($F$2-B6)),0) -> 0
A7: 5 | B7: 30000 | C7: ~ | D7: 40000 | E7: 95 | F7: =IF(AND($F$2<=D7,$F$2>B7),1,) -> 0 | G7: =IF(F7=1,(E6+(E7-E6)/(D7-B7)*($F$2-B7)),0) -> 0
A8: 6 | B8: 40000 | C8: ~ | D8: 50000 | E8: 104 | F8: =IF(AND($F$2<=D8,$F$2>B8),1,) -> 0 | G8: =IF(F8=1,(E7+(E8-E7)/(D8-B8)*($F$2-B8)),0) -> 0
A9: 7 | B9: 50000 | C9: ~ | D9: 60000 | E9: 116 | F9: =IF(AND($F$2<=D9,$F$2>B9),1,) -> 0 | G9: =IF(F9=1,(E8+(E9-E8)/(D9-B9)*($F$2-B9)),0) -> 0
A10: 8 | B10: 60000 | C10: ~ | D10: 70000 | E10: 119 | F10: =IF(AND($F$2<=D10,$F$2>B10),1,) -> 0 | G10: =IF(F10=1,(E9+(E10-E9)/(D10-B10)*($F$2-B10)),0) -> 0
A11: 9 | B11: 70000 | C11: ~ | D11: 80000 | E11: 132 | F11: =IF(AND($F$2<=D11,$F$2>B11),1,) -> 0 | G11: =IF(F11=1,(E10+(E11-E10)/(D11-B11)*($F$2-B11)),0) -> 0
A12: 10 | B12: 80000 | C12: ~ | D12: 90000 | E12: 156 | F12: =IF(AND($F$2<=D12,$F$2>B12),1,) -> 0 | G12: =IF(F12=1,(E11+(E12-E11)/(D12-B12)*($F$2-B12)),0) -> 0
A13: 11 | B13: 90000 | C13: ~ | D13: 100000 | E13: 171 | F13: =IF(AND($F$2<=D13,$F$2>B13),1,) -> 0 | G13: =IF(F13=1,(E12+(E13-E12)/(D13-B13)*($F$2-B13)),0) -> 0
A14: 12 | B14: 100000 | C14: ~ | D14: 110000 | E14: 185 | F14: =IF(AND($F$2<=D14,$F$2>B14),1,) -> 0 | G14: =IF(F14=1,(E13+(E14-E13)/(D14-B14)*($F$2-B14)),0) -> 0
A15: 13 | B15: 110000 | C15: ~ | D15: 120000 | E15: 200 | F15: =IF(AND($F$2<=D15,$F$2>B15),1,) -> 0 | G15: =IF(F15=1,(E14+(E15-E14)/(D15-B15)*($F$2-B15)),0) -> 0
... A23: 21 | B23: 190000 | C23: ~ | D23: 200000 | E23: 350 | F23: =IF(AND($F$2<=D23,$F$2>B23),1,) -> 0 | G23: =IF(F23=1,(E22+(E23-E22)/(D23-B23)*($F$2-B23)),0) -> 0
A24: 22 | B24: 200000 | C24: < | F24: =IF(F2>B24,1,0) -> 0 | G24: =IF(F24=1,E23/B24*F2,0) -> 0

Sheet 交通影响评估
A1: 序号 | B1: 规模 （建筑总面积：万平方米） | E1: 单价 （元/平方米） | F1: 收费基数 （万元） | G1: 输入建筑面积 | H1: 差额累进法计算 | I1: 系数 | J1: 总计
H2: =SUM(H3:H7) -> 0 | I2: 1 | J2: =SUM(J3:J7) -> 0
A3: 1 | C3: < | D3: 5 | E3: 2 | F3: 10 | G3: =IF(AND(G2<=D3,G2>0),1,0) -> 0 | H3: =IF(G3=1,F3,0) -> 0 | I3: =I$2 -> 1 | J3: =H3*I3 -> 0
A4: 2 | B4: 5 | C4: ~ | D4: 20 | E4: 2 | F4: 10 | G4: =IF(AND($G$2<=D4,$G$2>B4),1,0) -> 0 | H4: =IF(G4=1,(F4+(G$2-B4)*E4),0) -> 0 | I4: =I$2 -> 1 | J4: =H4*I4 -> 0
A5: 3 | B5: 20 | C5: ~ | D5: 100 | E5: 1.5 | F5: 40 | G5: =IF(AND($G$2<=D5,$G$2>B5),1,0) -> 0 | H5: =IF(G5=1,(F5+(G$2-B5)*E5),0) -> 0 | I5: =I$2 -> 1 | J5: =H5*I5 -> 0
A6: 4 | B6: 100 | C6: ~ | D6: 200 | E6: 1 | F6: 160 | G6: =IF(AND($G$2<=D6,$G$2>B6),1,0) -> 0 | H6: =IF(G6=1,(F6+(G$2-B6)*E6),0) -> 0 | I6: =I$2 -> 1 | J6: =H6*I6 -> 0
A7: 5 | B7: 200 | C7: < | E7: 0.8 | F7: 260 | G7: =IF(G2>B7,1,0) -> 0 | H7: =IF(G7=1,MAX(F7,E7*$G$2),0) -> 0 | I7: =I$2 -> 1 | J7: =H7*I7 -> 0

Sheet 环境影响评估
A1: 序号 | B1: 计费额 | E1: 基价 | I1: 输入费用 | J1: 直线内插法计取
E2: 编制报告书 （含大纲） | F2: 编制报告表 | G2: 评估报告书 | H2: 评估报告表 | J2: 编制报告书 （含大纲） | K2: 编制报告表 | L2: 评估报告书 | M2: 评估报告表
I3: 120000 | J3: =SUM(J4:J9) -> 835.038 | K3: =SUM(K4:K9) -> -133.00665 | L3: =SUM(L4:L9) -> 47.0019 | M3: =SUM(M4:M9) -> -38.0019
A4: 1 | C4: > | D4: 3000 | E4: 5 | F4: 1 | G4: 0.8 | H4: 0.5 | I4: =IF(I3<=D4,1,0) -> 0 | J4: =IF(I4=1,(E4/I3*D4),0) -> 0 | K4: =IF($I4=1,(F4/$I$3*$D4),0) -> 0 | L4: =IF($I4=1,(G4/$I$3*$D4),0) -> 0 | M4: =IF($I4=1,(H4/$I$3*$D4),0) -> 0
A5: 2 | B5: 3000 | C5: ~ | D5: 20000 | E5: 6 | F5: 2 | G5: 1.5 | H5: 0.8 | I5: =IF(AND($I$3<=D5,$I$3>B5),1,0) -> 0 | J5: =IF($I5=1,(E5+(E6-E5)/($I$3-$B5)*($D5-$B5)),0) -> 0 | K5: =IF($I5=1,(F5+(F6-F5)/($I$3-$B5)*($D5-$B5)),0) -> 0 | L5: =IF($I5=1,(G5+(G6-G5)/($I$3-$B5)*($D5-$B5)),0) -> 0 | M5: =IF($I5=1,(H5+(H6-H5)/($I$3-$B5)*($D5-$B5)),0) -> 0
A6: 3 | B6: 20001 | C6: ~ | D6: 100000 | E6: 15 | F6: 4 | G6: 3 | H6: 1.5 | I6: =IF(AND($I$3<=D6,$I$3>B6),1,0) -> 0 | J6: =IF($I6=1,(E6+(E7-E6)/($I$3-$B6)*($D6-$B6)),0) -> 0 | K6: =IF($I6=1,(F6+(F7-F6)/($I$3-$B6)*($D6-$B6)),0) -> 0 | L6: =IF($I6=1,(G6+(G7-G6)/($I$3-$B6)*($D6-$B6)),0) -> 0 | M6: =IF($I6=1,(H6+(H7-H6)/($I$3-$B6)*($D6-$B6)),0) -> 0
A7: 4 | B7: 100001 | C7: ~ | D7: 500000 | E7: 35 | F7: 7 | G7: 7 | H7: 2 | I7: =IF(AND($I$3<=D7,$I$3>B7),1,0) -> 1 | J7: =IF($I7=1,(E7+(E8-E7)/($I$3-$B7)*($D7-$B7)),0) -> 835.038 | K7: =IF($I7=1,(F7+(F8-F7)/($I$3-$B7)*($D7-$B7)),0) -> -133.00665 | L7: =IF($I7=1,(G7+(G8-G7)/($I$3-$B7)*($D7-$B7)),0) -> 47.0019 | M7: =IF($I7=1,(H7+(H8-H7)/($I$3-$B7)*($D7-$B7)),0) -> -38.0019
A8: 5 | B8: 500001 | C8: ~ | D8: 1000000 | E8: 75 | G8: 9 | I8: =IF(AND($I$3<=D8,$I$3>B8),1,0) -> 0 | J8: =IF($I8=1,(E8+(E9-E8)/($I$3-$B8)*($D8-$B8)),0) -> 0 | K8: =IF($I8=1,(F8+(F9-F8)/($I$3-$B8)*($D8-$B8)),0) -> 0 | L8: =IF($I8=1,(G8+(G9-G8)/($I$3-$B8)*($D8-$B8)),0) -> 0 | M8: =IF($I8=1,(H8+(H9-H8)/($I$3-$B8)*($D8-$B8)),0) -> 0
A9: 6 | B9: 1000000 | C9: ~ | D9: 500000 | E9: 110 | G9: 13 | I9: =IF(AND($I$3<=D9,$I$3>B9),1,0) -> 0 | J9: =IF($I9=1,(E9+(E10-E9)/($I$3-$B9)*($D9-$B9)),0) -> 0 | K9: =IF($I9=1,(F9+(F10-F9)/($I$3-$B9)*($D9-$B9)),0) -> 0 | L9: =IF($I9=1,(G9+(G10-G9)/($I$3-$B9)*($D9-$B9)),0) -> 0 | M9: =IF($I9=1,(H9+(H10-H9)/($I$3-$B9)*($D9-$B9)),0) -> 0

Sheet 前期工程咨询费
A1: 估算投资额 | B1: 1000万元 | C1: 1000～3000 | D1: 3000万元～ | E1: 1亿元～ | F1: 5亿元～ | I1: 10亿元～ | J1: 50亿元
A2: 咨询评估项目 | B2: 以下 | C2: 万元 | D2: 1亿元 | E2: 5亿元 | F2: 10亿元 | I2: 50亿元 | J2: 以上
A3: 一、编制项目建议书 | B3: 2～4 | C3: 4～6 | D3: 6～14 | E3: 14～37 | F3: 37～55 | I3: 55～100 | J3: 100～125
A4: 二、编制可行性研究报告 | B4: 3～6 | C4: 6～12 | D4: 12～28 | E4: 28～75 | F4: 75～110 | I4: 110～200 | J4: 200～250
A5: 三、评估项目建议书 | B5: 1～2 | C5: 2～4 | D5: 4～8 | E5: 8～12 | F5: 12～15 | I5: 15～17 | J5: 17～20
A6: 四、评估可行性研究报告 | B6: 1.5～3 | C6: 3～5 | D6: 5～10 | E6: 10～15 | F6: 15～20 | I6: 20～25 | J6: 25～35
A7: 行业调整系数 | B7: 林业与建筑0.8， 市政公用工程与交通（公路）0.7。工程复杂程度调整系数0.8~1.2。
A8: 收费基价表
A9: 序号 | B9: 计费额 | E9: 基价 | I9: 输入费用 | J9: 直线内插法计取
J10: 项目建议书 | K10: 可行性研究报告 | L10: 评估项目建议书 | M10: 评估可行性研究报告
E11: 项目建议书 | F11: 可行性研究报告 | G11: 评估项目建议书 | H11: 评估可行性研究报告 | I11: 5600 | J11: =SUM(J12:J18) -> 27.543671 | K11: =SUM(K12:K18) -> 55.087341 | L11: =SUM(L12:L18) -> 14.771835 | M11: =SUM(M12:M18) -> 18.464794
A12: 1 | C12: > | D12: 1000 | E12: 2 | F12: 3 | G12: 1 | H12: 1.5 | I12: =IF(I11<=D12,1,0) -> 0 | J12: =IF(I12=1,(E12/I11*D12),0) -> 0 | K12: =IF($I12=1,(F12/$I$11*$D12),0) -> 0 | L12: =IF($I12=1,(G12/$I$11*$D12),0) -> 0 | M12: =IF($I12=1,(H12/$I$11*$D12),0) -> 0
A13: 2 | B13: 1001 | C13: ~ | D13: 3000 | E13: 4 | F13: 6 | G13: 2 | H13: 3 | I13: =IF(AND($I$11<=D13,$I$11>B13),1,0) -> 0 | J13: =IF($I13=1,(E13+(E14-E13)/($I$11-$B13)*($D13-$B13)),0) -> 0 | K13: =IF($I13=1,(F13+(F14-F13)/($I$11-$B13)*($D13-$B13)),0) -> 0 | L13: =IF($I13=1,(G13+(G14-G13)/($I$11-$B13)*($D13-$B13)),0) -> 0 | M13: =IF($I13=1,(H13+(H14-H13)/($I$11-$B13)*($D13-$B13)),0) -> 0
A14: 3 | B14: 3001 | C14: ~ | D14: 10000 | E14: 6 | F14: 12 | G14: 4 | H14: 5 | I14: =IF(AND($I$11<=D14,$I$11>B14),1,0) -> 1 | J14: =IF($I14=1,(E14+(E15-E14)/($I$11-$B14)*($D14-$B14)),0) -> 27.543671 | K14: =IF($I14=1,(F14+(F15-F14)/($I$11-$B14)*($D14-$B14)),0) -> 55.087341 | L14: =IF($I14=1,(G14+(G15-G14)/($I$11-$B14)*($D14-$B14)),0) -> 14.771835 | M14: =IF($I14=1,(H14+(H15-H14)/($I$11-$B14)*($D14-$B14)),0) -> 18.464794
A15: 4 | B15: 10001 | C15: ~ | D15: 50000 | E15: 14 | F15: 28 | G15: 8 | H15: 10 | I15: =IF(AND($I$11<=D15,$I$11>B15),1,0) -> 0 | J15: =IF($I15=1,(E15+(E16-E15)/($I$11-$B15)*($D15-$B15)),0) -> 0 | K15: =IF($I15=1,(F15+(F16-F15)/($I$11-$B15)*($D15-$B15)),0) -> 0 | L15: =IF($I15=1,(G15+(G16-G15)/($I$11-$B15)*($D15-$B15)),0) -> 0 | M15: =IF($I15=1,(H15+(H16-H15)/($I$11-$B15)*($D15-$B15)),0) -> 0
A16: 5 | B16: 50001 | C16: ~ | D16: 100000 | E16: 37 | F16: 75 | G16: 12 | H16: 15 | I16: =IF(AND($I$11<=D16,$I$11>B16),1,0) -> 0 | J16: =IF($I16=1,(E16+(E17-E16)/($I$11-$B16)*($D16-$B16)),0) -> 0 | K16: =IF($I16=1,(F16+(F17-F16)/($I$11-$B16)*($D16-$B16)),0) -> 0 | L16: =IF($I16=1,(G16+(G17-G16)/($I$11-$B16)*($D16-$B16)),0) -> 0 | M16: =IF($I16=1,(H16+(H17-H16)/($I$11-$B16)*($D16-$B16)),0) -> 0
A17: 6 | B17: 100000 | C17: ~ | D17: 500000 | E17: 55 | F17: 110 | G17: 15 | H17: 20 | I17: =IF(AND($I$11<=D17,$I$11>B17),1,0) -> 0 | J17: =IF($I17=1,(E17+(E18-E17)/($I$11-$B17)*($D17-$B17)),0) -> 0 | K17: =IF($I17=1,(F17+(F18-F17)/($I$11-$B17)*($D17-$B17)),0) -> 0 | L17: =IF($I17=1,(G17+(G18-G17)/($I$11-$B17)*($D17-$B17)),0) -> 0 | M17: =IF($I17=1,(H17+(H18-H17)/($I$11-$B17)*($D17-$B17)),0) -> 0
A18: 7 | B18: 500000 | E18: 100 | F18: 200 | G18: 17 | H18: 25 | I18: =IF(AND($I$11>B18),1,0) -> 0 | J18: =IF($I18=1,(E18+(E19-E18)/($I$11-$B18)*($D18-$B18)),0) -> 0 | K18: =IF($I18=1,(F18+(F19-F18)/($I$11-$B18)*($D18-$B18)),0) -> 0 | L18: =IF($I18=1,(G18+(G19-G18)/($I$11-$B18)*($D18-$B18)),0) -> 0 | M18: =IF($I18=1,(H18+(H19-H18)/($I$11-$B18)*($D18-$B18)),0) -> 0
E19: 125 | F19: 250 | G19: 20 | H19: 35

Sheet 施工图审查费
A1: 收费基价表 | G1: 输入工程费用 | H1: 差额定率累进法
A2: 序号 | B2: 计费额 | E2: 费率 | F2: 全额 | G2: =其他费自动计算!C2 -> 17385.78 | H2: =SUM(H3:H6) -> 18.98578
A3: 1 | C3: > | D3: 500 | E3: 0.002 | F3: =E3*D3 -> 1 | G3: =IF($G$2<=D3,1,0) -> 0 | H3: =IF(G3=1,(G2*E3),0) -> 0
A4: 2 | B4: 500 | C4: ~ | D4: 1000 | E4: 0.0016 | F4: =F3+(D4-B4)*E4 -> 1.8 | G4: =IF(AND($G$2<=D4,$G$2>B4),1,0) -> 0 | H4: =IF(G4=1,(F3+($G$2-D3)*E4),0) -> 0
A5: 3 | B5: 1000 | C5: ~ | D5: 5000 | E5: 0.0012 | F5: =F4+(D5-B5)*E5 -> 6.6 | G5: =IF(AND($G$2<=D5,$G$2>B5),1,0) -> 0 | H5: =IF(G5=1,(F4+($G$2-D4)*E5),0) -> 0
A6: 4 | B6: 5000 | C6: < | E6: 0.001 | G6: =IF(AND($G$2>B6),1,0) -> 1 | H6: =IF(G6=1,(F5+($G$2-B6)*E6),0) -> 18.98578

Sheet 招标代理费
A1: 造价区间（万） | E1: 货物采购招标 | G1: 服务招标（勘察） | I1: 服务招标（设计） | K1: 服务招标（监理） | M1: 工程招标
A2: 要计算的造价（万） | E2: 600 | G2: 600 | I2: =其他费自动计算!C16 -> 498.30744 | K2: 600 | M2: 300
A3: 100以下 | B3: 100 | C3: 100 | E3: 0.015 | F3: =IF(E$2>=$B3,$C3*E3,E$2*E3) -> 1.5 | G3: 0.015 | H3: =IF(G$2>=$B3,$C3*G3,G$2*G3) -> 1.5 | I3: 0.015 | J3: =IF(I$2>=$B3,$C3*I3,I$2*I3) -> 1.5 | K3: 0.015 | L3: =IF(K$2>=$B3,$C3*K3,K$2*K3) -> 1.5 | M3: 0.01 | N3: =IF(M$2>=$B3,$C3*M3,M$2*M3) -> 1
A4: 100－500 | B4: 500 | C4: 400 | E4: 0.011 | F4: =IF(E$2<$B3,0,IF(E$2>=$B4,$C4*E4,(E$2-$B3)*E4)) -> 4.4 | G4: 0.008 | H4: =IF(G$2<$B3,0,IF(G$2>=$B4,$C4*G4,(G$2-$B3)*G4)) -> 3.2 | I4: 0.008 | J4: =IF(I$2<$B3,0,IF(I$2>=$B4,$C4*I4,(I$2-$B3)*I4)) -> 3.1864595 | K4: 0.008 | L4: =IF(K$2<$B3,0,IF(K$2>=$B4,$C4*K4,(K$2-$B3)*K4)) -> 3.2 | M4: 0.007 | N4: =IF(M$2<$B3,0,IF(M$2>=$B4,$C4*M4,(M$2-$B3)*M4)) -> 1.4
A5: 500－1000 | B5: 1000 | C5: 500 | E5: 0.008 | F5: =IF(E$2<$B4,0,IF(E$2>=$B5,$C5*E5,(E$2-$B4)*E5)) -> 0.8 | G5: 0.0045 | H5: =IF(G$2<$B4,0,IF(G$2>=$B5,$C5*G5,(G$2-$B4)*G5)) -> 0.45 | I5: 0.0045 | J5: =IF(I$2<$B4,0,IF(I$2>=$B5,$C5*I5,(I$2-$B4)*I5)) -> 0 | K5: 0.0045 | L5: =IF(K$2<$B4,0,IF(K$2>=$B5,$C5*K5,(K$2-$B4)*K5)) -> 0.45 | M5: 0.0055 | N5: =IF(M$2<$B4,0,IF(M$2>=$B5,$C5*M5,(M$2-$B4)*M5)) -> 0
A6: 1000－5000 | B6: 5000 | C6: 4000 | E6: 0.005 | F6: =IF(E$2<$B5,0,IF(E$2>=$B6,$C6*E6,(E$2-$B5)*E6)) -> 0 | G6: 0.0025 | H6: =IF(G$2<$B5,0,IF(G$2>=$B6,$C6*G6,(G$2-$B5)*G6)) -> 0 | I6: 0.0025 | J6: =IF(I$2<$B5,0,IF(I$2>=$B6,$C6*I6,(I$2-$B5)*I6)) -> 0 | K6: 0.0025 | L6: =IF(K$2<$B5,0,IF(K$2>=$B6,$C6*K6,(K$2-$B5)*K6)) -> 0 | M6: 0.0035 | N6: =IF(M$2<$B5,0,IF(M$2>=$B6,$C6*M6,(M$2-$B5)*M6)) -> 0
A7: 5000－10000 | B7: 10000 | C7: 5000 | E7: 0.0025 | F7: =IF(E$2<$B6,0,IF(E$2>=$B7,$C7*E7,(E$2-$B6)*E7)) -> 0 | G7: 0.001 | H7: =IF(G$2<$B6,0,IF(G$2>=$B7,$C7*G7,(G$2-$B6)*G7)) -> 0 | I7: 0.001 | J7: =IF(I$2<$B6,0,IF(I$2>=$B7,$C7*I7,(I$2-$B6)*I7)) -> 0 | K7: 0.001 | L7: =IF(K$2<$B6,0,IF(K$2>=$B7,$C7*K7,(K$2-$B6)*K7)) -> 0 | M7: 0.002 | N7: =IF(M$2<$B6,0,IF(M$2>=$B7,$C7*M7,(M$2-$B6)*M7)) -> 0
A8: 10000－100000 | B8: 100000 | C8: 90000 | E8: 0.0005 | F8: =IF(E$2<$B7,0,IF(E$2>=$B8,$C8*E8,(E$2-$B7)*E8)) -> 0 | G8: 0.0005 | H8: =IF(G$2<$B7,0,IF(G$2>=$B8,$C8*G8,(G$2-$B7)*G8)) -> 0 | I8: 0.0005 | J8: =IF(I$2<$B7,0,IF(I$2>=$B8,$C8*I8,(I$2-$B7)*I8)) -> 0 | K8: 0.0005 | L8: =IF(K$2<$B7,0,IF(K$2>=$B8,$C8*K8,(K$2-$B7)*K8)) -> 0 | M8: 0.0005 | N8: =IF(M$2<$B7,0,IF(M$2>=$B8,$C8*M8,(M$2-$B7)*M8)) -> 0
A9: 100000以上 | E9: 0.0001 | F9: =IF(E$2<$B8,0,(E$2-$B8)*E9) -> 0 | G9: 0.0001 | H9: =IF(G$2<$B8,0,(G$2-$B8)*G9) -> 0 | I9: 0.0001 | J9: =IF(I$2<$B8,0,(I$2-$B8)*I9) -> 0 | K9: 0.0001 | L9: =IF(K$2<$B8,0,(K$2-$B8)*K9) -> 0 | M9: 0.0001 | N9: =IF(M$2<$B8,0,(M$2-$B8)*M9) -> 0 | O9: 合计费用
A10: 最终费用万元： | E10: =SUM(F3:F9) -> 6.7 | G10: =SUM(H3:H9) -> 5.15 | I10: =SUM(J3:J9) -> 4.6864595 | K10: =SUM(L3:L9) -> 5.15 | M10: =SUM(N3:N9) -> 2.4 | O10: =+M10+K10+I10+G10+E10 -> 24.086459
A11: 允许范围：上浮20% | E11: =+E10*1.2 -> 8.04 | G11: =+G10*1.2 -> 6.18 | I11: =+I10*1.2 -> 5.6237514 | K11: =+K10*1.2 -> 6.18 | M11: =+M10*1.2 -> 2.88
A12: 允许范围：下浮20% | E12: =+E10*0.8 -> 5.36 | G12: =+G10*0.8 -> 4.12 | I12: =+I10*0.8 -> 3.7491676 | K12: =+K10*0.8 -> 4.12 | M12: =+M10*0.8 -> 1.92
A16: 计费额 | D16: 货物采购 | G16: 服务招标（勘察） | J16: 服务招标（设计） | M16: 服务招标（监理） | P16: 工程招标
D17: 600 | G17: 600 | J17: 100 | M17: 600 | P17: 300
B18: < | C18: 100 | D18: =C18*E18 -> 1.5 | E18: 0.015 | F18: =IF(D17<=C18,D17*E18,0) -> 0 | G18: =C18*H18 -> 1.5 | H18: 0.015 | I18: =IF(H17<=C18,H17*H18,0) -> 0 | J18: =C18*K18 -> 1.5 | K18: 0.015 | L18: =IF(K17<=C18,J17*K18,0) -> 1.5 | M18: =C18*N18 -> 1.5 | N18: 0.015 | O18: =IF(M17<=C18,M17*N18,0) -> 0 | P18: =C18*Q18 -> 1 | Q18: 0.01 | R18: =IF(P17<=C18,P17*Q18,0) -> 0
A19: 100 | B19: ~ | C19: 500 | D19: =D18+(C19-A19)*E19 -> 5.9 | E19: 0.011 | F19: =IF(AND($D$17>A19,$D$17<C19),(D18+($D$17-C18)*E19),0) -> 0 | G19: =G18+(C19-C18)*H19 -> 4.7 | H19: 0.008 | I19: =IF(AND($G$17>A19,$G$17<C19),(G18+($G$17-C18)*H19),0) -> 0 | J19: =J18+(C19-A19)*K19 -> 4.7 | K19: 0.008 | L19: =IF(AND($J$17>A19,$J$17<C19),(J18+($J$17-C18)*K19),0) -> 0 | M19: =M18+(C19-C18)*N19 -> 4.7 | N19: 0.008 | O19: =IF(AND($M$17>A19,$M$17<C19),(M18+($M$17-C18)*N19),0) -> 0 | P19: =P18+(C19-C18)*Q19 -> 3.8 | Q19: 0.007 | R19: =IF(AND($P$17>A19,$P$17<C19),(P18+($P$17-C18)*Q19),0) -> 2.4
A20: 500 | B20: ~ | C20: 1000 | D20: =D19+(C20-A20)*E20 -> 9.9 | E20: 0.008 | F20: =IF(AND($D$17>A20,$D$17<C20),(D19+($D$17-C19)*E20),0) -> 6.7 | G20: =G19+(C20-C19)*H20 -> 6.95 | H20: 0.0045 | I20: =IF(AND($G$17>A20,$G$17<C20),(G19+($G$17-C19)*H20),0) -> 5.15 | J20: =J19+(C20-A20)*K20 -> 6.95 | K20: 0.0045 | L20: =IF(AND($J$17>A20,$J$17<C20),(J19+($J$17-C19)*K20),0) -> 0 | M20: =M19+(C20-C19)*N20 -> 6.95 | N20: 0.0045 | O20: =IF(AND($M$17>A20,$M$17<C20),(M19+($M$17-C19)*N20),0) -> 5.15 | P20: =P19+(C20-C19)*Q20 -> 6.55 | Q20: 0.0055 | R20: =IF(AND($P$17>A20,$P$17<C20),(P19+($P$17-C19)*Q20),0) -> 0
A21: 1000 | B21: ~ | C21: 5000 | D21: =D20+(C21-A21)*E21 -> 29.9 | E21: 0.005 | F21: =IF(AND($D$17>A21,$D$17<C21),(D20+($D$17-C20)*E21),0) -> 0 | G21: =G20+(C21-C20)*H21 -> 16.95 | H21: 0.0025 | I21: =IF(AND($G$17>A21,$G$17<C21),(G20+($G$17-C20)*H21),0) -> 0 | J21: =J20+(C21-A21)*K21 -> 16.95 | K21: 0.0025 | L21: =IF(AND($J$17>A21,$J$17<C21),(J20+($J$17-C20)*K21),0) -> 0 | M21: =M20+(C21-C20)*N21 -> 16.95 | N21: 0.0025 | O21: =IF(AND($M$17>A21,$M$17<C21),(M20+($M$17-C20)*N21),0) -> 0 | P21: =P20+(C21-C20)*Q21 -> 20.55 | Q21: 0.0035 | R21: =IF(AND($P$17>A21,$P$17<C21),(P20+($P$17-C20)*Q21),0) -> 0
A22: 5000 | B22: ~ | C22: 10000 | D22: =D21+(C22-A22)*E22 -> 42.4 | E22: 0.0025 | F22: =IF(AND($D$17>A22,$D$17<C22),(D21+($D$17-C21)*E22),0) -> 0 | G22: =G21+(C22-C21)*H22 -> 21.95 | H22: 0.001 | I22: =IF(AND($G$17>A22,$G$17<C22),(G21+($G$17-C21)*H22),0) -> 0 | J22: =J21+(C22-A22)*K22 -> 21.95 | K22: 0.001 | L22: =IF(AND($J$17>A22,$J$17<C22),(J21+($J$17-C21)*K22),0) -> 0 | M22: =M21+(C22-C21)*N22 -> 21.95 | N22: 0.001 | O22: =IF(AND($M$17>A22,$M$17<C22),(M21+($M$17-C21)*N22),0) -> 0 | P22: =P21+(C22-C21)*Q22 -> 30.55 | Q22: 0.002 | R22: =IF(AND($P$17>A22,$P$17<C22),(P21+($P$17-C21)*Q22),0) -> 0
A23: 10000 | B23: ~ | C23: 50000 | D23: =D22+(C23-A23)*E23 -> 62.4 | E23: 0.0005 | F23: =IF(AND($D$17>A23,$D$17<C23),(D22+($D$17-C22)*E23),0) -> 0 | G23: =G22+(C23-C22)*H23 -> 41.95 | H23: 0.0005 | I23: =IF(AND($G$17>A23,$G$17<C23),(G22+($G$17-C22)*H23),0) -> 0 | J23: =J22+(C23-A23)*K23 -> 41.95 | K23: 0.0005 | L23: =IF(AND($J$17>A23,$J$17<C23),(J22+($J$17-C22)*K23),0) -> 0 | M23: =M22+(C23-C22)*N23 -> 41.95 | N23: 0.0005 | O23: =IF(AND($M$17>A23,$M$17<C23),(M22+($M$17-C22)*N23),0) -> 0 | P23: =P22+(C23-C22)*Q23 -> 50.55 | Q23: 0.0005 | R23: =IF(AND($P$17>A23,$P$17<C23),(P22+($P$17-C22)*Q23),0) -> 0
A24: 50000 | B24: ~ | C24: 100000 | D24: =D23+(C24-A24)*E24 -> 79.9 | E24: 0.00035 | F24: =IF(AND($D$17>A24,$D$17<C24),(D23+($D$17-C23)*E24),0) -> 0 | G24: =G23+(C24-C23)*H24 -> 59.45 | H24: 0.00035 | I24: =IF(AND($G$17>A24,$G$17<C24),(G23+($G$17-C23)*H24),0) -> 0 | J24: =J23+(C24-A24)*K24 -> 59.45 | K24: 0.00035 | L24: =IF(AND($J$17>A24,$J$17<C24),(J23+($J$17-C23)*K24),0) -> 0 | M24: =M23+(C24-C23)*N24 -> 59.45 | N24: 0.00035 | O24: =IF(AND($M$17>A24,$M$17<C24),(M23+($M$17-C23)*N24),0) -> 0 | P24: =P23+(C24-C23)*Q24 -> 68.05 | Q24: 0.00035 | R24: =IF(AND($P$17>A24,$P$17<C24),(P23+($P$17-C23)*Q24),0) -> 0
A25: 100000 | B25: ~ | C25: 500000 | D25: =D24+(C25-A25)*E25 -> 111.9 | E25: 8e-05 | F25: =IF(AND($D$17>A25,$D$17<C25),(D24+($D$17-C24)*E25),0) -> 0 | G25: =G24+(C25-C24)*H25 -> 91.45 | H25: 8e-05 | I25: =IF(AND($G$17>A25,$G$17<C25),(G24+($G$17-C24)*H25),0) -> 0 | J25: =J24+(C25-A25)*K25 -> 91.45 | K25: 8e-05 | L25: =IF(AND($J$17>A25,$J$17<C25),(J24+($J$17-C24)*K25),0) -> 0 | M25: =M24+(C25-C24)*N25 -> 91.45 | N25: 8e-05 | O25: =IF(AND($M$17>A25,$M$17<C25),(M24+($M$17-C24)*N25),0) -> 0 | P25: =P24+(C25-C24)*Q25 -> 100.05 | Q25: 8e-05 | R25: =IF(AND($P$17>A25,$P$17<C25),(P24+($P$17-C24)*Q25),0) -> 0
A26: 500000 | B26: ~ | C26: 1000000 | D26: =D25+(C26-A26)*E26 -> 141.9 | E26: 6e-05 | F26: =IF(AND($D$17>A26,$D$17<C26),(D25+($D$17-C25)*E26),0) -> 0 | G26: =G25+(C26-C25)*H26 -> 121.45 | H26: 6e-05 | I26: =IF(AND($G$17>A26,$G$17<C26),(G25+($G$17-C25)*H26),0) -> 0 | J26: =J25+(C26-A26)*K26 -> 121.45 | K26: 6e-05 | L26: =IF(AND($J$17>A26,$J$17<C26),(J25+($J$17-C25)*K26),0) -> 0 | M26: =M25+(C26-C25)*N26 -> 121.45 | N26: 6e-05 | O26: =IF(AND($M$17>A26,$M$17<C26),(M25+($M$17-C25)*N26),0) -> 0 | P26: =P25+(C26-C25)*Q26 -> 130.05 | Q26: 6e-05 | R26: =IF(AND($P$17>A26,$P$17<C26),(P25+($P$17-C25)*Q26),0) -> 0
A27: 1000000 | B27: < | E27: 4e-05 | F27: =IF(AND($D$17>A27),(D26+($D$17-A27)*E27),0) -> 0 | H27: 4e-05 | I27: =IF(AND(G17>A27),(G26+(G17-A27)*H27),0) -> 0 | K27: 4e-05 | L27: =IF(AND(J17>A27),(J26+(J17-A27)*K27),0) -> 0 | N27: 4e-05 | O27: =IF(AND(M17>A27),(M26+(M17-A27)*N27),0) -> 0 | Q27: 4e-05 | R27: =IF(AND(P17>A27),(P26+(P17-A27)*Q27),0) -> 0 | S27: 总费用
A28: 费用合计 | D28: =SUM(F18:F27) -> 6.7 | G28: =SUM(I18:I27) -> 5.15 | J28: =SUM(L18:L27) -> 1.5 | M28: =SUM(O18:O27) -> 5.15 | P28: =SUM(R18:R27) -> 2.4 | S28: =SUM(D28:Q28) -> 20.9

Sheet 造价咨询
A1: 收费基价表 | G1: 输入工程费用 | H1: 差额定率累进法
A2: 序号 | B2: 计费额 | E2: 费率 | F2: 全额 | G2: =其他费自动计算!C2 -> 17385.78 | H2: =SUM(H3:H9) -> 127.16615
A3: 1 | C3: > | D3: 200 | E3: 0.0102 | F3: =E3*D3 -> 2.04 | G3: =IF($G$2<=D3,1,0) -> 0 | H3: =IF(G3=1,(G2*E3),0) -> 0 | I3: 内容锁定区
A4: 2 | B4: 200 | C4: ~ | D4: 500 | E4: 0.0096 | F4: =F3+(D4-B4)*E4 -> 4.92 | G4: =IF(AND($G$2<=D4,$G$2>B4),1,0) -> 0 | H4: =IF(G4=1,(F3+($G$2-D3)*E4),0) -> 0
A5: 3 | B5: 500 | C5: ~ | D5: 1000 | E5: 0.009 | F5: =F4+(D5-B5)*E5 -> 9.42 | G5: =IF(AND($G$2<=D5,$G$2>B5),1,0) -> 0 | H5: =IF(G5=1,(F4+($G$2-D4)*E5),0) -> 0
A6: 4 | B6: 1000 | C6: ~ | D6: 3000 | E6: 0.0084 | F6: =F5+(D6-B6)*E6 -> 26.22 | G6: =IF(AND($G$2<=D6,$G$2>B6),1,0) -> 0 | H6: =IF(G6=1,(F5+($G$2-D5)*E6),0) -> 0
A7: 5 | B7: 3000 | C7: ~ | D7: 6000 | E7: 0.0078 | F7: =F6+(D7-B7)*E7 -> 49.62 | G7: =IF(AND($G$2<=D7,$G$2>B7),1,0) -> 0 | H7: =IF(G7=1,(F6+($G$2-D6)*E7),0) -> 0
A8: 6 | B8: 6000 | C8: ~ | D8: 10000 | E8: 0.0072 | F8: =F7+(D8-B8)*E8 -> 78.42 | G8: =IF(AND($G$2<=D8,$G$2>B8),1,0) -> 0 | H8: =IF(G8=1,(F7+($G$2-D7)*E8),0) -> 0
A9: 7 | B9: 10000 | C9: < | E9: 0.0066 | G9: =IF(AND($G$2>B9),1,0) -> 1 | H9: =IF(G9=1,(F8+($G$2-D8)*E9),0) -> 127.16615

Sheet 监理费
A1: 序号 | B1: 收费额 | C1: 收费基价 | D1: 输入费用 | E1: 直线内插法计取
D2: =其他费自动计算!C2 -> 17385.78 | E2: =SUM(E3:E19) -> 347.70343
A3: 1 | B3: 500 | C3: 16.5 | D3: =IF(D2<=B3,1,0) -> 0 | E3: =IF(D3=1,(C3/D2*B3),0) -> 0
A4: 2 | B4: 1000 | C4: 30.1 | D4: =IF(AND($D$2<=B4,$D$2>B3),1,0) -> 0 | E4: =IF($D4=1,(C3+(C4-C3)/($B4-$B3)*($D$2-$B3)),0) -> 0
A5: 3 | B5: 3000 | C5: 78.1 | D5: =IF(AND($D$2<=B5,$D$2>B4),1,0) -> 0 | E5: =IF($D5=1,(C4+(C5-C4)/($B5-$B4)*($D$2-$B4)),0) -> 0
A6: 4 | B6: 5000 | C6: 120.8 | D6: =IF(AND($D$2<=B6,$D$2>B5),1,0) -> 0 | E6: =IF($D6=1,(C5+(C6-C5)/($B6-$B5)*($D$2-$B5)),0) -> 0
A7: 5 | B7: 8000 | C7: 181 | D7: =IF(AND($D$2<=B7,$D$2>B6),1,0) -> 0 | E7: =IF($D7=1,(C6+(C7-C6)/($B7-$B6)*($D$2-$B6)),0) -> 0
A8: 6 | B8: 10000 | C8: 218.6 | D8: =IF(AND($D$2<=B8,$D$2>B7),1,0) -> 0 | E8: =IF($D8=1,(C7+(C8-C7)/($B8-$B7)*($D$2-$B7)),0) -> 0
A9: 7 | B9: 20000 | C9: 393.4 | D9: =IF(AND($D$2<=B9,$D$2>B8),1,0) -> 1 | E9: =IF($D9=1,(C8+(C9-C8)/($B9-$B8)*($D$2-$B8)),0) -> 347.70343
A10: 8 | B10: 40000 | C10: 708.2 | D10: =IF(AND($D$2<=B10,$D$2>B9),1,0) -> 0 | E10: =IF($D10=1,(C9+(C10-C9)/($B10-$B9)*($D$2-$B9)),0) -> 0
A11: 9 | B11: 60000 | C11: 991.4 | D11: =IF(AND($D$2<=B11,$D$2>B10),1,0) -> 0 | E11: =IF($D11=1,(C10+(C11-C10)/($B11-$B10)*($D$2-$B10)),0) -> 0
A12: 10 | B12: 80000 | C12: 1255.8 | D12: =IF(AND($D$2<=B12,$D$2>B11),1,0) -> 0 | E12: =IF($D12=1,(C11+(C12-C11)/($B12-$B11)*($D$2-$B11)),0) -> 0
A13: 11 | B13: 100000 | C13: 1507 | D13: =IF(AND($D$2<=B13,$D$2>B12),1,0) -> 0 | E13: =IF($D13=1,(C12+(C13-C12)/($B13-$B12)*($D$2-$B12)),0) -> 0
A14: 12 | B14: 200000 | C14: 2712.5 | D14: =IF(AND($D$2<=B14,$D$2>B13),1,0) -> 0 | E14: =IF($D14=1,(C13+(C14-C13)/($B14-$B13)*($D$2-$B13)),0) -> 0
A15: 13 | B15: 400000 | C15: 4882.6 | D15: =IF(AND($D$2<=B15,$D$2>B14),1,0) -> 0 | E15: =IF($D15=1,(C14+(C15-C14)/($B15-$B14)*($D$2-$B14)),0) -> 0
... A18: 16 | B18: 1000000 | C18: 10390.1 | D18: =IF(AND($D$2<=B18,$D$2>B17),1,0) -> 0 | E18: =IF($D18=1,(C17+(C18-C17)/($B18-$B17)*($D$2-$B17)),0) -> 0
A19: 16 | D19: =IF(D2>B18,1,0) -> 0 | E19: =IF(D19=1,D2*1.039%,0) -> 0

Sheet 设计费
A1: 序号 | B1: 收费额 | C1: 收费基价 | D1: 输入费用 | E1: 直线内插法计取
D2: =其他费自动计算!C2 -> 17385.78 | E2: =SUM(E3:E21) -> 498.30744
A3: 1 | B3: 200 | C3: 9 | D3: =IF(D2<=B3,1,0) -> 0 | E3: =IF(D3=1,(C3/D2*B3),0) -> 0
A4: 2 | B4: 500 | C4: 20.9 | D4: =IF(AND($D$2<=B4,$D$2>B3),1,0) -> 0 | E4: =IF($D4=1,(C3+(C4-C3)/($B4-$B3)*($D$2-$B3)),0) -> 0
A5: 3 | B5: 1000 | C5: 38.8 | D5: =IF(AND($D$2<=B5,$D$2>B4),1,0) -> 0 | E5: =IF($D5=1,(C4+(C5-C4)/($B5-$B4)*($D$2-$B4)),0) -> 0
A6: 4 | B6: 3000 | C6: 103.8 | D6: =IF(AND($D$2<=B6,$D$2>B5),1,0) -> 0 | E6: =IF($D6=1,(C5+(C6-C5)/($B6-$B5)*($D$2-$B5)),0) -> 0
A7: 5 | B7: 5000 | C7: 163.9 | D7: =IF(AND($D$2<=B7,$D$2>B6),1,0) -> 0 | E7: =IF($D7=1,(C6+(C7-C6)/($B7-$B6)*($D$2-$B6)),0) -> 0
A8: 6 | B8: 8000 | C8: 249.6 | D8: =IF(AND($D$2<=B8,$D$2>B7),1,0) -> 0 | E8: =IF($D8=1,(C7+(C8-C7)/($B8-$B7)*($D$2-$B7)),0) -> 0
A9: 7 | B9: 10000 | C9: 304.8 | D9: =IF(AND($D$2<=B9,$D$2>B8),1,0) -> 0 | E9: =IF($D9=1,(C8+(C9-C8)/($B9-$B8)*($D$2-$B8)),0) -> 0
A10: 8 | B10: 20000 | C10: 566.8 | D10: =IF(AND($D$2<=B10,$D$2>B9),1,0) -> 1 | E10: =IF($D10=1,(C9+(C10-C9)/($B10-$B9)*($D$2-$B9)),0) -> 498.30744
A11: 9 | B11: 40000 | C11: 1054 | D11: =IF(AND($D$2<=B11,$D$2>B10),1,0) -> 0 | E11: =IF($D11=1,(C10+(C11-C10)/($B11-$B10)*($D$2-$B10)),0) -> 0
A12: 10 | B12: 60000 | C12: 1515.2 | D12: =IF(AND($D$2<=B12,$D$2>B11),1,0) -> 0 | E12: =IF($D12=1,(C11+(C12-C11)/($B12-$B11)*($D$2-$B11)),0) -> 0
A13: 11 | B13: 80000 | C13: 1960.1 | D13: =IF(AND($D$2<=B13,$D$2>B12),1,0) -> 0 | E13: =IF($D13=1,(C12+(C13-C12)/($B13-$B12)*($D$2-$B12)),0) -> 0
A14: 12 | B14: 100000 | C14: 2393.4 | D14: =IF(AND($D$2<=B14,$D$2>B13),1,0) -> 0 | E14: =IF($D14=1,(C13+(C14-C13)/($B14-$B13)*($D$2-$B13)),0) -> 0
A15: 13 | B15: 200000 | C15: 4450.8 | D15: =IF(AND($D$2<=B15,$D$2>B14),1,0) -> 0 | E15: =IF($D15=1,(C14+(C15-C14)/($B15-$B14)*($D$2-$B14)),0) -> 0
... A20: 18 | B20: 2000000 | C20: 34948.9 | D20: =IF(AND($D$2<=B20,$D$2>B19),1,0) -> 0 | E20: =IF($D20=1,(C19+(C20-C19)/($B20-$B19)*($D$2-$B19)),0) -> 0
A21: 19 | D21: =IF(D2>B20,1,0) -> 0 | E21: =IF(D21=1,D2*1.6%,0) -> 0

Sheet 建设单位管理费
A1: 关于印发《基本建设项目建设成本管理规定》的通知
A2: 财建[2016]504号
A3: 党中央有关部门，国务院各部委、各直属机构，军委后勤保障部，武警总部，全国人大常委会办公厅，全国政协办公厅，高法院，高检院，各民主党派中央，有关人民团体，各中央管理企业，各省、自治区、计划单列市财政厅（局），新疆生产建设兵团财务局： | F3: 收费基价表 | L3: 输入工程费用 | M3: 差额定率累进法
A4: 为推动各部门、各地区进一步加强基本建设成本核算管理，提高资金使用效益，针对基本建设成本管理中反映出的主要问题，依据《基本建设财务规则》，现印发《基本建设项目建设成本管理规定》，请认真贯彻执行。 | F4: 序号 | G4: 计费额 | J4: 费率 | K4: 全额 | L4: =其他费自动计算!C2 -> 17385.78 | M4: =SUM(M5:M10) -> 193.8578
A5: 附件：1.基本建设项目建设成本管理规定 | F5: 1 | H5: > | I5: 1000 | J5: 0.02 | K5: =J5*I5 -> 20 | L5: =IF($L$4<=I5,1,0) -> 0 | M5: =IF(L5=1,(L4*J5),0) -> 0 | N5: 内容锁定区
A6: 2.项目建设管理费总额控制数费率表 | F6: 2 | G6: 1001 | H6: ~ | I6: 5000 | J6: 0.015 | K6: =J6*I6 -> 75 | L6: =IF(AND($L$4<=I6,$L$4>G6),1,0) -> 0 | M6: =IF(L6=1,(K5+($L$4-I5)*J6),0) -> 0
A7: 财 政 部 | F7: 3 | G7: 5001 | H7: ~ | I7: 10000 | J7: 0.012 | K7: =J7*I7 -> 120 | L7: =IF(AND($L$4<=I7,$L$4>G7),1,0) -> 0 | M7: =IF(L7=1,(K6+($L$4-I6)*J7),0) -> 0
A8: 42557 | F8: 4 | G8: 10001 | H8: ~ | I8: 50000 | J8: 0.01 | K8: =J8*I8 -> 500 | L8: =IF(AND($L$4<=I8,$L$4>G8),1,0) -> 1 | M8: =IF(L8=1,(K7+($L$4-I7)*J8),0) -> 193.8578
A9: 附件1： | F9: 5 | G9: 50001 | H9: ~ | I9: 100000 | J9: 0.008 | K9: =J9*I9 -> 800 | L9: =IF(AND($L$4<=I9,$L$4>G9),1,0) -> 0 | M9: =IF(L9=1,(K8+($L$4-I8)*J9),0) -> 0
A10: 基本建设项目建设成本管理规定 | F10: 6 | G10: 100000 | H10: < | J10: 0.004 | L10: =IF(AND($L$4>G10),1,0) -> 0 | M10: =IF(L10=1,(K9+($L$4-I9)*J10),0) -> 0
A11: 第一条 为了规范基本建设项目建设成本管理，提高建设资金使用效益，依据《基本建设财务规则》（财政部令第81号），制定本规定。
A12: 第二条 建筑安装工程投资支出是指基本建设项目（以下简称项目）建设单位按照批准的建设内容发生的建筑工程和安装工程的实际成本，其中不包括被安装设备本身的价值，以及按照合同规定支付给施工单位的预付备料款和预付工程款。 | L12: 在此区域输入
A13: 第三条 设备投资支出是指项目建设单位按照批准的建设内容发生的各种设备的实际成本（不包括工程抵扣的增值税进项税额），包括需要安装设备、不需要安装设备和为生产准备的不够固定资产标准的工具、器具的实际成本。
A14: 需要安装设备是指必须将其整体或几个部位装配起来，安装在基础上或建筑物支架上才能使用的设备。不需要安装设备是指不必固定在一定位置或支架上就可以使用的设备。
A15: 第四条 待摊投资支出是指项目建设单位按照批准的建设内容发生的，应当分摊计入相关资产价值的各项费用和税金支出。主要包括：
A16: （一）勘察费、设计费、研究试验费、可行性研究费及项目其他前期费用；
A17: （二）土地征用及迁移补偿费、土地复垦及补偿费、森林植被恢复费及其他为取得或租用土地使用权而发生的费用；
A18: （三）土地使用税、耕地占用税、契税、车船税、印花税及按规定缴纳的其他税费；
A19: （四）项目建设管理费、代建管理费、临时设施费、监理费、招标投标费、社会中介机构审查费及其他管理性质的费用；
A20: （五）项目建设期间发生的各类借款利息、债券利息、贷款评估费、国外借款手续费及承诺费、汇兑损益、债券发行费用及其他债务利息支出或融资费用；
A21: （六）工程检测费、设备检验费、负荷联合试车费及其他检验检测类费用；
A22: （七）固定资产损失、器材处理亏损、设备盘亏及毁损、报废工程净损失及其他损失；
A23: （八）系统集成等信息工程的费用支出；
A24: （九）其他待摊投资性质支出。
... A43: 万元
A44: 工程总概算 | B44: 费率 | C44: 算例
C45: 工程总概算 | D45: 项目建设管理费
A46: 1000以下 | B46: 2 | C46: 1000 | D46: 1000*2%=20
A47: 1001-5000 | B47: 1.5 | C47: 5000 | D47: 20+（5000-1000）*1.5%=80
A48: 5001-10000 | B48: 1.2 | C48: 10000 | D48: 80+（10000-5000）*1.2%=140
A49: 10001-50000 | B49: 1 | C49: 50000 | D49: 140+（50000-10000）*1%=540
A50: 50001-100000 | B50: 0.8 | C50: 100000 | D50: 540+（100000-50000）*0.8%=940
A51: 100000以上 | B51: 0.4 | C51: 200000 | D51: 940+（200000-100000）*0.4%=1340
A53: 发布日期: 2016年08月18日

Sheet 场地准备费
A1: 场地准备及临时设施费:包括场地准备费和临时设施费.
A2: 1)场地准备费是使工程项目的建设场地达到开工条件，由建设单位组织进行的场地平整等准备工作而发生的费用。
A3: 2)临时设施费是指为满足施工建设需要而供到场地界区的、未列人工程费用的临时水、电、路、通信、气等其他工程费用和建设单位的现场临时建（构)筑物的搭设、建设、维修、拆除、摊销费用或租赁费用，货物、码头租赁等费用，以及施工期间专用公路养护费、维修费.
A4: 3)场地准备及临时设施应尽量与永久性工程统一考虑.建设场地的大型土石方工程应进人工程费用中的总图运输费用中.
A5: 计算方法:
A6: 1）新建项目的场地准备和临时设施费应根据实际工程量估算，或按工程费用的比例计算，一般可按第一部分工程费用的 0. 5% ^ 2.0%计列。
A7: (2)改扩建项目一般只计拆除清理费。
A8: (3)发生拆除清理费时可按新建同类工程造价或主材费、设备费的比例计算.凡可回收材料的拆除采用以料抵工方式，不再计算拆除清理费。
A9: (4)此费用不包括已列入建筑安装工程费用中的施工单位临时设施费用。

Sheet 安全预评价
A1: 序号 | B1: 总投资额 （亿元） | E1: 基础报价 | F1: 输入费用 | G1: 直线内插法计取
A3: 1 | C3: < | D3: =10000*0.05 -> 500 | E3: 2 | F3: =IF(F2<=D3,1,0) -> 1 | G3: =IF(F3=1,E3/D3*F2,0) -> 0
A4: 2 | B4: =10000*0.05 -> 500 | C4: ~ | D4: =10000*0.1 -> 1000 | E4: 3.5 | F4: =IF(AND($F$2<=D4,$F$2>B4),1,0) -> 0 | G4: =IF(F4=1,(E3+(E4-E3)/(D4-B4)*($F$2-B4)),0) -> 0
A5: 3 | B5: =10000*0.1 -> 1000 | C5: ~ | D5: =10000*0.2 -> 2000 | E5: 5 | F5: =IF(AND($F$2<=D5,$F$2>B5),1,0) -> 0 | G5: =IF(F5=1,(E4+(E5-E4)/(D5-B5)*($F$2-B5)),0) -> 0
A6: 4 | B6: =10000*0.2 -> 2000 | C6: ~ | D6: 5000 | E6: 7 | F6: =IF(AND($F$2<=D6,$F$2>B6),1,0) -> 0 | G6: =IF(F6=1,(E5+(E6-E5)/(D6-B6)*($F$2-B6)),0) -> 0
A7: 5 | B7: =10000*0.5 -> 5000 | C7: ~ | D7: 10000 | E7: =0.5*1.5*10000/1000 -> 7.5 | F7: =IF(AND($F$2<=D7,$F$2>B7),1,0) -> 0 | G7: =IF(F7=1,(E6+(E7-E6)/(D7-B7)*($F$2-B7)),0) -> 0
A8: 6 | B8: 10000 | C8: ~ | D8: 20000 | E8: =1*10000*1/1000 -> 10 | F8: =IF(AND($F$2<=D8,$F$2>B8),1,0) -> 0 | G8: =IF(F8=1,(E7+(E8-E7)/(D8-B8)*($F$2-B8)),0) -> 0
A9: 7 | B9: 20000 | C9: ~ | D9: 50000 | E9: =2*0.7*10000/1000 -> 14 | F9: =IF(AND($F$2<=D9,$F$2>B9),1,0) -> 0 | G9: =IF(F9=1,(E8+(E9-E8)/(D9-B9)*($F$2-B9)),0) -> 0
A10: 8 | B10: 50000 | C10: ~ | D10: 100000 | E10: =5*0.4*10000/1000 -> 20 | F10: =IF(AND($F$2<=D10,$F$2>B10),1,0) -> 0 | G10: =IF(F10=1,(E9+(E10-E9)/(D10-B10)*($F$2-B10)),0) -> 0
A11: 9 | B11: 100000 | E11: =10*0.3*10000/1000 -> 30 | F11: =IF(F2>B11,1,0) -> 0 | G11: =IF(F11=1,E11/B11*F2,0) -> 0
