Workbook
Name 在此区间: '建设单位管理费'!$L$5
Name 在此区间内: '建设单位管理费'!$L$5

Sheet 标准化指标设定
C1: 本表所有此颜色单元格为基础数据，需自行嵌入。其余单元格均为联动，勿调整。
B3: 农村污水处理及中水再利用建设项目
A4: 江西省指标要求和假设参数设计 | J4: 江西省生活用水定额 | S4: 吉水县2021年末人口统计
A5: 序号 | B5: 指标项 | C5: 江西省用地指标（2018） | D5: 参数设定 | E5: 单位 | F5: 项目数据 | G5: 备注
A6: 1 | B6: 二级污水处理站用地 | C6: 参考城市污水处理厂建设用地指标 | D6: =1.5+(F11/10000-1)*((6-1.5)/(5-1)) -> 0.7125 | E6: 公顷 | G6: 1、为应对突发情况污水处理厂、污水管网泵站设计规模应比计算规模适当增大 2、污水处理厂规模按项目数据中的污水处理量来测算，收入计算时按参数设定中的处理量来计算
A7: 1.1 | B7: 区域人口 | C7: 根据地区情况确定 | D7: =G60/10000 -> 28.4983 | E7: 万人
A8: 1.2 | B8: 用水定额 | C8: 参考江西省生活用水定额 | D8: 200 | E8: L/（人*天）
A9: 1.3 | B9: 产污系数 | C9: 0.80-0.9 | D9: 0.85
A10: 1.4 | B10: 污水收集系数 | C10: 0.7-0.95 | D10: 0.9
A11: 1.5 | B11: 污水处理量 | D11: =D7*D8*D9*D10*10000/1000 -> 43602.399 | E11: m³/天 | F11: 3000
A12: 1.6 | B12: 容积率 | C12: ≥0.7 | D12: 0.75
A13: 2 | B13: 污水管网泵站用地 | C13: 参考污水管网泵站建设用地指标 | D13: =800+(F15-0.1)*(2500-800)/(1-0.1) -> 2122.2222 | E13: ㎡
A14: 2.1 | B14: 容积率 | C14: ≥0.7 | D14: =F28/D13 -> 0.84816754 | I14: 污水处理厂规模按项目数据中的污水处理量来测定，收入计算时按参数设定中的处理量来计算
A15: 2.2 | B15: 建设规模 | C15: 参考污水管网泵站建设用地指标 | D15: =F11/(24*60*60) -> 0.034722222 | F15: 0.8
A16: 一 | B16: 总建筑面积 | F16: =F17+F28 -> 7143
A17: 1 | B17: 污水处理厂 | E17: ㎡ | F17: =INT(D6*10000*D12) -> 5343 | G17: 0.15774845 | K17: 江西省用地指标（2018）
A18: 1.1 | B18: 粗格栅池 | C18: 根据实际需要确定 | E18: ㎡ | F18: 6300 | G18: =F17*G17 -> 842.84999
A19: 1.2 | B19: 提升池 | C19: 根据实际需要确定 | E19: ㎡ | F19: 6300 | G19: =F17*G17 -> 842.84999
A20: 1.3 | B20: 沉砂池 | C20: 根据实际需要确定 | E20: ㎡ | F20: 6300 | G20: =F17*G17 -> 842.84999
A21: 1.4 | B21: 兼氧 FMBR 池 | C21: 根据实际需要确定 | E21: ㎡ | F21: 3800 | G21: =F17*H21 -> 508.38571 | H21: 0.095149861
A22: 1.5 | B22: 消毒回用池 | C22: 根据实际需要确定 | E22: ㎡ | F22: 3800 | G22: =F17*H21 -> 508.38571
A23: 1.6 | B23: 污泥池 | C23: 根据实际需要确定 | E23: ㎡ | F23: 3100 | G23: =F17*H23 -> 414.73571 | H23: 0.077622255
A24: 1.7 | B24: 贮泥池 | C24: 根据实际需要确定 | E24: ㎡ | F24: 3100 | G24: =F17*H23 -> 414.73571
A25: 1.8 | B25: 污泥脱水机房 | C25: 根据实际需要确定 | E25: ㎡ | F25: 3600 | G25: =F17*H25 -> 481.62856 | H25: 0.090141974
A26: 1.9 | B26: 管理用房 | C26: 建筑面积比例不超过总建筑面积的15% | E26: ㎡ | F26: =F17-SUM(G18:G25) -> 486.57864 | G26: =F16*0.15 -> 1071.45
A27: 2 | B27: 厂区室外工程 | C27: 不得低于用地面积的30% | D27: 0.3 | E27: ㎡ | F27: =INT(D6*10000*D27) -> 2137
A28: 3 | B28: 污水管网泵站 | E28: ㎡ | F28: 1800 | K28: 容积率
A29: 4 | B29: 污水管网 | E29: ㎞ | F29: =F30 -> 3.6
A30: 4.1 | B30: 新建污水管道 | C30: 根据实际需要确定 | E30: ㎞ | F30: =F31+F32+F33 -> 3.6
A31: 4.1.1 | B31: HDPE缠绕结构壁管-DN300 | C31: 根据实际需要确定 | E31: ㎞ | F31: 1.2
A32: 4.1.2 | B32: HDPE缠绕结构壁管-DN400 | C32: 根据实际需要确定 | E32: ㎞ | F32: 1.3
A33: 4.1.3 | B33: HDPE缠绕结构壁管-DN500 | C33: 根据实际需要确定 | E33: ㎞ | F33: 1.1
A34: 4.2 | B34: 检查井 | C34: 检查井之间的距离不宜大于50m | D34: 40 | E34: 个 | F34: =F30*1000/D34 -> 90
I42: 吉水县农村生活污水治理专项规划
E50: 36573 | F50: 24368 | G50: 42477
E51: 31338 | F51: 19132 | G51: 29008
E52: 27783 | F52: 18504 | G52: 34226
E53: 31264 | F53: 27490 | G53: 38580
E54: 16007 | F54: 6259 | G54: 14591
E55: 10649 | F55: 8510 | G55: 14010
E56: 17935 | F56: 16414 | G56: 24144
E57: 18586 | F57: 16323 | G57: 40074
E58: 12149 | F58: 9862 | G58: 15002
E59: 25757 | F59: 19966 | G59: 32871
E60: =SUM(E50:E59) -> 228041 | F60: =SUM(F50:F59) -> 166828 | G60: =SUM(G50:G59) -> 284983

Sheet 项目技术经济指标
A1: 序号 | B1: 内容名称 | C1: 单位 | D1: 数量 | E1: 备注
A2: 一 | B2: 方案技术指标
B3: 总建筑面积 | D3: =D4+D15 -> 7200
A4: ='标准化指标设定'!A17 -> 1 | B4: ='标准化指标设定'!B17 -> 污水处理厂 | C4: ='标准化指标设定'!E17 -> ㎡ | D4: =SUM(D5:D13) -> 5200
A5: ='标准化指标设定'!A18 -> 1.1 | B5: ='标准化指标设定'!B18 -> 粗格栅池 | C5: ='标准化指标设定'!E18 -> ㎡ | D5: 800
A6: ='标准化指标设定'!A19 -> 1.2 | B6: ='标准化指标设定'!B19 -> 提升池 | C6: ='标准化指标设定'!E19 -> ㎡ | D6: 800
A7: ='标准化指标设定'!A20 -> 1.3 | B7: ='标准化指标设定'!B20 -> 沉砂池 | C7: ='标准化指标设定'!E20 -> ㎡ | D7: 800
A8: ='标准化指标设定'!A21 -> 1.4 | B8: ='标准化指标设定'!B21 -> 兼氧 FMBR 池 | C8: ='标准化指标设定'!E21 -> ㎡ | D8: 500 | G8: 成本 | H8: 工资 | I8: 管理人员 | K8: 职工 | M8: 每五年增长率
A9: ='标准化指标设定'!A22 -> 1.5 | B9: ='标准化指标设定'!B22 -> 消毒回用池 | C9: ='标准化指标设定'!E22 -> ㎡ | D9: 500 | I9: 人数 | J9: 月工资 | K9: 人数 | L9: 月工资
A10: ='标准化指标设定'!A23 -> 1.6 | B10: ='标准化指标设定'!B23 -> 污泥池 | C10: ='标准化指标设定'!E23 -> ㎡ | D10: 400 | I10: 1 | J10: 4000 | K10: 3 | L10: 3500 | M10: 0.1
A11: ='标准化指标设定'!A24 -> 1.7 | B11: ='标准化指标设定'!B24 -> 贮泥池 | C11: ='标准化指标设定'!E24 -> ㎡ | D11: 400
A12: ='标准化指标设定'!A25 -> 1.8 | B12: ='标准化指标设定'!B25 -> 污泥脱水机房 | C12: ='标准化指标设定'!E25 -> ㎡ | D12: 500
A13: ='标准化指标设定'!A26 -> 1.9 | B13: ='标准化指标设定'!B26 -> 管理用房 | C13: ='标准化指标设定'!E26 -> ㎡ | D13: 500
A14: ='标准化指标设定'!A27 -> 2 | B14: ='标准化指标设定'!B27 -> 厂区室外工程 | C14: ='标准化指标设定'!E27 -> ㎡ | D14: 2000
A15: ='标准化指标设定'!A28 -> 3 | B15: ='标准化指标设定'!B28 -> 污水管网泵站 | C15: ='标准化指标设定'!E28 -> ㎡ | D15: 2000
A16: ='标准化指标设定'!A29 -> 4 | B16: ='标准化指标设定'!B29 -> 污水管网 | C16: ='标准化指标设定'!E29 -> ㎞ | D16: ='标准化指标设定'!F29 -> 3.6 | H16: 项目总建筑面积为16260平方米，其中新建污水处理厂15468㎡，污水处理规模为1.5万m³/天，含粗格栅池2400㎡、提升池2400㎡、沉砂池2400㎡、兼氧 FMBR 池2000㎡、消毒回用池1600㎡、污泥池1200㎡、贮泥池1200㎡、污泥脱水机房1500㎡、管理用房768㎡；新建污水管网提升泵站792㎡，污水提升规模为0.2m³/秒；新建污水管网50㎞、检查井1250座。
A17: ='标准化指标设定'!A30 -> 4.1 | B17: ='标准化指标设定'!B30 -> 新建污水管道 | C17: ='标准化指标设定'!E30 -> ㎞ | D17: ='标准化指标设定'!F30 -> 3.6
A18: ='标准化指标设定'!A31 -> 4.1.1 | B18: ='标准化指标设定'!B31 -> HDPE缠绕结构壁管-DN300 | C18: ='标准化指标设定'!E31 -> ㎞ | D18: ='标准化指标设定'!F31 -> 1.2
A19: ='标准化指标设定'!A32 -> 4.1.2 | B19: ='标准化指标设定'!B32 -> HDPE缠绕结构壁管-DN400 | C19: ='标准化指标设定'!E32 -> ㎞ | D19: ='标准化指标设定'!F32 -> 1.3
A20: ='标准化指标设定'!A33 -> 4.1.3 | B20: ='标准化指标设定'!B33 -> HDPE缠绕结构壁管-DN500 | C20: ='标准化指标设定'!E33 -> ㎞ | D20: ='标准化指标设定'!F33 -> 1.1
A21: ='标准化指标设定'!A34 -> 4.2 | B21: ='标准化指标设定'!B34 -> 检查井 | C21: ='标准化指标设定'!E34 -> 个 | D21: ='标准化指标设定'!F34 -> 90
A22: 5 | B22: 中水管网 | C22: km | D22: =D23 -> 8
A23: 5.1 | B23: 新建污水管道 | C23: ㎞ | D23: =SUM(D24:D26) -> 8
A24: 5.1.1 | B24: HDPE缠绕结构壁管-DN300 | C24: ㎞ | D24: 2.6
A25: 5.1.2 | B25: HDPE缠绕结构壁管-DN400 | C25: ㎞ | D25: 2.8
A26: 5.1.3 | B26: HDPE缠绕结构壁管-DN500 | C26: ㎞ | D26: 2.6
A27: 5.2 | B27: 检查井 | C27: 个 | D27: 200
A28: 二 | B28: 经济技术指标
A29: 1 | B29: 总投资 | C29: 万元 | D29: ='总投资估算'!G55 -> 5000
A30: 1.1 | B30: 工程费用 | C30: 万元 | D30: =D31+D32 -> 3992.88
A31: 1.1.1 | B31: 建筑安装工程费用 | C31: 万元 | D31: ='总投资估算'!C3+'总投资估算'!D3 -> 3427.98
A32: 1.1.2 | B32: 设备及工器具购置费 | C32: 万元 | D32: ='总投资估算'!E3 -> 564.9
A33: 1.2 | B33: 工程建设其他费用 | C33: 万元 | D33: ='总投资估算'!G31 -> 559.82
A34: 1.3 | B34: 基本预备费 | C34: 万元 | D34: ='总投资估算'!G50 -> 348.3
A35: 1.4 | B35: 建设期利息 | C35: 万元 | D35: ='总投资估算'!G54 -> 99
A36: 2 | B36: 资金筹措 | C36: 万元 | D36: =SUM(D37:D38) -> 5000
A37: 2.1 | B37: 自筹资本金 | C37: 万元 | D37: ='分年计划及建设期利息'!G2 -> 2800 | E37: =D37/$D$36 -> 0.56
A38: 2.2 | B38: 融资及政府债券 | C38: 万元 | D38: ='资金平衡表'!C36 -> 2200 | E38: =D38/$D$36 -> 0.44
A39: 3 | B39: 年均营业收入 | C39: 万元 | D39: =AVERAGE('收入成本'!P5:P34) -> 369.93931
A40: 4 | B40: 年均税收 | C40: 万元 | D40: =AVERAGE('收入成本'!Z5:Z34) -> 5.1172414
A41: 5 | B41: 运营期总收入 | C41: 万元 | D41: ='资金平衡表'!F36 -> 10728.24
A42: 6 | B42: 运营期总成本 | C42: 万元 | D42: ='资金平衡表'!H36 -> 2536.53
A43: 7 | B43: 项目总收益 | C43: 万元 | D43: ='资金平衡表'!J36 -> 8191.71
A44: 8 | B44: 债券覆盖倍数 | C44: - | D44: ='资金平衡表'!J37 -> 1.58 | E44: 正常情况下
D45: ='资金平衡表'!K37 -> 1.38 | E45: ='资金平衡表'!K2 -> 收入下降10%
D46: ='资金平衡表'!L37 -> 1.54 | E46: ='资金平衡表'!L2 -> 成本上升10%
D47: ='资金平衡表'!M37 -> 1.33 | E47: ='资金平衡表'!M2 -> 收入下降10%且成本上升10%

Sheet 总投资估算
A1: 序号 | B1: 工程或费用名称 | C1: 估算金额（万元） | I1: 技术经济指标 | L1: 备注
C2: 建筑工程费 | D2: 安装工程费 | E2: 设备购置费 | F2: 其他费用 | G2: 小计 | H2: 比例 | I2: 单位 | J2: 数量 | K2: 单价（元）
A3: 一 | B3: 工程费用 | C3: =C4+C17+C18+C19+C25 -> 2199 | D3: =D4+D17+D18+D19+D25 -> 1228.98 | E3: =E4+E17+E18+E19+E25 -> 564.9 | F3: =F4+F17+F18+F19+F25 -> 0 | G3: =C3+E3+D3+F3 -> 3992.88 | H3: =G3/$G$55 -> 0.798576 | M3: =G3/'标准化指标设定'!F16 -> 0.55899202
A4: ='项目技术经济指标'!A4 -> 1 | B4: ='项目技术经济指标'!B4 -> 污水处理厂 | C4: =SUM(C5:C16) -> 1499 | D4: =SUM(D5:D16) -> 385 | E4: =SUM(E5:E16) -> 400 | F4: =SUM(F5:F16) -> 0 | G4: =C4+E4+D4+F4 -> 2284 | H4: =G4/$G$55 -> 0.4568 | I4: ='项目技术经济指标'!C4 -> ㎡ | J4: ='项目技术经济指标'!D4 -> 5200
A5: ='项目技术经济指标'!A5 -> 1.1 | B5: ='项目技术经济指标'!B5 -> 粗格栅池 | C5: =ROUND(J5*K5/10000,2) -> 248 | G5: =C5+E5+D5+F5 -> 248 | H5: =G5/$G$55 -> 0.0496 | I5: ='项目技术经济指标'!C5 -> ㎡ | J5: ='项目技术经济指标'!D5 -> 800 | K5: 3100 | L5: 含装修 | M5: 2600±400
A6: ='项目技术经济指标'!A6 -> 1.2 | B6: ='项目技术经济指标'!B6 -> 提升池 | C6: =ROUND(J6*K6/10000,2) -> 248 | G6: =C6+E6+D6+F6 -> 248 | H6: =G6/$G$55 -> 0.0496 | I6: ='项目技术经济指标'!C6 -> ㎡ | J6: ='项目技术经济指标'!D6 -> 800 | K6: 3100 | L6: 含装修 | M6: 2400±200
A7: ='项目技术经济指标'!A7 -> 1.3 | B7: ='项目技术经济指标'!B7 -> 沉砂池 | C7: =ROUND(J7*K7/10000,2) -> 224 | G7: =C7+E7+D7+F7 -> 224 | H7: =G7/$G$55 -> 0.0448 | I7: ='项目技术经济指标'!C7 -> ㎡ | J7: ='项目技术经济指标'!D7 -> 800 | K7: 2800 | L7: 含装修 | M7: 2200±200
A8: ='项目技术经济指标'!A8 -> 1.4 | B8: ='项目技术经济指标'!B8 -> 兼氧 FMBR 池 | C8: =ROUND(J8*K8/10000,2) -> 155 | G8: =C8+E8+D8+F8 -> 155 | H8: =G8/$G$55 -> 0.031 | I8: ='项目技术经济指标'!C8 -> ㎡ | J8: ='项目技术经济指标'!D8 -> 500 | K8: 3100 | L8: 含装修 | M8: 2600±400
A9: ='项目技术经济指标'!A9 -> 1.5 | B9: ='项目技术经济指标'!B9 -> 消毒回用池 | C9: =ROUND(J9*K9/10000,2) -> 140 | G9: =C9+E9+D9+F9 -> 140 | H9: =G9/$G$55 -> 0.028 | I9: ='项目技术经济指标'!C9 -> ㎡ | J9: ='项目技术经济指标'!D9 -> 500 | K9: 2800 | L9: 含装修 | M9: 2000±300
A10: ='项目技术经济指标'!A10 -> 1.6 | B10: ='项目技术经济指标'!B10 -> 污泥池 | C10: =ROUND(J10*K10/10000,2) -> 112 | G10: =C10+E10+D10+F10 -> 112 | H10: =G10/$G$55 -> 0.0224 | I10: ='项目技术经济指标'!C10 -> ㎡ | J10: ='项目技术经济指标'!D10 -> 400 | K10: 2800 | L10: 含装修 | M10: 2000±200
A11: ='项目技术经济指标'!A11 -> 1.7 | B11: ='项目技术经济指标'!B11 -> 贮泥池 | C11: =ROUND(J11*K11/10000,2) -> 112 | G11: =C11+E11+D11+F11 -> 112 | H11: =G11/$G$55 -> 0.0224 | I11: ='项目技术经济指标'!C11 -> ㎡ | J11: ='项目技术经济指标'!D11 -> 400 | K11: 2800 | L11: 含装修 | M11: 2000±200
A12: ='项目技术经济指标'!A12 -> 1.8 | B12: ='项目技术经济指标'!B12 -> 污泥脱水机房 | C12: =ROUND(J12*K12/10000,2) -> 130 | G12: =C12+E12+D12+F12 -> 130 | H12: =G12/$G$55 -> 0.026 | I12: ='项目技术经济指标'!C12 -> ㎡ | J12: ='项目技术经济指标'!D12 -> 500 | K12: 2600 | L12: 含装修 | M12: 2400±200
A13: ='项目技术经济指标'!A13 -> 1.9 | B13: ='项目技术经济指标'!B13 -> 管理用房 | C13: =ROUND(J13*K13/10000,2) -> 130 | G13: =C13+E13+D13+F13 -> 130 | H13: =G13/$G$55 -> 0.026 | I13: ='项目技术经济指标'!C13 -> ㎡ | J13: ='项目技术经济指标'!D13 -> 500 | K13: 2600 | L13: 含装修 | M13: 2400±200
A14: 1.1 | B14: 终端水质在线监测系统 | D14: =ROUND(J14*K14/10000,2)*20% -> 40 | E14: =ROUND(J14*K14/10000,2)*80% -> 160 | G14: =C14+E14+D14+F14 -> 200 | H14: =G14/$G$55 -> 0.04 | I14: 套 | J14: 1 | K14: 2000000 | M14: 1500000±500000
A15: 1.11 | B15: 中控系统 | D15: =ROUND(J15*K15/10000,2)*20% -> 60 | E15: =ROUND(J15*K15/10000,2)*80% -> 240 | G15: =C15+E15+D15+F15 -> 300 | H15: =G15/$G$55 -> 0.06 | I15: 套 | J15: 1 | K15: 3000000 | M15: 3000000±1000000
A16: 1.12 | B16: 场内配套基础设施 | D16: =ROUND(J16*K16/10000,2) -> 285 | G16: =C16+E16+D16+F16 -> 285 | H16: =G16/$G$55 -> 0.057 | I16: ㎡ | J16: ='标准化指标设定'!D6*10000 -> 7125 | K16: 400 | M16: 200±100
A17: ='项目技术经济指标'!A14 -> 2 | B17: ='项目技术经济指标'!B14 -> 厂区室外工程 | C17: =J17*K17/10000 -> 100 | G17: =C17+E17+D17+F17 -> 100 | H17: =G17/$G$55 -> 0.02 | I17: ='项目技术经济指标'!C14 -> ㎡ | J17: ='项目技术经济指标'!D14 -> 2000 | K17: 500
A18: ='项目技术经济指标'!A15 -> 3 | B18: ='项目技术经济指标'!B15 -> 污水管网泵站 | C18: =ROUND(J18*K18/10000,2) -> 600 | D18: =E18*20% -> 15 | E18: 75 | G18: =C18+E18+D18+F18 -> 690 | H18: =G18/$G$55 -> 0.138 | I18: ='项目技术经济指标'!C15 -> ㎡ | J18: 2000 | K18: 3000 | M18: 2400±300
A19: ='项目技术经济指标'!A16 -> 4 | B19: ='项目技术经济指标'!B16 -> 污水管网 | C19: =C20+C24 -> 0 | D19: =D20+D24 -> 256.58 | E19: =E20+E24 -> 27.9 | F19: =F20+F24 -> 0 | G19: =C19+E19+D19+F19 -> 284.48 | H19: =G19/$G$55 -> 0.056896 | I19: ='项目技术经济指标'!C16 -> ㎞ | J19: ='项目技术经济指标'!D16 -> 3.6
A20: ='项目技术经济指标'!A17 -> 4.1 | B20: ='项目技术经济指标'!B17 -> 新建污水管道 | C20: =SUM(C21:C23) -> 0 | D20: =SUM(D21:D23) -> 251 | E20: =SUM(E21:E23) -> 0 | F20: =SUM(F21:F23) -> 0 | G20: =C20+E20+D20+F20 -> 251 | H20: =G20/$G$55 -> 0.0502 | I20: ='项目技术经济指标'!C17 -> ㎞ | J20: ='项目技术经济指标'!D17 -> 3.6
A21: ='项目技术经济指标'!A18 -> 4.1.1 | B21: ='项目技术经济指标'!B18 -> HDPE缠绕结构壁管-DN300 | D21: =ROUND(J21*K21/10000,2) -> 72 | G21: =C21+E21+D21+F21 -> 72 | H21: =G21/$G$55 -> 0.0144 | I21: m | J21: ='项目技术经济指标'!D18*1000 -> 1200 | K21: 600 | M21: 400±100
A22: ='项目技术经济指标'!A19 -> 4.1.2 | B22: ='项目技术经济指标'!B19 -> HDPE缠绕结构壁管-DN400 | D22: =ROUND(J22*K22/10000,2) -> 91 | G22: =C22+E22+D22+F22 -> 91 | H22: =G22/$G$55 -> 0.0182 | I22: m | J22: ='项目技术经济指标'!D19*1000 -> 1300 | K22: 700 | M22: 500±100
A23: ='项目技术经济指标'!A20 -> 4.1.3 | B23: ='项目技术经济指标'!B20 -> HDPE缠绕结构壁管-DN500 | D23: =ROUND(J23*K23/10000,2) -> 88 | G23: =C23+E23+D23+F23 -> 88 | H23: =G23/$G$55 -> 0.0176 | I23: m | J23: ='项目技术经济指标'!D20*1000 -> 1100 | K23: 800 | M23: 600±200
A24: ='项目技术经济指标'!A21 -> 4.2 | B24: ='项目技术经济指标'!B21 -> 检查井 | D24: =E24*20% -> 5.58 | E24: =ROUND(J24*K24/10000,2) -> 27.9 | G24: =C24+E24+D24+F24 -> 33.48 | H24: =G24/$G$55 -> 0.006696 | I24: ='项目技术经济指标'!C21 -> 个 | J24: ='项目技术经济指标'!D21 -> 90 | K24: 3100 | M24: 2800±400
A25: ='项目技术经济指标'!A22 -> 5 | B25: ='项目技术经济指标'!B22 -> 中水管网 | C25: =C26+C30 -> 0 | D25: =D26+D30 -> 572.4 | E25: =E26+E30 -> 62 | F25: =F26+F30 -> 0 | G25: =C25+E25+D25+F25 -> 634.4 | H25: =G25/$G$55 -> 0.12688 | I25: ='项目技术经济指标'!C22 -> km | J25: ='项目技术经济指标'!D22 -> 8
A26: ='项目技术经济指标'!A23 -> 5.1 | B26: ='项目技术经济指标'!B23 -> 新建污水管道 | C26: =SUM(C27:C29) -> 0 | D26: =SUM(D27:D29) -> 560 | E26: =SUM(E27:E29) -> 0 | F26: =SUM(F27:F29) -> 0 | G26: =C26+E26+D26+F26 -> 560 | H26: =G26/$G$55 -> 0.112 | I26: ='项目技术经济指标'!C23 -> ㎞ | J26: ='项目技术经济指标'!D23 -> 8
A27: ='项目技术经济指标'!A24 -> 5.1.1 | B27: ='项目技术经济指标'!B24 -> HDPE缠绕结构壁管-DN300 | D27: =ROUND(J27*K27/10000,2) -> 156 | G27: =C27+E27+D27+F27 -> 156 | H27: =G27/$G$55 -> 0.0312 | I27: m | J27: 2600 | K27: 600
A28: ='项目技术经济指标'!A25 -> 5.1.2 | B28: ='项目技术经济指标'!B25 -> HDPE缠绕结构壁管-DN400 | D28: =ROUND(J28*K28/10000,2) -> 196 | G28: =C28+E28+D28+F28 -> 196 | H28: =G28/$G$55 -> 0.0392 | I28: m | J28: 2800 | K28: 700
A29: ='项目技术经济指标'!A26 -> 5.1.3 | B29: ='项目技术经济指标'!B26 -> HDPE缠绕结构壁管-DN500 | D29: =ROUND(J29*K29/10000,2) -> 208 | G29: =C29+E29+D29+F29 -> 208 | H29: =G29/$G$55 -> 0.0416 | I29: m | J29: 2600 | K29: 800
A30: ='项目技术经济指标'!A27 -> 5.2 | B30: ='项目技术经济指标'!B27 -> 检查井 | D30: =E30*20% -> 12.4 | E30: =ROUND(J30*K30/10000,2) -> 62 | G30: =C30+E30+D30+F30 -> 74.4 | H30: =G30/$G$55 -> 0.01488 | I30: 个 | J30: ='项目技术经济指标'!D27 -> 200 | K30: 3100
A31: 二 | B31: 工程建设其他费用 | F31: =SUM(F32:F49) -> 559.82 | G31: =F31 -> 559.82 | H31: =G31/$G$55 -> 0.111964
A32: 1 | B32: ='其他费自动计算'!B12 -> 建设单位管理费 | F32: =ROUND('其他费自动计算'!C12,2) -> 64.89 | G32: =F32 -> 64.89 | H32: =G32/$G$55 -> 0.012978 | I32: ='工程建设其他费细则说明'!E4 -> 财建[2016]504号
A33: 2 | B33: ='其他费自动计算'!B13 -> 场地准备及临时设施费 | F33: =ROUND('其他费自动计算'!C13,2) -> 39.93 | G33: =F33 -> 39.93 | H33: =G33/$G$55 -> 0.007986 | I33: ='工程建设其他费细则说明'!E18 -> 建标〔2011〕1号
A34: 3 | B34: ='其他费自动计算'!B14 -> 前期工作咨询费 | F34: =ROUND('其他费自动计算'!C14,2) -> 16.57 | G34: =F34 -> 16.57 | H34: =G34/$G$55 -> 0.003314 | I34: ='工程建设其他费细则说明'!E21 -> 计价格［1999］1283号
A35: 4 | B35: ='其他费自动计算'!B15 -> 勘察费 | F35: =ROUND('其他费自动计算'!C15,2) -> 39.93 | G35: =F35 -> 39.93 | H35: =G35/$G$55 -> 0.007986 | I35: ='工程建设其他费细则说明'!E36 -> 建标〔2011〕1号
A36: 5 | B36: ='其他费自动计算'!B16 -> 设计费 | F36: =ROUND('其他费自动计算'!C16,2) -> 133.64 | G36: =F36 -> 133.64 | H36: =G36/$G$55 -> 0.026728 | I36: ='工程建设其他费细则说明'!E37 -> 计价格[2002]10号
A37: 6 | B37: ='其他费自动计算'!B17 -> 工程监理费 | F37: =ROUND('其他费自动计算'!C17,2) -> 99.3 | G37: =F37 -> 99.3 | H37: =G37/$G$55 -> 0.01986 | I37: ='工程建设其他费细则说明'!E38 -> 发改价格[2007]670号
A38: 7 | B38: ='其他费自动计算'!B18 -> 招标代理费 | F38: =ROUND('其他费自动计算'!C18,2) -> 31.34 | G38: =F38 -> 31.34 | H38: =G38/$G$55 -> 0.006268 | I38: ='工程建设其他费细则说明'!E42 -> 发改价格[2011]534号
A39: 8 | B39: ='其他费自动计算'!B19 -> 施工图审查费 | F39: =ROUND('其他费自动计算'!C19,2) -> 5.39 | G39: =F39 -> 5.39 | H39: =G39/$G$55 -> 0.001078 | I39: ='工程建设其他费细则说明'!E43 -> 赣价房字[2000]6号
A40: 9 | B40: ='其他费自动计算'!B20 -> 工程造价咨询费 | F40: =ROUND('其他费自动计算'!C20,2) -> 33.96 | G40: =F40 -> 33.96 | H40: =G40/$G$55 -> 0.006792 | I40: ='工程建设其他费细则说明'!E45 -> 赣价协[2021]23号
A41: 10 | B41: ='其他费自动计算'!B21 -> 工程保险费 | F41: =ROUND('其他费自动计算'!C21,2) -> 19.96 | G41: =F41 -> 19.96 | H41: =G41/$G$55 -> 0.003992 | I41: ='工程建设其他费细则说明'!E46 -> 建标〔2011〕1号
A42: 11 | B42: ='其他费自动计算'!B22 -> 环境影响评价费 | F42: =ROUND('其他费自动计算'!C22,2) -> 5.12 | G42: =F42 -> 5.12 | H42: =G42/$G$55 -> 0.001024 | I42: ='工程建设其他费细则说明'!E23 -> 计价格[2002]125 号
A43: 12 | B43: ='其他费自动计算'!B23 -> 节能评估费 | F43: =ROUND('其他费自动计算'!C23,2) -> 6 | G43: =F43 -> 6 | H43: =G43/$G$55 -> 0.0012 | I43: ='工程建设其他费细则说明'!E29 -> 沪发改环资（2012）043号
A44: 13 | B44: ='其他费自动计算'!B24 -> 水土保持评价费 | F44: =ROUND('其他费自动计算'!C24,2) -> 30 | G44: =F44 -> 30 | H44: =G44/$G$55 -> 0.006 | I44: ='工程建设其他费细则说明'!E27 -> 保监[2005]22 号 2005 年 6 月 17 日
A45: 14 | B45: ='其他费自动计算'!B25 -> 劳动安全卫生评审费 | F45: =ROUND('其他费自动计算'!C25,2) -> 19.96 | G45: =F45 -> 19.96 | H45: =G45/$G$55 -> 0.003992 | I45: ='工程建设其他费细则说明'!E32 -> 建标〔2011〕1号
A46: 15 | B46: ='其他费自动计算'!B26 -> 社会稳定风险评估费 | F46: =ROUND('其他费自动计算'!C26,2) -> 4.63 | G46: =F46 -> 4.63 | H46: =G46/$G$55 -> 0.000926 | I46: ='工程建设其他费细则说明'!E31 -> 赣评审字[2015]70 号
A47: 16 | B47: ='其他费自动计算'!B27 -> 安全预评价费 | F47: =ROUND('其他费自动计算'!C27,2) -> 7 | G47: =F47 -> 7 | H47: =G47/$G$55 -> 0.0014 | I47: ='工程建设其他费细则说明'!E24 -> 江西省安全评价收费指导价格（试行）
A48: 17 | B48: ='其他费自动计算'!B28 -> 交通影响评估费 | F48: =ROUND('其他费自动计算'!C28,2) -> 0 | G48: =F48 -> 0 | H48: =G48/$G$55 -> 0 | I48: ='工程建设其他费细则说明'!E33 -> 5万平米（含）以下，2元/平米，5-20万平米，2元/平米，20-100万平米，1.5元/平米，100-200万平米，1.0元/平米；大于200万平米的，0.8元/平米
A49: 18 | B49: 债券发行费 | F49: =ROUND('还本付息'!E38*I49,2) -> 2.2 | G49: =F49 -> 2.2 | H49: =G49/$G$55 -> 0.00044 | I49: 0.001 | M49: ←可直接调整数字，前面文字为单元格格式，不影响计算
A50: 三 | B50: 预备费 | F50: =F51+F52 -> 348.3 | G50: =F50 -> 348.3 | H50: =G50/$G$55 -> 0.06966
A51: 1 | B51: 基本预备费 | F51: =ROUND((G3+G31)*8%,2)-15.92 -> 348.3 | G51: =F51 -> 348.3 | H51: =G51/$G$55 -> 0.06966 | I51: 不超过（一+二）*8%
A52: 2 | B52: 涨价预备费 | F52: 0 | G52: =F52 -> 0 | H52: =G52/$G$55 -> 0
B53: 一+二+三部分合计 | C53: =C3+C31+C50 -> 2199 | D53: =D3+D31+D50 -> 1228.98 | E53: =E3+E31+E50 -> 564.9 | F53: =F3+F31+F50 -> 908.12 | G53: =C53+E53+D53+F53 -> 4901 | H53: =G53/$G$55 -> 0.9802
A54: 四 | B54: 建设期利息 | F54: =G54 -> 99 | G54: ='分年计划及建设期利息'!D20 -> 99 | H54: =G54/$G$55 -> 0.0198 | I54: =TEXT('还本付息'!G5,"0.00%")&"利率，建设期"&TEXT('分年计划及建设期利息'!D2/12,"0")&"年，发债"&TEXT('分年计划及建设期利息'!G3,"0")&"万元" -> 4.50%利率，建设期1年，发债2200万元
A55: 五 | B55: 总投资 | C55: =C3+C31+C50+C54 -> 2199 | D55: =D3+D31+D50+D54 -> 1228.98 | E55: =E3+E31+E50+E54 -> 564.9 | F55: =F3+F31+F50+F54 -> 1007.12 | G55: =G53+G54 -> 5000 | H55: =G55/$G$55 -> 1

Sheet 其他费自动计算
A1: 序号 | B1: 费用输入（万元） | C1: 输入👇
A2: 1 | B2: 工程费用 | C2: ='总投资估算'!G3 -> 3992.88 | E2: 总投资 | G2: 总建筑面积
A3: 2 | B3: 总投资 | E3: 5000 | F3: ☜手动输入 | G3: ='项目技术经济指标'!D3/10000 -> 0.72 | H3: ☜手动输入
A4: 3 | B4: 设备购置费 | C4: ='总投资估算'!E3 -> 564.9
A7: 地区筛选 | B7: 红谷滩区
E9: 单位：万元 | G9: 地区折扣目录
A10: 序号 | B10: 费用名称 | C10: 估算金额 | D10: 地区折扣 | E10: 折后金额 | F10: 计费基础 | G10: 南昌市 | I10: 红谷滩区 | K10: 南昌县
G11: 参考文件 | H11: 折扣率 | I11: 参考文件 | J11: 折扣率 | K11: 参考文件 | L11: 折扣率
A12: 1 | B12: ='工程建设其他费细则说明'!B4 -> 建设单位管理费 | C12: =H112 -> 64.8932 | D12: =SUMIF(G$10:L$10,B$7,H12) -> 0.8 | E12: =C12*D12 -> 51.91456 | F12: 工程费用 | H12: 0.3 | J12: 0.8 | L12: 0.7
A13: 2 | B13: ='工程建设其他费细则说明'!B18 -> 场地准备及临时设施费 | C13: =C2*1% -> 39.9288 | D13: =SUMIF(G$10:L$10,B$7,H13) -> 0.6 | E13: =C13*D13 -> 23.95728 | F13: 工程费用 | H13: 0.6 | J13: 0.6 | L13: 0.6
A14: 3 | B14: ='工程建设其他费细则说明'!B21 -> 前期工作咨询费 | C14: =G34 -> 16.569796 | D14: =SUMIF(G$10:L$10,B$7,H14) -> 0.5 | E14: =C14*D14 -> 8.2848978 | F14: 总投资 | H14: 0.5 | J14: 0.5 | L14: 0.6
A15: 4 | B15: ='工程建设其他费细则说明'!B36 -> 勘察费 | C15: =C2*1% -> 39.9288 | D15: =SUMIF(G$10:L$10,B$7,H15) -> 0.4 | E15: =C15*D15 -> 15.97152 | F15: 工程费用 | H15: 0.8 | J15: 0.4 | L15: 0.85
A16: 5 | B16: ='工程建设其他费细则说明'!B37 -> 设计费 | C16: =E123 -> 133.63604 | D16: =SUMIF(G$10:L$10,B$7,H16) -> 0.4 | E16: =C16*D16 -> 53.454418 | F16: 工程费用 | H16: 0.9 | J16: 0.4 | L16: 0.85
A17: 6 | B17: ='工程建设其他费细则说明'!B38 -> 工程监理费 | C17: =E147 -> 99.297988 | D17: =SUMIF(G$10:L$10,B$7,H17) -> 0.7 | E17: =C17*D17 -> 69.508592 | F17: 工程费用 | H17: 0.5 | J17: 0.7 | L17: 0.7
A18: 7 | B18: ='工程建设其他费细则说明'!B42 -> 招标代理费 | C18: =S57 -> 31.339588 | D18: =SUMIF(G$10:L$10,B$7,H18) -> 0.49 | E18: =C18*D18 -> 15.356398 | F18: 分包 | H18: 0.3 | J18: 0.49 | L18: 0.8
A19: 8 | B19: ='工程建设其他费细则说明'!B43 -> 施工图审查费 | C19: =H181 -> 5.391456 | D19: =SUMIF(G$10:L$10,B$7,H19) -> 0.7 | E19: =C19*D19 -> 3.7740192 | F19: 工程费用 | H19: 0.4 | J19: 0.7 | L19: 0.6
A20: 9 | B20: ='工程建设其他费细则说明'!B45 -> 工程造价咨询费 | C20: =H169 -> 33.964464 | D20: =SUMIF(G$10:L$10,B$7,H20) -> 0.5 | E20: =C20*D20 -> 16.982232 | F20: 工程费用 | H20: 0.7 | J20: 0.5 | L20: 0.7
A21: 10 | B21: ='工程建设其他费细则说明'!B46 -> 工程保险费 | C21: =C2*0.5% -> 19.9644 | D21: =SUMIF(G$10:L$10,B$7,H21) -> 0.7 | E21: =C21*D21 -> 13.97508 | F21: 工程费用 | H21: 0.6 | J21: 0.7 | L21: 0.7
A22: 11 | B22: ='工程建设其他费细则说明'!B23 -> 环境影响评价费 | C22: =G64 -> 5.1176471 | D22: =SUMIF(G$10:L$10,B$7,H22) -> 0.7 | E22: =C22*D22 -> 3.5823529 | F22: 总投资 | H22: 0.7 | J22: 0.7 | L22: 0.7
A23: 12 | B23: ='工程建设其他费细则说明'!B29 -> 节能评估费 | C23: =H218 -> 6 | D23: =SUMIF(G$10:L$10,B$7,H23) -> 0.7 | E23: =C23*D23 -> 4.2 | F23: 工程费用 | H23: 0.7 | J23: 0.7 | L23: 0.7
A24: 13 | B24: ='工程建设其他费细则说明'!B27 -> 水土保持评价费 | C24: =G190 -> 30 | D24: =SUMIF(G$10:L$10,B$7,H24) -> 0.7 | E24: =C24*D24 -> 21 | F24: 工程费用 | H24: 0.7 | J24: 0.7 | L24: 0.7
A25: 14 | B25: ='工程建设其他费细则说明'!B32 -> 劳动安全卫生评审费 | C25: =C2*0.5% -> 19.9644 | D25: =SUMIF(G$10:L$10,B$7,H25) -> 0.7 | E25: =C25*D25 -> 13.97508 | F25: 工程费用 | H25: 0.7 | J25: 0.7 | L25: 0.7
A26: 15 | B26: ='工程建设其他费细则说明'!B31 -> 社会稳定风险评估费 | C26: =I75 -> 4.6285714 | D26: =SUMIF(G$10:L$10,B$7,H26) -> 0.7 | E26: =C26*D26 -> 3.24 | F26: 总投资 | H26: 0.7 | J26: 0.7 | L26: 0.7
A27: 16 | B27: ='工程建设其他费细则说明'!B24 -> 安全预评价费 | C27: =G87 -> 7 | D27: =SUMIF(G$10:L$10,B$7,H27) -> 0.7 | E27: =C27*D27 -> 4.9 | F27: 总投资 | H27: 0.7 | J27: 0.7 | L27: 0.7
A28: 17 | B28: ='工程建设其他费细则说明'!B33 -> 交通影响评估费 | C28: 0 | D28: =SUMIF(G$10:L$10,B$7,H28) -> 0.7 | E28: =C28*D28 -> 0 | F28: 总建筑面积 | H28: 0.7 | J28: 0.7 | L28: 0.7
A29: 合计 | C29: =SUM(C12:C28) -> 557.62515
A32: 前期工作咨询费（可行性研究报告）
A33: 序号 | B33: 计费额 | E33: 基价 | F33: 输入费用👇 | G33: 直线内插法计取
F34: =E3 -> 5000 | G34: =SUM(G35:G41) -> 16.569796
A35: 1 | C35: > | D35: 1000 | E35: 3 | F35: =IF(F34<=D35,1,0) -> 0 | G35: =IF($F35=1,(E35/D35*$F34),0) -> 0
A36: 2 | B36: 1001 | C36: ~ | D36: 3000 | E36: 6 | F36: =IF(AND($F$34<=D36,$F$34>B36),1,0) -> 0 | G36: =IF($F36=1,(E36+((E37-E36)/(D36-B36)*($F$34-B36))),0) -> 0
A37: 3 | B37: 3001 | C37: ~ | D37: 10000 | E37: 12 | F37: =IF(AND($F$34<=D37,$F$34>B37),1,0) -> 1 | G37: =IF($F37=1,(E37+((E38-E37)/(D37-B37)*($F$34-B37))),0) -> 16.569796
A38: 4 | B38: 10001 | C38: ~ | D38: 50000 | E38: 28 | F38: =IF(AND($F$34<=D38,$F$34>B38),1,0) -> 0 | G38: =IF($F38=1,(E38+((E39-E38)/(D38-B38)*($F$34-B38))),0) -> 0
A39: 5 | B39: 50001 | C39: ~ | D39: 100000 | E39: 75 | F39: =IF(AND($F$34<=D39,$F$34>B39),1,0) -> 0 | G39: =IF($F39=1,(E39+((E40-E39)/(D39-B39)*($F$34-B39))),0) -> 0
A40: 6 | B40: 100000 | C40: ~ | D40: 500000 | E40: 110 | F40: =IF(AND($F$34<=D40,$F$34>B40),1,0) -> 0 | G40: =IF($F40=1,(E40+((E41-E40)/(D40-B40)*($F$34-B40))),0) -> 0
A41: 7 | B41: 500000 | E41: 200 | F41: =IF(AND($F$34>B41),1,0) -> 0 | G41: =IF($F41=1,MIN(250,F34*E41/B41),0) -> 0
A44: 招标代理服务费
A45: 计费额 | D45: 货物采购 | G45: 服务招标（勘察） | J45: 服务招标（设计） | M45: 服务招标（监理） | P45: 工程招标
D46: =C4 -> 564.9 | G46: =C15 -> 39.9288 | J46: =C16 -> 133.63604 | M46: =C17 -> 99.297988 | P46: =C2-C4 -> 3427.98
B47: < | C47: 100 | D47: =C47*E47 -> 1.5 | E47: 0.015 | F47: =IF(D46<=C47,D46*E47,0) -> 0 | G47: =C47*H47 -> 1.5 | H47: 0.015 | I47: =IF(H46<=C47,H46*H47,0) -> 0 | J47: =C47*K47 -> 1.5 | K47: 0.015 | L47: =IF(J46<=C47,J46*K47,0) -> 0 | M47: =C47*N47 -> 1.5 | N47: 0.015 | O47: =IF(M46<=C47,M46*N47,0) -> 1.4894698 | P47: =C47*Q47 -> 1 | Q47: 0.01 | R47: =IF(P46<=C47,P46*Q47,0) -> 0
A48: 100 | B48: ~ | C48: 500 | D48: =D47+(C48-A48)*E48 -> 5.9 | E48: 0.011 | F48: =IF(AND($D$46>A48,$D$458<C48),(D47+($D$46-C47)*E48),0) -> 6.6139 | G48: =G47+(C48-C47)*H48 -> 4.7 | H48: 0.008 | I48: =IF(AND($G$46>A48,$G$46<C48),(G47+($G$46-C47)*H48),0) -> 0 | J48: =J47+(C48-A48)*K48 -> 4.7 | K48: 0.008 | L48: =IF(AND($J$46>A48,$J$46<C48),(J47+($J$46-C47)*K48),0) -> 1.7690884 | M48: =M47+(C48-C47)*N48 -> 4.7 | N48: 0.008 | O48: =IF(AND($M$46>A48,$M$46<C48),(M47+($M$46-C47)*N48),0) -> 0 | P48: =P47+(C48-C47)*Q48 -> 3.8 | Q48: 0.007 | R48: =IF(AND($P$46>A48,$P$46<C48),(P47+($P$46-C47)*Q48),0) -> 0
A49: 500 | B49: ~ | C49: 1000 | D49: =D48+(C49-A49)*E49 -> 9.9 | E49: 0.008 | F49: =IF(AND($D$46>A49,$D$458<C49),(D48+($D$46-C48)*E49),0) -> 6.4192 | G49: =G48+(C49-C48)*H49 -> 6.95 | H49: 0.0045 | I49: =IF(AND($G$46>A49,$G$46<C49),(G48+($G$46-C48)*H49),0) -> 0 | J49: =J48+(C49-A49)*K49 -> 6.95 | K49: 0.0045 | L49: =IF(AND($J$46>A49,$J$46<C49),(J48+($J$46-C48)*K49),0) -> 0 | M49: =M48+(C49-C48)*N49 -> 6.95 | N49: 0.0045 | O49: =IF(AND($M$46>A49,$M$46<C49),(M48+($M$46-C48)*N49),0) -> 0 | P49: =P48+(C49-C48)*Q49 -> 6.55 | Q49: 0.0055 | R49: =IF(AND($P$46>A49,$P$46<C49),(P48+($P$46-C48)*Q49),0) -> 0
A50: 1000 | B50: ~ | C50: 5000 | D50: =D49+(C50-A50)*E50 -> 29.9 | E50: 0.005 | F50: =IF(AND($D$46>A50,$D$458<C50),(D49+($D$46-C49)*E50),0) -> 0 | G50: =G49+(C50-C49)*H50 -> 16.95 | H50: 0.0025 | I50: =IF(AND($G$46>A50,$G$46<C50),(G49+($G$46-C49)*H50),0) -> 0 | J50: =J49+(C50-A50)*K50 -> 16.95 | K50: 0.0025 | L50: =IF(AND($J$46>A50,$J$46<C50),(J49+($J$46-C49)*K50),0) -> 0 | M50: =M49+(C50-C49)*N50 -> 16.95 | N50: 0.0025 | O50: =IF(AND($M$46>A50,$M$46<C50),(M49+($M$46-C49)*N50),0) -> 0 | P50: =P49+(C50-C49)*Q50 -> 20.55 | Q50: 0.0035 | R50: =IF(AND($P$46>A50,$P$46<C50),(P49+($P$46-C49)*Q50),0) -> 15.04793
A51: 5000 | B51: ~ | C51: 10000 | D51: =D50+(C51-A51)*E51 -> 42.4 | E51: 0.0025 | F51: =IF(AND($D$46>A51,$D$458<C51),(D50+($D$46-C50)*E51),0) -> 0 | G51: =G50+(C51-C50)*H51 -> 21.95 | H51: 0.001 | I51: =IF(AND($G$46>A51,$G$46<C51),(G50+($G$46-C50)*H51),0) -> 0 | J51: =J50+(C51-A51)*K51 -> 21.95 | K51: 0.001 | L51: =IF(AND($J$46>A51,$J$46<C51),(J50+($J$46-C50)*K51),0) -> 0 | M51: =M50+(C51-C50)*N51 -> 21.95 | N51: 0.001 | O51: =IF(AND($M$46>A51,$M$46<C51),(M50+($M$46-C50)*N51),0) -> 0 | P51: =P50+(C51-C50)*Q51 -> 30.55 | Q51: 0.002 | R51: =IF(AND($P$46>A51,$P$46<C51),(P50+($P$46-C50)*Q51),0) -> 0
A52: 10000 | B52: ~ | C52: 50000 | D52: =D51+(C52-A52)*E52 -> 62.4 | E52: 0.0005 | F52: =IF(AND($D$46>A52,$D$458<C52),(D51+($D$46-C51)*E52),0) -> 0 | G52: =G51+(C52-C51)*H52 -> 41.95 | H52: 0.0005 | I52: =IF(AND($G$46>A52,$G$46<C52),(G51+($G$46-C51)*H52),0) -> 0 | J52: =J51+(C52-A52)*K52 -> 41.95 | K52: 0.0005 | L52: =IF(AND($J$46>A52,$J$46<C52),(J51+($J$46-C51)*K52),0) -> 0 | M52: =M51+(C52-C51)*N52 -> 41.95 | N52: 0.0005 | O52: =IF(AND($M$46>A52,$M$46<C52),(M51+($M$46-C51)*N52),0) -> 0 | P52: =P51+(C52-C51)*Q52 -> 50.55 | Q52: 0.0005 | R52: =IF(AND($P$46>A52,$P$46<C52),(P51+($P$46-C51)*Q52),0) -> 0
A53: 50000 | B53: ~ | C53: 100000 | D53: =D52+(C53-A53)*E53 -> 79.9 | E53: 0.00035 | F53: =IF(AND($D$46>A53,$D$458<C53),(D52+($D$46-C52)*E53),0) -> 0 | G53: =G52+(C53-C52)*H53 -> 59.45 | H53: 0.00035 | I53: =IF(AND($G$46>A53,$G$46<C53),(G52+($G$46-C52)*H53),0) -> 0 | J53: =J52+(C53-A53)*K53 -> 59.45 | K53: 0.00035 | L53: =IF(AND($J$46>A53,$J$46<C53),(J52+($J$46-C52)*K53),0) -> 0 | M53: =M52+(C53-C52)*N53 -> 59.45 | N53: 0.00035 | O53: =IF(AND($M$46>A53,$M$46<C53),(M52+($M$46-C52)*N53),0) -> 0 | P53: =P52+(C53-C52)*Q53 -> 68.05 | Q53: 0.00035 | R53: =IF(AND($P$46>A53,$P$46<C53),(P52+($P$46-C52)*Q53),0) -> 0
A54: 100000 | B54: ~ | C54: 500000 | D54: =D53+(C54-A54)*E54 -> 111.9 | E54: 8e-05 | F54: =IF(AND($D$46>A54,$D$458<C54),(D53+($D$46-C53)*E54),0) -> 0 | G54: =G53+(C54-C53)*H54 -> 91.45 | H54: 8e-05 | I54: =IF(AND($G$46>A54,$G$46<C54),(G53+($G$46-C53)*H54),0) -> 0 | J54: =J53+(C54-A54)*K54 -> 91.45 | K54: 8e-05 | L54: =IF(AND($J$46>A54,$J$46<C54),(J53+($J$46-C53)*K54),0) -> 0 | M54: =M53+(C54-C53)*N54 -> 91.45 | N54: 8e-05 | O54: =IF(AND($M$46>A54,$M$46<C54),(M53+($M$46-C53)*N54),0) -> 0 | P54: =P53+(C54-C53)*Q54 -> 100.05 | Q54: 8e-05 | R54: =IF(AND($P$46>A54,$P$46<C54),(P53+($P$46-C53)*Q54),0) -> 0
A55: 500000 | B55: ~ | C55: 1000000 | D55: =D54+(C55-A55)*E55 -> 141.9 | E55: 6e-05 | F55: =IF(AND($D$46>A55,$D$458<C55),(D54+($D$46-C54)*E55),0) -> 0 | G55: =G54+(C55-C54)*H55 -> 121.45 | H55: 6e-05 | I55: =IF(AND($G$46>A55,$G$46<C55),(G54+($G$46-C54)*H55),0) -> 0 | J55: =J54+(C55-A55)*K55 -> 121.45 | K55: 6e-05 | L55: =IF(AND($J$46>A55,$J$46<C55),(J54+($J$46-C54)*K55),0) -> 0 | M55: =M54+(C55-C54)*N55 -> 121.45 | N55: 6e-05 | O55: =IF(AND($M$46>A55,$M$46<C55),(M54+($M$46-C54)*N55),0) -> 0 | P55: =P54+(C55-C54)*Q55 -> 130.05 | Q55: 6e-05 | R55: =IF(AND($P$46>A55,$P$46<C55),(P54+($P$46-C54)*Q55),0) -> 0
A56: 1000000 | B56: < | E56: 4e-05 | F56: =IF(AND($D$46>A56),(D55+($D$46-A56)*E56),0) -> 0 | H56: 4e-05 | I56: =IF(AND(G46>A56),(G55+(G46-A56)*H56),0) -> 0 | K56: 4e-05 | L56: =IF(AND(J46>A56),(J55+(J46-A56)*K56),0) -> 0 | N56: 4e-05 | O56: =IF(AND(M46>A56),(M55+(M46-A56)*N56),0) -> 0 | Q56: 4e-05 | R56: =IF(AND(P46>A56),(P55+(P46-A56)*Q56),0) -> 0 | S56: 总费用
A57: 费用合计 | D57: =SUM(F47:F56) -> 13.0331 | G57: =SUM(I47:I56) -> 0 | J57: =SUM(L47:L56) -> 1.7690884 | M57: =SUM(O47:O56) -> 1.4894698 | P57: =SUM(R47:R56) -> 15.04793 | S57: =SUM(D57:Q57) -> 31.339588
A61: 环境影响评估费
A62: 序号 | B62: 计费额 | E62: 基价 | F62: 输入费用👇 | G62: 直线内插法
E63: 编制报告书 （含大纲） | G63: 编制报告表
F64: =E3 -> 5000 | G64: =SUM(G65:G70) -> 5.1176471
A65: 1 | C65: > | D65: 3000 | E65: 5 | F65: =IF(F64<=D65,1,0) -> 0 | G65: =IF(F65=1,(E65/D65*F64),0) -> 0
A66: 2 | B66: 3000 | C66: ~ | D66: 20000 | E66: 6 | F66: =IF(AND($F$64<=D66,$F$64>B66),1,0) -> 1 | G66: =IF(F66=1,(E65+((E66-E65)/(D66-B66)*($F$64-B66))),0) -> 5.1176471
A67: 3 | B67: 20000 | C67: ~ | D67: 100000 | E67: 15 | F67: =IF(AND($F$64<=D67,$F$64>B67),1,0) -> 0 | G67: =IF(F67=1,(E66+((E67-E66)/(D67-B67)*($F$64-B67))),0) -> 0
A68: 4 | B68: 100000 | C68: ~ | D68: 500000 | E68: 35 | F68: =IF(AND($F$64<=D68,$F$64>B68),1,0) -> 0 | G68: =IF(F68=1,(E67+((E68-E67)/(D68-B68)*($F$64-B68))),0) -> 0
A69: 5 | B69: 500000 | C69: ~ | D69: 1000000 | E69: 75 | F69: =IF(AND($F$64<=D69,$F$64>B69),1,0) -> 0 | G69: =IF(F69=1,(E68+((E69-E68)/(D69-B69)*($F$64-B69))),0) -> 0
A70: 6 | B70: 1000000 | C70: ~ | D70: 500000 | E70: 110 | F70: =IF(AND($F$64<=D70,$F$64>B70),1,0) -> 0 | G70: =IF(F70=1,(E69+((E70-E69)/(D70-B70)*($F$64-B70))),0) -> 0
A73: ='工程建设其他费细则说明'!B31 -> 社会稳定风险评估费
A74: 序号 | B74: 投资额 | E74: 基费 | F74: 输入费用👇 | G74: 直线内插法计算 | H74: 风险敏感系数 | I74: 合计
F75: =E3 -> 5000 | G75: =SUM(G76:G81) -> 3.8571429 | H75: 1.2 | I75: =SUM(I76:I81) -> 4.6285714
A76: 1 | C76: < | D76: 3000 | E76: 3 | F76: =IF(AND(F75<=D76,F75>0),1,0) -> 0 | G76: =IF(F76=1,E76/D76*F75,0) -> 0 | H76: 1.2 | I76: =IF(F76=1,MAX(G76*H76,E76),0) -> 0
A77: 2 | B77: 3000 | C77: ~ | D77: 10000 | E77: 6 | F77: =IF(AND($F$75>B77,$F$75<=D77),1,0) -> 1 | G77: =IF(F77=1,(E76+(E77-E76)/(D77-B77)*($F$75-B77)),0) -> 3.8571429 | H77: 1.2 | I77: =G77*H77 -> 4.6285714
A78: 3 | B78: 10000 | C78: ~ | D78: 50000 | E78: 9 | F78: =IF(AND($F$75>B78,$F$75<=D78),1,0) -> 0 | G78: =IF(F78=1,(E77+(E78-E77)/(D78-B78)*($F$75-B78)),0) -> 0 | H78: 1.2 | I78: =G78*H78 -> 0
A79: 4 | B79: 50000 | C79: ~ | D79: 100000 | E79: 12 | F79: =IF(AND($F$75>B79,$F$75<=D79),1,0) -> 0 | G79: =IF(F79=1,(E78+(E79-E78)/(D79-B79)*($F$75-B79)),0) -> 0 | H79: 1.2 | I79: =G79*H79 -> 0
A80: 5 | B80: 100000 | C80: ~ | D80: 500000 | E80: 15 | F80: =IF(AND($F$75>B80,$F$75<=D80),1,0) -> 0 | G80: =IF(F80=1,(E79+(E80-E79)/(D80-B80)*($F$75-B80)),0) -> 0 | H80: 1.2 | I80: =G80*H80 -> 0
A81: 6 | B81: 500000 | C81: < | E81: 20 | F81: =IF(F75>B81,1,0) -> 0 | G81: =IF(F81=1,E81/B81*F75,0) -> 0 | H81: 1.2 | I81: =IF(F81=1,MIN(G81*H81,E81),0) -> 0
A82: 注：不考虑行业调整系数，敏感性系数按规划方案、环评、拆迁征地补偿方案等尚未公示，项目社会稳定风险尚不确定的项目考虑，系数为1.2，收费低于3万元的，按3万元收取；高于20万元的，按20万元收取。
A85: 安全预评价
A86: 序号 | B86: 总投资额 （万元） | E86: 基础报价 （万元） | F86: 输入费用👇 | G86: 直线内插法计取
F87: =E3 -> 5000 | G87: =SUM(G88:G96) -> 7
A88: 1 | C88: < | D88: =10000*0.05 -> 500 | E88: 2 | F88: =IF(F87<=D88,1,0) -> 0 | G88: =IF(F88=1,E88/D88*F87,0) -> 0
A89: 2 | B89: =10000*0.05 -> 500 | C89: ~ | D89: =10000*0.1 -> 1000 | E89: 3.5 | F89: =IF(AND($F$87>B89,$F$87<=D89),1,0) -> 0 | G89: =IF(F89=1,(E88+(E89-E88)/(D89-B89)*($F$87-B89)),0) -> 0
A90: 3 | B90: =10000*0.1 -> 1000 | C90: ~ | D90: =10000*0.2 -> 2000 | E90: 5 | F90: =IF(AND($F$87>B90,$F$87<=D90),1,0) -> 0 | G90: =IF(F90=1,(E89+(E90-E89)/(D90-B90)*($F$87-B90)),0) -> 0
A91: 4 | B91: =10000*0.2 -> 2000 | C91: ~ | D91: =10000*0.5 -> 5000 | E91: 7 | F91: =IF(AND($F$87>B91,$F$87<=D91),1,0) -> 1 | G91: =IF(F91=1,(E90+(E91-E90)/(D91-B91)*($F$87-B91)),0) -> 7
A92: 5 | B92: =10000*0.5 -> 5000 | C92: ~ | D92: 10000 | E92: =0.5*1.5*10000/1000 -> 7.5 | F92: =IF(AND($F$87>B92,$F$87<=D92),1,0) -> 0 | G92: =IF(F92=1,(E91+(E92-E91)/(D92-B92)*($F$87-B92)),0) -> 0
A93: 6 | B93: 10000 | C93: ~ | D93: 20000 | E93: =1*10000*1/1000 -> 10 | F93: =IF(AND($F$87>B93,$F$87<=D93),1,0) -> 0 | G93: =IF(F93=1,(E92+(E93-E92)/(D93-B93)*($F$87-B93)),0) -> 0
A94: 7 | B94: 20000 | C94: ~ | D94: 50000 | E94: =2*0.7*10000/1000 -> 14 | F94: =IF(AND($F$87>B94,$F$87<=D94),1,0) -> 0 | G94: =IF(F94=1,(E93+(E94-E93)/(D94-B94)*($F$87-B94)),0) -> 0
A95: 8 | B95: 50000 | C95: ~ | D95: 100000 | E95: =5*0.4*10000/1000 -> 20 | F95: =IF(AND($F$87>B95,$F$87<=D95),1,0) -> 0 | G95: =IF(F95=1,(E94+(E95-E94)/(D95-B95)*($F$87-B95)),0) -> 0
A96: 9 | B96: 100000 | E96: =10*0.3*10000/1000 -> 30 | F96: =IF(F87>B96,1,0) -> 0 | G96: =IF(F96=1,E96/B96*F87,0) -> 0
A99: 交通影响评估费
A100: 序号 | B100: 规模 （建筑总面积：万平方米） | E100: 单价 （元/平方米） | F100: 收费基数 （万元） | G100: 输入建筑面积👇 | H100: 差额累进法计算 | I100: 系数 | J100: 总计
G101: =G3 -> 0.72 | H101: =SUM(H102:H106) -> 10 | I101: 1 | J101: =SUM(J102:J106) -> 10
A102: 1 | C102: < | D102: 5 | E102: 2 | F102: 10 | G102: =IF(AND(G101<=D102,G101>0),1,0) -> 1 | H102: =IF(G102=1,F102,0) -> 10 | I102: =I$101 -> 1 | J102: =H102*I102 -> 10
A103: 2 | B103: 5 | C103: ~ | D103: 20 | E103: 2 | F103: 10 | G103: =IF(AND($G$2<=D103,$G$2>B103),1,0) -> 0 | H103: =IF(G103=1,(F103+(G$2-B103)*E103),0) -> 0 | I103: =I$101 -> 1 | J103: =H103*I103 -> 0
A104: 3 | B104: 20 | C104: ~ | D104: 100 | E104: 1.5 | F104: 40 | G104: =IF(AND($G$2<=D104,$G$2>B104),1,0) -> 0 | H104: =IF(G104=1,(F104+(G$2-B104)*E104),0) -> 0 | I104: =I$101 -> 1 | J104: =H104*I104 -> 0
A105: 4 | B105: 100 | C105: ~ | D105: 200 | E105: 1 | F105: 160 | G105: =IF(AND($G$2<=D105,$G$2>B105),1,0) -> 0 | H105: =IF(G105=1,(F105+(G$2-B105)*E105),0) -> 0 | I105: =I$101 -> 1 | J105: =H105*I105 -> 0
A106: 5 | B106: 200 | C106: < | E106: 0.8 | F106: 260 | G106: =IF(G101>B106,1,0) -> 0 | H106: =IF(G106=1,MAX(F106,E106*$G$2),0) -> 0 | I106: =I$101 -> 1 | J106: =H106*I106 -> 0
A107: 注：大型会议中心、体育运动中心、居住区、商业中心、学校、大型停车场（库）、区域路网等收费应取 1.5-1.8 系数。
A110: 建设单位管理费
A111: 收费基价表 | G111: 工程费用👇 | H111: 差额定率累进法
A112: 序号 | B112: 计费额 | E112: 费率 | F112: 全额 | G112: =C2 -> 3992.88 | H112: =SUM(H113:H118) -> 64.8932
A113: 1 | C113: > | D113: 1000 | E113: 0.02 | F113: =E113*D113 -> 20 | G113: =IF(G112<=D113,1,0) -> 0 | H113: =IF(G113=1,(G112*E113),0) -> 0
A114: 2 | B114: 1001 | C114: ~ | D114: 5000 | E114: 0.015 | F114: =F113+(D114-D113)*E114 -> 80 | G114: =IF(AND($G$112<=D114,$G$112>B114),1,0) -> 1 | H114: =IF(G114=1,(F113+($G$112-D113)*E114),0) -> 64.8932
A115: 3 | B115: 5001 | C115: ~ | D115: 10000 | E115: 0.012 | F115: =F114+(D115-D114)*E115 -> 140 | G115: =IF(AND($G$112<=D115,$G$112>B115),1,0) -> 0 | H115: =IF(G115=1,(F114+($G$112-D114)*E115),0) -> 0
A116: 4 | B116: 10001 | C116: ~ | D116: 50000 | E116: 0.01 | F116: =F115+(D116-D115)*E116 -> 540 | G116: =IF(AND($G$112<=D116,$G$112>B116),1,0) -> 0 | H116: =IF(G116=1,(F115+($G$112-D115)*E116),0) -> 0
A117: 5 | B117: 50001 | C117: ~ | D117: 100000 | E117: 0.008 | F117: =F116+(D117-D116)*E117 -> 940 | G117: =IF(AND($G$112<=D117,$G$112>B117),1,0) -> 0 | H117: =IF(G117=1,(F116+($G$112-D116)*E117),0) -> 0
A118: 6 | B118: 100000 | C118: < | E118: 0.004 | G118: =IF(AND($G$112>B118),1,0) -> 0 | H118: =IF(G118=1,(F117+($G$112-D117)*E118),0) -> 0
...

Sheet 分年计划及建设期利息
B1: 工期起始 | C1: 45108.9 | D1: 月数汇总 | F1: 资金来源 | G1: 金额（万元） | H1: 占比 | K1: ☜该色块为需手动输入
B2: 工期结束 | C2: 45900 | D2: 12 | F2: 资本金 | G2: =G4-G3 -> 2800 | H2: =G2/$G$4 -> 0.56 | K2: ☜出现该色块的单元格为报错格
B3: 建设年度 | C3: 建设年度起 | D3: 建设年度止 | F3: 发债金额 | G3: ='资金平衡表'!C36 -> 2200 | H3: =G3/$G$4 -> 0.44
B4: 第一年度 | C4: =C1 -> 45108.9 | D4: =EOMONTH(C4,11) -> 45473 | F4: 总投资 | G4: ='总投资估算'!G55 -> 5000 | H4: =G4/$G$4 -> 1
B5: 第二年度 | C5: =EOMONTH(D4,1) -> 45504 | D5: =EOMONTH(C5,11) -> 45838
B6: 第三年度 | C6: =EOMONTH(D5,1) -> 45869 | D6: =C2 -> 45900
B8: 表1-分年资金使用
B9: 序号 | C9: 项目 | D9: 合计 | E9: 建设期 | I9: 检查列
E10: 2024 | F10: =E10+1 -> 2025 | G10: =F10+1 -> 2026 | H10: =G10+1 -> 2027
B11: 一 | C11: 进度安排
B12: 1 | C12: 建设进度 | D12: =SUM(E12:H12) -> 1 | E12: 0.9 | F12: 0.1 | G12: =1-F12-E12 -> 0 | H12: 0 | I12: =SUM(E12:H12) -> 1
B13: 2 | C13: 其他费投入进度 | D13: =SUM(E13:H13) -> 1 | E13: 0.9 | F13: 0.1 | G13: =1-F13-E13 -> 0 | H13: 0 | I13: =SUM(E13:H13) -> 1
B14: 3 | C14: 专项债投入进度 | D14: =SUM(E14:H14) -> 1 | E14: 1 | F14: 0 | G14: =1-F14-E14 -> 0 | H14: 0 | I14: =SUM(E14:H14) -> 1
B15: 一 | C15: 总投资 | D15: =D16+D20 -> 5000 | E15: =E16+E20 -> 4509.9 | F15: =F16+F20 -> 490.1 | G15: =G16+G20 -> 0 | H15: =H16+H20 -> 0 | I15: =SUM(E15:H15) -> 5000 | J15: =I15-D15 -> 0
B16: 1 | C16: 建设投资 | D16: =SUM(E16:H16) -> 4901 | E16: =E17+E18+E19 -> 4410.9 | F16: =F17+F18+F19 -> 490.1 | G16: =G17+G18+G19 -> 0 | H16: =H17+H18+H19 -> 0 | I16: =SUM(E16:H16) -> 4901 | J16: =I16-D16 -> 0
B17: 1.1 | C17: 工程费用 | D17: ='总投资估算'!G3 -> 3992.88 | E17: =ROUND($D$17*E12,2) -> 3593.59 | F17: =ROUND($D$17*F12,2) -> 399.29 | G17: =ROUND($D$17*G12,2) -> 0 | H17: =ROUND($D$17*H12,2) -> 0 | I17: =SUM(E17:H17) -> 3992.88 | J17: =I17-D17 -> 0
B18: 1.2 | C18: 工程建设其他费 | D18: ='总投资估算'!G31 -> 559.82 | E18: =ROUND($D$18*E13,2) -> 503.84 | F18: =ROUND($D$18*F13,2) -> 55.98 | G18: =ROUND($D$18*G13,2) -> 0 | H18: =ROUND($D$18*H13,2) -> 0 | I18: =SUM(E18:H18) -> 559.82 | J18: =I18-D18 -> 0
B19: 1.3 | C19: 基本预备费 | D19: ='总投资估算'!G50 -> 348.3 | E19: =ROUND($D$19*E12,2) -> 313.47 | F19: =ROUND($D$19*F12,2) -> 34.83 | G19: =ROUND($D$19*G12,2) -> 0 | H19: =ROUND($D$19*H12,2) -> 0 | I19: =SUM(E19:H19) -> 348.3 | J19: =I19-D19 -> 0
B20: 2 | C20: 建设期利息 | D20: =SUM(E20:H20) -> 99 | E20: ='还本付息'!H5 -> 99 | F20: 0 | G20: 0 | H20: 0 | I20: =SUM(E20:H20) -> 99 | J20: =I20-D20 -> 0
B21: 二 | C21: 资金筹措 | D21: =D22+D23 -> 5000 | E21: =E15 -> 4509.9 | F21: =F15 -> 490.1 | G21: =G15 -> 0 | H21: =H15 -> 0 | I21: =SUM(E21:H21) -> 5000 | J21: =I21-D21 -> 0
B22: 1 | C22: 项目资本金 | D22: =G2 -> 2800 | E22: =E21-E23 -> 2309.9 | F22: =F21-F23 -> 490.1 | G22: =G21-G23 -> 0 | H22: =H21-H23 -> 0 | I22: =SUM(E22:H22) -> 2800 | J22: =I22-D22 -> 0
B23: 2 | C23: 专项债券 | D23: ='资金平衡表'!C36 -> 2200 | E23: =$D$23*E14 -> 2200 | F23: =$D$23*F14 -> 0 | G23: =$D$23*G14 -> 0 | H23: =$D$23*H14 -> 0 | I23: =SUM(E23:H23) -> 2200 | J23: =I23-D23 -> 0

Sheet 信息采集表
A1: 填表注释：公式请勿修改 | B1: 黄色单元格需要填写 | C1: 此为测算结果
A2: 1、项目建设期运营期相关
A3: 项目实际情况：
A4: ①截止到填表日，本项目是否开工 | B4: 否
A5: ②本项目建设期 | B5: =DATEDIF(B6,B7+1,"M") -> 26 | C5: 个月。
A6: ③本项目建设期开工日期 | B6: ='分年计划及建设期利息'!C1 -> 45108.9 | C6: 如：202X年X月1日
A7: ④本项目建设期完工日期 | B7: ='分年计划及建设期利息'!C2 -> 45900 | C7: 如：202X年X月1日 | D7: =(B7-B6)/30-B5 -> 0.37 | E7: （④-③）/30-② | F7: 注意与B5单元格的勾稽关系
A9: 项目可研报告中数据情况：
A10: ⑤本项目建设期 | B10: =B5 -> 26 | C10: 个月。 | D10: =B10-B5 -> 0 | E10: ⑤-②
A11: ⑥本项目建设期开工日期 | B11: =B6 -> 45108.9 | C11: 如：202X年X月1日 | D11: =B11-B6 -> 0 | E11: ⑥-③ | F11: 如与项目实际情况存在较大差异。1、笔误等情况酌情修改可研；2、编制错误或是以前年度编制可研造成，考虑是否影响可研数据的准确性（以前年度编制的可研，依据的参考数据都是以前年度的，是否与现在情况存在偏差，是否合理）；
A12: ⑦本项目建设期完工日期 | B12: =B7 -> 45900 | C12: 如：202X年X月1日 | D12: =B12-B7 -> 0 | E12: ⑦-④
A13: ⑧建设工程费用 | B13: ='分年计划及建设期利息'!D17 -> 3992.88 | C13: =B13-B24 -> 0 | D13: ⑧-⑭ | E13: 此处进行测算，存在差异，则需找具体原因
A14: ⑨工程建设其他费用 | B14: ='分年计划及建设期利息'!D18 -> 559.82 | C14: =B14-B25 -> 0 | D14: ⑨-⑮ | E14: 此处进行测算，存在差异，则需找具体原因
A15: ⑩预备费 | B15: ='分年计划及建设期利息'!D19 -> 348.3 | C15: =B15-B26 -> 0 | D15: ⑩-⑯ | E15: 此处进行测算，存在差异，则需找具体原因
A16: ⑪建设期利息 | B16: ='分年计划及建设期利息'!D20 -> 99 | C16: =B16-B27 -> 0 | D16: ⑪-⑰ | E16: 此处进行测算，存在差异，则需找具体原因
A17: 合计 | B17: =SUM(B13:B16) -> 5000 | C17: =B17-B28 -> 0 | D17: 合计差异 | E17: 此处进行测算，存在差异，则需找具体原因
A19: 2、投资构成及分年度计划（万元）
A20: 可研批复文号
A21: ⑫可研批复金额 | B21: =B22 -> 5000 | C21: =B21-B22 -> 0 | D21: ⑫-⑬ | E21: 此处进行测算，存在差异，则需找具体原因
A22: ⑬可研总投资金额 | B22: ='总投资估算'!G55 -> 5000 | C22: =B28-B22 -> 0 | D22: ⑬-（⑭+⑮+⑯+⑰） | E22: 此处进行测算，存在差异，则需找具体原因
A23: 具体每年项目投资情况 | B23: 合计 | C23: 以前年度 | D23: 2022年 | E23: 2023年 | F23: 2024年 | G23: 2025年 | H23: 2026年 | I23: 2027年
A24: ⑭建设工程费用 | B24: =SUM(C24:I24) -> 3992.88 | D24: ='分年计划及建设期利息'!E17 -> 3593.59 | E24: ='分年计划及建设期利息'!F17 -> 399.29 | F24: ='分年计划及建设期利息'!G17 -> 0 | G24: ='分年计划及建设期利息'!H17 -> 0
A25: ⑮工程建设其他费用 | B25: =SUM(C25:I25) -> 559.82 | D25: ='分年计划及建设期利息'!E18 -> 503.84 | E25: ='分年计划及建设期利息'!F18 -> 55.98 | F25: ='分年计划及建设期利息'!G18 -> 0 | G25: ='分年计划及建设期利息'!H18 -> 0
A26: ⑯预备费 | B26: =SUM(C26:I26) -> 348.3 | D26: ='分年计划及建设期利息'!E19 -> 313.47 | E26: ='分年计划及建设期利息'!F19 -> 34.83 | F26: ='分年计划及建设期利息'!G19 -> 0 | G26: ='分年计划及建设期利息'!H19 -> 0
A27: ⑰建设期利息 | B27: =SUM(C27:I27) -> 99 | D27: ='分年计划及建设期利息'!E20 -> 99 | E27: ='分年计划及建设期利息'!F20 -> 0 | F27: ='分年计划及建设期利息'!G20 -> 0 | G27: ='分年计划及建设期利息'!H20 -> 0
A28: 合计 | B28: =SUM(B24:B27) -> 5000 | C28: =SUM(C24:C27) -> 0 | D28: =SUM(D24:D27) -> 4509.9 | E28: =SUM(E24:E27) -> 490.1 | F28: =SUM(F24:F27) -> 0 | G28: =SUM(G24:G27) -> 0 | H28: =SUM(H24:H27) -> 0 | I28: =SUM(I24:I27) -> 0 | J28: 此处数据请与建设期所填数据核对，是否勾稽，不要存在无建设期，但存在项目投资的情况
A29: 注：若项目已开工，以前年度的支出按实际支出金额填写；若项目截止目前还未开工，按未来计划支出金额分年度填写
A31: 3、项目建设期运营期相关（万元） | B31: =B28-B36 -> 0 | C31: （⑭+⑮+⑯+⑰）-（⑱+⑲+⑳） | E31: 此处进行测算，存在差异，则需找具体原因 | G31: =B33/B36 -> 0.56 | H31: ⑱/（⑱+⑲+⑳） | I31: 此处不能小于20%，资本金必须大于等于占比20%
A32: 项目筹资情况 | B32: 合计 | C32: 以前年度 | D32: 2022年 | E32: 2023年 | F32: 2024年 | G32: 2025年 | H32: 2026年 | I32: 2027年
A33: ⑱资本金 | B33: =SUM(C33:I33) -> 2800 | D33: ='分年计划及建设期利息'!E22 -> 2309.9 | E33: ='分年计划及建设期利息'!F22 -> 490.1 | F33: ='分年计划及建设期利息'!G22 -> 0 | G33: ='分年计划及建设期利息'!H22 -> 0
A34: ⑲其他融资 | B34: =SUM(C34:I34) -> 0 | J34: 如果该列填数，则前面的资料，一定要囊括这部分的资料
A35: ⑳债券发行 | B35: =SUM(C35:I35) -> 2200 | D35: ='分年计划及建设期利息'!E23 -> 2200 | E35: ='分年计划及建设期利息'!F23 -> 0 | F35: ='分年计划及建设期利息'!G23 -> 0 | G35: ='分年计划及建设期利息'!H23 -> 0
A36: 合计 | B36: =SUM(C36:I36) -> 5000 | C36: =SUM(C33:C35) -> 0 | D36: =SUM(D33:D35) -> 4509.9 | E36: =SUM(E33:E35) -> 490.1 | F36: =SUM(F33:F35) -> 0 | G36: =SUM(G33:G35) -> 0 | H36: =SUM(H33:H35) -> 0 | I36: =SUM(I33:I35) -> 0
A37: 注：此列允许存在差异：如果是负数，则填列无误；如果是正数，则需修改发行债券分年计划，因此当年发债金额不允许大于当年投资金额 | D37: =D35-D28 -> -2309.9 | E37: =E35-E28 -> -490.1 | F37: =F35-F28 -> 0 | G37: =G35-G28 -> 0 | H37: =H35-H28 -> 0 | I37: =I35-I28 -> 0

Sheet 收入成本
A1: 周期 | B1: 年度 | C1: 污水处理收入 | H1: 中水收入 | L1: 污泥处理费 | P1: 经营收 入合计 | R1: 修理费占比折旧（自行键入） | X1: 0.05 | Y1: 金额单位：人民币万元
C2: 负荷率 | D2: 单价（元/t） | E2: 政府补贴（元/t） | F2: 收费数量（t/d) | G2: 年运营收入（万元） | H2: 负荷率 | I2: 单价（元/t） | J2: 收费数量（t/d) | K2: 年运营收入（万元） | L2: 负荷率 | M2: 单价（元/t） | N2: 收费数量（t/d) | O2: 年运营收入（万元） | S2: 年度 | T2: 外购原材料费 | U2: 外购燃料动力 | V2: 污泥处理费 | W2: 工资福利费用 | X2: 年维修成本 | Y2: 其他费用 | Z2: 税费 | AA2: 经营成本合计 | AB2: ='资金流入流出平衡表'!A20 -> 业务成本流出
T3: 0.05 | X3: 0.05 | Y3: 0.02
A4: 建设期 | B4: 1 | S4: 1 | U4: =ROUND(P4*3%,2) -> 0
A5: 运营期 | B5: 2 | C5: 0.5 | D5: 2.5 | E5: 1 | F5: 3000 | G5: =ROUND(C5*(D5+E5)*F5*365/10000,2) -> 191.63 | H5: 0.5 | I5: 0.5 | J5: =F5*0.7 -> 2100 | K5: =ROUND(H5*I5*J5*365/10000,2) -> 19.16 | L5: 0 | M5: 0 | N5: 0 | O5: =ROUND(L5*M5*N5*365/10000,2) -> 0 | P5: =G5+K5+O5 -> 210.79 | R5: 运营期 | S5: 2 | T5: =$X$51*C5 -> 8.4831 | U5: =$AC$50*C5 -> 6.57 | V5: =AC47 -> 1.752 | W5: =ROUND(('项目技术经济指标'!I10*'项目技术经济指标'!J10+'项目技术经济指标'!K10*'项目技术经济指标'!L10)*12/10000,2) -> 17.4 | X5: =ROUND('固定资产折旧'!$E$17*$X$1,2) -> 8.63 | Y5: =ROUND(P5*$Y$3,2) -> 4.22 | Z5: =ROUND('税费计算'!P7,2) -> 0 | AA5: =ROUND(SUM(T5:Z5),2) -> 47.06 | AB5: =AA5-Z5 -> 47.06
B6: 3 | C6: =C5+5% -> 0.55 | D6: =D5 -> 2.5 | E6: =E5 -> 1 | F6: =F5 -> 3000 | G6: =ROUND(C6*(D6+E6)*F6*365/10000,2) -> 210.79 | H6: =H5+5% -> 0.55 | I6: =I5 -> 0.5 | J6: =J5 -> 2100 | K6: =ROUND(H6*I6*J6*365/10000,2) -> 21.08 | L6: =H6 -> 0.55 | M6: =M5 -> 0 | N6: =N5 -> 0 | O6: =ROUND(L6*M6*N6*365/10000,2) -> 0 | P6: =G6+K6+O6 -> 231.87 | S6: 3 | T6: =$X$51*C6 -> 9.33141 | U6: =$AC$50*C6 -> 7.227 | V6: =V5 -> 1.752 | W6: =W5 -> 17.4 | X6: =ROUND('固定资产折旧'!$E$17*$X$1,2) -> 8.63 | Y6: =ROUND(P6*$Y$3,2) -> 4.64 | Z6: =ROUND('税费计算'!P8,2) -> 0 | AA6: =ROUND(SUM(T6:Z6),2) -> 48.98 | AB6: =AA6-Z6 -> 48.98
B7: 4 | C7: =C6+5% -> 0.6 | D7: =D6 -> 2.5 | E7: =E6 -> 1 | F7: =F6 -> 3000 | G7: =ROUND(C7*(D7+E7)*F7*365/10000,2) -> 229.95 | H7: =H6+5% -> 0.6 | I7: =I6 -> 0.5 | J7: =J6 -> 2100 | K7: =ROUND(H7*I7*J7*365/10000,2) -> 23 | L7: =H7 -> 0.6 | M7: =M6 -> 0 | N7: =N6 -> 0 | O7: =ROUND(L7*M7*N7*365/10000,2) -> 0 | P7: =G7+K7+O7 -> 252.95 | S7: 4 | T7: =$X$51*C7 -> 10.17972 | U7: =$AC$50*C7 -> 7.884 | V7: =V6 -> 1.752 | W7: =W6 -> 17.4 | X7: =ROUND('固定资产折旧'!$E$17*$X$1,2) -> 8.63 | Y7: =ROUND(P7*$Y$3,2) -> 5.06 | Z7: =ROUND('税费计算'!P9,2) -> 0 | AA7: =ROUND(SUM(T7:Z7),2) -> 50.91 | AB7: =AA7-Z7 -> 50.91
B8: 5 | C8: =C7+5% -> 0.65 | D8: =D7 -> 2.5 | E8: =E7 -> 1 | F8: =F7 -> 3000 | G8: =ROUND(C8*(D8+E8)*F8*365/10000,2) -> 249.11 | H8: =H7+5% -> 0.65 | I8: =I7 -> 0.5 | J8: =J7 -> 2100 | K8: =ROUND(H8*I8*J8*365/10000,2) -> 24.91 | L8: =H8 -> 0.65 | M8: =M7 -> 0 | N8: =N7 -> 0 | O8: =ROUND(L8*M8*N8*365/10000,2) -> 0 | P8: =G8+K8+O8 -> 274.02 | S8: 5 | T8: =$X$51*C8 -> 11.02803 | U8: =$AC$50*C8 -> 8.541 | V8: =V7 -> 1.752 | W8: =W7 -> 17.4 | X8: =ROUND('固定资产折旧'!$E$17*$X$1,2) -> 8.63 | Y8: =ROUND(P8*$Y$3,2) -> 5.48 | Z8: =ROUND('税费计算'!P10,2) -> 0 | AA8: =ROUND(SUM(T8:Z8),2) -> 52.83 | AB8: =AA8-Z8 -> 52.83
B9: 6 | C9: =C8+5% -> 0.7 | D9: =D8 -> 2.5 | E9: =E8 -> 1 | F9: =F8 -> 3000 | G9: =ROUND(C9*(D9+E9)*F9*365/10000,2) -> 268.28 | H9: =H8+5% -> 0.7 | I9: =I8 -> 0.5 | J9: =J8 -> 2100 | K9: =ROUND(H9*I9*J9*365/10000,2) -> 26.83 | L9: =H9 -> 0.7 | M9: =M8 -> 0 | N9: =N8 -> 0 | O9: =ROUND(L9*M9*N9*365/10000,2) -> 0 | P9: =G9+K9+O9 -> 295.11 | S9: 6 | T9: =$X$51*C9 -> 11.87634 | U9: =$AC$50*C9 -> 9.198 | V9: =V8 -> 1.752 | W9: =W8 -> 17.4 | X9: =ROUND('固定资产折旧'!$E$17*$X$1,2) -> 8.63 | Y9: =ROUND(P9*$Y$3,2) -> 5.9 | Z9: =ROUND('税费计算'!P11,2) -> 0 | AA9: =ROUND(SUM(T9:Z9),2) -> 54.76 | AB9: =AA9-Z9 -> 54.76
B10: 7 | C10: =C9+5% -> 0.75 | D10: =ROUND(D9*$C$36,2) -> 2.75 | E10: =E9 -> 1 | F10: =F9 -> 3000 | G10: =ROUND(C10*(D10+E10)*F10*365/10000,2) -> 307.97 | H10: =H9+5% -> 0.75 | I10: =ROUND(I9*$C$36,2) -> 0.55 | J10: =J9 -> 2100 | K10: =ROUND(H10*I10*J10*365/10000,2) -> 31.62 | L10: =H10 -> 0.75 | M10: =ROUND(M9*$C$36,2) -> 0 | N10: =N9 -> 0 | O10: =ROUND(L10*M10*N10*365/10000,2) -> 0 | P10: =G10+K10+O10 -> 339.59 | S10: 7 | T10: =$X$51*C10 -> 12.72465 | U10: =$AC$50*C10 -> 9.855 | V10: =V9 -> 1.752 | W10: =ROUND(W5*(1+'项目技术经济指标'!$M$10),2) -> 19.14 | X10: =ROUND(X5*(1+$X$3),2) -> 9.06 | Y10: =ROUND(P10*$Y$3,2) -> 6.79 | Z10: =ROUND('税费计算'!P12,2) -> 0 | AA10: =ROUND(SUM(T10:Z10),2) -> 59.32 | AB10: =AA10-Z10 -> 59.32
B11: 8 | C11: =C10 -> 0.75 | D11: =D10 -> 2.75 | E11: =E10 -> 1 | F11: =F10 -> 3000 | G11: =ROUND(C11*(D11+E11)*F11*365/10000,2) -> 307.97 | H11: =H10 -> 0.75 | I11: =I10 -> 0.55 | J11: =J10 -> 2100 | K11: =ROUND(H11*I11*J11*365/10000,2) -> 31.62 | L11: =H11 -> 0.75 | M11: =M10 -> 0 | N11: =N10 -> 0 | O11: =ROUND(L11*M11*N11*365/10000,2) -> 0 | P11: =G11+K11+O11 -> 339.59 | S11: 8 | T11: =$X$51*C11 -> 12.72465 | U11: =$AC$50*C11 -> 9.855 | V11: =V10 -> 1.752 | W11: =ROUND(W6*(1+'项目技术经济指标'!$M$10),2) -> 19.14 | X11: =ROUND(X6*(1+$X$3),2) -> 9.06 | Y11: =ROUND(P11*$Y$3,2) -> 6.79 | Z11: =ROUND('税费计算'!P13,2) -> 0 | AA11: =ROUND(SUM(T11:Z11),2) -> 59.32 | AB11: =AA11-Z11 -> 59.32
B12: 9 | C12: =C11 -> 0.75 | D12: =D11 -> 2.75 | E12: =E11 -> 1 | F12: =F11 -> 3000 | G12: =ROUND(C12*(D12+E12)*F12*365/10000,2) -> 307.97 | H12: =H11 -> 0.75 | I12: =I11 -> 0.55 | J12: =J11 -> 2100 | K12: =ROUND(H12*I12*J12*365/10000,2) -> 31.62 | L12: =H12 -> 0.75 | M12: =M11 -> 0 | N12: =N11 -> 0 | O12: =ROUND(L12*M12*N12*365/10000,2) -> 0 | P12: =G12+K12+O12 -> 339.59 | S12: 9 | T12: =$X$51*C12 -> 12.72465 | U12: =$AC$50*C12 -> 9.855 | V12: =V11 -> 1.752 | W12: =ROUND(W7*(1+'项目技术经济指标'!$M$10),2) -> 19.14 | X12: =ROUND(X7*(1+$X$3),2) -> 9.06 | Y12: =ROUND(P12*$Y$3,2) -> 6.79 | Z12: =ROUND('税费计算'!P14,2) -> 0 | AA12: =ROUND(SUM(T12:Z12),2) -> 59.32 | AB12: =AA12-Z12 -> 59.32
B13: 10 | C13: =C12 -> 0.75 | D13: =D12 -> 2.75 | E13: =E12 -> 1 | F13: =F12 -> 3000 | G13: =ROUND(C13*(D13+E13)*F13*365/10000,2) -> 307.97 | H13: =H12 -> 0.75 | I13: =I12 -> 0.55 | J13: =J12 -> 2100 | K13: =ROUND(H13*I13*J13*365/10000,2) -> 31.62 | L13: =H13 -> 0.75 | M13: =M12 -> 0 | N13: =N12 -> 0 | O13: =ROUND(L13*M13*N13*365/10000,2) -> 0 | P13: =G13+K13+O13 -> 339.59 | S13: 10 | T13: =$X$51*C13 -> 12.72465 | U13: =$AC$50*C13 -> 9.855 | V13: =V12 -> 1.752 | W13: =ROUND(W8*(1+'项目技术经济指标'!$M$10),2) -> 19.14 | X13: =ROUND(X8*(1+$X$3),2) -> 9.06 | Y13: =ROUND(P13*$Y$3,2) -> 6.79 | Z13: =ROUND('税费计算'!P15,2) -> 0 | AA13: =ROUND(SUM(T13:Z13),2) -> 59.32 | AB13: =AA13-Z13 -> 59.32
B14: 11 | C14: =C13 -> 0.75 | D14: =D13 -> 2.75 | E14: =E13 -> 1 | F14: =F13 -> 3000 | G14: =ROUND(C14*(D14+E14)*F14*365/10000,2) -> 307.97 | H14: =H13 -> 0.75 | I14: =I13 -> 0.55 | J14: =J13 -> 2100 | K14: =ROUND(H14*I14*J14*365/10000,2) -> 31.62 | L14: =H14 -> 0.75 | M14: =M13 -> 0 | N14: =N13 -> 0 | O14: =ROUND(L14*M14*N14*365/10000,2) -> 0 | P14: =G14+K14+O14 -> 339.59 | S14: 11 | T14: =$X$51*C14 -> 12.72465 | U14: =$AC$50*C14 -> 9.855 | V14: =V13 -> 1.752 | W14: =ROUND(W9*(1+'项目技术经济指标'!$M$10),2) -> 19.14 | X14: =ROUND(X9*(1+$X$3),2) -> 9.06 | Y14: =ROUND(P14*$Y$3,2) -> 6.79 | Z14: =ROUND('税费计算'!P16,2) -> 0 | AA14: =ROUND(SUM(T14:Z14),2) -> 59.32 | AB14: =AA14-Z14 -> 59.32
B15: 12 | C15: =C14 -> 0.75 | D15: =ROUND(D14*$C$36,2) -> 3.03 | E15: =E14 -> 1 | F15: =F14 -> 3000 | G15: =ROUND(C15*(D15+E15)*F15*365/10000,2) -> 330.96 | H15: =H14 -> 0.75 | I15: =ROUND(I14*$C$36,2) -> 0.61 | J15: =J14 -> 2100 | K15: =ROUND(H15*I15*J15*365/10000,2) -> 35.07 | L15: =H15 -> 0.75 | M15: =ROUND(M14*$C$36,2) -> 0 | N15: =N14 -> 0 | O15: =ROUND(L15*M15*N15*365/10000,2) -> 0 | P15: =G15+K15+O15 -> 366.03 | S15: 12 | T15: =$X$51*C15 -> 12.72465 | U15: =$AC$50*C15 -> 9.855 | V15: =V14 -> 1.752 | W15: =ROUND(W10*(1+'项目技术经济指标'!$M$10),2) -> 21.05 | X15: =ROUND(X10*(1+$X$3),2) -> 9.51 | Y15: =ROUND(P15*$Y$3,2) -> 7.32 | Z15: =ROUND('税费计算'!P17,2) -> 0 | AA15: =ROUND(SUM(T15:Z15),2) -> 62.21 | AB15: =AA15-Z15 -> 62.21
B16: 13 | C16: =C15 -> 0.75 | D16: =D15 -> 3.03 | E16: =E15 -> 1 | F16: =F15 -> 3000 | G16: =ROUND(C16*(D16+E16)*F16*365/10000,2) -> 330.96 | H16: =H15 -> 0.75 | I16: =I15 -> 0.61 | J16: =J15 -> 2100 | K16: =ROUND(H16*I16*J16*365/10000,2) -> 35.07 | L16: =H16 -> 0.75 | M16: =M15 -> 0 | N16: =N15 -> 0 | O16: =ROUND(L16*M16*N16*365/10000,2) -> 0 | P16: =G16+K16+O16 -> 366.03 | S16: 13 | T16: =$X$51*C16 -> 12.72465 | U16: =$AC$50*C16 -> 9.855 | V16: =V15 -> 1.752 | W16: =ROUND(W11*(1+'项目技术经济指标'!$M$10),2) -> 21.05 | X16: =ROUND(X11*(1+$X$3),2) -> 9.51 | Y16: =ROUND(P16*$Y$3,2) -> 7.32 | Z16: =ROUND('税费计算'!P18,2) -> 0 | AA16: =ROUND(SUM(T16:Z16),2) -> 62.21 | AB16: =AA16-Z16 -> 62.21
B17: 14 | C17: =C16 -> 0.75 | D17: =D16 -> 3.03 | E17: =E16 -> 1 | F17: =F16 -> 3000 | G17: =ROUND(C17*(D17+E17)*F17*365/10000,2) -> 330.96 | H17: =H16 -> 0.75 | I17: =I16 -> 0.61 | J17: =J16 -> 2100 | K17: =ROUND(H17*I17*J17*365/10000,2) -> 35.07 | L17: =H17 -> 0.75 | M17: =M16 -> 0 | N17: =N16 -> 0 | O17: =ROUND(L17*M17*N17*365/10000,2) -> 0 | P17: =G17+K17+O17 -> 366.03 | S17: 14 | T17: =$X$51*C17 -> 12.72465 | U17: =$AC$50*C17 -> 9.855 | V17: =V16 -> 1.752 | W17: =ROUND(W12*(1+'项目技术经济指标'!$M$10),2) -> 21.05 | X17: =ROUND(X12*(1+$X$3),2)+'总投资估算'!E3/2 -> 291.96 | Y17: =ROUND(P17*$Y$3,2) -> 7.32 | Z17: =ROUND('税费计算'!P19,2) -> 0 | AA17: =ROUND(SUM(T17:Z17),2) -> 344.66 | AB17: =AA17-Z17 -> 344.66
B18: 15 | C18: =C17 -> 0.75 | D18: =D17 -> 3.03 | E18: =E17 -> 1 | F18: =F17 -> 3000 | G18: =ROUND(C18*(D18+E18)*F18*365/10000,2) -> 330.96 | H18: =H17 -> 0.75 | I18: =I17 -> 0.61 | J18: =J17 -> 2100 | K18: =ROUND(H18*I18*J18*365/10000,2) -> 35.07 | L18: =H18 -> 0.75 | M18: =M17 -> 0 | N18: =N17 -> 0 | O18: =ROUND(L18*M18*N18*365/10000,2) -> 0 | P18: =G18+K18+O18 -> 366.03 | S18: 15 | T18: =$X$51*C18 -> 12.72465 | U18: =$AC$50*C18 -> 9.855 | V18: =V17 -> 1.752 | W18: =ROUND(W13*(1+'项目技术经济指标'!$M$10),2) -> 21.05 | X18: =ROUND(X13*(1+$X$3),2)+'总投资估算'!E3/2 -> 291.96 | Y18: =ROUND(P18*$Y$3,2) -> 7.32 | Z18: =ROUND('税费计算'!P20,2) -> 0 | AA18: =ROUND(SUM(T18:Z18),2) -> 344.66 | AB18: =AA18-Z18 -> 344.66
B19: 16 | C19: =C18 -> 0.75 | D19: =D18 -> 3.03 | E19: =E18 -> 1 | F19: =F18 -> 3000 | G19: =ROUND(C19*(D19+E19)*F19*365/10000,2) -> 330.96 | H19: =H18 -> 0.75 | I19: =I18 -> 0.61 | J19: =J18 -> 2100 | K19: =ROUND(H19*I19*J19*365/10000,2) -> 35.07 | L19: =H19 -> 0.75 | M19: =M18 -> 0 | N19: =N18 -> 0 | O19: =ROUND(L19*M19*N19*365/10000,2) -> 0 | P19: =G19+K19+O19 -> 366.03 | S19: 16 | T19: =$X$51*C19 -> 12.72465 | U19: =$AC$50*C19 -> 9.855 | V19: =V18 -> 1.752 | W19: =ROUND(W14*(1+'项目技术经济指标'!$M$10),2) -> 21.05 | X19: =ROUND(X14*(1+$X$3),2) -> 9.51 | Y19: =ROUND(P19*$Y$3,2) -> 7.32 | Z19: =ROUND('税费计算'!P21,2) -> 0 | AA19: =ROUND(SUM(T19:Z19),2) -> 62.21 | AB19: =AA19-Z19 -> 62.21
B20: 17 | C20: =C19 -> 0.75 | D20: =ROUND(D15*$C$36,2) -> 3.33 | E20: =E19 -> 1 | F20: =F19 -> 3000 | G20: =ROUND(C20*(D20+E20)*F20*365/10000,2) -> 355.6 | H20: =H19 -> 0.75 | I20: =ROUND(I15*$C$36,2) -> 0.67 | J20: =J19 -> 2100 | K20: =ROUND(H20*I20*J20*365/10000,2) -> 38.52 | L20: =H20 -> 0.75 | M20: =ROUND(M19*$C$36,2) -> 0 | N20: =N19 -> 0 | O20: =ROUND(L20*M20*N20*365/10000,2) -> 0 | P20: =G20+K20+O20 -> 394.12 | S20: 17 | T20: =$X$51*C20 -> 12.72465 | U20: =$AC$50*C20 -> 9.855 | V20: =V19 -> 1.752 | W20: =ROUND(W15*(1+'项目技术经济指标'!$M$10),2) -> 23.16 | X20: =ROUND(X15*(1+$X$3),2) -> 9.99 | Y20: =ROUND(P20*$Y$3,2) -> 7.88 | Z20: =ROUND('税费计算'!P22,2) -> 0 | AA20: =ROUND(SUM(T20:Z20),2) -> 65.36 | AB20: =AA20-Z20 -> 65.36
B21: 18 | C21: =C20 -> 0.75 | D21: =D20 -> 3.33 | E21: =E20 -> 1 | F21: =F20 -> 3000 | G21: =ROUND(C21*(D21+E21)*F21*365/10000,2) -> 355.6 | H21: =H20 -> 0.75 | I21: =I20 -> 0.67 | J21: =J20 -> 2100 | K21: =ROUND(H21*I21*J21*365/10000,2) -> 38.52 | L21: =H21 -> 0.75 | M21: =M20 -> 0 | N21: =N20 -> 0 | O21: =ROUND(L21*M21*N21*365/10000,2) -> 0 | P21: =G21+K21+O21 -> 394.12 | S21: 18 | T21: =$X$51*C21 -> 12.72465 | U21: =$AC$50*C21 -> 9.855 | V21: =V20 -> 1.752 | W21: =ROUND(W16*(1+'项目技术经济指标'!$M$10),2) -> 23.16 | X21: =ROUND(X16*(1+$X$3),2) -> 9.99 | Y21: =ROUND(P21*$Y$3,2) -> 7.88 | Z21: =ROUND('税费计算'!P23,2) -> 0 | AA21: =ROUND(SUM(T21:Z21),2) -> 65.36 | AB21: =AA21-Z21 -> 65.36
B22: 19 | C22: =C21 -> 0.75 | D22: =D21 -> 3.33 | E22: =E21 -> 1 | F22: =F21 -> 3000 | G22: =ROUND(C22*(D22+E22)*F22*365/10000,2) -> 355.6 | H22: =H21 -> 0.75 | I22: =I21 -> 0.67 | J22: =J21 -> 2100 | K22: =ROUND(H22*I22*J22*365/10000,2) -> 38.52 | L22: =H22 -> 0.75 | M22: =M21 -> 0 | N22: =N21 -> 0 | O22: =ROUND(L22*M22*N22*365/10000,2) -> 0 | P22: =G22+K22+O22 -> 394.12 | S22: 19 | T22: =$X$51*C22 -> 12.72465 | U22: =$AC$50*C22 -> 9.855 | V22: =V21 -> 1.752 | W22: =ROUND(W17*(1+'项目技术经济指标'!$M$10),2) -> 23.16 | X22: =ROUND(X19*(1+$X$3),2) -> 9.99 | Y22: =ROUND(P22*$Y$3,2) -> 7.88 | Z22: =ROUND('税费计算'!P24,2) -> 0 | AA22: =ROUND(SUM(T22:Z22),2) -> 65.36 | AB22: =AA22-Z22 -> 65.36
B23: 20 | C23: =C22 -> 0.75 | D23: =D22 -> 3.33 | E23: =E22 -> 1 | F23: =F22 -> 3000 | G23: =ROUND(C23*(D23+E23)*F23*365/10000,2) -> 355.6 | H23: =H22 -> 0.75 | I23: =I22 -> 0.67 | J23: =J22 -> 2100 | K23: =ROUND(H23*I23*J23*365/10000,2) -> 38.52 | L23: =H23 -> 0.75 | M23: =M22 -> 0 | N23: =N22 -> 0 | O23: =ROUND(L23*M23*N23*365/10000,2) -> 0 | P23: =G23+K23+O23 -> 394.12 | S23: 20 | T23: =$X$51*C23 -> 12.72465 | U23: =$AC$50*C23 -> 9.855 | V23: =V22 -> 1.752 | W23: =ROUND(W18*(1+'项目技术经济指标'!$M$10),2) -> 23.16 | X23: =ROUND(X19*(1+$X$3),2) -> 9.99 | Y23: =ROUND(P23*$Y$3,2) -> 7.88 | Z23: =ROUND('税费计算'!P25,2) -> 0 | AA23: =ROUND(SUM(T23:Z23),2) -> 65.36 | AB23: =AA23-Z23 -> 65.36
B24: 21 | C24: =C23 -> 0.75 | D24: =D23 -> 3.33 | E24: =E23 -> 1 | F24: =F23 -> 3000 | G24: =ROUND(C24*(D24+E24)*F24*365/10000,2) -> 355.6 | H24: =H23 -> 0.75 | I24: =I23 -> 0.67 | J24: =J23 -> 2100 | K24: =ROUND(H24*I24*J24*365/10000,2) -> 38.52 | L24: =H24 -> 0.75 | M24: =M23 -> 0 | N24: =N23 -> 0 | O24: =ROUND(L24*M24*N24*365/10000,2) -> 0 | P24: =G24+K24+O24 -> 394.12 | S24: 21 | T24: =$X$51*C24 -> 12.72465 | U24: =$AC$50*C24 -> 9.855 | V24: =V23 -> 1.752 | W24: =ROUND(W19*(1+'项目技术经济指标'!$M$10),2) -> 23.16 | X24: =ROUND(X19*(1+$X$3),2) -> 9.99 | Y24: =ROUND(P24*$Y$3,2) -> 7.88 | Z24: =ROUND('税费计算'!P26,2) -> 0 | AA24: =ROUND(SUM(T24:Z24),2) -> 65.36 | AB24: =AA24-Z24 -> 65.36
B25: 22 | C25: =C24 -> 0.75 | D25: =ROUND(D20*$C$36,2) -> 3.66 | E25: =E24 -> 1 | F25: =F24 -> 3000 | G25: =ROUND(C25*(D25+E25)*F25*365/10000,2) -> 382.7 | H25: =H24 -> 0.75 | I25: =ROUND(I20*$C$36,2) -> 0.74 | J25: =J24 -> 2100 | K25: =ROUND(H25*I25*J25*365/10000,2) -> 42.54 | L25: =H25 -> 0.75 | M25: =ROUND(M24*$C$36,2) -> 0 | N25: =N24 -> 0 | O25: =ROUND(L25*M25*N25*365/10000,2) -> 0 | P25: =G25+K25+O25 -> 425.24 | S25: 22 | T25: =$X$51*C25 -> 12.72465 | U25: =$AC$50*C25 -> 9.855 | V25: =V24 -> 1.752 | W25: =ROUND(W20*(1+'项目技术经济指标'!$M$10),2) -> 25.48 | X25: =ROUND(X20*(1+$X$3),2) -> 10.49 | Y25: =ROUND(P25*$Y$3,2) -> 8.5 | Z25: =ROUND('税费计算'!P27,2) -> 0 | AA25: =ROUND(SUM(T25:Z25),2) -> 68.8 | AB25: =AA25-Z25 -> 68.8
B26: 23 | C26: =C25 -> 0.75 | D26: =D25 -> 3.66 | E26: =E25 -> 1 | F26: =F25 -> 3000 | G26: =ROUND(C26*(D26+E26)*F26*365/10000,2) -> 382.7 | H26: =H25 -> 0.75 | I26: =I25 -> 0.74 | J26: =J25 -> 2100 | K26: =ROUND(H26*I26*J26*365/10000,2) -> 42.54 | L26: =H26 -> 0.75 | M26: =M25 -> 0 | N26: =N25 -> 0 | O26: =ROUND(L26*M26*N26*365/10000,2) -> 0 | P26: =G26+K26+O26 -> 425.24 | S26: 23 | T26: =$X$51*C26 -> 12.72465 | U26: =$AC$50*C26 -> 9.855 | V26: =V25 -> 1.752 | W26: =ROUND(W21*(1+'项目技术经济指标'!$M$10),2) -> 25.48 | X26: =ROUND(X21*(1+$X$3),2) -> 10.49 | Y26: =ROUND(P26*$Y$3,2) -> 8.5 | Z26: =ROUND('税费计算'!P28,2) -> 0 | AA26: =ROUND(SUM(T26:Z26),2) -> 68.8 | AB26: =AA26-Z26 -> 68.8
B27: 24 | C27: =C26 -> 0.75 | D27: =D26 -> 3.66 | E27: =E26 -> 1 | F27: =F26 -> 3000 | G27: =ROUND(C27*(D27+E27)*F27*365/10000,2) -> 382.7 | H27: =H26 -> 0.75 | I27: =I26 -> 0.74 | J27: =J26 -> 2100 | K27: =ROUND(H27*I27*J27*365/10000,2) -> 42.54 | L27: =H27 -> 0.75 | M27: =M26 -> 0 | N27: =N26 -> 0 | O27: =ROUND(L27*M27*N27*365/10000,2) -> 0 | P27: =G27+K27+O27 -> 425.24 | S27: 24 | T27: =$X$51*C27 -> 12.72465 | U27: =$AC$50*C27 -> 9.855 | V27: =V26 -> 1.752 | W27: =ROUND(W22*(1+'项目技术经济指标'!$M$10),2) -> 25.48 | X27: =ROUND(X22*(1+$X$3),2) -> 10.49 | Y27: =ROUND(P27*$Y$3,2) -> 8.5 | Z27: =ROUND('税费计算'!P29,2) -> 10.57 | AA27: =ROUND(SUM(T27:Z27),2) -> 79.37 | AB27: =AA27-Z27 -> 68.8
B28: 25 | C28: =C27 -> 0.75 | D28: =D27 -> 3.66 | E28: =E27 -> 1 | F28: =F27 -> 3000 | G28: =ROUND(C28*(D28+E28)*F28*365/10000,2) -> 382.7 | H28: =H27 -> 0.75 | I28: =I27 -> 0.74 | J28: =J27 -> 2100 | K28: =ROUND(H28*I28*J28*365/10000,2) -> 42.54 | L28: =H28 -> 0.75 | M28: =M27 -> 0 | N28: =N27 -> 0 | O28: =ROUND(L28*M28*N28*365/10000,2) -> 0 | P28: =G28+K28+O28 -> 425.24 | S28: 25 | T28: =$X$51*C28 -> 12.72465 | U28: =$AC$50*C28 -> 9.855 | V28: =V27 -> 1.752 | W28: =ROUND(W23*(1+'项目技术经济指标'!$M$10),2) -> 25.48 | X28: =ROUND(X23*(1+$X$3),2) -> 10.49 | Y28: =ROUND(P28*$Y$3,2) -> 8.5 | Z28: =ROUND('税费计算'!P30,2) -> 25.79 | AA28: =ROUND(SUM(T28:Z28),2) -> 94.59 | AB28: =AA28-Z28 -> 68.8
B29: 26 | C29: =C28 -> 0.75 | D29: =D28 -> 3.66 | E29: =E28 -> 1 | F29: =F28 -> 3000 | G29: =ROUND(C29*(D29+E29)*F29*365/10000,2) -> 382.7 | H29: =H28 -> 0.75 | I29: =I28 -> 0.74 | J29: =J28 -> 2100 | K29: =ROUND(H29*I29*J29*365/10000,2) -> 42.54 | L29: =H29 -> 0.75 | M29: =M28 -> 0 | N29: =N28 -> 0 | O29: =ROUND(L29*M29*N29*365/10000,2) -> 0 | P29: =G29+K29+O29 -> 425.24 | S29: 26 | T29: =$X$51*C29 -> 12.72465 | U29: =$AC$50*C29 -> 9.855 | V29: =V28 -> 1.752 | W29: =ROUND(W24*(1+'项目技术经济指标'!$M$10),2) -> 25.48 | X29: =ROUND(X24*(1+$X$3),2) -> 10.49 | Y29: =ROUND(P29*$Y$3,2) -> 8.5 | Z29: =ROUND('税费计算'!P31,2) -> 28.01 | AA29: =ROUND(SUM(T29:Z29),2) -> 96.81 | AB29: =AA29-Z29 -> 68.8
B30: 27 | C30: =C29 -> 0.75 | D30: =ROUND(D25*$C$36,2) -> 4.03 | E30: =E29 -> 1 | F30: =F29 -> 3000 | G30: =ROUND(C30*(D30+E30)*F30*365/10000,2) -> 413.09 | H30: =H29 -> 0.75 | I30: =ROUND(I25*$C$36,2) -> 0.81 | J30: =J29 -> 2100 | K30: =ROUND(H30*I30*J30*365/10000,2) -> 46.56 | L30: =H30 -> 0.75 | M30: =ROUND(M29*$C$36,2) -> 0 | N30: =N29 -> 0 | O30: =ROUND(L30*M30*N30*365/10000,2) -> 0 | P30: =G30+K30+O30 -> 459.65 | S30: 27 | T30: =$X$51*C30 -> 12.72465 | U30: =$AC$50*C30 -> 9.855 | V30: =V29 -> 1.752 | W30: =ROUND(W25*(1+'项目技术经济指标'!$M$10),2) -> 28.03 | X30: =ROUND(X25*(1+$X$3),2) -> 11.01 | Y30: =ROUND(P30*$Y$3,2) -> 9.19 | Z30: =ROUND('税费计算'!P32,2) -> 28.01 | AA30: =ROUND(SUM(T30:Z30),2) -> 100.57 | AB30: =AA30-Z30 -> 72.56
B31: 28 | C31: =C30 -> 0.75 | D31: =D30 -> 4.03 | E31: =E30 -> 1 | F31: =F30 -> 3000 | G31: =ROUND(C31*(D31+E31)*F31*365/10000,2) -> 413.09 | H31: =H30 -> 0.75 | I31: =I30 -> 0.81 | J31: =J30 -> 2100 | K31: =ROUND(H31*I31*J31*365/10000,2) -> 46.56 | L31: =H31 -> 0.75 | M31: =M30 -> 0 | N31: =N30 -> 0 | O31: =ROUND(L31*M31*N31*365/10000,2) -> 0 | P31: =G31+K31+O31 -> 459.65 | S31: 28 | T31: =$X$51*C31 -> 12.72465 | U31: =$AC$50*C31 -> 9.855 | V31: =V30 -> 1.752 | W31: =ROUND(W26*(1+'项目技术经济指标'!$M$10),2) -> 28.03 | X31: =ROUND(X26*(1+$X$3),2) -> 11.01 | Y31: =ROUND(P31*$Y$3,2) -> 9.19 | Z31: =ROUND('税费计算'!P33,2) -> 28.01 | AA31: =ROUND(SUM(T31:Z31),2) -> 100.57 | AB31: =AA31-Z31 -> 72.56
B32: 29 | C32: =C31 -> 0.75 | D32: =D31 -> 4.03 | E32: =E31 -> 1 | F32: =F31 -> 3000 | G32: =ROUND(C32*(D32+E32)*F32*365/10000,2) -> 413.09 | H32: =H31 -> 0.75 | I32: =I31 -> 0.81 | J32: =J31 -> 2100 | K32: =ROUND(H32*I32*J32*365/10000,2) -> 46.56 | L32: =H32 -> 0.75 | M32: =M31 -> 0 | N32: =N31 -> 0 | O32: =ROUND(L32*M32*N32*365/10000,2) -> 0 | P32: =G32+K32+O32 -> 459.65 | S32: 29 | T32: =$X$51*C32 -> 12.72465 | U32: =$AC$50*C32 -> 9.855 | V32: =V31 -> 1.752 | W32: =ROUND(W27*(1+'项目技术经济指标'!$M$10),2) -> 28.03 | X32: =ROUND(X27*(1+$X$3),2) -> 11.01 | Y32: =ROUND(P32*$Y$3,2) -> 9.19 | Z32: =ROUND('税费计算'!P34,2) -> 28.01 | AA32: =ROUND(SUM(T32:Z32),2) -> 100.57 | AB32: =AA32-Z32 -> 72.56
B33: 30 | C33: =C32 -> 0.75 | D33: =D32 -> 4.03 | E33: =E32 -> 1 | F33: =F32 -> 3000 | G33: =ROUND(C33*(D33+E33)*F33*365/10000,2) -> 413.09 | H33: =H32 -> 0.75 | I33: =I32 -> 0.81 | J33: =J32 -> 2100 | K33: =ROUND(H33*I33*J33*365/10000,2) -> 46.56 | L33: =H33 -> 0.75 | M33: =M32 -> 0 | N33: =N32 -> 0 | O33: =ROUND(L33*M33*N33*365/10000,2) -> 0 | P33: =G33+K33+O33 -> 459.65 | S33: 30 | T33: =$X$51*C33 -> 12.72465 | U33: =$AC$50*C33 -> 9.855 | V33: =V32 -> 1.752 | W33: =ROUND(W28*(1+'项目技术经济指标'!$M$10),2) -> 28.03 | X33: =ROUND(X28*(1+$X$3),2) -> 11.01 | Y33: =ROUND(P33*$Y$3,2) -> 9.19 | Z33: =ROUND('税费计算'!P35,2) -> 0 | AA33: =ROUND(SUM(T33:Z33),2) -> 72.56 | AB33: =AA33-Z33 -> 72.56
V34: =V33 -> 1.752
A35: 合计 | G35: =SUM(G4:G34) -> 9688.27 | K35: =SUM(K4:K34) -> 1039.97 | O35: =SUM(O4:O34) -> 0 | P35: =SUM(P4:P34) -> 10728.24 | R35: 合计 | T35: =SUM(T4:T34) -> 356.2902 | U35: =SUM(U4:U34) -> 275.94 | V35: =SUM(V4:V34) -> 52.56 | W35: =SUM(W4:W34) -> 643.27 | X35: =SUM(X4:X34) -> 847.34 | Y35: =SUM(Y4:Y34) -> 214.51 | Z35: =SUM(Z4:Z34) -> 148.4 | AA35: =SUM(AA4:AA34) -> 2536.53 | AB35: =SUM(AB5:AB34) -> 2388.13 | AC35: =P35-AA35 -> 8191.71
C36: 1.1
T45: 参考同类型项目
T46: 原材料 | U46: 消耗量（吨） | W46: 单价/吨 | X46: 总价（万元） | Y46: 污水处理量（吨） | Z46: 每万吨污水 淤泥产生量（吨） | AA46: 年淤泥量（吨） | AB46: 处理单价（元/吨） | AC46: 淤泥处理费
T47: 药剂 PAC | U47: =$F$5/20000*160 -> 24 | W47: 1800 | X47: =U47*W47/10000 -> 4.32 | Y47: =F5 -> 3000 | Z47: 1 | AA47: =Y47/10000*Z47*365 -> 109.5 | AB47: 160 | AC47: =AA47*AB47/10000 -> 1.752
T48: 药剂 PAM | U48: =$F$5/20000*7.8 -> 1.17 | W48: 28600 | X48: =U48*W48/10000 -> 3.3462
T49: NaCl | U49: =$F$5/20000*125 -> 18.75 | W49: 2200 | X49: =U49*W49/10000 -> 4.125 | Y49: 污水处理量（吨） | Z49: 电耗（kW·h/m³） | AA49: 天数 | AB49: 电价 | AC49: 年耗电费用
T50: 乙酸钠 | U50: =$F$5/20000*115 -> 17.25 | W50: 3000 | X50: =U50*W50/10000 -> 5.175 | Y50: =Y47 -> 3000 | Z50: 0.2 | AA50: 365 | AB50: 0.6 | AC50: =ROUND(Y50*Z50*AA50*AB50/10000,2) -> 13.14
T51: 合计 | X51: =SUM(X47:X50) -> 16.9662
T54: 吉水县移民安置区排水防涝蓄水功能建设项目

Sheet 税费计算
A1: 年份 | B1: 增值税 | L1: 城市建设 维护税 | M1: 教育费 附加 | N1: 地方教育费附加 | O1: 房产税 | P1: 税费合计 | Q1: 工程施工进项税计算表
B2: 销项税 | G2: 进项税 | K2: 进销项 抵扣后 合计 | Q2: 序号 | R2: 项目 | S2: 含税金额 | T2: 税率 | U2: 进项税 | V2: 不含税金额（用于折旧）
B3: ='收入成本'!C1 -> 污水处理收入 | D3: ='收入成本'!H1 -> 中水收入 | F3: 销项税 合计 | G3: 外购燃料动力 | H3: 维修 | I3: 进项税 合计 | J3: 工程施工留抵进项余额 | Q3: 1.1 | R3: 工程费用 | S3: ='项目技术经济指标'!D30 -> 3992.88 | T3: - | U3: =U4+U5 -> 348.03 | V3: =S3-U3 -> 3644.85
B4: 0.06 | D4: 0.09 | G4: 0.13 | H4: 0.06 | L4: 0.05 | M4: 0.03 | N4: 0.02 | Q4: 1.1.1 | R4: 建筑安装工程费 | S4: ='项目技术经济指标'!D31 -> 3427.98 | T4: 0.09 | U4: =ROUND(S4/(1+T4)*T4,2) -> 283.04 | V4: =S4-U4 -> 3144.94
A5: 1 | B5: =ROUND('收入成本'!G4/(1+$B$4)*$B$4*0.3,2) -> 0 | D5: =ROUND('收入成本'!K4/(1+$D$4)*$D$4*0.5,2) -> 0 | E5: =ROUND('收入成本'!O4/(1+$E$4)*$E$4,2) -> 0 | F5: =SUM(B5:E5) -> 0 | G5: =ROUND('收入成本'!U4/(1+$G$4)*$G$4,2) -> 0 | H5: =ROUND('收入成本'!X4/(1+$H$4)*$H$4,2) -> 0 | I5: =G5+H5 -> 0 | J5: 初始值 | P5: =SUM(K5:O5) -> 0 | Q5: 1.1.2 | R5: 设备购置费 | S5: ='项目技术经济指标'!D32 -> 564.9 | T5: 0.13 | U5: =ROUND(S5/(1+T5)*T5,2) -> 64.99 | V5: =S5-U5 -> 499.91
A6: 2 | B6: =ROUND('收入成本'!G5/(1+$B$4)*$B$4,2) -> 10.85 | D6: =ROUND('收入成本'!K5/(1+$D$4)*$D$4,2) -> 1.58 | E6: =ROUND('收入成本'!O5/(1+$E$4)*$E$4,2) -> 0 | F6: =SUM(B6:E6) -> 12.43 | G6: =ROUND('收入成本'!U5/(1+$G$4)*$G$4,2) -> 0.76 | H6: =ROUND('收入成本'!X5/(1+$H$4)*$H$4,2) -> 0.49 | I6: =G6+H6 -> 1.25 | J6: =U9 -> 408.48 | P6: =SUM(K6:O6) -> 0 | Q6: 1.2 | R6: 工程建设其他费 | S6: ='项目技术经济指标'!D33 -> 559.82 | T6: 0.06 | U6: =ROUND(S6/(1+T6)*T6,2) -> 31.69 | V6: =S6-U6 -> 528.13
A7: 3 | B7: =ROUND('收入成本'!G6/(1+$B$4)*$B$4,2) -> 11.93 | D7: =ROUND('收入成本'!K6/(1+$D$4)*$D$4,2) -> 1.74 | E7: =ROUND('收入成本'!O6/(1+$E$4)*$E$4,2) -> 0 | F7: =SUM(B7:E7) -> 13.67 | G7: =ROUND('收入成本'!U6/(1+$G$4)*$G$4,2) -> 0.83 | H7: =ROUND('收入成本'!X6/(1+$H$4)*$H$4,2) -> 0.49 | I7: =G7+H7 -> 1.32 | J7: =IF((J6+H7+G7)-SUM(B7:E7)<0,0,(J6+H7+G7)-SUM(B7:E7)) -> 396.13 | K7: =IF((J6+H7+G7)-SUM(B7:E7)>0,0,SUM(B7:E7)-(J6+H7+G7)) -> 0 | L7: =ROUND(K7*$L$4,2) -> 0 | M7: =ROUND(K7*$M$4,2) -> 0 | N7: =ROUND(K7*$N$4,2) -> 0 | P7: =SUM(K7:O7) -> 0 | Q7: 1.3 | R7: 基本预备费 | S7: ='项目技术经济指标'!D34 -> 348.3 | T7: 0.09 | U7: =ROUND(S7/(1+T7)*T7,2) -> 28.76 | V7: =S7-U7 -> 319.54
A8: 4 | B8: =ROUND('收入成本'!G7/(1+$B$4)*$B$4,2) -> 13.02 | D8: =ROUND('收入成本'!K7/(1+$D$4)*$D$4,2) -> 1.9 | E8: =ROUND('收入成本'!O7/(1+$E$4)*$E$4,2) -> 0 | F8: =SUM(B8:E8) -> 14.92 | G8: =ROUND('收入成本'!U7/(1+$G$4)*$G$4,2) -> 0.91 | H8: =ROUND('收入成本'!X7/(1+$H$4)*$H$4,2) -> 0.49 | I8: =G8+H8 -> 1.4 | J8: =IF((J7+H8+G8)-SUM(B8:E8)<0,0,(J7+H8+G8)-SUM(B8:E8)) -> 382.61 | K8: =IF((J7+H8+G8)-SUM(B8:E8)>0,0,SUM(B8:E8)-(J7+H8+G8)) -> 0 | L8: =ROUND(K8*$L$4,2) -> 0 | M8: =ROUND(K8*$M$4,2) -> 0 | N8: =ROUND(K8*$N$4,2) -> 0 | P8: =SUM(K8:O8) -> 0 | Q8: 1.4 | R8: 建设期利息 | S8: ='项目技术经济指标'!D35 -> 99 | T8: 0 | U8: =ROUND(S8/(1+T8)*T8,2) -> 0 | V8: =S8-U8 -> 99
A9: 5 | B9: =ROUND('收入成本'!G8/(1+$B$4)*$B$4,2) -> 14.1 | D9: =ROUND('收入成本'!K8/(1+$D$4)*$D$4,2) -> 2.06 | E9: =ROUND('收入成本'!O8/(1+$E$4)*$E$4,2) -> 0 | F9: =SUM(B9:E9) -> 16.16 | G9: =ROUND('收入成本'!U8/(1+$G$4)*$G$4,2) -> 0.98 | H9: =ROUND('收入成本'!X8/(1+$H$4)*$H$4,2) -> 0.49 | I9: =G9+H9 -> 1.47 | J9: =IF((J8+H9+G9)-SUM(B9:E9)<0,0,(J8+H9+G9)-SUM(B9:E9)) -> 367.92 | K9: =IF((J8+H9+G9)-SUM(B9:E9)>0,0,SUM(B9:E9)-(J8+H9+G9)) -> 0 | L9: =ROUND(K9*$L$4,2) -> 0 | M9: =ROUND(K9*$M$4,2) -> 0 | N9: =ROUND(K9*$N$4,2) -> 0 | P9: =SUM(K9:O9) -> 0 | Q9: 1 | R9: 总投资 | S9: =S3+S6+S7+S8 -> 5000 | U9: =SUM(U4:U8) -> 408.48 | V9: =SUM(V4:V8) -> 4591.52
A10: 6 | B10: =ROUND('收入成本'!G9/(1+$B$4)*$B$4,2) -> 15.19 | D10: =ROUND('收入成本'!K9/(1+$D$4)*$D$4,2) -> 2.22 | E10: =ROUND('收入成本'!O9/(1+$E$4)*$E$4,2) -> 0 | F10: =SUM(B10:E10) -> 17.41 | G10: =ROUND('收入成本'!U9/(1+$G$4)*$G$4,2) -> 1.06 | H10: =ROUND('收入成本'!X9/(1+$H$4)*$H$4,2) -> 0.49 | I10: =G10+H10 -> 1.55 | J10: =IF((J9+H10+G10)-SUM(B10:E10)<0,0,(J9+H10+G10)-SUM(B10:E10)) -> 352.06 | K10: =IF((J9+H10+G10)-SUM(B10:E10)>0,0,SUM(B10:E10)-(J9+H10+G10)) -> 0 | L10: =ROUND(K10*$L$4,2) -> 0 | M10: =ROUND(K10*$M$4,2) -> 0 | N10: =ROUND(K10*$N$4,2) -> 0 | P10: =SUM(K10:O10) -> 0
A11: 7 | B11: =ROUND('收入成本'!G10/(1+$B$4)*$B$4,2) -> 17.43 | D11: =ROUND('收入成本'!K10/(1+$D$4)*$D$4,2) -> 2.61 | E11: =ROUND('收入成本'!O10/(1+$E$4)*$E$4,2) -> 0 | F11: =SUM(B11:E11) -> 20.04 | G11: =ROUND('收入成本'!U10/(1+$G$4)*$G$4,2) -> 1.13 | H11: =ROUND('收入成本'!X10/(1+$H$4)*$H$4,2) -> 0.51 | I11: =G11+H11 -> 1.64 | J11: =IF((J10+H11+G11)-SUM(B11:E11)<0,0,(J10+H11+G11)-SUM(B11:E11)) -> 333.66 | K11: =IF((J10+H11+G11)-SUM(B11:E11)>0,0,SUM(B11:E11)-(J10+H11+G11)) -> 0 | L11: =ROUND(K11*$L$4,2) -> 0 | M11: =ROUND(K11*$M$4,2) -> 0 | N11: =ROUND(K11*$N$4,2) -> 0 | P11: =SUM(K11:O11) -> 0
A12: 8 | B12: =ROUND('收入成本'!G11/(1+$B$4)*$B$4,2) -> 17.43 | D12: =ROUND('收入成本'!K11/(1+$D$4)*$D$4,2) -> 2.61 | E12: =ROUND('收入成本'!O11/(1+$E$4)*$E$4,2) -> 0 | F12: =SUM(B12:E12) -> 20.04 | G12: =ROUND('收入成本'!U11/(1+$G$4)*$G$4,2) -> 1.13 | H12: =ROUND('收入成本'!X11/(1+$H$4)*$H$4,2) -> 0.51 | I12: =G12+H12 -> 1.64 | J12: =IF((J11+H12+G12)-SUM(B12:E12)<0,0,(J11+H12+G12)-SUM(B12:E12)) -> 315.26 | K12: =IF((J11+H12+G12)-SUM(B12:E12)>0,0,SUM(B12:E12)-(J11+H12+G12)) -> 0 | L12: =ROUND(K12*$L$4,2) -> 0 | M12: =ROUND(K12*$M$4,2) -> 0 | N12: =ROUND(K12*$N$4,2) -> 0 | P12: =SUM(K12:O12) -> 0
A13: 9 | B13: =ROUND('收入成本'!G12/(1+$B$4)*$B$4,2) -> 17.43 | D13: =ROUND('收入成本'!K12/(1+$D$4)*$D$4,2) -> 2.61 | E13: =ROUND('收入成本'!O12/(1+$E$4)*$E$4,2) -> 0 | F13: =SUM(B13:E13) -> 20.04 | G13: =ROUND('收入成本'!U12/(1+$G$4)*$G$4,2) -> 1.13 | H13: =ROUND('收入成本'!X12/(1+$H$4)*$H$4,2) -> 0.51 | I13: =G13+H13 -> 1.64 | J13: =IF((J12+H13+G13)-SUM(B13:E13)<0,0,(J12+H13+G13)-SUM(B13:E13)) -> 296.86 | K13: =IF((J12+H13+G13)-SUM(B13:E13)>0,0,SUM(B13:E13)-(J12+H13+G13)) -> 0 | L13: =ROUND(K13*$L$4,2) -> 0 | M13: =ROUND(K13*$M$4,2) -> 0 | N13: =ROUND(K13*$N$4,2) -> 0 | P13: =SUM(K13:O13) -> 0
A14: 10 | B14: =ROUND('收入成本'!G13/(1+$B$4)*$B$4,2) -> 17.43 | D14: =ROUND('收入成本'!K13/(1+$D$4)*$D$4,2) -> 2.61 | E14: =ROUND('收入成本'!O13/(1+$E$4)*$E$4,2) -> 0 | F14: =SUM(B14:E14) -> 20.04 | G14: =ROUND('收入成本'!U13/(1+$G$4)*$G$4,2) -> 1.13 | H14: =ROUND('收入成本'!X13/(1+$H$4)*$H$4,2) -> 0.51 | I14: =G14+H14 -> 1.64 | J14: =IF((J13+H14+G14)-SUM(B14:E14)<0,0,(J13+H14+G14)-SUM(B14:E14)) -> 278.46 | K14: =IF((J13+H14+G14)-SUM(B14:E14)>0,0,SUM(B14:E14)-(J13+H14+G14)) -> 0 | L14: =ROUND(K14*$L$4,2) -> 0 | M14: =ROUND(K14*$M$4,2) -> 0 | N14: =ROUND(K14*$N$4,2) -> 0 | P14: =SUM(K14:O14) -> 0
A15: 11 | B15: =ROUND('收入成本'!G14/(1+$B$4)*$B$4,2) -> 17.43 | D15: =ROUND('收入成本'!K14/(1+$D$4)*$D$4,2) -> 2.61 | E15: =ROUND('收入成本'!O14/(1+$E$4)*$E$4,2) -> 0 | F15: =SUM(B15:E15) -> 20.04 | G15: =ROUND('收入成本'!U14/(1+$G$4)*$G$4,2) -> 1.13 | H15: =ROUND('收入成本'!X14/(1+$H$4)*$H$4,2) -> 0.51 | I15: =G15+H15 -> 1.64 | J15: =IF((J14+H15+G15)-SUM(B15:E15)<0,0,(J14+H15+G15)-SUM(B15:E15)) -> 260.06 | K15: =IF((J14+H15+G15)-SUM(B15:E15)>0,0,SUM(B15:E15)-(J14+H15+G15)) -> 0 | L15: =ROUND(K15*$L$4,2) -> 0 | M15: =ROUND(K15*$M$4,2) -> 0 | N15: =ROUND(K15*$N$4,2) -> 0 | P15: =SUM(K15:O15) -> 0
A16: 12 | B16: =ROUND('收入成本'!G15/(1+$B$4)*$B$4,2) -> 18.73 | D16: =ROUND('收入成本'!K15/(1+$D$4)*$D$4,2) -> 2.9 | E16: =ROUND('收入成本'!O15/(1+$E$4)*$E$4,2) -> 0 | F16: =SUM(B16:E16) -> 21.63 | G16: =ROUND('收入成本'!U15/(1+$G$4)*$G$4,2) -> 1.13 | H16: =ROUND('收入成本'!X15/(1+$H$4)*$H$4,2) -> 0.54 | I16: =G16+H16 -> 1.67 | J16: =IF((J15+H16+G16)-SUM(B16:E16)<0,0,(J15+H16+G16)-SUM(B16:E16)) -> 240.1 | K16: =IF((J15+H16+G16)-SUM(B16:E16)>0,0,SUM(B16:E16)-(J15+H16+G16)) -> 0 | L16: =ROUND(K16*$L$4,2) -> 0 | M16: =ROUND(K16*$M$4,2) -> 0 | N16: =ROUND(K16*$N$4,2) -> 0 | P16: =SUM(K16:O16) -> 0
A17: 13 | B17: =ROUND('收入成本'!G16/(1+$B$4)*$B$4,2) -> 18.73 | D17: =ROUND('收入成本'!K16/(1+$D$4)*$D$4,2) -> 2.9 | E17: =ROUND('收入成本'!O16/(1+$E$4)*$E$4,2) -> 0 | F17: =SUM(B17:E17) -> 21.63 | G17: =ROUND('收入成本'!U16/(1+$G$4)*$G$4,2) -> 1.13 | H17: =ROUND('收入成本'!X16/(1+$H$4)*$H$4,2) -> 0.54 | I17: =G17+H17 -> 1.67 | J17: =IF((J16+H17+G17)-SUM(B17:E17)<0,0,(J16+H17+G17)-SUM(B17:E17)) -> 220.14 | K17: =IF((J16+H17+G17)-SUM(B17:E17)>0,0,SUM(B17:E17)-(J16+H17+G17)) -> 0 | L17: =ROUND(K17*$L$4,2) -> 0 | M17: =ROUND(K17*$M$4,2) -> 0 | N17: =ROUND(K17*$N$4,2) -> 0 | P17: =SUM(K17:O17) -> 0
A18: 14 | B18: =ROUND('收入成本'!G17/(1+$B$4)*$B$4,2) -> 18.73 | D18: =ROUND('收入成本'!K17/(1+$D$4)*$D$4,2) -> 2.9 | E18: =ROUND('收入成本'!O17/(1+$E$4)*$E$4,2) -> 0 | F18: =SUM(B18:E18) -> 21.63 | G18: =ROUND('收入成本'!U17/(1+$G$4)*$G$4,2) -> 1.13 | H18: =ROUND('收入成本'!X17/(1+$H$4)*$H$4,2) -> 16.53 | I18: =G18+H18 -> 17.66 | J18: =IF((J17+H18+G18)-SUM(B18:E18)<0,0,(J17+H18+G18)-SUM(B18:E18)) -> 216.17 | K18: =IF((J17+H18+G18)-SUM(B18:E18)>0,0,SUM(B18:E18)-(J17+H18+G18)) -> 0 | L18: =ROUND(K18*$L$4,2) -> 0 | M18: =ROUND(K18*$M$4,2) -> 0 | N18: =ROUND(K18*$N$4,2) -> 0 | P18: =SUM(K18:O18) -> 0
A19: 15 | B19: =ROUND('收入成本'!G18/(1+$B$4)*$B$4,2) -> 18.73 | D19: =ROUND('收入成本'!K18/(1+$D$4)*$D$4,2) -> 2.9 | E19: =ROUND('收入成本'!O18/(1+$E$4)*$E$4,2) -> 0 | F19: =SUM(B19:E19) -> 21.63 | G19: =ROUND('收入成本'!U18/(1+$G$4)*$G$4,2) -> 1.13 | H19: =ROUND('收入成本'!X18/(1+$H$4)*$H$4,2) -> 16.53 | I19: =G19+H19 -> 17.66 | J19: =IF((J18+H19+G19)-SUM(B19:E19)<0,0,(J18+H19+G19)-SUM(B19:E19)) -> 212.2 | K19: =IF((J18+H19+G19)-SUM(B19:E19)>0,0,SUM(B19:E19)-(J18+H19+G19)) -> 0 | L19: =ROUND(K19*$L$4,2) -> 0 | M19: =ROUND(K19*$M$4,2) -> 0 | N19: =ROUND(K19*$N$4,2) -> 0 | P19: =SUM(K19:O19) -> 0
A20: 16 | B20: =ROUND('收入成本'!G19/(1+$B$4)*$B$4,2) -> 18.73 | D20: =ROUND('收入成本'!K19/(1+$D$4)*$D$4,2) -> 2.9 | E20: =ROUND('收入成本'!O19/(1+$E$4)*$E$4,2) -> 0 | F20: =SUM(B20:E20) -> 21.63 | G20: =ROUND('收入成本'!U19/(1+$G$4)*$G$4,2) -> 1.13 | H20: =ROUND('收入成本'!X19/(1+$H$4)*$H$4,2) -> 0.54 | I20: =G20+H20 -> 1.67 | J20: =IF((J19+H20+G20)-SUM(B20:E20)<0,0,(J19+H20+G20)-SUM(B20:E20)) -> 192.24 | K20: =IF((J19+H20+G20)-SUM(B20:E20)>0,0,SUM(B20:E20)-(J19+H20+G20)) -> 0 | L20: =ROUND(K20*$L$4,2) -> 0 | M20: =ROUND(K20*$M$4,2) -> 0 | N20: =ROUND(K20*$N$4,2) -> 0 | P20: =SUM(K20:O20) -> 0
A21: 17 | B21: =ROUND('收入成本'!G20/(1+$B$4)*$B$4,2) -> 20.13 | D21: =ROUND('收入成本'!K20/(1+$D$4)*$D$4,2) -> 3.18 | E21: =ROUND('收入成本'!O20/(1+$E$4)*$E$4,2) -> 0 | F21: =SUM(B21:E21) -> 23.31 | G21: =ROUND('收入成本'!U20/(1+$G$4)*$G$4,2) -> 1.13 | H21: =ROUND('收入成本'!X20/(1+$H$4)*$H$4,2) -> 0.57 | I21: =G21+H21 -> 1.7 | J21: =IF((J20+H21+G21)-SUM(B21:E21)<0,0,(J20+H21+G21)-SUM(B21:E21)) -> 170.63 | K21: =IF((J20+H21+G21)-SUM(B21:E21)>0,0,SUM(B21:E21)-(J20+H21+G21)) -> 0 | L21: =ROUND(K21*$L$4,2) -> 0 | M21: =ROUND(K21*$M$4,2) -> 0 | N21: =ROUND(K21*$N$4,2) -> 0 | P21: =SUM(K21:O21) -> 0
... A34: 30 | B34: =ROUND('收入成本'!G33/(1+$B$4)*$B$4,2) -> 23.38 | D34: =ROUND('收入成本'!K33/(1+$D$4)*$D$4,2) -> 3.84 | E34: =ROUND('收入成本'!O33/(1+$E$4)*$E$4,2) -> 0 | F34: =SUM(B34:E34) -> 27.22 | G34: =ROUND('收入成本'!U33/(1+$G$4)*$G$4,2) -> 1.13 | H34: =ROUND('收入成本'!X33/(1+$H$4)*$H$4,2) -> 0.62 | I34: =G34+H34 -> 1.75 | J34: =IF((J33+H34+G34)-SUM(B34:E34)<0,0,(J33+H34+G34)-SUM(B34:E34)) -> 0 | K34: =IF((J33+H34+G34)-SUM(B34:E34)>0,0,SUM(B34:E34)-(J33+H34+G34)) -> 25.47 | L34: =ROUND(K34*$L$4,2) -> 1.27 | M34: =ROUND(K34*$M$4,2) -> 0.76 | N34: =ROUND(K34*$N$4,2) -> 0.51 | P34: =SUM(K34:O34) -> 28.01
A35: 31 | B35: =ROUND('收入成本'!G34/(1+$B$4)*$B$4,2) -> 0 | D35: =ROUND('收入成本'!K34/(1+$D$4)*$D$4,2) -> 0 | E35: =ROUND('收入成本'!O33/(1+$E$4)*$E$4,2) -> 0 | F35: =SUM(B35:E35) -> 0 | G35: =ROUND('收入成本'!U33/(1+$G$4)*$G$4,2) -> 1.13 | H35: =ROUND('收入成本'!X33/(1+$H$4)*$H$4,2) -> 0.62 | I35: =G35+H35 -> 1.75 | J35: =IF((J34+H35+G35)-SUM(B35:E35)<0,0,(J34+H35+G35)-SUM(B35:E35)) -> 1.75 | K35: =IF((J34+H35+G35)-SUM(B35:E35)>0,0,SUM(B35:E35)-(J34+H35+G35)) -> 0 | L35: =ROUND(K35*$L$4,2) -> 0 | M35: =ROUND(K35*$M$4,2) -> 0 | N35: =ROUND(K35*$N$4,2) -> 0 | P35: =SUM(K35:O35) -> 0
A37: 合计 | B37: =SUM(B5:B36) -> 548.36 | C37: =SUM(C5:C36) -> 0 | D37: =SUM(D5:D36) -> 85.86 | E37: =SUM(E5:E36) -> 0 | F37: =SUM(F5:F36) -> 634.22 | G37: =SUM(G5:G36) -> 32.79 | H37: =SUM(H5:H36) -> 48.58 | I37: =SUM(I5:I36) -> 81.37 | K37: =SUM(K7:K36) -> 134.94 | L37: =SUM(L7:L36) -> 6.73 | M37: =SUM(M7:M36) -> 4.03 | N37: =SUM(N7:N36) -> 2.7 | O37: =SUM(O7:O36) -> 0 | P37: =SUM(P7:P36) -> 148.4

Sheet 还本付息
H2: 金额单位：人民币万元
B3: 年度 | C3: 期初本金余额 | D3: 本年发放 | E3: 本期偿还本金 | F3: 期末本金余额 | G3: 融资利率 | H3: 应付利息 | I3: 本息合计
B5: 1 | C5: 0 | D5: ='分年计划及建设期利息'!E23 -> 2200 | F5: =C5+D5-E5 -> 2200 | G5: 0.045 | H5: =F5*G5 -> 99 | I5: =E5+H5 -> 99
B6: 2 | C6: =F5 -> 2200 | F6: =C6+D6-E6 -> 2200 | G6: =G5 -> 0.045 | H6: =(C6+D6)*G6 -> 99 | I6: =E6+H6 -> 99
B7: 3 | C7: =F6 -> 2200 | F7: =C7+D7-E7 -> 2200 | G7: =G6 -> 0.045 | H7: =(C7+D7)*G7 -> 99 | I7: =E7+H7 -> 99
B8: 4 | C8: =F7 -> 2200 | F8: =C8+D8-E8 -> 2200 | G8: =G7 -> 0.045 | H8: =(C8+D8)*G8 -> 99 | I8: =E8+H8 -> 99
B9: 5 | C9: =F8 -> 2200 | F9: =C9+D9-E9 -> 2200 | G9: =G8 -> 0.045 | H9: =(C9+D9)*G9 -> 99 | I9: =E9+H9 -> 99
B10: 6 | C10: =F9 -> 2200 | F10: =C10+D10-E10 -> 2200 | G10: =G9 -> 0.045 | H10: =(C10+D10)*G10 -> 99 | I10: =E10+H10 -> 99
B11: 7 | C11: =F10 -> 2200 | F11: =C11+D11-E11 -> 2200 | G11: =G10 -> 0.045 | H11: =(C11+D11)*G11 -> 99 | I11: =E11+H11 -> 99
B12: 8 | C12: =F11 -> 2200 | F12: =C12+D12-E12 -> 2200 | G12: =G11 -> 0.045 | H12: =(C12+D12)*G12 -> 99 | I12: =E12+H12 -> 99
B13: 9 | C13: =F12 -> 2200 | F13: =C13+D13-E13 -> 2200 | G13: =G12 -> 0.045 | H13: =(C13+D13)*G13 -> 99 | I13: =E13+H13 -> 99
B14: 10 | C14: =F13 -> 2200 | F14: =C14+D14-E14 -> 2200 | G14: =G13 -> 0.045 | H14: =(C14+D14)*G14 -> 99 | I14: =E14+H14 -> 99
B15: 11 | C15: =F14 -> 2200 | F15: =C15+D15-E15 -> 2200 | G15: =G14 -> 0.045 | H15: =(C15+D15)*G15 -> 99 | I15: =E15+H15 -> 99
B16: 12 | C16: =F15 -> 2200 | F16: =C16+D16-E16 -> 2200 | G16: =G15 -> 0.045 | H16: =(C16+D16)*G16 -> 99 | I16: =E16+H16 -> 99
B17: 13 | C17: =F16 -> 2200 | F17: =C17+D17-E17 -> 2200 | G17: =G16 -> 0.045 | H17: =(C17+D17)*G17 -> 99 | I17: =E17+H17 -> 99
... B33: 29 | C33: =F32 -> 2200 | F33: =C33+D33-E33 -> 2200 | G33: =G32 -> 0.045 | H33: =(C33+D33)*G33 -> 99 | I33: =E33+H33 -> 99
B34: 30 | C34: =F33 -> 2200 | E34: =D5 -> 2200 | F34: =C34+D34-E34 -> 0 | G34: =G33 -> 0.045 | H34: =(C34+D34)*G34 -> 99 | I34: =E34+H34 -> 2299
B35: 31 | C35: =F34 -> 0 | E35: =D6 -> 0 | F35: =C35+D35-E35 -> 0 | G35: =G34 -> 0.045 | H35: =(C35+D35)*G35 -> 0 | I35: =E35+H35 -> 0
B36: 32 | C36: =F35 -> 0 | E36: =D7 -> 0 | F36: =C36+D36-E36 -> 0 | G36: =G35 -> 0.045 | H36: =(C36+D36)*G36 -> 0 | I36: =E36+H36 -> 0
B37: 33 | C37: =F36 -> 0 | E37: =D8 -> 0 | F37: =C37+D37-E37 -> 0 | G37: =G36 -> 0.045 | H37: =(C37+D37)*G37 -> 0 | I37: =E37+H37 -> 0
B38: 合计 | E38: =SUM(E5:E37) -> 2200 | H38: =SUM(H5:H37) -> 2970 | I38: =SUM(I5:I37) -> 5170
H41: =E38*4.5%*30 -> 2970

Sheet 资金平衡表
B1: 年度 | C1: 借贷本息支付 | F1: 经营收入 | H1: 总费用成本 | J1: 收益余额
C2: 本金 | D2: 利息 | E2: 本息合计 | F2: 1 | G2: 下降10% | H2: 1 | I2: 上升10% | J2: 1 | K2: 收入下降10% | L2: 成本上升10% | M2: 收入下降10%且成本上升10%
B3: 1 | C3: ='还本付息'!E5 -> 0 | D3: ='还本付息'!H5 -> 99 | E3: =C3+D3 -> 99 | F3: =ROUND('收入成本'!P4,2) -> 0 | G3: =ROUND('收入成本'!P4*0.9,2) -> 0 | H3: =ROUND('收入成本'!AA4,2) -> 0 | I3: =ROUND('收入成本'!AA4*1.1,2) -> 0 | J3: =F3-H3 -> 0
B4: 2 | C4: ='还本付息'!E6 -> 0 | D4: ='还本付息'!H6 -> 99 | E4: =C4+D4 -> 99 | F4: =ROUND('收入成本'!P5,2) -> 210.79 | G4: =ROUND('收入成本'!P5*0.9,2) -> 189.71 | H4: =ROUND('收入成本'!AA5,2) -> 47.06 | I4: =ROUND('收入成本'!AA5*1.1,2) -> 51.77 | J4: =F4-H4 -> 163.73 | K4: =G4-H4 -> 142.65 | L4: =F4-I4 -> 159.02 | M4: =G4-I4 -> 137.94
B5: 3 | C5: ='还本付息'!E7 -> 0 | D5: ='还本付息'!H7 -> 99 | E5: =C5+D5 -> 99 | F5: =ROUND('收入成本'!P6,2) -> 231.87 | G5: =ROUND('收入成本'!P6*0.9,2) -> 208.68 | H5: =ROUND('收入成本'!AA6,2) -> 48.98 | I5: =ROUND('收入成本'!AA6*1.1,2) -> 53.88 | J5: =F5-H5 -> 182.89 | K5: =G5-H5 -> 159.7 | L5: =F5-I5 -> 177.99 | M5: =G5-I5 -> 154.8
B6: 4 | C6: ='还本付息'!E8 -> 0 | D6: ='还本付息'!H8 -> 99 | E6: =C6+D6 -> 99 | F6: =ROUND('收入成本'!P7,2) -> 252.95 | G6: =ROUND('收入成本'!P7*0.9,2) -> 227.66 | H6: =ROUND('收入成本'!AA7,2) -> 50.91 | I6: =ROUND('收入成本'!AA7*1.1,2) -> 56 | J6: =F6-H6 -> 202.04 | K6: =G6-H6 -> 176.75 | L6: =F6-I6 -> 196.95 | M6: =G6-I6 -> 171.66
B7: 5 | C7: ='还本付息'!E9 -> 0 | D7: ='还本付息'!H9 -> 99 | E7: =C7+D7 -> 99 | F7: =ROUND('收入成本'!P8,2) -> 274.02 | G7: =ROUND('收入成本'!P8*0.9,2) -> 246.62 | H7: =ROUND('收入成本'!AA8,2) -> 52.83 | I7: =ROUND('收入成本'!AA8*1.1,2) -> 58.11 | J7: =F7-H7 -> 221.19 | K7: =G7-H7 -> 193.79 | L7: =F7-I7 -> 215.91 | M7: =G7-I7 -> 188.51
B8: 6 | C8: ='还本付息'!E10 -> 0 | D8: ='还本付息'!H10 -> 99 | E8: =C8+D8 -> 99 | F8: =ROUND('收入成本'!P9,2) -> 295.11 | G8: =ROUND('收入成本'!P9*0.9,2) -> 265.6 | H8: =ROUND('收入成本'!AA9,2) -> 54.76 | I8: =ROUND('收入成本'!AA9*1.1,2) -> 60.24 | J8: =F8-H8 -> 240.35 | K8: =G8-H8 -> 210.84 | L8: =F8-I8 -> 234.87 | M8: =G8-I8 -> 205.36
B9: 7 | C9: ='还本付息'!E11 -> 0 | D9: ='还本付息'!H11 -> 99 | E9: =C9+D9 -> 99 | F9: =ROUND('收入成本'!P10,2) -> 339.59 | G9: =ROUND('收入成本'!P10*0.9,2) -> 305.63 | H9: =ROUND('收入成本'!AA10,2) -> 59.32 | I9: =ROUND('收入成本'!AA10*1.1,2) -> 65.25 | J9: =F9-H9 -> 280.27 | K9: =G9-H9 -> 246.31 | L9: =F9-I9 -> 274.34 | M9: =G9-I9 -> 240.38
B10: 8 | C10: ='还本付息'!E12 -> 0 | D10: ='还本付息'!H12 -> 99 | E10: =C10+D10 -> 99 | F10: =ROUND('收入成本'!P11,2) -> 339.59 | G10: =ROUND('收入成本'!P11*0.9,2) -> 305.63 | H10: =ROUND('收入成本'!AA11,2) -> 59.32 | I10: =ROUND('收入成本'!AA11*1.1,2) -> 65.25 | J10: =F10-H10 -> 280.27 | K10: =G10-H10 -> 246.31 | L10: =F10-I10 -> 274.34 | M10: =G10-I10 -> 240.38
B11: 9 | C11: ='还本付息'!E13 -> 0 | D11: ='还本付息'!H13 -> 99 | E11: =C11+D11 -> 99 | F11: =ROUND('收入成本'!P12,2) -> 339.59 | G11: =ROUND('收入成本'!P12*0.9,2) -> 305.63 | H11: =ROUND('收入成本'!AA12,2) -> 59.32 | I11: =ROUND('收入成本'!AA12*1.1,2) -> 65.25 | J11: =F11-H11 -> 280.27 | K11: =G11-H11 -> 246.31 | L11: =F11-I11 -> 274.34 | M11: =G11-I11 -> 240.38
B12: 10 | C12: ='还本付息'!E14 -> 0 | D12: ='还本付息'!H14 -> 99 | E12: =C12+D12 -> 99 | F12: =ROUND('收入成本'!P13,2) -> 339.59 | G12: =ROUND('收入成本'!P13*0.9,2) -> 305.63 | H12: =ROUND('收入成本'!AA13,2) -> 59.32 | I12: =ROUND('收入成本'!AA13*1.1,2) -> 65.25 | J12: =F12-H12 -> 280.27 | K12: =G12-H12 -> 246.31 | L12: =F12-I12 -> 274.34 | M12: =G12-I12 -> 240.38
B13: 11 | C13: ='还本付息'!E15 -> 0 | D13: ='还本付息'!H15 -> 99 | E13: =C13+D13 -> 99 | F13: =ROUND('收入成本'!P14,2) -> 339.59 | G13: =ROUND('收入成本'!P14*0.9,2) -> 305.63 | H13: =ROUND('收入成本'!AA14,2) -> 59.32 | I13: =ROUND('收入成本'!AA14*1.1,2) -> 65.25 | J13: =F13-H13 -> 280.27 | K13: =G13-H13 -> 246.31 | L13: =F13-I13 -> 274.34 | M13: =G13-I13 -> 240.38
B14: 12 | C14: ='还本付息'!E16 -> 0 | D14: ='还本付息'!H16 -> 99 | E14: =C14+D14 -> 99 | F14: =ROUND('收入成本'!P15,2) -> 366.03 | G14: =ROUND('收入成本'!P15*0.9,2) -> 329.43 | H14: =ROUND('收入成本'!AA15,2) -> 62.21 | I14: =ROUND('收入成本'!AA15*1.1,2) -> 68.43 | J14: =F14-H14 -> 303.82 | K14: =G14-H14 -> 267.22 | L14: =F14-I14 -> 297.6 | M14: =G14-I14 -> 261
B15: 13 | C15: ='还本付息'!E17 -> 0 | D15: ='还本付息'!H17 -> 99 | E15: =C15+D15 -> 99 | F15: =ROUND('收入成本'!P16,2) -> 366.03 | G15: =ROUND('收入成本'!P16*0.9,2) -> 329.43 | H15: =ROUND('收入成本'!AA16,2) -> 62.21 | I15: =ROUND('收入成本'!AA16*1.1,2) -> 68.43 | J15: =F15-H15 -> 303.82 | K15: =G15-H15 -> 267.22 | L15: =F15-I15 -> 297.6 | M15: =G15-I15 -> 261
... B32: 30 | C32: ='还本付息'!E34 -> 2200 | D32: ='还本付息'!H34 -> 99 | E32: =C32+D32 -> 2299 | F32: =ROUND('收入成本'!P33,2) -> 459.65 | G32: =ROUND('收入成本'!P33*0.9,2) -> 413.69 | H32: =ROUND('收入成本'!AA33,2) -> 72.56 | I32: =ROUND('收入成本'!AA33*1.1,2) -> 79.82 | J32: =F32-H32 -> 387.09 | K32: =G32-H32 -> 341.13 | L32: =F32-I32 -> 379.83 | M32: =G32-I32 -> 333.87
B33: 31
B34: 32 | C34: ='还本付息'!E36 -> 0 | D34: ='还本付息'!H36 -> 0 | E34: =C34+D34 -> 0
B35: 33 | C35: ='还本付息'!E37 -> 0 | D35: ='还本付息'!H37 -> 0 | E35: =C35+D35 -> 0 | F35: =ROUND('收入成本'!P34,2) -> 0 | G35: =ROUND('收入成本'!P34*0.9,2) -> 0 | H35: =ROUND('收入成本'!AA34,2) -> 0 | I35: =ROUND('收入成本'!AA34*1.1,2) -> 0 | J35: =F35-H35 -> 0 | K35: =G35-H35 -> 0 | L35: =F35-I35 -> 0 | M35: =G35-I35 -> 0
B36: 合计 | C36: 2200 | D36: =SUM(D3:D35) -> 2970 | E36: =SUM(E3:E35) -> 5170 | F36: =SUM(F3:F35) -> 10728.24 | G36: =SUM(G3:G35) -> 9655.48 | H36: =SUM(H3:H35) -> 2536.53 | I36: =SUM(I3:I35) -> 2790.22 | J36: =SUM(J3:J35) -> 8191.71 | K36: =SUM(K3:K35) -> 7118.95 | ... M36: =SUM(M3:M35) -> 6865.26
B37: 本息覆盖率 | J37: =ROUND(J36/$E$36,2) -> 1.58 | K37: =ROUND(K36/$E$36,2) -> 1.38 | L37: =ROUND(L36/$E$36,2) -> 1.54 | M37: =ROUND(M36/$E$36,2) -> 1.33
C38: ☝输入发债额试算

Sheet 资金流入流出平衡表
A1: 项目资金流入流出平衡
AI2: 单位：万元
A3: 项目 | B3: 第1年 | C3: 第2年 | D3: 第3年 | E3: 第4年 | F3: 第5年 | G3: 第6年 | H3: 第7年 | I3: 第8年 | J3: 第9年 | K3: 第10年 | L3: 第11年 | M3: 第12年 | N3: 第13年 | O3: 第14年 | P3: 第15年 | Q3: 第16年 | R3: 第17年 | S3: 第18年 | T3: 第19年 | U3: 第20年 | V3: 第21年 | W3: 第22年 | X3: 第23年 | Y3: 第24年 | Z3: 第25年 | AA3: 第26年 | AB3: 第27年 | AC3: 第28年 | AD3: 第29年 | AE3: 第30年 | AF3: 第31年 | AG3: 第32年 | AH3: 第33年 | AI3: 合计
A4: 一、项目现金流入 | B4: =B5+B13 -> 4509.9 | C4: =C5+C13 -> 700.89 | D4: =D5+D13 -> 231.87 | E4: =E5+E13 -> 252.95 | F4: =F5+F13 -> 274.02 | G4: =G5+G13 -> 295.11 | H4: =H5+H13 -> 339.59 | I4: =I5+I13 -> 339.59 | ... AH4: =AH5+AH13 -> #N/A | AI4: =SUM(B4:AE4) -> 15728.24
A5: 1.业务活动现金流入 | B5: =SUM(B6:B8) -> 0 | C5: =SUM(C6:C8) -> 210.79 | D5: =SUM(D6:D12) -> 231.87 | E5: =SUM(E6:E12) -> 252.95 | F5: =SUM(F6:F12) -> 274.02 | G5: =SUM(G6:G12) -> 295.11 | H5: =SUM(H6:H12) -> 339.59 | I5: =SUM(I6:I12) -> 339.59 | J5: =SUM(J6:J12) -> 339.59 | K5: =SUM(K6:K12) -> 339.59 | ... AH5: =SUM(AH6:AH12) -> #N/A | AI5: =SUM(B5:AE5) -> 10728.24
A6: =CONCATENATE("其中：",'收入成本'!C1,"收入") -> 其中：污水处理收入收入 | B6: {=TRANSPOSE('收入成本'!G4:G34)} -> 0 | C6: 191.63 | D6: 210.79 | E6: 229.95 | F6: 249.11 | G6: 268.28 | H6: 307.97 | I6: 307.97 | J6: 307.97 | K6: 307.97 | L6: 307.97 | M6: 330.96 | N6: 330.96 | O6: 330.96 | P6: 330.96 | Q6: 330.96 | R6: 355.6 | S6: 355.6 | T6: 355.6 | U6: 355.6 | V6: 355.6 | W6: 382.7 | X6: 382.7 | Y6: 382.7 | Z6: 382.7 | AA6: 382.7 | AB6: 413.09 | AC6: 413.09 | AD6: 413.09 | AE6: 413.09 | AF6: 0 | AG6: #N/A | AH6: #N/A | AI6: =SUM(B6:AE6) -> 9688.27
A7: =CONCATENATE('收入成本'!H1,"收入") -> 中水收入收入 | B7: {=TRANSPOSE('收入成本'!K4:K34)} -> 0 | C7: 19.16 | D7: 21.08 | E7: 23 | F7: 24.91 | G7: 26.83 | H7: 31.62 | I7: 31.62 | J7: 31.62 | K7: 31.62 | L7: 31.62 | M7: 35.07 | N7: 35.07 | O7: 35.07 | P7: 35.07 | Q7: 35.07 | R7: 38.52 | S7: 38.52 | T7: 38.52 | U7: 38.52 | V7: 38.52 | W7: 42.54 | X7: 42.54 | Y7: 42.54 | Z7: 42.54 | AA7: 42.54 | AB7: 46.56 | AC7: 46.56 | AD7: 46.56 | AE7: 46.56 | AF7: 0 | AG7: #N/A | AH7: #N/A | AI7: =SUM(B7:AE7) -> 1039.97
A8: =CONCATENATE('收入成本'!L1) -> 污泥处理费 | B8: {=TRANSPOSE('收入成本'!O4:O34)} -> 0 | C8: 0 | D8: 0 | E8: 0 | F8: 0 | G8: 0 | H8: 0 | I8: 0 | J8: 0 | K8: 0 | L8: 0 | M8: 0 | N8: 0 | O8: 0 | P8: 0 | Q8: 0 | R8: 0 | S8: 0 | T8: 0 | U8: 0 | V8: 0 | W8: 0 | X8: 0 | Y8: 0 | Z8: 0 | AA8: 0 | AB8: 0 | AC8: 0 | AD8: 0 | AE8: 0 | AF8: 0 | AG8: #N/A | AH8: #N/A | AI8: =SUM(B8:AE8) -> 0
AI9: =SUM(B9:AE9) -> 0
AI10: =SUM(B10:AE10) -> 0
AI11: =SUM(B11:AE11) -> 0
AI12: =SUM(B12:AE12) -> 0
A13: 2.融资活动现金流入 | B13: =SUM(B14:B15) -> 4509.9 | C13: =SUM(C14:C15) -> 490.1 | D13: =SUM(D14:D15) -> 0 | E13: =SUM(E14:E15) -> 0 | F13: =SUM(F14:F15) -> 0 | G13: =SUM(G14:G15) -> 0 | H13: =SUM(H14:H15) -> 0 | I13: =SUM(I14:I15) -> 0 | ... AH13: =SUM(AH14:AH15) -> 0 | AI13: =SUM(B13:AE13) -> 5000
A14: 其中：专项债券资金 | B14: ='分年计划及建设期利息'!E23 -> 2200 | C14: ='分年计划及建设期利息'!F23 -> 0 | D14: ='分年计划及建设期利息'!G23 -> 0 | E14: ='分年计划及建设期利息'!H23 -> 0 | AI14: =SUM(B14:AE14) -> 2200
A15: 资本金投入 | B15: ='分年计划及建设期利息'!E22 -> 2309.9 | C15: ='分年计划及建设期利息'!F22 -> 490.1 | D15: ='分年计划及建设期利息'!G22 -> 0 | E15: ='分年计划及建设期利息'!H22 -> 0 | AI15: =SUM(B15:AE15) -> 2800
A16: 二、项目现金流出 | B16: =B17+B21 -> 4509.9 | C16: =C17+C21 -> 146.06 | D16: =D17+D21 -> 147.98 | E16: =E17+E21 -> 149.91 | F16: =F17+F21 -> 151.83 | G16: =G17+G21 -> 153.76 | H16: =H17+H21 -> 158.32 | I16: =I17+I21 -> 158.32 | ... AH16: =AH17+AH21 -> #N/A | AI16: =SUM(B16:AE16) -> 12117.43
A17: 1.业务活动现金流出 | B17: =SUM(B18:B20) -> 4408.7 | C17: =SUM(C18:C20) -> 47.06 | D17: =SUM(D18:D20) -> 48.98 | E17: =SUM(E18:E20) -> 50.91 | F17: =SUM(F18:F20) -> 52.83 | G17: =SUM(G18:G20) -> 54.76 | H17: =SUM(H18:H20) -> 59.32 | I17: =SUM(I18:I20) -> 59.32 | ... AH17: =SUM(AH18:AH20) -> #N/A | AI17: =SUM(B17:AE17) -> 6945.23
A18: 其中：项目建设流出 | B18: ='分年计划及建设期利息'!E15-B21 -> 4408.7 | AI18: =SUM(B18:AE18) -> 4408.7
A19: 相关税费流出 | B19: {=TRANSPOSE('税费计算'!P5:P36)} -> 0 | C19: 0 | D19: 0 | E19: 0 | F19: 0 | G19: 0 | H19: 0 | I19: 0 | J19: 0 | K19: 0 | L19: 0 | M19: 0 | N19: 0 | O19: 0 | P19: 0 | Q19: 0 | R19: 0 | S19: 0 | T19: 0 | U19: 0 | V19: 0 | W19: 0 | X19: 0 | Y19: 0 | Z19: 10.57 | AA19: 25.79 | AB19: 28.01 | AC19: 28.01 | AD19: 28.01 | AE19: 28.01 | AF19: 0 | AG19: 0 | AH19: #N/A | AI19: =SUM(B19:AE19) -> 148.4
A20: 业务成本流出 | B20: {=TRANSPOSE('收入成本'!AB4:AB34)} -> 0 | C20: 47.06 | D20: 48.98 | E20: 50.91 | F20: 52.83 | G20: 54.76 | H20: 59.32 | I20: 59.32 | J20: 59.32 | K20: 59.32 | L20: 59.32 | M20: 62.21 | N20: 62.21 | O20: 344.66 | P20: 344.66 | Q20: 62.21 | R20: 65.36 | S20: 65.36 | T20: 65.36 | U20: 65.36 | V20: 65.36 | W20: 68.8 | X20: 68.8 | Y20: 68.8 | Z20: 68.8 | AA20: 68.8 | AB20: 72.56 | AC20: 72.56 | AD20: 72.56 | AE20: 72.56 | AF20: 0 | AG20: #N/A | AH20: #N/A | AI20: =SUM(B20:AE20) -> 2388.13
A21: 2.融资活动现金流出 | B21: =SUM(B22:B24) -> 101.2 | C21: =SUM(C22:C24) -> 99 | D21: =SUM(D22:D24) -> 99 | E21: =SUM(E22:E24) -> 99 | F21: =SUM(F22:F24) -> 99 | G21: =SUM(G22:G24) -> 99 | H21: =SUM(H22:H24) -> 99 | I21: =SUM(I22:I24) -> 99 | ... AF21: =SUM(AF22:AF24) -> 0 | AI21: =SUM(B21:AE21) -> 5172.2
A22: 其中：债券发行费用 | B22: =B14*0.1% -> 2.2 | C22: =C14*0.1% -> 0 | D22: =D14*0.1% -> 0 | E22: =E14*0.1% -> 0 | F22: =F14*0.1% -> 0 | G22: =G14*0.1% -> 0 | H22: =H14*0.1% -> 0 | I22: =I14*0.1% -> 0 | ... AH22: =AH14*0.1% -> 0 | AI22: =SUM(B22:AE22) -> 2.2
A23: 偿还债券本金 | B23: {=TRANSPOSE('还本付息'!E5:E37)} -> 0 | C23: 0 | D23: 0 | E23: 0 | F23: 0 | G23: 0 | H23: 0 | I23: 0 | J23: 0 | K23: 0 | L23: 0 | M23: 0 | N23: 0 | O23: 0 | P23: 0 | Q23: 0 | R23: 0 | S23: 0 | T23: 0 | U23: 0 | V23: 0 | W23: 0 | X23: 0 | Y23: 0 | Z23: 0 | AA23: 0 | AB23: 0 | AC23: 0 | AD23: 0 | AE23: 2200 | AF23: 0 | AG23: 0 | AH23: 0 | AI23: =SUM(B23:AE23) -> 2200
A24: 支付债券利息 | B24: {=TRANSPOSE('还本付息'!H5:H37)} -> 99 | C24: 99 | D24: 99 | E24: 99 | F24: 99 | G24: 99 | H24: 99 | I24: 99 | J24: 99 | K24: 99 | L24: 99 | M24: 99 | N24: 99 | O24: 99 | P24: 99 | Q24: 99 | R24: 99 | S24: 99 | T24: 99 | U24: 99 | V24: 99 | W24: 99 | X24: 99 | Y24: 99 | Z24: 99 | AA24: 99 | AB24: 99 | AC24: 99 | AD24: 99 | AE24: 99 | AF24: 0 | AG24: 0 | AH24: 0 | AI24: =SUM(B24:AE24) -> 2970
A25: 项目期初现金余额 | C25: =B27 -> 0 | D25: =C27 -> 554.83 | E25: =D27 -> 638.72 | F25: =E27 -> 741.76 | G25: =F27 -> 863.95 | H25: =G27 -> 1005.3 | I25: =H27 -> 1186.57 | J25: =I27 -> 1367.84 | ... AH25: =AG27 -> #N/A
A26: 项目期内现金变动 | B26: =B4-B16 -> 0 | C26: =C4-C16 -> 554.83 | D26: =D4-D16 -> 83.89 | E26: =E4-E16 -> 103.04 | F26: =F4-F16 -> 122.19 | G26: =G4-G16 -> 141.35 | H26: =H4-H16 -> 181.27 | I26: =I4-I16 -> 181.27 | ... AH26: =AH4-AH16 -> #N/A | AI26: =SUM(B26:AE26) -> 3610.81
A27: 项目期末现金余额 | B27: =B25+B26 -> 0 | C27: =C25+C26 -> 554.83 | D27: =D25+D26 -> 638.72 | E27: =E25+E26 -> 741.76 | F27: =F25+F26 -> 863.95 | G27: =G25+G26 -> 1005.3 | H27: =H25+H26 -> 1186.57 | I27: =I25+I26 -> 1367.84 | ... AH27: =AH25+AH26 -> #N/A | AI27: =AE27 -> 3610.81

Sheet Sheet2
A1: 项目 | B1: 第21年 | C1: 第22年 | D1: 第23年 | E1: 第24年 | F1: 第25年 | G1: 第26年 | H1: 第27年 | I1: 第28年 | J1: 第29年 | K1: 第30年 | L1: 合计
A2: 一、项目现金流入 | B2: 394.12 | C2: 425.24 | D2: 425.24 | E2: 425.24 | F2: 425.24 | G2: 425.24 | H2: 459.65 | I2: 459.65 | J2: 459.65 | K2: 459.65 | L2: 15728.24
A3: 1.业务活动现金流入 | B3: 394.12 | C3: 425.24 | D3: 425.24 | E3: 425.24 | F3: 425.24 | G3: 425.24 | H3: 459.65 | I3: 459.65 | J3: 459.65 | K3: 459.65 | L3: 10728.24
A4: 其中：污水处理收入收入 | B4: 355.6 | C4: 382.7 | D4: 382.7 | E4: 382.7 | F4: 382.7 | G4: 382.7 | H4: 413.09 | I4: 413.09 | J4: 413.09 | K4: 413.09 | L4: 9688.27
A5: 中水收入收入 | B5: 38.52 | C5: 42.54 | D5: 42.54 | E5: 42.54 | F5: 42.54 | G5: 42.54 | H5: 46.56 | I5: 46.56 | J5: 46.56 | K5: 46.56 | L5: 1039.97
A6: 污泥处理费 | B6: 0 | C6: 0 | D6: 0 | E6: 0 | F6: 0 | G6: 0 | H6: 0 | I6: 0 | J6: 0 | K6: 0 | L6: 0
A7: 2.融资活动现金流入 | B7: 0 | C7: 0 | D7: 0 | E7: 0 | F7: 0 | G7: 0 | H7: 0 | I7: 0 | J7: 0 | K7: 0 | L7: 5000
A8: 其中：专项债券资金 | L8: 2200
A9: 资本金投入 | L9: 2800
A10: 二、项目现金流出 | B10: 164.36 | C10: 167.8 | D10: 167.8 | E10: 167.8 | F10: 178.37 | G10: 193.59 | H10: 199.57 | I10: 199.57 | J10: 199.57 | K10: 2399.57 | L10: 12117.43
A11: 1.业务活动现金流出 | B11: 65.36 | C11: 68.8 | D11: 68.8 | E11: 68.8 | F11: 79.37 | G11: 94.59 | H11: 100.57 | I11: 100.57 | J11: 100.57 | K11: 100.57 | L11: 6945.23
A12: 其中：项目建设流出 | L12: 4408.7
A13: 相关税费流出 | B13: 0 | C13: 0 | D13: 0 | E13: 0 | F13: 10.57 | G13: 25.79 | H13: 28.01 | I13: 28.01 | J13: 28.01 | K13: 28.01 | L13: 148.4
A14: 业务成本流出 | B14: 65.36 | C14: 68.8 | D14: 68.8 | E14: 68.8 | F14: 68.8 | G14: 68.8 | H14: 72.56 | I14: 72.56 | J14: 72.56 | K14: 72.56 | L14: 2388.13
A15: 2.融资活动现金流出 | B15: 99 | C15: 99 | D15: 99 | E15: 99 | F15: 99 | G15: 99 | H15: 99 | I15: 99 | J15: 99 | K15: 2299 | L15: 5172.2
A16: 其中：债券发行费用 | B16: 0 | C16: 0 | D16: 0 | E16: 0 | F16: 0 | G16: 0 | H16: 0 | I16: 0 | J16: 0 | K16: 0 | L16: 2.2
A17: 偿还债券本金 | B17: 0 | C17: 0 | D17: 0 | E17: 0 | F17: 0 | G17: 0 | H17: 0 | I17: 0 | J17: 0 | K17: 2200 | L17: 2200
A18: 支付债券利息 | B18: 99 | C18: 99 | D18: 99 | E18: 99 | F18: 99 | G18: 99 | H18: 99 | I18: 99 | J18: 99 | K18: 99 | L18: 2970
A19: 项目期初现金余额 | B19: 3289.89 | C19: 3519.65 | D19: 3777.09 | E19: 4034.53 | F19: 4291.97 | G19: 4538.84 | H19: 4770.49 | I19: 5030.57 | J19: 5290.65 | K19: 5550.73
A20: 项目期内现金变动 | B20: 229.76 | C20: 257.44 | D20: 257.44 | E20: 257.44 | F20: 246.87 | G20: 231.65 | H20: 260.08 | I20: 260.08 | J20: 260.08 | K20: -1939.92 | L20: 3610.81
A21: 项目期末现金余额 | B21: 3519.65 | C21: 3777.09 | D21: 4034.53 | E21: 4291.97 | F21: 4538.84 | G21: 4770.49 | H21: 5030.57 | I21: 5290.65 | J21: 5550.73 | K21: 3610.81 | L21: 3610.81

Sheet Sheet1
A1: 项目 | B1: 第21年 | C1: 第22年 | D1: 第23年 | E1: 第24年 | F1: 第25年 | G1: 第26年 | H1: 第27年 | I1: 第28年 | J1: 第29年 | K1: 第30年 | L1: 第31年 | M1: 第32年 | N1: 第33年 | O1: 合计
A2: 一、项目现金流入 | B2: 394.12 | C2: 425.24 | D2: 425.24 | E2: 425.24 | F2: 425.24 | G2: 425.24 | H2: 459.65 | I2: 459.65 | J2: 459.65 | K2: 459.65 | L2: 0 | M2: #N/A | N2: #N/A | O2: 15728.24
A3: 1.业务活动现金流入 | B3: 394.12 | C3: 425.24 | D3: 425.24 | E3: 425.24 | F3: 425.24 | G3: 425.24 | H3: 459.65 | I3: 459.65 | J3: 459.65 | K3: 459.65 | L3: 0 | M3: #N/A | N3: #N/A | O3: 10728.24
A4: 其中：污水处理收入收入 | B4: 355.6 | C4: 382.7 | D4: 382.7 | E4: 382.7 | F4: 382.7 | G4: 382.7 | H4: 413.09 | I4: 413.09 | J4: 413.09 | K4: 413.09 | L4: 0 | M4: #N/A | N4: #N/A | O4: 9688.27
A5: 中水收入收入 | B5: 38.52 | C5: 42.54 | D5: 42.54 | E5: 42.54 | F5: 42.54 | G5: 42.54 | H5: 46.56 | I5: 46.56 | J5: 46.56 | K5: 46.56 | L5: 0 | M5: #N/A | N5: #N/A | O5: 1039.97
A6: 污泥处理费 | B6: 0 | C6: 0 | D6: 0 | E6: 0 | F6: 0 | G6: 0 | H6: 0 | I6: 0 | J6: 0 | K6: 0 | L6: 0 | M6: #N/A | N6: #N/A | O6: 0
A7: 2.融资活动现金流入 | O7: 0
A8: 其中：专项债券资金 | O8: 0
A9: 资本金投入 | O9: 0
A10: 二、项目现金流出 | O10: 0
A11: 1.业务活动现金流出 | B11: 0 | C11: 0 | D11: 0 | E11: 0 | F11: 0 | G11: 0 | H11: 0 | I11: 0 | J11: 0 | K11: 0 | L11: 0 | M11: 0 | N11: 0 | O11: 5000
A12: 其中：项目建设流出 | O12: 2200
A13: 相关税费流出 | O13: 2800
A14: 业务成本流出 | B14: 164.36 | C14: 167.8 | D14: 167.8 | E14: 167.8 | F14: 178.37 | G14: 193.59 | H14: 199.57 | I14: 199.57 | J14: 199.57 | K14: 2399.57 | L14: 0 | M14: #N/A | N14: #N/A | O14: 12117.43
A15: 2.融资活动现金流出 | B15: 65.36 | C15: 68.8 | D15: 68.8 | E15: 68.8 | F15: 79.37 | G15: 94.59 | H15: 100.57 | I15: 100.57 | J15: 100.57 | K15: 100.57 | L15: 0 | M15: #N/A | N15: #N/A | O15: 6945.23
A16: 其中：债券发行费用 | O16: 4408.7
A17: 偿还债券本金 | B17: 0 | C17: 0 | D17: 0 | E17: 0 | F17: 10.57 | G17: 25.79 | H17: 28.01 | I17: 28.01 | J17: 28.01 | K17: 28.01 | L17: 0 | M17: 0 | N17: #N/A | O17: 148.4
A18: 支付债券利息 | B18: 65.36 | C18: 68.8 | D18: 68.8 | E18: 68.8 | F18: 68.8 | G18: 68.8 | H18: 72.56 | I18: 72.56 | J18: 72.56 | K18: 72.56 | L18: 0 | M18: #N/A | N18: #N/A | O18: 2388.13
A19: 项目期初现金余额 | B19: 99 | C19: 99 | D19: 99 | E19: 99 | F19: 99 | G19: 99 | H19: 99 | I19: 99 | J19: 99 | K19: 2299 | L19: 0 | O19: 5172.2
A20: 项目期内现金变动 | B20: 0 | C20: 0 | D20: 0 | E20: 0 | F20: 0 | G20: 0 | H20: 0 | I20: 0 | J20: 0 | K20: 0 | L20: 0 | M20: 0 | N20: 0 | O20: 2.2
A21: 项目期末现金余额 | B21: 0 | C21: 0 | D21: 0 | E21: 0 | F21: 0 | G21: 0 | H21: 0 | I21: 0 | J21: 0 | K21: 2200 | L21: 0 | M21: 0 | N21: 0 | O21: 2200
B22: 99 | C22: 99 | D22: 99 | E22: 99 | F22: 99 | G22: 99 | H22: 99 | I22: 99 | J22: 99 | K22: 99 | L22: 0 | M22: 0 | N22: 0 | O22: 2970
B23: 3289.89 | C23: 3519.65 | D23: 3777.09 | E23: 4034.53 | F23: 4291.97 | G23: 4538.84 | H23: 4770.49 | I23: 5030.57 | J23: 5290.65 | K23: 5550.73 | L23: 3610.81 | M23: 3610.81 | N23: #N/A
B24: 229.76 | C24: 257.44 | D24: 257.44 | E24: 257.44 | F24: 246.87 | G24: 231.65 | H24: 260.08 | I24: 260.08 | J24: 260.08 | K24: -1939.92 | L24: 0 | M24: #N/A | N24: #N/A | O24: 3610.81
B25: 3519.65 | C25: 3777.09 | D25: 4034.53 | E25: 4291.97 | F25: 4538.84 | G25: 4770.49 | H25: 5030.57 | I25: 5290.65 | J25: 5550.73 | K25: 3610.81 | L25: 3610.81 | M25: #N/A | N25: #N/A | O25: 3610.81

Sheet 固定资产折旧
A1: 序号 | B1: 项 目 | C1: 折旧年限 | D1: 合 计 | E1: 计 算 期
C2: (年) | E2: 4 | F2: =E2+1 -> 5 | G2: =F2+1 -> 6 | H2: =G2+1 -> 7 | I2: =H2+1 -> 8 | J2: =I2+1 -> 9 | K2: =J2+1 -> 10 | L2: =K2+1 -> 11 | M2: =L2+1 -> 12 | ... Q2: =P2+1 -> 16
A3: 1 | B3: 房屋、建筑物（新增） | C3: 30
A4: 1.1 | B4: 原值 | E4: =ROUND(('税费计算'!V4+'税费计算'!V7+'税费计算'!V8)*0.95,2) -> 3385.31
A5: 1.2 | B5: 当期折旧费 | E5: =ROUND($E$4/$C$3,2) -> 112.84 | F5: =E5 -> 112.84 | G5: =F5 -> 112.84 | H5: =G5 -> 112.84 | I5: =H5 -> 112.84 | J5: =I5 -> 112.84 | K5: =J5 -> 112.84 | L5: =K5 -> 112.84 | M5: =L5 -> 112.84 | ... Q5: =P5 -> 112.84
A6: 1.3 | B6: 净值 | E6: =E4-E5 -> 3272.47 | F6: =E6-F5 -> 3159.63 | G6: =F6-G5 -> 3046.79 | H6: =G6-H5 -> 2933.95 | I6: =H6-I5 -> 2821.11 | J6: =I6-J5 -> 2708.27 | K6: =J6-K5 -> 2595.43 | L6: =K6-L5 -> 2482.59 | M6: =L6-M5 -> 2369.75 | ... Q6: =P6-Q5 -> 1918.39
A7: 2 | B7: 机器设备 | C7: 15
A8: 2.1 | B8: 原值 | E8: =ROUND('税费计算'!V5,2) -> 499.91
A9: 2.2 | B9: 当期折旧费 | E9: =ROUND($E$8/$C$7,2) -> 33.33 | F9: =E9 -> 33.33 | G9: =F9 -> 33.33 | H9: =G9 -> 33.33 | I9: =H9 -> 33.33 | J9: =I9 -> 33.33 | K9: =J9 -> 33.33 | L9: =K9 -> 33.33 | M9: =L9 -> 33.33 | ... Q9: =P9 -> 33.33
A10: 2.3 | B10: 净值 | E10: =E8-E9 -> 466.58 | F10: =E10-F9 -> 433.25 | G10: =F10-G9 -> 399.92 | H10: =G10-H9 -> 366.59 | I10: =H10-I9 -> 333.26 | J10: =I10-J9 -> 299.93 | K10: =J10-K9 -> 266.6 | L10: =K10-L9 -> 233.27 | M10: =L10-M9 -> 199.94 | ... Q10: =P10-Q9 -> 66.62
A11: 3 | B11: 属于固定资产的其他费用 | C11: 20
A12: 3.1 | B12: 原值 | E12: =ROUND('税费计算'!V6,2) -> 528.13
A13: 3.2 | B13: 当期折旧费 | E13: =ROUND(E12/$C$11,2) -> 26.41 | F13: =E13 -> 26.41 | G13: =F13 -> 26.41 | H13: =G13 -> 26.41 | I13: =H13 -> 26.41 | J13: =I13 -> 26.41 | K13: =J13 -> 26.41 | L13: =K13 -> 26.41 | M13: =L13 -> 26.41 | ... Q13: =P13 -> 26.41
A14: 3.3 | B14: 净值 | E14: =E12-E13 -> 501.72 | F14: =E14-F13 -> 475.31 | G14: =F14-G13 -> 448.9 | H14: =G14-H13 -> 422.49 | I14: =H14-I13 -> 396.08 | J14: =I14-J13 -> 369.67 | K14: =J14-K13 -> 343.26 | L14: =K14-L13 -> 316.85 | M14: =L14-M13 -> 290.44 | ... Q14: =P14-Q13 -> 184.8
A15: 4 | B15: 固定资产合计
A16: 4.1 | B16: 原值 | E16: =E4+E8+E12 -> 4413.35
A17: 4.2 | B17: 当期折旧费 | E17: =E5+E9+E13 -> 172.58 | F17: =F5+F9+F13 -> 172.58 | G17: =G5+G9+G13 -> 172.58 | H17: =H5+H9+H13 -> 172.58 | I17: =I5+I9+I13 -> 172.58 | J17: =J5+J9+J13 -> 172.58 | K17: =K5+K9+K13 -> 172.58 | L17: =L5+L9+L13 -> 172.58 | ... Q17: =Q5+Q9+Q13 -> 172.58
A18: 4.3 | B18: 净值 | E18: =E6+E10+E14 -> 4240.77 | F18: =F6+F10+F14 -> 4068.19 | G18: =G6+G10+G14 -> 3895.61 | H18: =H6+H10+H14 -> 3723.03 | I18: =I6+I10+I14 -> 3550.45 | J18: =J6+J10+J14 -> 3377.87 | K18: =K6+K10+K14 -> 3205.29 | L18: =L6+L10+L14 -> 3032.71 | ... Q18: =Q6+Q10+Q14 -> 2169.81

Sheet 工程建设其他费细则说明
A1: 工程建设其他费
A2: 序号 | B2: 项目 | C2: 内容 | D2: 计算方式 | E2: 参考取费标准 | F2: 地区折扣 | G2: 备注
F3: 南昌市
A4: 一 | B4: 建设单位管理费 | C4: 从筹建之日起至办理竣工财务决算之日止发生的管理性质的支出，包括工作人员薪酬及相关费用、办公费、办公场地租用费、差旅交通费、劳动保护费、工具用具使用费、固定资产使用费、招募生产工人费、技术图书资料费（含软件）、业务招待费、竣工验收费和其他管理性质开支 | D4: 工程费用×建设单位管理费费率 | E4: 财建[2016]504号 | F4: 按80%计取
A5: 二 | B5: 用地与工程准备费
A6: （一） | B6: 土地使用费和补偿费 | C6: 此部分不考虑
A7: 1 | B7: 征地补偿费
A8: 1.1 | B8: 土地补偿费
A9: 1.2 | B9: 青苗补偿费和地上附着物补偿费
A10: 1.3 | B10: 安置补助费
A11: 1.4 | B11: 耕地开垦费和森林植被恢复费
A12: 1.5 | B12: 生态补偿与压覆矿产资源补偿费
A13: 1.6 | B13: 其他补偿费
A14: 2 | B14: 拆迁补偿费用
A15: 2.1 | B15: 拆迁补偿金
A16: 2.2 | B16: 迁移补偿费
A17: 3 | B17: 土地出让金
A18: （二） | B18: 场地准备及临时设施费 | C18: 场地准备费是使工程项目的建设场地达到开工条件，由建设单位组织进行的场地平整等准备工作而发生的费用。 临时设施费是指建设单位为满足施工建设需要而提供的未列入工程费用的临时水、电、路、信、气、热等工程和临时仓库等建（构）筑物的建设、维修、拆除、摊销费用或租赁费用，以及货物、码头租赁等费用 | D18: 工程费用×费率+拆除清理费 | E18: 建标〔2011〕1号 | F18: 按照“洪府发[2004]3号”的60%计取
A19: 三 | B19: 市政公用配套设施费 | C19: 使用市政公用设施的建设项目，按照项目所在地省级人民政府有关规定建设或缴纳的市政公用设施建设配套费用，可能发生的公用供水、供气、供热设施建设的贴补费用、供电多回路高可靠性供电费用以及绿化工程补偿费用。 | E19: 《南昌市市政公用设施配套费征收管理办法实施细则》计取，计取金额不包含“可能发生的公用供水、供气、供热设施建设的贴补费用、供电多回路高可靠性供电费用以及绿化工程补偿费用”
A20: 四 | B20: 技术服务费
A21: （一） | B21: 前期工作咨询费 | C21: 建设项目前期工作的咨询收费。包括：建设项目专题研究、编制目建议书、可行性研究报告,以及其他与建设项目前期工作有关的咨询服务收费。 | E21: 计价格［1999］1283号 | F21: 按照“洪府发[2004]3号”的60%计取
A22: （二） | B22: 专项评价费
A23: 1 | B23: 环境影响评价费 | E23: 计价格[2002]125 号 | F23: 洪府发[2004]3号”的70%计取
A24: 2 | B24: 安全预评价费 | E24: 江西省安全评价收费指导价格（试行） | F24: 洪府发[2004]3号”的70%计取
A25: 3 | B25: 职业病危害预评价费
A26: 4 | B26: 地质灾害危险性评价费
A27: 5 | B27: 水土保持评价费 | E27: 保监[2005]22 号 2005 年 6 月 17 日 | F27: “洪府发[2004]3号”的70%计取
A28: 6 | B28: 压覆矿产资源评价费
A29: 7 | B29: 节能评估费 | E29: 沪发改环资（2012）043号 | F29: “洪府发[2004]3号”的70%计取
A30: 8 | B30: 危险与可操作性分析及安全完整性评价费
A31: 9 | B31: 社会稳定风险评估费 | E31: 赣评审字[2015]70 号
A32: 10 | B32: 劳动安全卫生评审费 | C32: 按照原劳动部《建设项目（工程）劳动安全卫生监察规定》和《建设项目（工程）劳动安全卫生评价管理办法》的规定，为分析建设项目存在的职业危害、危害因素的种类和危害成都，并提出先进、科学、合理可行的劳动安全卫生技术和管理对策的所需费用。 | D32: 工程费用X(0.1%-0.5%) | E32: 建标〔2011〕1号 | F32: 洪府发[2004]3号”的70%计取
A33: 11 | B33: 交通影响评估费 | E33: 5万平米（含）以下，2元/平米，5-20万平米，2元/平米，20-100万平米，1.5元/平米，100-200万平米，1.0元/平米；大于200万平米的，0.8元/平米
A34: 12 | B34: 其他专项评价费
A35: （三） | B35: 勘察设计费
A36: 1 | B36: 勘察费 | D36: 工程费用的0.8%-1.1% | E36: 建标〔2011〕1号
A37: 2 | B37: 设计费 | E37: 计价格[2002]10号 | F37: 工程设计费参照执行“计价格[2002]10号”标准，并按照投资5000万元以下按85%、投资5000万元以上（含）按80%计取。
A38: （四） | B38: 工程监理费 | C38: 指委托工程监理单位对工程实施监理工作所需费用。包括：施工监理和勘察、设计、保修等阶段监理。 | E38: 发改价格[2007]670号 | F38: 洪府发[2004]3号”的70%计取
A39: （五） | B39: 研究试验费
A40: （六） | B40: 特殊设备安全监督检验费
A41: （七） | B41: 监造费
A42: （八） | B42: 招标代理费 | C42: 指招标代理机构接受招标人委托,从事招标业务所需的费用。包括：编制招标文件，审查投标人资格，组织投标人踏勘现场并答疑，组织开标、评标、定标、以及提供招标前期咨询、协调合同的签订等业务。 | E42: 发改价格[2011]534号 | F42: 下浮20%计取
A43: （九） | B43: 施工图审查费 | C43: 指施工图审查机构受建设单位委托，根据国家法律、法规、技术标准与规范，对施工图进行审查所需的费用。 | E43: 赣价房字[2000]6号 | F43: 按70%计取
A44: （十） | B44: 技术经济标准使用费
A45: （十一） | B45: 工程造价咨询费 | C45: 指委托工程造价咨询单位审核设计概算、编制工程量清单、工程结算和竣工决算等计价文件，以及从事建设各阶段工程造价管理的咨询服务，出具工程造价成果文件等费用。 | E45: 赣价协[2021]23号 | F45: 洪府发[2004]3号”的70%计取
A46: （十二） | B46: 工程保险费 | C46: 指建设项目在建设期间根据需要对建筑工程、安装工程及机器设备和人身安全进行投保而发生的保险费用。包括：建筑安装工程一切险、人身意外伤害险和引进设备财产保险等费用。 | D46: 工程费用 X(0.3%~.6%) | E46: 建标〔2011〕1号 | F46: 洪府发[2004]3号”的70%计取

Sheet 节能评估文件编制费
A1: 序号 | B1: 收费区间 | E1: 基价 | F1: 费率 | G1: 工程费用 | H1: 直线内插法计取
G2: ='其他费自动计算'!C2 -> 3992.88
A3: 1 | C3: < | D3: 10000 | E3: 6 | G3: =IF(G2<D3,1,0) -> 1 | H3: =IF(AND(G3=1,G2>0),E3,0) -> 6
A4: 2 | B4: 10000 | C4: ~ | D4: 50000 | E4: 13 | F4: 0.000175 | G4: =IF(AND(G$2<=D4,G$2>B4),1,0) -> 0 | H4: =IF(G4=1,(E3+($G$2-B4)*F4),0) -> 0
A5: 3 | B5: 50000 | C5: ~ | D5: 100000 | E5: 20 | F5: 0.00014 | G5: =IF(AND(G$2<=D5,G$2>B5),1,0) -> 0 | H5: =IF(G5=1,(E4+($G$2-B5)*F5),0) -> 0
A6: 4 | B6: 100000 | C6: < | G6: =IF(G2>B6,1,0) -> 0 | H6: =IF(G6=1,E5,0) -> 0

Sheet 社会稳定风险评估
A1: 序号 | B1: 投资额 | E1: 基费 | F1: 输入费用 | G1: 直线内插法计算 | H1: 风险敏感系数 | I1: 合计
G2: =SUM(G3:G8) -> 0 | H2: 1.2 | I2: =SUM(I3:I8) -> 0
A3: 1 | C3: < | D3: 3000 | E3: 3 | F3: =IF(AND(F2<=D3,F2>0),1,0) -> 0 | G3: =IF(F3=1,E3/D3*F2,0) -> 0 | H3: 1.2 | I3: =IF(F3=1,MAX(G3*H3,E3),0) -> 0
A4: 2 | B4: 3000 | C4: ~ | D4: 10000 | E4: 6 | F4: =IF(AND($F$2>B4,$F$2<=D4),1,0) -> 0 | G4: =IF(F4=1,(E3+(E4-E3)/(D4-B4)*($F$2-B4)),0) -> 0 | H4: 1.2 | I4: =G4*H4 -> 0
A5: 3 | B5: 10000 | C5: ~ | D5: 50000 | E5: 9 | F5: =IF(AND($F$2>B5,$F$2<=D5),1,0) -> 0 | G5: =IF(F5=1,(E4+(E5-E4)/(D5-B5)*($F$2-B5)),0) -> 0 | H5: 1.2 | I5: =G5*H5 -> 0
A6: 4 | B6: 50000 | C6: ~ | D6: 100000 | E6: 12 | F6: =IF(AND($F$2>B6,$F$2<=D6),1,0) -> 0 | G6: =IF(F6=1,(E5+(E6-E5)/(D6-B6)*($F$2-B6)),0) -> 0 | H6: 1.2 | I6: =G6*H6 -> 0
A7: 5 | B7: 100000 | C7: ~ | D7: 500000 | E7: 15 | F7: =IF(AND($F$2>B7,$F$2<=D7),1,0) -> 0 | G7: =IF(F7=1,(E6+(E7-E6)/(D7-B7)*($F$2-B7)),0) -> 0 | H7: 1.2 | I7: =G7*H7 -> 0
A8: 6 | B8: 500000 | C8: < | E8: 20 | F8: =IF(F2>B8,1,0) -> 0 | G8: =IF(F8=1,E8/B8*F2,0) -> 0 | H8: 1.2 | I8: =IF(F8=1,MIN(G8*H8,E8),0) -> 0

Sheet 水土保持费
A1: 序号 | B1: 计费区间 | E1: 基价 | F1: 工程费用 | G1: 直线内插法计取
F2: ='其他费自动计算'!C2 -> 3992.88 | G2: =SUM(G3:G24) -> 23.95728
A3: 1 | C3: < | D3: 5000 | E3: 30 | F3: =IF(F2<=D3,1,0) -> 1 | G3: =IF(F3=1,E3/D3*F2,0) -> 23.95728
A4: 2 | B4: 5000 | C4: ~ | D4: 10000 | E4: 52 | F4: =IF(AND($F$2<=D4,$F$2>B4),1,) -> 0 | G4: =IF(F4=1,(E3+(E4-E3)/(D4-B4)*($F$2-B4)),0) -> 0
A5: 3 | B5: 10000 | C5: ~ | D5: 20000 | E5: 72 | F5: =IF(AND($F$2<=D5,$F$2>B5),1,) -> 0 | G5: =IF(F5=1,(E4+(E5-E4)/(D5-B5)*($F$2-B5)),0) -> 0
A6: 4 | B6: 20000 | C6: ~ | D6: 30000 | E6: 82 | F6: =IF(AND($F$2<=D6,$F$2>B6),1,) -> 0 | G6: =IF(F6=1,(E5+(E6-E5)/(D6-B6)*($F$2-B6)),0) -> 0
A7: 5 | B7: 30000 | C7: ~ | D7: 40000 | E7: 95 | F7: =IF(AND($F$2<=D7,$F$2>B7),1,) -> 0 | G7: =IF(F7=1,(E6+(E7-E6)/(D7-B7)*($F$2-B7)),0) -> 0
A8: 6 | B8: 40000 | C8: ~ | D8: 50000 | E8: 104 | F8: =IF(AND($F$2<=D8,$F$2>B8),1,) -> 0 | G8: =IF(F8=1,(E7+(E8-E7)/(D8-B8)*($F$2-B8)),0) -> 0
A9: 7 | B9: 50000 | C9: ~ | D9: 60000 | E9: 116 | F9: =IF(AND($F$2<=D9,$F$2>B9),1,) -> 0 | G9: =IF(F9=1,(E8+(E9-E8)/(D9-B9)*($F$2-B9)),0) -> 0
A10: 8 | B10: 60000 | C10: ~ | D10: 70000 | E10: 119 | F10: =IF(AND($F$2<=D10,$F$2>B10),1,) -> 0 | G10: =IF(F10=1,(E9+(E10-E9)/(D10-B10)*($F$2-B10)),0) -> 0
A11: 9 | B11: 70000 | C11: ~ | D11: 80000 | E11: 132 | F11: =IF(AND($F$2<=D11,$F$2>B11),1,) -> 0 | G11: =IF(F11=1,(E10+(E11-E10)/(D11-B11)*($F$2-B11)),0) -> 0
A12: 10 | B12: 80000 | C12: ~ | D12: 90000 | E12: 156 | F12: =IF(AND($F$2<=D12,$F$2>B12),1,) -> 0 | G12: =IF(F12=1,(E11+(E12-E11)/(D12-B12)*($F$2-B12)),0) -> 0
A13: 11 | B13: 90000 | C13: ~ | D13: 100000 | E13: 171 | F13: =IF(AND($F$2<=D13,$F$2>B13),1,) -> 0 | G13: =IF(F13=1,(E12+(E13-E12)/(D13-B13)*($F$2-B13)),0) -> 0
A14: 12 | B14: 100000 | C14: ~ | D14: 110000 | E14: 185 | F14: =IF(AND($F$2<=D14,$F$2>B14),1,) -> 0 | G14: =IF(F14=1,(E13+(E14-E13)/(D14-B14)*($F$2-B14)),0) -> 0
A15: 13 | B15: 110000 | C15: ~ | D15: 120000 | E15: 200 | F15: =IF(AND($F$2<=D15,$F$2>B15),1,) -> 0 | G15: =IF(F15=1,(E14+(E15-E14)/(D15-B15)*($F$2-B15)),0) -> 0
... A23: 21 | B23: 190000 | C23: ~ | D23: 200000 | E23: 350 | F23: =IF(AND($F$2<=D23,$F$2>B23),1,) -> 0 | G23: =IF(F23=1,(E22+(E23-E22)/(D23-B23)*($F$2-B23)),0) -> 0
A24: 22 | B24: 200000 | C24: < | F24: =IF(F2>B24,1,0) -> 0 | G24: =IF(F24=1,E23/B24*F2,0) -> 0

Sheet 交通影响评估
A1: 序号 | B1: 规模 （建筑总面积：万平方米） | E1: 单价 （元/平方米） | F1: 收费基数 （万元） | G1: 输入建筑面积 | H1: 差额累进法计算 | I1: 系数 | J1: 总计
H2: =SUM(H3:H7) -> 0 | I2: 1 | J2: =SUM(J3:J7) -> 0
A3: 1 | C3: < | D3: 5 | E3: 2 | F3: 10 | G3: =IF(AND(G2<=D3,G2>0),1,0) -> 0 | H3: =IF(G3=1,F3,0) -> 0 | I3: =I$2 -> 1 | J3: =H3*I3 -> 0
A4: 2 | B4: 5 | C4: ~ | D4: 20 | E4: 2 | F4: 10 | G4: =IF(AND($G$2<=D4,$G$2>B4),1,0) -> 0 | H4: =IF(G4=1,(F4+(G$2-B4)*E4),0) -> 0 | I4: =I$2 -> 1 | J4: =H4*I4 -> 0
A5: 3 | B5: 20 | C5: ~ | D5: 100 | E5: 1.5 | F5: 40 | G5: =IF(AND($G$2<=D5,$G$2>B5),1,0) -> 0 | H5: =IF(G5=1,(F5+(G$2-B5)*E5),0) -> 0 | I5: =I$2 -> 1 | J5: =H5*I5 -> 0
A6: 4 | B6: 100 | C6: ~ | D6: 200 | E6: 1 | F6: 160 | G6: =IF(AND($G$2<=D6,$G$2>B6),1,0) -> 0 | H6: =IF(G6=1,(F6+(G$2-B6)*E6),0) -> 0 | I6: =I$2 -> 1 | J6: =H6*I6 -> 0
A7: 5 | B7: 200 | C7: < | E7: 0.8 | F7: 260 | G7: =IF(G2>B7,1,0) -> 0 | H7: =IF(G7=1,MAX(F7,E7*$G$2),0) -> 0 | I7: =I$2 -> 1 | J7: =H7*I7 -> 0

Sheet 环境影响评估
A1: 序号 | B1: 计费额 | E1: 基价 | I1: 输入费用 | J1: 直线内插法计取
E2: 编制报告书 （含大纲） | F2: 编制报告表 | G2: 评估报告书 | H2: 评估报告表 | J2: 编制报告书 （含大纲） | K2: 编制报告表 | L2: 评估报告书 | M2: 评估报告表
I3: 120000 | J3: =SUM(J4:J9) -> 835.038 | K3: =SUM(K4:K9) -> -133.00665 | L3: =SUM(L4:L9) -> 47.0019 | M3: =SUM(M4:M9) -> -38.0019
A4: 1 | C4: > | D4: 3000 | E4: 5 | F4: 1 | G4: 0.8 | H4: 0.5 | I4: =IF(I3<=D4,1,0) -> 0 | J4: =IF(I4=1,(E4/I3*D4),0) -> 0 | K4: =IF($I4=1,(F4/$I$3*$D4),0) -> 0 | L4: =IF($I4=1,(G4/$I$3*$D4),0) -> 0 | M4: =IF($I4=1,(H4/$I$3*$D4),0) -> 0
A5: 2 | B5: 3000 | C5: ~ | D5: 20000 | E5: 6 | F5: 2 | G5: 1.5 | H5: 0.8 | I5: =IF(AND($I$3<=D5,$I$3>B5),1,0) -> 0 | J5: =IF($I5=1,(E5+(E6-E5)/($I$3-$B5)*($D5-$B5)),0) -> 0 | K5: =IF($I5=1,(F5+(F6-F5)/($I$3-$B5)*($D5-$B5)),0) -> 0 | L5: =IF($I5=1,(G5+(G6-G5)/($I$3-$B5)*($D5-$B5)),0) -> 0 | M5: =IF($I5=1,(H5+(H6-H5)/($I$3-$B5)*($D5-$B5)),0) -> 0
A6: 3 | B6: 20001 | C6: ~ | D6: 100000 | E6: 15 | F6: 4 | G6: 3 | H6: 1.5 | I6: =IF(AND($I$3<=D6,$I$3>B6),1,0) -> 0 | J6: =IF($I6=1,(E6+(E7-E6)/($I$3-$B6)*($D6-$B6)),0) -> 0 | K6: =IF($I6=1,(F6+(F7-F6)/($I$3-$B6)*($D6-$B6)),0) -> 0 | L6: =IF($I6=1,(G6+(G7-G6)/($I$3-$B6)*($D6-$B6)),0) -> 0 | M6: =IF($I6=1,(H6+(H7-H6)/($I$3-$B6)*($D6-$B6)),0) -> 0
A7: 4 | B7: 100001 | C7: ~ | D7: 500000 | E7: 35 | F7: 7 | G7: 7 | H7: 2 | I7: =IF(AND($I$3<=D7,$I$3>B7),1,0) -> 1 | J7: =IF($I7=1,(E7+(E8-E7)/($I$3-$B7)*($D7-$B7)),0) -> 835.038 | K7: =IF($I7=1,(F7+(F8-F7)/($I$3-$B7)*($D7-$B7)),0) -> -133.00665 | L7: =IF($I7=1,(G7+(G8-G7)/($I$3-$B7)*($D7-$B7)),0) -> 47.0019 | M7: =IF($I7=1,(H7+(H8-H7)/($I$3-$B7)*($D7-$B7)),0) -> -38.0019
A8: 5 | B8: 500001 | C8: ~ | D8: 1000000 | E8: 75 | G8: 9 | I8: =IF(AND($I$3<=D8,$I$3>B8),1,0) -> 0 | J8: =IF($I8=1,(E8+(E9-E8)/($I$3-$B8)*($D8-$B8)),0) -> 0 | K8: =IF($I8=1,(F8+(F9-F8)/($I$3-$B8)*($D8-$B8)),0) -> 0 | L8: =IF($I8=1,(G8+(G9-G8)/($I$3-$B8)*($D8-$B8)),0) -> 0 | M8: =IF($I8=1,(H8+(H9-H8)/($I$3-$B8)*($D8-$B8)),0) -> 0
A9: 6 | B9: 1000000 | C9: ~ | D9: 500000 | E9: 110 | G9: 13 | I9: =IF(AND($I$3<=D9,$I$3>B9),1,0) -> 0 | J9: =IF($I9=1,(E9+(E10-E9)/($I$3-$B9)*($D9-$B9)),0) -> 0 | K9: =IF($I9=1,(F9+(F10-F9)/($I$3-$B9)*($D9-$B9)),0) -> 0 | L9: =IF($I9=1,(G9+(G10-G9)/($I$3-$B9)*($D9-$B9)),0) -> 0 | M9: =IF($I9=1,(H9+(H10-H9)/($I$3-$B9)*($D9-$B9)),0) -> 0

Sheet 前期工程咨询费
A1: 估算投资额 | B1: 1000万元 | C1: 1000～3000 | D1: 3000万元～ | E1: 1亿元～ | F1: 5亿元～ | I1: 10亿元～ | J1: 50亿元
A2: 咨询评估项目 | B2: 以下 | C2: 万元 | D2: 1亿元 | E2: 5亿元 | F2: 10亿元 | I2: 50亿元 | J2: 以上
A3: 一、编制项目建议书 | B3: 2～4 | C3: 4～6 | D3: 6～14 | E3: 14～37 | F3: 37～55 | I3: 55～100 | J3: 100～125
A4: 二、编制可行性研究报告 | B4: 3～6 | C4: 6～12 | D4: 12～28 | E4: 28～75 | F4: 75～110 | I4: 110～200 | J4: 200～250
A5: 三、评估项目建议书 | B5: 1～2 | C5: 2～4 | D5: 4～8 | E5: 8～12 | F5: 12～15 | I5: 15～17 | J5: 17～20
A6: 四、评估可行性研究报告 | B6: 1.5～3 | C6: 3～5 | D6: 5～10 | E6: 10～15 | F6: 15～20 | I6: 20～25 | J6: 25～35
A7: 行业调整系数 | B7: 林业与建筑0.8， 市政公用工程与交通（公路）0.7。工程复杂程度调整系数0.8~1.2。
A8: 收费基价表
A9: 序号 | B9: 计费额 | E9: 基价 | I9: 输入费用 | J9: 直线内插法计取
J10: 项目建议书 | K10: 可行性研究报告 | L10: 评估项目建议书 | M10: 评估可行性研究报告
E11: 项目建议书 | F11: 可行性研究报告 | G11: 评估项目建议书 | H11: 评估可行性研究报告 | I11: 5600 | J11: =SUM(J12:J18) -> 27.543671 | K11: =SUM(K12:K18) -> 55.087341 | L11: =SUM(L12:L18) -> 14.771835 | M11: =SUM(M12:M18) -> 18.464794
A12: 1 | C12: > | D12: 1000 | E12: 2 | F12: 3 | G12: 1 | H12: 1.5 | I12: =IF(I11<=D12,1,0) -> 0 | J12: =IF(I12=1,(E12/I11*D12),0) -> 0 | K12: =IF($I12=1,(F12/$I$11*$D12),0) -> 0 | L12: =IF($I12=1,(G12/$I$11*$D12),0) -> 0 | M12: =IF($I12=1,(H12/$I$11*$D12),0) -> 0
A13: 2 | B13: 1001 | C13: ~ | D13: 3000 | E13: 4 | F13: 6 | G13: 2 | H13: 3 | I13: =IF(AND($I$11<=D13,$I$11>B13),1,0) -> 0 | J13: =IF($I13=1,(E13+(E14-E13)/($I$11-$B13)*($D13-$B13)),0) -> 0 | K13: =IF($I13=1,(F13+(F14-F13)/($I$11-$B13)*($D13-$B13)),0) -> 0 | L13: =IF($I13=1,(G13+(G14-G13)/($I$11-$B13)*($D13-$B13)),0) -> 0 | M13: =IF($I13=1,(H13+(H14-H13)/($I$11-$B13)*($D13-$B13)),0) -> 0
A14: 3 | B14: 3001 | C14: ~ | D14: 10000 | E14: 6 | F14: 12 | G14: 4 | H14: 5 | I14: =IF(AND($I$11<=D14,$I$11>B14),1,0) -> 1 | J14: =IF($I14=1,(E14+(E15-E14)/($I$11-$B14)*($D14-$B14)),0) -> 27.543671 | K14: =IF($I14=1,(F14+(F15-F14)/($I$11-$B14)*($D14-$B14)),0) -> 55.087341 | L14: =IF($I14=1,(G14+(G15-G14)/($I$11-$B14)*($D14-$B14)),0) -> 14.771835 | M14: =IF($I14=1,(H14+(H15-H14)/($I$11-$B14)*($D14-$B14)),0) -> 18.464794
A15: 4 | B15: 10001 | C15: ~ | D15: 50000 | E15: 14 | F15: 28 | G15: 8 | H15: 10 | I15: =IF(AND($I$11<=D15,$I$11>B15),1,0) -> 0 | J15: =IF($I15=1,(E15+(E16-E15)/($I$11-$B15)*($D15-$B15)),0) -> 0 | K15: =IF($I15=1,(F15+(F16-F15)/($I$11-$B15)*($D15-$B15)),0) -> 0 | L15: =IF($I15=1,(G15+(G16-G15)/($I$11-$B15)*($D15-$B15)),0) -> 0 | M15: =IF($I15=1,(H15+(H16-H15)/($I$11-$B15)*($D15-$B15)),0) -> 0
A16: 5 | B16: 50001 | C16: ~ | D16: 100000 | E16: 37 | F16: 75 | G16: 12 | H16: 15 | I16: =IF(AND($I$11<=D16,$I$11>B16),1,0) -> 0 | J16: =IF($I16=1,(E16+(E17-E16)/($I$11-$B16)*($D16-$B16)),0) -> 0 | K16: =IF($I16=1,(F16+(F17-F16)/($I$11-$B16)*($D16-$B16)),0) -> 0 | L16: =IF($I16=1,(G16+(G17-G16)/($I$11-$B16)*($D16-$B16)),0) -> 0 | M16: =IF($I16=1,(H16+(H17-H16)/($I$11-$B16)*($D16-$B16)),0) -> 0
A17: 6 | B17: 100000 | C17: ~ | D17: 500000 | E17: 55 | F17: 110 | G17: 15 | H17: 20 | I17: =IF(AND($I$11<=D17,$I$11>B17),1,0) -> 0 | J17: =IF($I17=1,(E17+(E18-E17)/($I$11-$B17)*($D17-$B17)),0) -> 0 | K17: =IF($I17=1,(F17+(F18-F17)/($I$11-$B17)*($D17-$B17)),0) -> 0 | L17: =IF($I17=1,(G17+(G18-G17)/($I$11-$B17)*($D17-$B17)),0) -> 0 | M17: =IF($I17=1,(H17+(H18-H17)/($I$11-$B17)*($D17-$B17)),0) -> 0
A18: 7 | B18: 500000 | E18: 100 | F18: 200 | G18: 17 | H18: 25 | I18: =IF(AND($I$11>B18),1,0) -> 0 | J18: =IF($I18=1,(E18+(E19-E18)/($I$11-$B18)*($D18-$B18)),0) -> 0 | K18: =IF($I18=1,(F18+(F19-F18)/($I$11-$B18)*($D18-$B18)),0) -> 0 | L18: =IF($I18=1,(G18+(G19-G18)/($I$11-$B18)*($D18-$B18)),0) -> 0 | M18: =IF($I18=1,(H18+(H19-H18)/($I$11-$B18)*($D18-$B18)),0) -> 0
E19: 125 | F19: 250 | G19: 20 | H19: 35

Sheet 施工图审查费
A1: 收费基价表 | G1: 输入工程费用 | H1: 差额定率累进法
A2: 序号 | B2: 计费额 | E2: 费率 | F2: 全额 | G2: ='其他费自动计算'!C2 -> 3992.88 | H2: =SUM(H3:H6) -> 5.391456
A3: 1 | C3: > | D3: 500 | E3: 0.002 | F3: =E3*D3 -> 1 | G3: =IF($G$2<=D3,1,0) -> 0 | H3: =IF(G3=1,(G2*E3),0) -> 0
A4: 2 | B4: 500 | C4: ~ | D4: 1000 | E4: 0.0016 | F4: =F3+(D4-B4)*E4 -> 1.8 | G4: =IF(AND($G$2<=D4,$G$2>B4),1,0) -> 0 | H4: =IF(G4=1,(F3+($G$2-D3)*E4),0) -> 0
A5: 3 | B5: 1000 | C5: ~ | D5: 5000 | E5: 0.0012 | F5: =F4+(D5-B5)*E5 -> 6.6 | G5: =IF(AND($G$2<=D5,$G$2>B5),1,0) -> 1 | H5: =IF(G5=1,(F4+($G$2-D4)*E5),0) -> 5.391456
A6: 4 | B6: 5000 | C6: < | E6: 0.001 | G6: =IF(AND($G$2>B6),1,0) -> 0 | H6: =IF(G6=1,(F5+($G$2-B6)*E6),0) -> 0

Sheet 招标代理费
A1: 造价区间（万） | E1: 货物采购招标 | G1: 服务招标（勘察） | I1: 服务招标（设计） | K1: 服务招标（监理） | M1: 工程招标
A2: 要计算的造价（万） | E2: 600 | G2: 600 | I2: ='其他费自动计算'!C16 -> 133.63604 | K2: 600 | M2: 300
A3: 100以下 | B3: 100 | C3: 100 | E3: 0.015 | F3: =IF(E$2>=$B3,$C3*E3,E$2*E3) -> 1.5 | G3: 0.015 | H3: =IF(G$2>=$B3,$C3*G3,G$2*G3) -> 1.5 | I3: 0.015 | J3: =IF(I$2>=$B3,$C3*I3,I$2*I3) -> 1.5 | K3: 0.015 | L3: =IF(K$2>=$B3,$C3*K3,K$2*K3) -> 1.5 | M3: 0.01 | N3: =IF(M$2>=$B3,$C3*M3,M$2*M3) -> 1
A4: 100－500 | B4: 500 | C4: 400 | E4: 0.011 | F4: =IF(E$2<$B3,0,IF(E$2>=$B4,$C4*E4,(E$2-$B3)*E4)) -> 4.4 | G4: 0.008 | H4: =IF(G$2<$B3,0,IF(G$2>=$B4,$C4*G4,(G$2-$B3)*G4)) -> 3.2 | I4: 0.008 | J4: =IF(I$2<$B3,0,IF(I$2>=$B4,$C4*I4,(I$2-$B3)*I4)) -> 0.26908835 | K4: 0.008 | L4: =IF(K$2<$B3,0,IF(K$2>=$B4,$C4*K4,(K$2-$B3)*K4)) -> 3.2 | M4: 0.007 | N4: =IF(M$2<$B3,0,IF(M$2>=$B4,$C4*M4,(M$2-$B3)*M4)) -> 1.4
A5: 500－1000 | B5: 1000 | C5: 500 | E5: 0.008 | F5: =IF(E$2<$B4,0,IF(E$2>=$B5,$C5*E5,(E$2-$B4)*E5)) -> 0.8 | G5: 0.0045 | H5: =IF(G$2<$B4,0,IF(G$2>=$B5,$C5*G5,(G$2-$B4)*G5)) -> 0.45 | I5: 0.0045 | J5: =IF(I$2<$B4,0,IF(I$2>=$B5,$C5*I5,(I$2-$B4)*I5)) -> 0 | K5: 0.0045 | L5: =IF(K$2<$B4,0,IF(K$2>=$B5,$C5*K5,(K$2-$B4)*K5)) -> 0.45 | M5: 0.0055 | N5: =IF(M$2<$B4,0,IF(M$2>=$B5,$C5*M5,(M$2-$B4)*M5)) -> 0
A6: 1000－5000 | B6: 5000 | C6: 4000 | E6: 0.005 | F6: =IF(E$2<$B5,0,IF(E$2>=$B6,$C6*E6,(E$2-$B5)*E6)) -> 0 | G6: 0.0025 | H6: =IF(G$2<$B5,0,IF(G$2>=$B6,$C6*G6,(G$2-$B5)*G6)) -> 0 | I6: 0.0025 | J6: =IF(I$2<$B5,0,IF(I$2>=$B6,$C6*I6,(I$2-$B5)*I6)) -> 0 | K6: 0.0025 | L6: =IF(K$2<$B5,0,IF(K$2>=$B6,$C6*K6,(K$2-$B5)*K6)) -> 0 | M6: 0.0035 | N6: =IF(M$2<$B5,0,IF(M$2>=$B6,$C6*M6,(M$2-$B5)*M6)) -> 0
A7: 5000－10000 | B7: 10000 | C7: 5000 | E7: 0.0025 | F7: =IF(E$2<$B6,0,IF(E$2>=$B7,$C7*E7,(E$2-$B6)*E7)) -> 0 | G7: 0.001 | H7: =IF(G$2<$B6,0,IF(G$2>=$B7,$C7*G7,(G$2-$B6)*G7)) -> 0 | I7: 0.001 | J7: =IF(I$2<$B6,0,IF(I$2>=$B7,$C7*I7,(I$2-$B6)*I7)) -> 0 | K7: 0.001 | L7: =IF(K$2<$B6,0,IF(K$2>=$B7,$C7*K7,(K$2-$B6)*K7)) -> 0 | M7: 0.002 | N7: =IF(M$2<$B6,0,IF(M$2>=$B7,$C7*M7,(M$2-$B6)*M7)) -> 0
A8: 10000－100000 | B8: 100000 | C8: 90000 | E8: 0.0005 | F8: =IF(E$2<$B7,0,IF(E$2>=$B8,$C8*E8,(E$2-$B7)*E8)) -> 0 | G8: 0.0005 | H8: =IF(G$2<$B7,0,IF(G$2>=$B8,$C8*G8,(G$2-$B7)*G8)) -> 0 | I8: 0.0005 | J8: =IF(I$2<$B7,0,IF(I$2>=$B8,$C8*I8,(I$2-$B7)*I8)) -> 0 | K8: 0.0005 | L8: =IF(K$2<$B7,0,IF(K$2>=$B8,$C8*K8,(K$2-$B7)*K8)) -> 0 | M8: 0.0005 | N8: =IF(M$2<$B7,0,IF(M$2>=$B8,$C8*M8,(M$2-$B7)*M8)) -> 0
A9: 100000以上 | E9: 0.0001 | F9: =IF(E$2<$B8,0,(E$2-$B8)*E9) -> 0 | G9: 0.0001 | H9: =IF(G$2<$B8,0,(G$2-$B8)*G9) -> 0 | I9: 0.0001 | J9: =IF(I$2<$B8,0,(I$2-$B8)*I9) -> 0 | K9: 0.0001 | L9: =IF(K$2<$B8,0,(K$2-$B8)*K9) -> 0 | M9: 0.0001 | N9: =IF(M$2<$B8,0,(M$2-$B8)*M9) -> 0 | O9: 合计费用
A10: 最终费用万元： | E10: =SUM(F3:F9) -> 6.7 | G10: =SUM(H3:H9) -> 5.15 | I10: =SUM(J3:J9) -> 1.7690884 | K10: =SUM(L3:L9) -> 5.15 | M10: =SUM(N3:N9) -> 2.4 | O10: =+M10+K10+I10+G10+E10 -> 21.169088
A11: 允许范围：上浮20% | E11: =+E10*1.2 -> 8.04 | G11: =+G10*1.2 -> 6.18 | I11: =+I10*1.2 -> 2.122906 | K11: =+K10*1.2 -> 6.18 | M11: =+M10*1.2 -> 2.88
A12: 允许范围：下浮20% | E12: =+E10*0.8 -> 5.36 | G12: =+G10*0.8 -> 4.12 | I12: =+I10*0.8 -> 1.4152707 | K12: =+K10*0.8 -> 4.12 | M12: =+M10*0.8 -> 1.92
A16: 计费额 | D16: 货物采购 | G16: 服务招标（勘察） | J16: 服务招标（设计） | M16: 服务招标（监理） | P16: 工程招标
D17: 600 | G17: 600 | J17: 100 | M17: 600 | P17: 300
B18: < | C18: 100 | D18: =C18*E18 -> 1.5 | E18: 0.015 | F18: =IF(D17<=C18,D17*E18,0) -> 0 | G18: =C18*H18 -> 1.5 | H18: 0.015 | I18: =IF(H17<=C18,H17*H18,0) -> 0 | J18: =C18*K18 -> 1.5 | K18: 0.015 | L18: =IF(K17<=C18,J17*K18,0) -> 1.5 | M18: =C18*N18 -> 1.5 | N18: 0.015 | O18: =IF(M17<=C18,M17*N18,0) -> 0 | P18: =C18*Q18 -> 1 | Q18: 0.01 | R18: =IF(P17<=C18,P17*Q18,0) -> 0
A19: 100 | B19: ~ | C19: 500 | D19: =D18+(C19-A19)*E19 -> 5.9 | E19: 0.011 | F19: =IF(AND($D$17>A19,$D$17<C19),(D18+($D$17-C18)*E19),0) -> 0 | G19: =G18+(C19-C18)*H19 -> 4.7 | H19: 0.008 | I19: =IF(AND($G$17>A19,$G$17<C19),(G18+($G$17-C18)*H19),0) -> 0 | J19: =J18+(C19-A19)*K19 -> 4.7 | K19: 0.008 | L19: =IF(AND($J$17>A19,$J$17<C19),(J18+($J$17-C18)*K19),0) -> 0 | M19: =M18+(C19-C18)*N19 -> 4.7 | N19: 0.008 | O19: =IF(AND($M$17>A19,$M$17<C19),(M18+($M$17-C18)*N19),0) -> 0 | P19: =P18+(C19-C18)*Q19 -> 3.8 | Q19: 0.007 | R19: =IF(AND($P$17>A19,$P$17<C19),(P18+($P$17-C18)*Q19),0) -> 2.4
A20: 500 | B20: ~ | C20: 1000 | D20: =D19+(C20-A20)*E20 -> 9.9 | E20: 0.008 | F20: =IF(AND($D$17>A20,$D$17<C20),(D19+($D$17-C19)*E20),0) -> 6.7 | G20: =G19+(C20-C19)*H20 -> 6.95 | H20: 0.0045 | I20: =IF(AND($G$17>A20,$G$17<C20),(G19+($G$17-C19)*H20),0) -> 5.15 | J20: =J19+(C20-A20)*K20 -> 6.95 | K20: 0.0045 | L20: =IF(AND($J$17>A20,$J$17<C20),(J19+($J$17-C19)*K20),0) -> 0 | M20: =M19+(C20-C19)*N20 -> 6.95 | N20: 0.0045 | O20: =IF(AND($M$17>A20,$M$17<C20),(M19+($M$17-C19)*N20),0) -> 5.15 | P20: =P19+(C20-C19)*Q20 -> 6.55 | Q20: 0.0055 | R20: =IF(AND($P$17>A20,$P$17<C20),(P19+($P$17-C19)*Q20),0) -> 0
A21: 1000 | B21: ~ | C21: 5000 | D21: =D20+(C21-A21)*E21 -> 29.9 | E21: 0.005 | F21: =IF(AND($D$17>A21,$D$17<C21),(D20+($D$17-C20)*E21),0) -> 0 | G21: =G20+(C21-C20)*H21 -> 16.95 | H21: 0.0025 | I21: =IF(AND($G$17>A21,$G$17<C21),(G20+($G$17-C20)*H21),0) -> 0 | J21: =J20+(C21-A21)*K21 -> 16.95 | K21: 0.0025 | L21: =IF(AND($J$17>A21,$J$17<C21),(J20+($J$17-C20)*K21),0) -> 0 | M21: =M20+(C21-C20)*N21 -> 16.95 | N21: 0.0025 | O21: =IF(AND($M$17>A21,$M$17<C21),(M20+($M$17-C20)*N21),0) -> 0 | P21: =P20+(C21-C20)*Q21 -> 20.55 | Q21: 0.0035 | R21: =IF(AND($P$17>A21,$P$17<C21),(P20+($P$17-C20)*Q21),0) -> 0
A22: 5000 | B22: ~ | C22: 10000 | D22: =D21+(C22-A22)*E22 -> 42.4 | E22: 0.0025 | F22: =IF(AND($D$17>A22,$D$17<C22),(D21+($D$17-C21)*E22),0) -> 0 | G22: =G21+(C22-C21)*H22 -> 21.95 | H22: 0.001 | I22: =IF(AND($G$17>A22,$G$17<C22),(G21+($G$17-C21)*H22),0) -> 0 | J22: =J21+(C22-A22)*K22 -> 21.95 | K22: 0.001 | L22: =IF(AND($J$17>A22,$J$17<C22),(J21+($J$17-C21)*K22),0) -> 0 | M22: =M21+(C22-C21)*N22 -> 21.95 | N22: 0.001 | O22: =IF(AND($M$17>A22,$M$17<C22),(M21+($M$17-C21)*N22),0) -> 0 | P22: =P21+(C22-C21)*Q22 -> 30.55 | Q22: 0.002 | R22: =IF(AND($P$17>A22,$P$17<C22),(P21+($P$17-C21)*Q22),0) -> 0
A23: 10000 | B23: ~ | C23: 50000 | D23: =D22+(C23-A23)*E23 -> 62.4 | E23: 0.0005 | F23: =IF(AND($D$17>A23,$D$17<C23),(D22+($D$17-C22)*E23),0) -> 0 | G23: =G22+(C23-C22)*H23 -> 41.95 | H23: 0.0005 | I23: =IF(AND($G$17>A23,$G$17<C23),(G22+($G$17-C22)*H23),0) -> 0 | J23: =J22+(C23-A23)*K23 -> 41.95 | K23: 0.0005 | L23: =IF(AND($J$17>A23,$J$17<C23),(J22+($J$17-C22)*K23),0) -> 0 | M23: =M22+(C23-C22)*N23 -> 41.95 | N23: 0.0005 | O23: =IF(AND($M$17>A23,$M$17<C23),(M22+($M$17-C22)*N23),0) -> 0 | P23: =P22+(C23-C22)*Q23 -> 50.55 | Q23: 0.0005 | R23: =IF(AND($P$17>A23,$P$17<C23),(P22+($P$17-C22)*Q23),0) -> 0
A24: 50000 | B24: ~ | C24: 100000 | D24: =D23+(C24-A24)*E24 -> 79.9 | E24: 0.00035 | F24: =IF(AND($D$17>A24,$D$17<C24),(D23+($D$17-C23)*E24),0) -> 0 | G24: =G23+(C24-C23)*H24 -> 59.45 | H24: 0.00035 | I24: =IF(AND($G$17>A24,$G$17<C24),(G23+($G$17-C23)*H24),0) -> 0 | J24: =J23+(C24-A24)*K24 -> 59.45 | K24: 0.00035 | L24: =IF(AND($J$17>A24,$J$17<C24),(J23+($J$17-C23)*K24),0) -> 0 | M24: =M23+(C24-C23)*N24 -> 59.45 | N24: 0.00035 | O24: =IF(AND($M$17>A24,$M$17<C24),(M23+($M$17-C23)*N24),0) -> 0 | P24: =P23+(C24-C23)*Q24 -> 68.05 | Q24: 0.00035 | R24: =IF(AND($P$17>A24,$P$17<C24),(P23+($P$17-C23)*Q24),0) -> 0
A25: 100000 | B25: ~ | C25: 500000 | D25: =D24+(C25-A25)*E25 -> 111.9 | E25: 8e-05 | F25: =IF(AND($D$17>A25,$D$17<C25),(D24+($D$17-C24)*E25),0) -> 0 | G25: =G24+(C25-C24)*H25 -> 91.45 | H25: 8e-05 | I25: =IF(AND($G$17>A25,$G$17<C25),(G24+($G$17-C24)*H25),0) -> 0 | J25: =J24+(C25-A25)*K25 -> 91.45 | K25: 8e-05 | L25: =IF(AND($J$17>A25,$J$17<C25),(J24+($J$17-C24)*K25),0) -> 0 | M25: =M24+(C25-C24)*N25 -> 91.45 | N25: 8e-05 | O25: =IF(AND($M$17>A25,$M$17<C25),(M24+($M$17-C24)*N25),0) -> 0 | P25: =P24+(C25-C24)*Q25 -> 100.05 | Q25: 8e-05 | R25: =IF(AND($P$17>A25,$P$17<C25),(P24+($P$17-C24)*Q25),0) -> 0
A26: 500000 | B26: ~ | C26: 1000000 | D26: =D25+(C26-A26)*E26 -> 141.9 | E26: 6e-05 | F26: =IF(AND($D$17>A26,$D$17<C26),(D25+($D$17-C25)*E26),0) -> 0 | G26: =G25+(C26-C25)*H26 -> 121.45 | H26: 6e-05 | I26: =IF(AND($G$17>A26,$G$17<C26),(G25+($G$17-C25)*H26),0) -> 0 | J26: =J25+(C26-A26)*K26 -> 121.45 | K26: 6e-05 | L26: =IF(AND($J$17>A26,$J$17<C26),(J25+($J$17-C25)*K26),0) -> 0 | M26: =M25+(C26-C25)*N26 -> 121.45 | N26: 6e-05 | O26: =IF(AND($M$17>A26,$M$17<C26),(M25+($M$17-C25)*N26),0) -> 0 | P26: =P25+(C26-C25)*Q26 -> 130.05 | Q26: 6e-05 | R26: =IF(AND($P$17>A26,$P$17<C26),(P25+($P$17-C25)*Q26),0) -> 0
A27: 1000000 | B27: < | E27: 4e-05 | F27: =IF(AND($D$17>A27),(D26+($D$17-A27)*E27),0) -> 0 | H27: 4e-05 | I27: =IF(AND(G17>A27),(G26+(G17-A27)*H27),0) -> 0 | K27: 4e-05 | L27: =IF(AND(J17>A27),(J26+(J17-A27)*K27),0) -> 0 | N27: 4e-05 | O27: =IF(AND(M17>A27),(M26+(M17-A27)*N27),0) -> 0 | Q27: 4e-05 | R27: =IF(AND(P17>A27),(P26+(P17-A27)*Q27),0) -> 0 | S27: 总费用
A28: 费用合计 | D28: =SUM(F18:F27) -> 6.7 | G28: =SUM(I18:I27) -> 5.15 | J28: =SUM(L18:L27) -> 1.5 | M28: =SUM(O18:O27) -> 5.15 | P28: =SUM(R18:R27) -> 2.4 | S28: =SUM(D28:Q28) -> 20.9

Sheet 造价咨询
A1: 收费基价表 | G1: 输入工程费用 | H1: 差额定率累进法
A2: 序号 | B2: 计费额 | E2: 费率 | F2: 全额 | G2: ='其他费自动计算'!C2 -> 3992.88 | H2: =SUM(H3:H9) -> 33.964464
A3: 1 | C3: > | D3: 200 | E3: 0.0102 | F3: =E3*D3 -> 2.04 | G3: =IF($G$2<=D3,1,0) -> 0 | H3: =IF(G3=1,(G2*E3),0) -> 0 | I3: 内容锁定区
A4: 2 | B4: 200 | C4: ~ | D4: 500 | E4: 0.0096 | F4: =F3+(D4-B4)*E4 -> 4.92 | G4: =IF(AND($G$2<=D4,$G$2>B4),1,0) -> 0 | H4: =IF(G4=1,(F3+($G$2-D3)*E4),0) -> 0
A5: 3 | B5: 500 | C5: ~ | D5: 1000 | E5: 0.009 | F5: =F4+(D5-B5)*E5 -> 9.42 | G5: =IF(AND($G$2<=D5,$G$2>B5),1,0) -> 0 | H5: =IF(G5=1,(F4+($G$2-D4)*E5),0) -> 0
A6: 4 | B6: 1000 | C6: ~ | D6: 3000 | E6: 0.0084 | F6: =F5+(D6-B6)*E6 -> 26.22 | G6: =IF(AND($G$2<=D6,$G$2>B6),1,0) -> 0 | H6: =IF(G6=1,(F5+($G$2-D5)*E6),0) -> 0
A7: 5 | B7: 3000 | C7: ~ | D7: 6000 | E7: 0.0078 | F7: =F6+(D7-B7)*E7 -> 49.62 | G7: =IF(AND($G$2<=D7,$G$2>B7),1,0) -> 1 | H7: =IF(G7=1,(F6+($G$2-D6)*E7),0) -> 33.964464
A8: 6 | B8: 6000 | C8: ~ | D8: 10000 | E8: 0.0072 | F8: =F7+(D8-B8)*E8 -> 78.42 | G8: =IF(AND($G$2<=D8,$G$2>B8),1,0) -> 0 | H8: =IF(G8=1,(F7+($G$2-D7)*E8),0) -> 0
A9: 7 | B9: 10000 | C9: < | E9: 0.0066 | G9: =IF(AND($G$2>B9),1,0) -> 0 | H9: =IF(G9=1,(F8+($G$2-D8)*E9),0) -> 0

Sheet 监理费
A1: 序号 | B1: 收费额 | C1: 收费基价 | D1: 输入费用 | E1: 直线内插法计取
D2: ='其他费自动计算'!C2 -> 3992.88 | E2: =SUM(E3:E19) -> 99.297988
A3: 1 | B3: 500 | C3: 16.5 | D3: =IF(D2<=B3,1,0) -> 0 | E3: =IF(D3=1,(C3/D2*B3),0) -> 0
A4: 2 | B4: 1000 | C4: 30.1 | D4: =IF(AND($D$2<=B4,$D$2>B3),1,0) -> 0 | E4: =IF($D4=1,(C3+(C4-C3)/($B4-$B3)*($D$2-$B3)),0) -> 0
A5: 3 | B5: 3000 | C5: 78.1 | D5: =IF(AND($D$2<=B5,$D$2>B4),1,0) -> 0 | E5: =IF($D5=1,(C4+(C5-C4)/($B5-$B4)*($D$2-$B4)),0) -> 0
A6: 4 | B6: 5000 | C6: 120.8 | D6: =IF(AND($D$2<=B6,$D$2>B5),1,0) -> 1 | E6: =IF($D6=1,(C5+(C6-C5)/($B6-$B5)*($D$2-$B5)),0) -> 99.297988
A7: 5 | B7: 8000 | C7: 181 | D7: =IF(AND($D$2<=B7,$D$2>B6),1,0) -> 0 | E7: =IF($D7=1,(C6+(C7-C6)/($B7-$B6)*($D$2-$B6)),0) -> 0
A8: 6 | B8: 10000 | C8: 218.6 | D8: =IF(AND($D$2<=B8,$D$2>B7),1,0) -> 0 | E8: =IF($D8=1,(C7+(C8-C7)/($B8-$B7)*($D$2-$B7)),0) -> 0
A9: 7 | B9: 20000 | C9: 393.4 | D9: =IF(AND($D$2<=B9,$D$2>B8),1,0) -> 0 | E9: =IF($D9=1,(C8+(C9-C8)/($B9-$B8)*($D$2-$B8)),0) -> 0
A10: 8 | B10: 40000 | C10: 708.2 | D10: =IF(AND($D$2<=B10,$D$2>B9),1,0) -> 0 | E10: =IF($D10=1,(C9+(C10-C9)/($B10-$B9)*($D$2-$B9)),0) -> 0
A11: 9 | B11: 60000 | C11: 991.4 | D11: =IF(AND($D$2<=B11,$D$2>B10),1,0) -> 0 | E11: =IF($D11=1,(C10+(C11-C10)/($B11-$B10)*($D$2-$B10)),0) -> 0
A12: 10 | B12: 80000 | C12: 1255.8 | D12: =IF(AND($D$2<=B12,$D$2>B11),1,0) -> 0 | E12: =IF($D12=1,(C11+(C12-C11)/($B12-$B11)*($D$2-$B11)),0) -> 0
A13: 11 | B13: 100000 | C13: 1507 | D13: =IF(AND($D$2<=B13,$D$2>B12),1,0) -> 0 | E13: =IF($D13=1,(C12+(C13-C12)/($B13-$B12)*($D$2-$B12)),0) -> 0
A14: 12 | B14: 200000 | C14: 2712.5 | D14: =IF(AND($D$2<=B14,$D$2>B13),1,0) -> 0 | E14: =IF($D14=1,(C13+(C14-C13)/($B14-$B13)*($D$2-$B13)),0) -> 0
A15: 13 | B15: 400000 | C15: 4882.6 | D15: =IF(AND($D$2<=B15,$D$2>B14),1,0) -> 0 | E15: =IF($D15=1,(C14+(C15-C14)/($B15-$B14)*($D$2-$B14)),0) -> 0
... A18: 16 | B18: 1000000 | C18: 10390.1 | D18: =IF(AND($D$2<=B18,$D$2>B17),1,0) -> 0 | E18: =IF($D18=1,(C17+(C18-C17)/($B18-$B17)*($D$2-$B17)),0) -> 0
A19: 16 | D19: =IF(D2>B18,1,0) -> 0 | E19: =IF(D19=1,D2*1.039%,0) -> 0

Sheet 设计费
A1: 序号 | B1: 收费额 | C1: 收费基价 | D1: 输入费用 | E1: 直线内插法计取
D2: ='其他费自动计算'!C2 -> 3992.88 | E2: =SUM(E3:E21) -> 133.63604
A3: 1 | B3: 200 | C3: 9 | D3: =IF(D2<=B3,1,0) -> 0 | E3: =IF(D3=1,(C3/D2*B3),0) -> 0
A4: 2 | B4: 500 | C4: 20.9 | D4: =IF(AND($D$2<=B4,$D$2>B3),1,0) -> 0 | E4: =IF($D4=1,(C3+(C4-C3)/($B4-$B3)*($D$2-$B3)),0) -> 0
A5: 3 | B5: 1000 | C5: 38.8 | D5: =IF(AND($D$2<=B5,$D$2>B4),1,0) -> 0 | E5: =IF($D5=1,(C4+(C5-C4)/($B5-$B4)*($D$2-$B4)),0) -> 0
A6: 4 | B6: 3000 | C6: 103.8 | D6: =IF(AND($D$2<=B6,$D$2>B5),1,0) -> 0 | E6: =IF($D6=1,(C5+(C6-C5)/($B6-$B5)*($D$2-$B5)),0) -> 0
A7: 5 | B7: 5000 | C7: 163.9 | D7: =IF(AND($D$2<=B7,$D$2>B6),1,0) -> 1 | E7: =IF($D7=1,(C6+(C7-C6)/($B7-$B6)*($D$2-$B6)),0) -> 133.63604
A8: 6 | B8: 8000 | C8: 249.6 | D8: =IF(AND($D$2<=B8,$D$2>B7),1,0) -> 0 | E8: =IF($D8=1,(C7+(C8-C7)/($B8-$B7)*($D$2-$B7)),0) -> 0
A9: 7 | B9: 10000 | C9: 304.8 | D9: =IF(AND($D$2<=B9,$D$2>B8),1,0) -> 0 | E9: =IF($D9=1,(C8+(C9-C8)/($B9-$B8)*($D$2-$B8)),0) -> 0
A10: 8 | B10: 20000 | C10: 566.8 | D10: =IF(AND($D$2<=B10,$D$2>B9),1,0) -> 0 | E10: =IF($D10=1,(C9+(C10-C9)/($B10-$B9)*($D$2-$B9)),0) -> 0
A11: 9 | B11: 40000 | C11: 1054 | D11: =IF(AND($D$2<=B11,$D$2>B10),1,0) -> 0 | E11: =IF($D11=1,(C10+(C11-C10)/($B11-$B10)*($D$2-$B10)),0) -> 0
A12: 10 | B12: 60000 | C12: 1515.2 | D12: =IF(AND($D$2<=B12,$D$2>B11),1,0) -> 0 | E12: =IF($D12=1,(C11+(C12-C11)/($B12-$B11)*($D$2-$B11)),0) -> 0
A13: 11 | B13: 80000 | C13: 1960.1 | D13: =IF(AND($D$2<=B13,$D$2>B12),1,0) -> 0 | E13: =IF($D13=1,(C12+(C13-C12)/($B13-$B12)*($D$2-$B12)),0) -> 0
A14: 12 | B14: 100000 | C14: 2393.4 | D14: =IF(AND($D$2<=B14,$D$2>B13),1,0) -> 0 | E14: =IF($D14=1,(C13+(C14-C13)/($B14-$B13)*($D$2-$B13)),0) -> 0
A15: 13 | B15: 200000 | C15: 4450.8 | D15: =IF(AND($D$2<=B15,$D$2>B14),1,0) -> 0 | E15: =IF($D15=1,(C14+(C15-C14)/($B15-$B14)*($D$2-$B14)),0) -> 0
... A20: 18 | B20: 2000000 | C20: 34948.9 | D20: =IF(AND($D$2<=B20,$D$2>B19),1,0) -> 0 | E20: =IF($D20=1,(C19+(C20-C19)/($B20-$B19)*($D$2-$B19)),0) -> 0
A21: 19 | D21: =IF(D2>B20,1,0) -> 0 | E21: =IF(D21=1,D2*1.6%,0) -> 0

Sheet 建设单位管理费
A1: 关于印发《基本建设项目建设成本管理规定》的通知
A2: 财建[2016]504号
A3: 党中央有关部门，国务院各部委、各直属机构，军委后勤保障部，武警总部，全国人大常委会办公厅，全国政协办公厅，高法院，高检院，各民主党派中央，有关人民团体，各中央管理企业，各省、自治区、计划单列市财政厅（局），新疆生产建设兵团财务局： | F3: 收费基价表 | L3: 输入工程费用 | M3: 差额定率累进法
A4: 为推动各部门、各地区进一步加强基本建设成本核算管理，提高资金使用效益，针对基本建设成本管理中反映出的主要问题，依据《基本建设财务规则》，现印发《基本建设项目建设成本管理规定》，请认真贯彻执行。 | F4: 序号 | G4: 计费额 | J4: 费率 | K4: 全额 | L4: ='其他费自动计算'!C2 -> 3992.88 | M4: =SUM(M5:M10) -> 64.8932
A5: 附件：1.基本建设项目建设成本管理规定 | F5: 1 | H5: > | I5: 1000 | J5: 0.02 | K5: =J5*I5 -> 20 | L5: =IF($L$4<=I5,1,0) -> 0 | M5: =IF(L5=1,(L4*J5),0) -> 0 | N5: 内容锁定区
A6: 2.项目建设管理费总额控制数费率表 | F6: 2 | G6: 1001 | H6: ~ | I6: 5000 | J6: 0.015 | K6: =J6*I6 -> 75 | L6: =IF(AND($L$4<=I6,$L$4>G6),1,0) -> 1 | M6: =IF(L6=1,(K5+($L$4-I5)*J6),0) -> 64.8932
A7: 财 政 部 | F7: 3 | G7: 5001 | H7: ~ | I7: 10000 | J7: 0.012 | K7: =J7*I7 -> 120 | L7: =IF(AND($L$4<=I7,$L$4>G7),1,0) -> 0 | M7: =IF(L7=1,(K6+($L$4-I6)*J7),0) -> 0
A8: 42557 | F8: 4 | G8: 10001 | H8: ~ | I8: 50000 | J8: 0.01 | K8: =J8*I8 -> 500 | L8: =IF(AND($L$4<=I8,$L$4>G8),1,0) -> 0 | M8: =IF(L8=1,(K7+($L$4-I7)*J8),0) -> 0
A9: 附件1： | F9: 5 | G9: 50001 | H9: ~ | I9: 100000 | J9: 0.008 | K9: =J9*I9 -> 800 | L9: =IF(AND($L$4<=I9,$L$4>G9),1,0) -> 0 | M9: =IF(L9=1,(K8+($L$4-I8)*J9),0) -> 0
A10: 基本建设项目建设成本管理规定 | F10: 6 | G10: 100000 | H10: < | J10: 0.004 | L10: =IF(AND($L$4>G10),1,0) -> 0 | M10: =IF(L10=1,(K9+($L$4-I9)*J10),0) -> 0
A11: 第一条 为了规范基本建设项目建设成本管理，提高建设资金使用效益，依据《基本建设财务规则》（财政部令第81号），制定本规定。
A12: 第二条 建筑安装工程投资支出是指基本建设项目（以下简称项目）建设单位按照批准的建设内容发生的建筑工程和安装工程的实际成本，其中不包括被安装设备本身的价值，以及按照合同规定支付给施工单位的预付备料款和预付工程款。 | L12: 在此区域输入
A13: 第三条 设备投资支出是指项目建设单位按照批准的建设内容发生的各种设备的实际成本（不包括工程抵扣的增值税进项税额），包括需要安装设备、不需要安装设备和为生产准备的不够固定资产标准的工具、器具的实际成本。
A14: 需要安装设备是指必须将其整体或几个部位装配起来，安装在基础上或建筑物支架上才能使用的设备。不需要安装设备是指不必固定在一定位置或支架上就可以使用的设备。
A15: 第四条 待摊投资支出是指项目建设单位按照批准的建设内容发生的，应当分摊计入相关资产价值的各项费用和税金支出。主要包括：
A16: （一）勘察费、设计费、研究试验费、可行性研究费及项目其他前期费用；
A17: （二）土地征用及迁移补偿费、土地复垦及补偿费、森林植被恢复费及其他为取得或租用土地使用权而发生的费用；
A18: （三）土地使用税、耕地占用税、契税、车船税、印花税及按规定缴纳的其他税费；
A19: （四）项目建设管理费、代建管理费、临时设施费、监理费、招标投标费、社会中介机构审查费及其他管理性质的费用；
A20: （五）项目建设期间发生的各类借款利息、债券利息、贷款评估费、国外借款手续费及承诺费、汇兑损益、债券发行费用及其他债务利息支出或融资费用；
A21: （六）工程检测费、设备检验费、负荷联合试车费及其他检验检测类费用；
A22: （七）固定资产损失、器材处理亏损、设备盘亏及毁损、报废工程净损失及其他损失；
A23: （八）系统集成等信息工程的费用支出；
A24: （九）其他待摊投资性质支出。
... A43: 万元
A44: 工程总概算 | B44: 费率 | C44: 算例
C45: 工程总概算 | D45: 项目建设管理费
A46: 1000以下 | B46: 2 | C46: 1000 | D46: 1000*2%=20
A47: 1001-5000 | B47: 1.5 | C47: 5000 | D47: 20+（5000-1000）*1.5%=80
A48: 5001-10000 | B48: 1.2 | C48: 10000 | D48: 80+（10000-5000）*1.2%=140
A49: 10001-50000 | B49: 1 | C49: 50000 | D49: 140+（50000-10000）*1%=540
A50: 50001-100000 | B50: 0.8 | C50: 100000 | D50: 540+（100000-50000）*0.8%=940
A51: 100000以上 | B51: 0.4 | C51: 200000 | D51: 940+（200000-100000）*0.4%=1340
A53: 发布日期: 2016年08月18日

Sheet 场地准备费
A1: 场地准备及临时设施费:包括场地准备费和临时设施费.
A2: 1)场地准备费是使工程项目的建设场地达到开工条件，由建设单位组织进行的场地平整等准备工作而发生的费用。
A3: 2)临时设施费是指为满足施工建设需要而供到场地界区的、未列人工程费用的临时水、电、路、通信、气等其他工程费用和建设单位的现场临时建（构)筑物的搭设、建设、维修、拆除、摊销费用或租赁费用，货物、码头租赁等费用，以及施工期间专用公路养护费、维修费.
A4: 3)场地准备及临时设施应尽量与永久性工程统一考虑.建设场地的大型土石方工程应进人工程费用中的总图运输费用中.
A5: 计算方法:
A6: 1）新建项目的场地准备和临时设施费应根据实际工程量估算，或按工程费用的比例计算，一般可按第一部分工程费用的 0. 5% ^ 2.0%计列。
A7: (2)改扩建项目一般只计拆除清理费。
A8: (3)发生拆除清理费时可按新建同类工程造价或主材费、设备费的比例计算.凡可回收材料的拆除采用以料抵工方式，不再计算拆除清理费。
A9: (4)此费用不包括已列入建筑安装工程费用中的施工单位临时设施费用。

Sheet 安全预评价
A1: 序号 | B1: 总投资额 （亿元） | E1: 基础报价 | F1: 输入费用 | G1: 直线内插法计取
A3: 1 | C3: < | D3: =10000*0.05 -> 500 | E3: 2 | F3: =IF(F2<=D3,1,0) -> 1 | G3: =IF(F3=1,E3/D3*F2,0) -> 0
A4: 2 | B4: =10000*0.05 -> 500 | C4: ~ | D4: =10000*0.1 -> 1000 | E4: 3.5 | F4: =IF(AND($F$2<=D4,$F$2>B4),1,0) -> 0 | G4: =IF(F4=1,(E3+(E4-E3)/(D4-B4)*($F$2-B4)),0) -> 0
A5: 3 | B5: =10000*0.1 -> 1000 | C5: ~ | D5: =10000*0.2 -> 2000 | E5: 5 | F5: =IF(AND($F$2<=D5,$F$2>B5),1,0) -> 0 | G5: =IF(F5=1,(E4+(E5-E4)/(D5-B5)*($F$2-B5)),0) -> 0
A6: 4 | B6: =10000*0.2 -> 2000 | C6: ~ | D6: 5000 | E6: 7 | F6: =IF(AND($F$2<=D6,$F$2>B6),1,0) -> 0 | G6: =IF(F6=1,(E5+(E6-E5)/(D6-B6)*($F$2-B6)),0) -> 0
A7: 5 | B7: =10000*0.5 -> 5000 | C7: ~ | D7: 10000 | E7: =0.5*1.5*10000/1000 -> 7.5 | F7: =IF(AND($F$2<=D7,$F$2>B7),1,0) -> 0 | G7: =IF(F7=1,(E6+(E7-E6)/(D7-B7)*($F$2-B7)),0) -> 0
A8: 6 | B8: 10000 | C8: ~ | D8: 20000 | E8: =1*10000*1/1000 -> 10 | F8: =IF(AND($F$2<=D8,$F$2>B8),1,0) -> 0 | G8: =IF(F8=1,(E7+(E8-E7)/(D8-B8)*($F$2-B8)),0) -> 0
A9: 7 | B9: 20000 | C9: ~ | D9: 50000 | E9: =2*0.7*10000/1000 -> 14 | F9: =IF(AND($F$2<=D9,$F$2>B9),1,0) -> 0 | G9: =IF(F9=1,(E8+(E9-E8)/(D9-B9)*($F$2-B9)),0) -> 0
A10: 8 | B10: 50000 | C10: ~ | D10: 100000 | E10: =5*0.4*10000/1000 -> 20 | F10: =IF(AND($F$2<=D10,$F$2>B10),1,0) -> 0 | G10: =IF(F10=1,(E9+(E10-E9)/(D10-B10)*($F$2-B10)),0) -> 0
A11: 9 | B11: 100000 | E11: =10*0.3*10000/1000 -> 30 | F11: =IF(F2>B11,1,0) -> 0 | G11: =IF(F11=1,E11/B11*F2,0) -> 0
